[
  {
    "article_id": "2596",
    "source": "report.az",
    "link": "https://report.az/xarici-siyaset/tramp-novbeti-defe-prezident-ilham-eliyevin-cixisi-ile-bagli-paylasim-edib",
    "pub_date": "2025-08-08 22:56:00.000",
    "title": "Tramp növbəti dəfə Prezident İlham Əliyevin çıxışı ilə bağlı paylaşım edib",
    "content": "ABŞ Prezidenti Donald Tramp növbəti dəfə “Truth Social” sosial şəbəkəsindəki səhifəsində Azərbaycan lideri İlham Əliyevin Şuşa Media Forumunda çıxışı ilə bağlı paylaşım edib.\n\n“Report”paylaşımı təqdim edir:",
    "gold_entities": {
      "persons": [
        "Donald Tramp",
        "İlham Əliyev"
      ],
      "organizations": [
        "Report",
        "Truth Social",
        "Şuşa Media Forumu"
      ],
      "locations": [
        "ABŞ",
        "Azərbaycan",
        "Şuşa"
      ],
      "positions": [
        "ABŞ Prezidenti",
        "Azərbaycan lideri"
      ],
      "dates": []
    },
    "manually_verified": true,
    "annotator_notes": ""
  },
  {
    "article_id": "1006",
    "source": "report.az",
    "link": "https://report.az/dini-xeberler/leyla-eliyeva-ramazan-bayrami-munasibetile-paylasim-edib",
    "pub_date": "2025-03-29 23:19:00.000",
    "title": "Leyla Əliyeva Ramazan bayramı münasibətilə paylaşım edib",
    "content": "Heydər Əliyev Fondunun vitse-prezidenti, IDEA İctimai Birliyinin təsisçisi və rəhbəri Leyla Əliyeva sosial media hesabında Ramazan bayramı münasibətilə paylaşım edib.\n\n\"Report\"xəbər verir ki, paylaşımda deyilir:\n\n\"Ramazan bayramınız mübarək!\"\n\nПубликация от Official page of Leyla Aliyeva (@leyla999)",
    "gold_entities": {
      "persons": [
        "Leyla Əliyeva"
      ],
      "organizations": [
        "Heydər Əliyev Fondu",
        "IDEA İctimai Birliyi",
        "Report"
      ],
      "locations": [],
      "positions": [
        "Heydər Əliyev Fondunun vitse-prezidenti",
        "IDEA İctimai Birliyinin təsisçisi",
        "IDEA İctimai Birliyinin rəhbəri"
      ],
      "dates": [
        "Ramazan bayramı"
      ]
    },
    "manually_verified": true,
    "annotator_notes": ""
  },
  {
    "article_id": "2845",
    "source": "report.az",
    "link": "https://report.az/region-xeberleri/turkiyede-teyyare-qezaya-ugrayib-xesaret-alan-var",
    "pub_date": "2025-08-29 22:45:00.000",
    "title": "Türkiyədə təyyarə qəzaya uğrayıb, xəsarət alan var",
    "content": "Türkiyənin Dənizli şəhərində meşə yanğının söndürülməsinə cəlb olunan təyyarə Muğla vilayətinin Yatağan rayonuna məcburi eniş edərkən qəzaya uğrayıb.\n\n\"Report\"xəbər verir ki, bu barədə NTV məlumat yayıb.\n\nNəticədə pilot yaralanıb. O, yaxınlıqdakı xəstəxanaya yerləşdirilib. Yaralının həyatı üçün təhlükə olmadığı bildirilir.",
    "gold_entities": {
      "persons": [],
      "organizations": [
        "Report",
        "NTV"
      ],
      "locations": [
        "Türkiyə",
        "Dənizli",
        "Muğla",
        "Yatağan"
      ],
      "positions": [
        "pilot"
      ],
      "dates": []
    },
    "manually_verified": true,
    "annotator_notes": ""
  },
  {
    "article_id": "2732",
    "source": "report.az",
    "link": "https://report.az/futbol-xeberleri/italiya-klubu-monteneqro-millisinin-futbolcusunu-heyetine-qatib",
    "pub_date": "2025-08-20 23:57:00.000",
    "title": "İtaliya təmsilçisi Monteneqro millisinin futbolçusunu heyətinə qatıb",
    "content": "İtaliya A Seriyası təmsilçisi \"Atalanta\" Monteneqro millisinin üzvü Nikola Krstoviçi transfer edib.\n\n\"Report\"xəbər verir ki, bu barədə Berqamo klubunun mətbuat xidməti məlumat yayıb.\n\nSon olaraq \"Leççe\"nin (İtaliya) formasını geyinən hücumçunun transfer qiyməti 25 milyon avro təşkil edib.\n\nQeyd edək ki, Nikola Krstoviç ötən mövsüm 37 oyunda 11 qol vurub.",
    "gold_entities": {
      "persons": [
        "Nikola Krstoviç"
      ],
      "organizations": [
        "Atalanta",
        "Leççe",
        "Report"
      ],
      "locations": [
        "İtaliya",
        "Monteneqro",
        "Berqamo"
      ],
      "positions": [
        "futbolçu",
        "hücumçu"
      ],
      "dates": []
    },
    "manually_verified": true,
    "annotator_notes": ""
  },
  {
    "article_id": "2638",
    "source": "report.az",
    "link": "https://report.az/region-xeberleri/balikesirde-novbeti-defe-zelzele-olub",
    "pub_date": "2025-08-12 23:22:00.000",
    "title": "Balıkesirdə yenə zəlzələ olub",
    "content": "Türkiyənin Balıkesir şəhərinin Sındırğı rayonunda yenidən zəlzələ olub.\n\n\"Report\"xəbər verir ki, bu barədə Fövqəladə Halların İdarə Olunması Agentliyi (AFAD) məlumat yayıb.\n\nQeyd edilib ki, 4 maqnituda gücündə zəlzələnin dərinliyi 10.97 kilometr olub.\n\nTəbii fəlakətin nəticələri barədə məlumat yoxdur.\n\nXatırladaq ki, avqustun 11-də Sındırqıda ard-arda iki zəlzələqeydə alınmışdı.",
    "gold_entities": {
      "persons": [],
      "organizations": [
        "Report",
        "Fövqəladə Halların İdarə Olunması Agentliyi (AFAD)"
      ],
      "locations": [
        "Türkiyə",
        "Balıkesir",
        "Sındırğı"
      ],
      "positions": [],
      "dates": [
        "avqustun 11-də"
      ]
    },
    "manually_verified": true,
    "annotator_notes": ""
  },
  {
    "article_id": "1463",
    "source": "report.az",
    "link": "https://report.az/ferdi/azerbaycanin-iki-gulescisi-turkiyede-kecirilen-yarisda-medal-qazanib",
    "pub_date": "2025-05-06 22:56:00.000",
    "title": "Azərbaycanın iki güləşçisi Türkiyədə keçirilən yarışda medal qazanıb",
    "content": "Azərbaycanın iki güləşçisi Türkiyənin Antalya şəhərində gənclər (U-20) arasında keçirilən “Çempionlar” turnirində medal qazanıblar.\n\n\"Report\"xəbər verir ki, ilk yarış günündə Turan Daşdəmirov (55 kq) gümüş, İsmayıl Rzayev (97 kq) bürünc medal qazanıb.\n\nXalid Ələsgərovla (55 kq) Davud Məmmədov (77 kq) isə beşinci yerlə kifayətlənib.\n\nSabah 60, 72 və 87 kq-da yer alan güləşçilər xalça üzərinə çıxacaqlar.",
    "gold_entities": {
      "persons": [
        "Turan Daşdəmirov",
        "İsmayıl Rzayev",
        "Xalid Ələsgərov",
        "Davud Məmmədov"
      ],
      "organizations": [
        "Report",
        "“Çempionlar” turniri"
      ],
      "locations": [
        "Türkiyə",
        "Antalya"
      ],
      "positions": [
        "güləşçi"
      ],
      "dates": []
    },
    "manually_verified": true,
    "annotator_notes": ""
  },
  {
    "article_id": "2479",
    "source": "report.az",
    "link": "https://report.az/futbol-xeberleri/karvan-almaniyali-futbolcu-ile-anlasib",
    "pub_date": "2025-07-29 22:24:00.000",
    "title": "\"Karvan\" almaniyalı futbolçu ilə anlaşıb",
    "content": "Premyer Liqa iştirakçısı \"Karvan\" yeni futbolçu ilə anlaşıb.\n\nKlubdan\"Report\"a verilən məlumata görə, Yevlax təmsilçisi almaniyalı sol cinah müdafiəçisi Mois Nqvisanini sıralarına cəlb edib.\n\nOnunla 1 illik sözləşmə imzalanıb.\n\n27 yaşlı futbolçu son olaraq Lüksenburqun “Vilç” klubunda forma geyinib. Mois karyerası ərzində Almaniyanın “Bohum”, “Aue”, “Ştutqart” və “Borussiya” (Münhenqladbax) komandalarında çıxış edib.",
    "gold_entities": {
      "persons": [
        "Mois Nqvisanini"
      ],
      "organizations": [
        "Karvan",
        "Vilç",
        "Bohum",
        "Aue",
        "Ştutqart",
        "Borussiya (Münhenqladbax)",
        "Report"
      ],
      "locations": [
        "Yevlax",
        "Almaniya",
        "Lüksenburq",
        "Münhenqladbax"
      ],
      "positions": [
        "futbolçu",
        "sol cinah müdafiəçisi"
      ],
      "dates": [
        "1 illik"
      ]
    },
    "manually_verified": true,
    "annotator_notes": ""
  },
  {
    "article_id": "698",
    "source": "report.az",
    "link": "https://report.az/diger-olkeler/kiv-tramp-rusiya-ukrayna-bohraninin-helli-ile-bagli-bu-gun-gorus-kecirecek",
    "pub_date": "2025-03-03 22:29:00.000",
    "title": "KİV: Tramp Rusiya-Ukrayna böhranının həlli ilə bağlı görüş keçirəcək",
    "content": "ABŞ Prezidenti Donald Tramp bu gün Rusiya-Ukrayna böhranının həlli, o cümlədən Ukraynaya hərbi yardımın mümkün dayandırılması ilə bağlı görüş keçirəcək.\n\n“Report” xəbər verir ki, bu barədə “Axios” mənbələrə istinadən məlumat yayıb.\n\nİddiaya görüşdə vitse-prezident Cey Di Vens, dövlət katibi Marko Rubio, müdafiə naziri (Pentaqonun rəhbəri) Pit Heqset, milli təhlükəsizlik müşaviri Mayk Vals və digər yüksək vəzifəli şəxslər iştirak edəcəklər.",
    "gold_entities": {
      "persons": [
        "Donald Tramp",
        "Cey Di Vens",
        "Marko Rubio",
        "Pit Heqset",
        "Mayk Vals"
      ],
      "organizations": [
        "Report",
        "Axios",
        "Pentaqon"
      ],
      "locations": [
        "Rusiya",
        "Ukrayna",
        "ABŞ"
      ],
      "positions": [
        "ABŞ Prezidenti",
        "vitse-prezident",
        "dövlət katibi",
        "müdafiə naziri",
        "milli təhlükəsizlik müşaviri"
      ],
      "dates": [
        "bu gün"
      ]
    },
    "manually_verified": true,
    "annotator_notes": ""
  },
  {
    "article_id": "3701",
    "source": "report.az",
    "link": "https://report.az/daxili-siyaset/gencede-zefer-gunune-hesr-edilmis-konsert-kecirilib-atesfesanliq-olub",
    "pub_date": "2025-11-08 22:38:00.000",
    "title": "Gəncədə Zəfər Gününə həsr edilmiş konsert keçirilib, atəşfəşanlıq olub",
    "content": "Gəncə şəhərində 8 Noyabr - Zəfər Günü münasibətilə konsert proqramı keçirilib, atəşfəşanlıq olub.\n\n\"Report\"un Qərb bürosunun məlumatına görə, mərkəzi meydanda təşkil olunmuş konsert proqramında mədəniyyət xadimlərinin və incəsənət nümayəndələrinin ifalarında rəqslər nümayiş edilib, vətənpərvərlik mahnıları səsləndirilib.\n\nKonsert proqramını rəsmi şəxslər, ictimaiyyət nümayəndələri, şəhər sakinləri izləyib.\n\nSonda Zəfər Günü münasibətilə atəşfəşanlıq olub.",
    "gold_entities": {
      "persons": [],
      "organizations": [
        "Report"
      ],
      "locations": [
        "Gəncə"
      ],
      "positions": [],
      "dates": [
        "8 Noyabr",
        "Zəfər Günü"
      ]
    },
    "manually_verified": true,
    "annotator_notes": ""
  },
  {
    "article_id": "3818",
    "source": "report.az",
    "link": "https://report.az/diger-olkeler/tramp-iran-abs-ile-sazis-baglamaq-isteyir",
    "pub_date": "2025-11-18 22:58:00.000",
    "title": "Tramp: İran ABŞ ilə saziş bağlamaq istəyir",
    "content": "ABŞ Prezidenti Donald Tramp İranla mümkün sazişə açıq olduğunu bildirib.\n\n\"Report\"xəbər verir ki, ABŞ lideri Ağ Evdə Səudiyyə Ərəbistanı vəliəhdi, Baş nazir Məhəmməd bin Salmanla görüşdə mövqeyini bildirib.\n\nO qeyd edib ki, tərəflər artıq bu mövzuda müzakirələrə başlayıblar. \"Yeri gəlmişkən, İran saziş bağlamaq istəyir. Mən də bəyan etməyə hazıram ki, onlar saziş bağlamağa can atırlar. Mən buna tam açıqam. Bu prosesi başlamaq üçün onlarla danışıqlar aparırıq\", - Tramp deyib.",
    "gold_entities": {
      "persons": [
        "Donald Tramp",
        "Məhəmməd bin Salman"
      ],
      "organizations": [
        "Report",
        "Ağ Ev"
      ],
      "locations": [
        "ABŞ",
        "İran",
        "Səudiyyə Ərəbistanı"
      ],
      "positions": [
        "ABŞ Prezidenti",
        "Səudiyyə Ərəbistanı vəliəhdi",
        "Baş nazir"
      ],
      "dates": []
    },
    "manually_verified": true,
    "annotator_notes": ""
  },
  {
    "article_id": "830",
    "source": "report.az",
    "link": "https://report.az/xarici-siyaset/monteneqro-azerbaycan-ermenistan-sulh-sazisi-layihesini-yuksek-qiymetlendirir",
    "pub_date": "2025-03-14 23:17:00.000",
    "title": "Monteneqro Azərbaycan - Ermənistan sülh sazişi layihəsini yüksək qiymətləndirir",
    "content": "Monteneqro Azərbaycan və Ermənistan arasında tarixi sülh sazişi layihəsini yüksək qiymətləndirir.\n\n“Report”xəbər verir ki, bu barədə Monteneqro Xarici İşlər Nazirliyinin “X”dəki paylaşımında vurğulanıb.\n\n“Bu, regionun sabitliyinə, Avropa və qlobal təhlükəsizliyə böyük töhfədir. Monteneqro sülh, təhlükəsizlik, sabitlik və iqtisadi rifah məqsədlərinə çatmaq üçün hər iki dost ölkə ilə tərəfdaşlıq münasibətlərinin möhkəmlənməsinə və onlarla sıx əməkdaşlığa ümid edir”, - paylaşımda əlavə olunub.",
    "gold_entities": {
      "persons": [],
      "organizations": [
        "Report",
        "Monteneqro Xarici İşlər Nazirliyi",
        "X"
      ],
      "locations": [
        "Monteneqro",
        "Azərbaycan",
        "Ermənistan",
        "Avropa"
      ],
      "positions": [],
      "dates": []
    },
    "manually_verified": true,
    "annotator_notes": ""
  },
  {
    "article_id": "837",
    "source": "report.az",
    "link": "https://report.az/diger-olkeler/latakiyada-guclu-partlayis-bas-verib-olenler-var",
    "pub_date": "2025-03-15 23:40:00.000",
    "title": "Latakiyada güclü partlayış baş verib, ölənlər var",
    "content": "Suriyanın cənubundakı Latakiya şəhərində güclü partlayış nəticəsində azı üç nəfər ölüb.\n\n“Report”xəbər verir ki, bu barədə “Suriya-TV” telekanalı məlumat yayıb.\n\nQeyd olunur ki, partlayış nəticəsində Ər-Raml məhəlləsindəki binalardan biri uçub, bir neçə sakin xəsarət alıb.\n\nHadisənin səbəbləri hələ müəyyən edilməyib.\n\nTelekanalın məlumatına görə, hadisə yerinə yerli mülki müdafiə qüvvələrinin xilasetmə qrupları cəlb olunub. Uçmuş evin dağıntıları altında qalan yaralıların xilas edilməsi üçün işlərə başlanılıb.",
    "gold_entities": {
      "persons": [],
      "organizations": [
        "Report",
        "Suriya-TV",
        "mülki müdafiə qüvvələri"
      ],
      "locations": [
        "Suriya",
        "Latakiya",
        "Ər-Raml"
      ],
      "positions": [],
      "dates": []
    },
    "manually_verified": true,
    "annotator_notes": ""
  },
  {
    "article_id": "1256",
    "source": "report.az",
    "link": "https://report.az/hadise/toydan-2-yasli-usagi-qaciran-sexs-saxlanilib",
    "pub_date": "2025-04-19 23:54:00.000",
    "title": "Ağstafada toydan 2 yaşlı uşağı qaçıran şəxs saxlanılıb",
    "content": "Toydan 2 yaşlı uşağı qaçıran şəxsi polis saxlayıb.\n\n“Report”un Qərb bürosunun məlumatına görə, aprelin 19-da Ağstafa rayon Aşağı Göycəli kəndi ərazisində keçirilmiş toy mərasimindən 2 yaşlı qız uşağının qaçırılması barədə məlumatlar yayılıb.\n\nMəlumata görə, 57 yaşlı Telman Omarov uşağı qaçıraraq yaşadığı evə gətirib, onu almaq üçün gələn valideynlərinin üzərinə həyətdə saxladığı iti buraxıb.\n\nSərxoş vəziyyətdə olan kişi polis əməkdaşları tərəfindən saxlanılıb, uşaq valideynlərinə təhvil verilib.\n\nFaktla bağlı araşdırma aparılır.",
    "gold_entities": {
      "persons": [
        "Telman Omarov"
      ],
      "organizations": [
        "Report",
        "polis"
      ],
      "locations": [
        "Ağstafa",
        "Ağstafa rayonu",
        "Aşağı Göycəli"
      ],
      "positions": [],
      "dates": [
        "aprelin 19-da"
      ]
    },
    "manually_verified": true,
    "annotator_notes": ""
  },
  {
    "article_id": "3109",
    "source": "report.az",
    "link": "https://report.az/region-xeberleri/iran-aeba-ile-emekdasligi-dayandirmaq-qerarina-gelib",
    "pub_date": "2025-09-20 22:20:00.000",
    "title": "İran AEBA ilə əməkdaşlığı dayandırmaq qərarına gəlib",
    "content": "\"Aİ3\"ölkə\"lərinin (Böyük Britaniya, Almaniya və Fransa) BMT Təhlükəsizlik Şurasının İrana qarşı sanksiyalarını bərpa etmək məqsədi daşıyan hərəkətləri səbəbindən Tehran Atom Enerjisi üzrə Beynəlxalq Agentliyi (AEBA) ilə əməkdaşlığı dayandıracaq.\n\n\"Report\"xəbər verir ki, bu barədə İranın Ali Milli Təhlükəsizlik Şurası məlumat yayıb.\n\nVurğulanıb ki, İran Xarici İşlər Nazirliyinin agentliklə əməkdaşlığına və böhranın həlli ilə bağlı planların təqdim olunmasına baxmayaraq, Avropa ölkələrinin hərəkətləri səbəbindən qurumla əməkdaşlıq dayandırılacaq.",
    "gold_entities": {
      "persons": [],
      "organizations": [
        "Report",
        "Atom Enerjisi üzrə Beynəlxalq Agentlik (AEBA)",
        "BMT Təhlükəsizlik Şurası",
        "İranın Ali Milli Təhlükəsizlik Şurası",
        "İran Xarici İşlər Nazirliyi",
        "Aİ3"
      ],
      "locations": [
        "Tehran",
        "İran",
        "Böyük Britaniya",
        "Almaniya",
        "Fransa"
      ],
      "positions": [],
      "dates": []
    },
    "manually_verified": true,
    "annotator_notes": ""
  },
  {
    "article_id": "2586",
    "source": "report.az",
    "link": "https://report.az/diger-olkeler/pensilvaniyada-2-herbci-namelum-seraitde-gullelenib",
    "pub_date": "2025-08-07 22:39:00.000",
    "title": "Pensilvaniyada 2 hərbçi naməlum şəraitdə güllələnib",
    "content": "ABŞ-nin Pensilvaniya ştatında atışma nəticəsində 2 təhlükəsizlik qüvvəsi əməkdaşı güllələnib.\n\n\"Report\"\"Associated Press\"ə istinadən xəbər verir ki, bu barədə ştat qubernatoru Coş Şapiro məlumat verib.\n\nO bildirib ki, atışma Pensilvaniyanın şimal-şərqində baş verib və polkovnik Kristofer Paris artıq hadisə yerindədir, yaralanan hərbçilər isə xəstəxanaya aparılıb. Qubernatorun sözlərinə görə, yaralıların vəziyyəti stabildir: \"Onlar üçün dua edirik\".\n\nC. Şapiro özünün də hadisə yerinə gedəcəyini bildirsə də, atışmanın baş vermə şəraiti haqqında məlumat paylaşmayıb.",
    "gold_entities": {
      "persons": [
        "Coş Şapiro",
        "Kristofer Paris"
      ],
      "organizations": [
        "Report",
        "Associated Press"
      ],
      "locations": [
        "ABŞ",
        "Pensilvaniya"
      ],
      "positions": [
        "ştat qubernatoru",
        "polkovnik"
      ],
      "dates": []
    },
    "manually_verified": true,
    "annotator_notes": ""
  },
  {
    "article_id": "771",
    "source": "report.az",
    "link": "https://report.az/komanda/azerbaycan-basketbol-liqasinda-xvii-tura-yekun-vurulub",
    "pub_date": "2025-03-09 21:33:00.000",
    "title": "Azərbaycan Basketbol Liqasında XVII tura yekun vurulub",
    "content": "Azərbaycan Basketbol Liqasında XVII tura yekun vurulub.\n\n\"Report\"un məlumatına görə, sonuncu matçda \"Sumqayıt\" \"Ordu\"nu qəbul edib.\n\nQarşılaşma meydan sahiblərinin qələbəsi ilə bitib - 122:116.\n\nBu nəticədən sonra xallarının sayını 24-ə çatdıran \"gənclik şəhəri\" təmsilçisi dördüncü pillədə qərarlaşıb. \"Hərbçilər\" 28 xalla üçüncü sıradadır.\n\nGünün ilk matçında \"Gəncə\" \"Lənkəran\"dan üstün olub - 90:76.\n\nQeyd edək ki, turun daha əvvəl baş tutan görüşlərində NTD \"Naxçıvan\"ı 85:78, “Sabah” “Neftçi”ni 105:77, “Şəki” “Quba”nı 66:63, \"Abşeron\" \"Sərhədçi\"ni 77:75 hesabı ilə məğlub edib.",
    "gold_entities": {
      "persons": [],
      "organizations": [
        "Report",
        "Azərbaycan Basketbol Liqası",
        "Sumqayıt",
        "Ordu",
        "Gəncə",
        "Lənkəran",
        "NTD",
        "Naxçıvan",
        "Sabah",
        "Neftçi",
        "Şəki",
        "Quba",
        "Abşeron",
        "Sərhədçi"
      ],
      "locations": [
        "Azərbaycan",
        "Sumqayıt",
        "Gəncə",
        "Lənkəran",
        "Naxçıvan",
        "Şəki",
        "Quba",
        "Abşeron"
      ],
      "positions": [],
      "dates": []
    },
    "manually_verified": true,
    "annotator_notes": ""
  },
  {
    "article_id": "3082",
    "source": "report.az",
    "link": "https://report.az/region-xeberleri/kamcatka-sahillerinde-7-7-bal-gucunde-zelzele-olub-sunami-tehlukesi-elan-edilib",
    "pub_date": "2025-09-18 23:41:00.000",
    "title": "Kamçatka sahillərində 7,7 bal gücündə zəlzələ olub, sunami təhlükəsi elan edilib",
    "content": "Kamçatkanın (Rusiya) şərq sahilləri yaxınlığında 7,7 bal gücündə zəlzələ qeydə alınıb.\n\n\"Report\"un məlumatına görə, bu barədə Avropa-Aralıq dənizi Seysmoloji Mərkəzi məlumat yayıb.\n\nMəlumata əsasən, yeraltı təkanların episentri Petropavlovsk-Kamçatski şəhərindən 125 km şimal-şərqdə, ocağı isə 40 km dərinlikdə yerləşib.\n\nABŞ-nin Okean və Atmosfer üzrə Milli İdarəsi (NOAA) bölgədə sunami təhlükəsi elan edib. ABŞ Geoloji Xidməti zəlzələnin gücünü 7,8 bal olaraq qiymətləndirib.\n\nKamçatka vilayətinin qubernatoru Vladimir Solodov bildirib ki, bütün xidmətlər gücləndirilmiş hazırlıq rejiminə keçirilib.",
    "gold_entities": {
      "persons": [
        "Vladimir Solodov"
      ],
      "organizations": [
        "Report",
        "Avropa-Aralıq dənizi Seysmoloji Mərkəzi",
        "ABŞ-nin Okean və Atmosfer üzrə Milli İdarəsi (NOAA)",
        "ABŞ Geoloji Xidməti"
      ],
      "locations": [
        "Kamçatka",
        "Rusiya",
        "Petropavlovsk-Kamçatski",
        "ABŞ"
      ],
      "positions": [
        "Kamçatka vilayətinin qubernatoru"
      ],
      "dates": []
    },
    "manually_verified": true,
    "annotator_notes": ""
  },
  {
    "article_id": "3933",
    "source": "report.az",
    "link": "https://report.az/region-xeberleri/eraqci-ve-kallas-tehranin-nuve-proqramini-muzakire-edibler",
    "pub_date": "2025-11-28 23:30:00.000",
    "title": "Əraqçi və Kallas Tehranın nüvə proqramını müzakirə ediblər",
    "content": "İranın xarici işlər naziri Abbas Əraqçi və Avropa diplomatiyasının rəhbəri Kaya Kallas telefon danışığı zamanı Tehranın nüvə proqramını müzakirə ediblər.\n\nBu barədə\"Report\"İran Xarici İşlər Nazirliyinə (XİN) istinadən xəbər verir.\n\nMəlumata görə, tərəflər həmçinin İran ilə Avropa İttifaqı arasındakı münasibətləri və Yaxın Şərqdəki vəziyyəti müzakirə ediblər. Əraqçi Tehranın nüvə proqramı ilə bağlı İranın mövqeyini təqdim edib.\n\n\"Onlar İran və Avropa tərəfləri arasında regional və beynəlxalq vəziyyətlə bağlı fikir mübadiləsi üçün təmasların davam etdirilməsinin vacibliyini vurğulayıblar\", – deyə İran XİN bildirib.",
    "gold_entities": {
      "persons": [
        "Abbas Əraqçi",
        "Kaya Kallas"
      ],
      "organizations": [
        "Report",
        "İran Xarici İşlər Nazirliyi (XİN)",
        "Avropa İttifaqı"
      ],
      "locations": [
        "İran",
        "Tehran",
        "Avropa",
        "Yaxın Şərq"
      ],
      "positions": [
        "İranın xarici işlər naziri",
        "Avropa diplomatiyasının rəhbəri"
      ],
      "dates": []
    },
    "manually_verified": true,
    "annotator_notes": ""
  },
  {
    "article_id": "3501",
    "source": "report.az",
    "link": "https://report.az/ferdi/azerbaycanin-yunan-roma-gulescileri-dunya-cempionatinda-ucuncu-olublar",
    "pub_date": "2025-10-23 23:37:00.000",
    "title": "Azərbaycanın yunan-Roma güləşçiləri dünya çempionatında üçüncü olublar",
    "content": "Azərbaycanın yunan-Roma güləşçiləri Serbiyanın Novi Sad şəhərində keçirilən U-23 dünya çempionatında üçüncü yeri tutublar.\n\n\"Report\"xəbər verir ki, 2 qızıl və 1 bürünc medal qazanan yığma 93 xalla komanda hesabında üçüncü olub.\n\nMilli medalların əyarına görə tarixinin ən yaxşı nəticəsinə imza atıb.\n\nAzərbaycan yalnız İran (143) və Ukraynadan (96) geri qalıb.\n\nQeyd edək ki, baş məşqçi Aleksandr Tarakanov, böyük məşqçi Rövşən Bayramov, məşqçilər Həsən Əliyevlə Kamran Məmmədovun rəhbərliyi altında DÇ-yə qatılan heyətdə Elmir Əliyevlə (55 kq) Ziya Babaşov (63 kq) dünya çempionu olub. Ruslan Nurullayev (72 kq) isə üçüncü yeri tutub.",
    "gold_entities": {
      "persons": [
        "Aleksandr Tarakanov",
        "Rövşən Bayramov",
        "Həsən Əliyev",
        "Kamran Məmmədov",
        "Elmir Əliyev",
        "Ziya Babaşov",
        "Ruslan Nurullayev"
      ],
      "organizations": [
        "Report",
        "U-23 dünya çempionatı"
      ],
      "locations": [
        "Serbiya",
        "Novi Sad",
        "Azərbaycan",
        "İran",
        "Ukrayna"
      ],
      "positions": [
        "baş məşqçi",
        "böyük məşqçi",
        "məşqçi"
      ],
      "dates": []
    },
    "manually_verified": true,
    "annotator_notes": ""
  },
  {
    "article_id": "919",
    "source": "report.az",
    "link": "https://report.az/diger-olkeler/tramp-boeing-e-altinci-nesil-f-47-qiricisinin-hazirlanmasini-tapsirib",
    "pub_date": "2025-03-21 20:47:00.000",
    "title": "Tramp “Boeing”ə altıncı nəsil F-47 qırıcısının hazırlanmasını tapşırıb",
    "content": "ABŞ Prezidenti Donald Tramp amerikan aerokosmik korporasiyası “Boeing”ə NGAD (Next-Generation Air Dominance) proqramı çərçivəsində növbəti nəsil qırıcı təyyarənin hazırlanması üçün müqavilə təqdim edib.\n\n“Report”xəbər verir ki, Amerika lideri müvafiq bəyanatı Ağ evin Oval kabinetində Pentaqon rəhbəri Pit Heqset ilə birlikdə jurnalistlər qarşısında çıxışı zamanı verib.\n\nTrampın sözlərinə görə, qırıcı təyyarə F-47 adını alacaq. Prezident vurğulayıb ki, yeni qırıcının eksperimental modelinin sınaq uçuşları artıq beş ildir həyata keçirilir.\n\nMətbuatın qeyd etdiyi kimi, müqavilə uğrunda mübarizədə “Boeing”in rəqibi “Lockheed Martin” şirkəti olmuşdu.",
    "gold_entities": {
      "persons": [
        "Donald Tramp",
        "Pit Heqset"
      ],
      "organizations": [
        "Report",
        "Boeing",
        "NGAD (Next-Generation Air Dominance)",
        "Ağ ev",
        "Oval kabinet",
        "Pentaqon",
        "Lockheed Martin"
      ],
      "locations": [
        "ABŞ"
      ],
      "positions": [
        "ABŞ Prezidenti",
        "Pentaqon rəhbəri"
      ],
      "dates": [
        "beş ildir"
      ]
    },
    "manually_verified": true,
    "annotator_notes": ""
  },
  {
    "article_id": "2434",
    "source": "report.az",
    "link": "https://report.az/diger-olkeler/sotlandiya-trampin-seferine-etiraz-edib",
    "pub_date": "2025-07-26 23:09:00.000",
    "title": "Şotlandiya sakinləri Trampın səfərinə etiraz edib",
    "content": "Şotlandiyada yüzlərlə insan ABŞ Prezidenti Donald Trampın səfərinə etiraz olaraq küçələrə çıxıb.\n\n\"Report\"xəbər verir ki, bu barədə \"The Independent\" qəzeti məlumat yayıb.\n\nMəlumata görə, insanlar Edinburq və Aberdin şəhərlərində toplaşıblar. Etirazçılar ABŞ liderinə qarşı şüarlar yazılmış plakatlarla yanaşı, əllərində Fələstin bayraqları da tutub və Qəzza zolağının azad edilməsini tələb ediblər.\n\nXatırladaq ki, Tramp iyulun 25-də Şotlandiyaya gedib. Ağ Ev rəhbəri orada iyulun 29-dək qalmaq niyyətindədir.\n\nAğ Ev daha əvvəl bildirib ki, Tramp ticarət razılaşmasını müzakirə etmək üçün Şotlandiyada Böyük Britaniyanın Baş naziri Kir Starmerlə görüşməyi planlaşdırır.",
    "gold_entities": {
      "persons": [
        "Donald Tramp",
        "Kir Starmer"
      ],
      "organizations": [
        "Report",
        "The Independent",
        "Ağ Ev"
      ],
      "locations": [
        "Şotlandiya",
        "Edinburq",
        "Aberdin",
        "ABŞ",
        "Fələstin",
        "Qəzza zolağı",
        "Böyük Britaniya"
      ],
      "positions": [
        "ABŞ Prezidenti",
        "Böyük Britaniyanın Baş naziri"
      ],
      "dates": [
        "iyulun 25-də",
        "iyulun 29-dək"
      ]
    },
    "manually_verified": true,
    "annotator_notes": ""
  },
  {
    "article_id": "3240",
    "source": "report.az",
    "link": "https://report.az/futbol-xeberleri/kopenhagen-in-bas-mesqcisi-qarabag-qelebeye-layiq-idi",
    "pub_date": "2025-10-01 23:27:00.000",
    "title": "\"Kopenhagen\"in baş məşqçisi: \"Qarabağ\" qələbəyə layiq idi\"",
    "content": "\"Qarabağ\" \"Kopenhagen\"lə oyunda qələbəyə layiq idi.\n\n\"Report\"un məlumatına görə, bunu Danimarkanın \"Kopenhagen\" komandasının baş məşqçisi Yakob Neestrup mətbuat konfransında deyib.\n\nMütəxəssis Bakıda \"Qarabağ\"a uduzduqları (0:2) UEFA Çempionlar Liqasının əsas mərhələsinin II turunun oyunu ilə bağlı fikirlərini bölüşüb:\n\n\"Rəqibin güclü olduğunu bilirdik. Birinci hissədə onlar mükəmməl oynadılar. İkinci yarıda çox dəyişiklik etdik. Aktiv oyun sərgilədik. İmkanları dəyərləndirə bilmədik. \"Qarabağ\" qələbəyə layiq idi\".\n\nO, bütün rəqiblərə hörmət etdiklərini söyləyib:\n\n\"Qarabağ\" təcrübəli kollektivdir. Mükəmməl oyunçuları var. Baş məşqçiləri Qurban Qurbanovu da xüsusi qeyd etməliyəm\".",
    "gold_entities": {
      "persons": [
        "Yakob Neestrup",
        "Qurban Qurbanov"
      ],
      "organizations": [
        "Report",
        "Qarabağ",
        "Kopenhagen",
        "UEFA Çempionlar Liqası"
      ],
      "locations": [
        "Danimarka",
        "Bakı"
      ],
      "positions": [
        "baş məşqçi"
      ],
      "dates": []
    },
    "manually_verified": true,
    "annotator_notes": ""
  },
  {
    "article_id": "2800",
    "source": "report.az",
    "link": "https://report.az/ferdi/azerbaycan-gulescisi-dunya-cempionati-menim-ucun-cox-ugurlu-alindi",
    "pub_date": "2025-08-25 22:33:00.000",
    "title": "Dünya çempionu olan Azərbaycan güləşçisi: \"Yarış mənim üçün çox uğurlu alındı\"",
    "content": "Bolqarıstanın Samokov şəhərində keçirilən U-20 dünya çempionatı Azərbaycanın yunan-Roma güləşçisi Ayxan Cavadov (60 kq) üçün olduqca uğurlu alınıb.\n\nBunu\"Report\"a açıqlamasında idmançı özü deyib.\n\nO, qazanılan nəticəyə görə Azərbaycan Güləş Federasiyasının rəhbərliyinə təşəkkür edib:\n\n\"Məni yarışa hazırlayan məşqçiləri unutmamalıyıq. Onların bu işdə zəhmətləri böyükdür. Bu dünya çempionatı mənim üçün çox uğurlu alındı. Hələ ki, bir müddət öz çəkimdə mübarizə aparmağı düşünürəm. Ümid edirəm ki, qarşıdakı yarışlarda da öz nəticələrimlə Azərbaycan xalqını sevindirəcəyəm\".\n\nQeyd edək ki, Ayxan Cavadov həlledici görüşdə ermənistanlı Yurik Mxitaryana 12:5 hesabı ilə qalib gələrək fəxri kürsüyə yüksəlib.",
    "gold_entities": {
      "persons": [
        "Ayxan Cavadov",
        "Yurik Mxitaryan"
      ],
      "organizations": [
        "Report",
        "Azərbaycan Güləş Federasiyası",
        "U-20 dünya çempionatı"
      ],
      "locations": [
        "Bolqarıstan",
        "Samokov",
        "Azərbaycan",
        "Ermənistan"
      ],
      "positions": [
        "güləşçi",
        "idmançı"
      ],
      "dates": []
    },
    "manually_verified": true,
    "annotator_notes": ""
  },
  {
    "article_id": "1861",
    "source": "report.az",
    "link": "https://report.az/diger-olkeler/qezzada-humanitar-yardim-menteqesi-atese-tutulub-olen-ve-xesaret-alanlar-var",
    "pub_date": "2025-06-08 22:16:00.000",
    "title": "Qəzzada humanitar yardım məntəqəsi atəşə tutulub, ölən və xəsarət alanlar var",
    "content": "İsrailin Qəzza zolağının cənubundakı Rəfah şəhərində humanitar yardım məntəqəsini atəşə tutması nəticəsində 11 nəfər ölüb, 125 nəfər yaralanıb.\n\n\"Report\"xəbər verir ki, bu barədə Fələstinin \"Al-Aqsa\" telekanalı məlumat yayıb.\n\nMay ayında İsrail hakimiyyəti hərbi əməliyyatların əhəmiyyətli dərəcədə artması fonunda Qəzza zolağının sakinlərinə humanitar yardımın çatdırılması üçün yeni planı elan edib. Plana əsasən, yardım üzvləri əvvəllər humanitar ləvazimatları talamaqda ittiham edilən HƏMAS hərəkatının mövcudluğundan təmizlənmiş ərazilərə paylanır.\n\nHƏMAS isə bildirib ki, İsrailin Qəzza zolağında humanitar yardımın paylanması üçün yaratdığı mexanizm iflasa uğrayıb və “mülki əhalini təhlükəyə atan tələyə” çevrilib.",
    "gold_entities": {
      "persons": [],
      "organizations": [
        "Report",
        "Al-Aqsa telekanalı",
        "HƏMAS"
      ],
      "locations": [
        "Qəzza zolağı",
        "Rəfah",
        "İsrail",
        "Fələstin"
      ],
      "positions": [],
      "dates": [
        "May ayında"
      ]
    },
    "manually_verified": true,
    "annotator_notes": ""
  },
  {
    "article_id": "121",
    "source": "report.az",
    "link": "https://report.az/region-xeberleri/erdogan-azerbaycana-yeni-sefir-teyin-edib",
    "pub_date": "2025-01-10 23:55:00.000",
    "title": "Ərdoğan Azərbaycana yeni səfir təyin edib",
    "content": "Türkiyə Prezidenti Rəcəb Tayyib Ərdoğanın qərarına əsasən Birol Akgün qardaş ölkənin Azərbaycandakı fövqəladə və səlahiyyətli səfiri təyin edilib.\n\n“Report”xəbər verir ki, dövlət başçısının qərarı “Rəsmi qəzet”də dərc olunub.\n\nBirol Akgün bundan öncə Türkiyə Maarif Fondunun sədri olub.\n\nPrezidentin qərarına görə əsasən xarici işlər nazirinin müavini və Türkiyənin bir sıra ölkələrdəki səfirliklərinə də təyinatlar olub. Belə ki, Zeki Levent Gümrükçü xarici işlər nazirinin müavini təyin edilib. Eyni zamanda Ferhat Alkan Türkiyənin Mozambik Respublikasında səfiri, Prezidentin baş müşaviri Yakup Caymazoğlu isə İordaniya Haşimilər Krallığında səfir təyin olunublar. Eyni zamanda dövlət başçısı Kuba və BƏƏ-yə də yeni səfirlər təyin edib.",
    "gold_entities": {
      "persons": [
        "Rəcəb Tayyib Ərdoğan",
        "Birol Akgün",
        "Zeki Levent Gümrükçü",
        "Ferhat Alkan",
        "Yakup Caymazoğlu"
      ],
      "organizations": [
        "Report",
        "Rəsmi qəzet",
        "Türkiyə Maarif Fondu",
        "Türkiyə Xarici İşlər Nazirliyi"
      ],
      "locations": [
        "Türkiyə",
        "Azərbaycan",
        "Mozambik",
        "İordaniya",
        "Kuba",
        "BƏƏ"
      ],
      "positions": [
        "Türkiyə Prezidenti",
        "fövqəladə və səlahiyyətli səfir",
        "Türkiyə Maarif Fondunun sədri",
        "xarici işlər nazirinin müavini",
        "Prezidentin baş müşaviri",
        "səfir"
      ],
      "dates": []
    },
    "manually_verified": true,
    "annotator_notes": ""
  },
  {
    "article_id": "700",
    "source": "report.az",
    "link": "https://report.az/region-xeberleri/turkiye-prezidenti-receb-tayyib-erdogan-avropaya-xeberdarliq-edib",
    "pub_date": "2025-03-03 22:03:00.000",
    "title": "Ərdoğan Avropaya xəbərdarlıq edib",
    "content": "Türkiyə Prezidenti Rəcəb Tayyib Ərdoğan Avropaya xəbərdarlıq edib.\n\n“Report” xəbər verir ki, o, bu barədə səfirlərlə iftar proqramında çıxışı zamanı deyib.\n\nÖlkə lideri qeyd edib ki, Türkiyənin Avropa İttifaqına üzvlük prosesi strateji prioritetdir: “Avropanın təhlükəsizliyi Türkiyəsiz mümkün deyil. Türkiyənin layiq olmadığı Avropanın qlobal aktor olaraq mövcudluğunu davam etdirməsi getdikcə mümkünsüz hala çevrilir”.\n\nOnun sözlərinə görə, bu gün dünyada “meşə qanunları” hökm sürür: “Təəssüf ki, güclü olanların zəifləri əzməsi nəticəsində yeni problemlər meydana çıxır. Bunun qarşısı alınmasa, hərbi və siyasi partlayışlar ola bilər. Problemlərin həllini zamana buraxaraq, gözlərimizi yumaraq, təhlükələrə laqeyd yanaşaraq heç bir yerə çıxa bilmərik”.",
    "gold_entities": {
      "persons": [
        "Rəcəb Tayyib Ərdoğan"
      ],
      "organizations": [
        "Report",
        "Avropa İttifaqı"
      ],
      "locations": [
        "Türkiyə",
        "Avropa"
      ],
      "positions": [
        "Türkiyə Prezidenti"
      ],
      "dates": []
    },
    "manually_verified": true,
    "annotator_notes": ""
  },
  {
    "article_id": "1278",
    "source": "report.az",
    "link": "https://report.az/futbol-xeberleri/premyer-liqa-xxxi-turun-sonuncu-oyununda-zire-qelebe-qazanib",
    "pub_date": "2025-04-20 20:53:00.000",
    "title": "Premyer Liqa: XXXI turun sonuncu oyununda \"Zirə\" qələbə qazanıb",
    "content": "Misli Premyer Liqasında XXXI tur başa çatıb.\n\n\"Report\"un məlumatına görə, sonuncu matçda \"Zirə\" \"Sumqayıt\"ı qəbul edib.\n\nQarşılaşma Bakı klubunun qələbəsi ilə yekunlaşıb - 3:1.\n\nMeydan sahiblərinin heyətində 6-cı dəqiqədə Giorgi Papunaşvili, 45+1-ci dəqiqədə Martins Junior, 89-cu dəqiqə Salifu Suma fərqləniblər. Qonaqlarda Bobur Abdixolikov 52-ci dəqiqədə adını tabloya yazdırıb.\n\nBu nəticədən sonra xallarının sayını 61-ə çatdıran \"Zirə\" ikinci pillədə qərarlaşıb. \"Gənclik şəhəri\" təmsilçisi 29 xalla səkkizinci sıradadır.\n\nGünün ilk matçında \"Şamaxı\" evdə \"Kəpəz\"i məğlub edib - 2:1.\n\nQeyd edək ki, turun əvvəlki oyunlarında \"Qarabağ\" \"Neftçi\"ni 3:0, \"Sabah\" \"Səbail\"i 3:2 hesabı ilə üstələyib. \"Araz-Naxçıvan\" - \"Turan Tovuz\" görüşündə isə qalib müəyyənləşməyib - 1:1.",
    "gold_entities": {
      "persons": [
        "Giorgi Papunaşvili",
        "Martins Junior",
        "Salifu Suma",
        "Bobur Abdixolikov"
      ],
      "organizations": [
        "Report",
        "Misli Premyer Liqası",
        "Zirə",
        "Sumqayıt",
        "Şamaxı",
        "Kəpəz",
        "Qarabağ",
        "Neftçi",
        "Sabah",
        "Səbail",
        "Araz-Naxçıvan",
        "Turan Tovuz"
      ],
      "locations": [
        "Bakı",
        "Azərbaycan"
      ],
      "positions": [],
      "dates": []
    },
    "manually_verified": true,
    "annotator_notes": ""
  },
  {
    "article_id": "543",
    "source": "report.az",
    "link": "https://report.az/diger-olkeler/konqoda-kilsede-70-den-cox-qacirilmis-insanin-meyiti-askarlanib",
    "pub_date": "2025-02-15 23:01:00.000",
    "title": "Konqoda kilsədə 70-dən çox qaçırılmış insanın meyiti aşkarlanıb",
    "content": "Konqo Demokratik Respublikasının (KDR) şərqində, Şimali Kivu əyalətinin Mayba kəndindəki kilsədə 70-dən çox başı kəsilmiş meyit aşkar edilib.\n\n“Report” xəbər verir ki, bu barədə ölkənin “Okapi” radiostansiyası məlumat yayıb.\n\nQeyd olunub ki, söhbət üç gün əvvəl Lubero rayonunda yaraqlılar tərəfindən qaçırılmış şəxslərdən gedir. Radiostansiyanın məlumatına görə, öldürülənlər arasında qadınlar, uşaqlar və yaşlı insanlar var.\n\nHakimiyyət orqanları qətllərdə “Demokratik Qüvvələr İttifaqı” (DQİ) ekstremist qruplaşmasının döyüşçülərinin əli olduğunu düşünür. Bu qruplaşma 1995-ci ildə Uqandada yaradılıb. 2003-cü ildə Uqanda silahlı qüvvələrinin zərbələri altında DQİ dəstələri geri çəkilərək KDR-in şərq bölgələrində gizləniblər və burada hərbi və mülki obyektlərə mütəmadi hücumlar edirlər.",
    "gold_entities": {
      "persons": [],
      "organizations": [
        "Report",
        "Okapi radiostansiyası",
        "Demokratik Qüvvələr İttifaqı (DQİ)",
        "Uqanda silahlı qüvvələri"
      ],
      "locations": [
        "Konqo Demokratik Respublikası (KDR)",
        "Şimali Kivu",
        "Mayba",
        "Lubero",
        "Uqanda"
      ],
      "positions": [],
      "dates": [
        "üç gün əvvəl",
        "1995-ci ildə",
        "2003-cü ildə"
      ]
    },
    "manually_verified": true,
    "annotator_notes": ""
  },
  {
    "article_id": "956",
    "source": "report.az",
    "link": "https://report.az/diger-olkeler/zelenski-abs-er-riyaddaki-razilasmalarin-monitorinqini-oz-uzerine-goturecek",
    "pub_date": "2025-03-25 23:50:00.000",
    "title": "ABŞ Ər-Riyaddakı razılaşmaların monitorinqini öz üzərinə götürəcək",
    "content": "Vaşinqton Ukrayna və ABŞ nümayəndə heyətləri arasında Səudiyyə Ərəbistanında aparılan danışıqlarda əldə olunmuş razılaşmaların yerinə yetirilməsinə nəzarət edəcək. Prosesə üçüncü dövlətlər də cəlb oluna bilər.\n\n\"Report\"un məlumatına görə, bunu Ukrayna Prezidenti Volodimir Zelenski jurnalistlərə açıqlamasında deyib.\n\n\"Biz başa düşürük ki, faktiki olaraq bizim razılaşmalarımız ABŞ ilədir. Onlar monitorinq üçün əsas məsul olanlardır. Üçüncü ölkələrin cəlb olunması məsələsini ABŞ gündəmə gətirir. Bu, əgər dənizdən danışırıqsa, Türkiyə, enerjidən danışırıqsa, Səudiyyə Ərəbistanı ola bilər. Hələlik bu, müzakirə səviyyəsindədir\", - Zelenski bildirib.\n\nOnun sözlərinə görə, Ər-Riyadda danışıqlar zamanı tərəflər Qara dənizdə atəşkəs və enerji infrastrukturuna hücumların qadağan edilməsi barədə razılığa gəliblər.",
    "gold_entities": {
      "persons": [
        "Volodimir Zelenski"
      ],
      "organizations": [
        "Report"
      ],
      "locations": [
        "Vaşinqton",
        "ABŞ",
        "Ukrayna",
        "Səudiyyə Ərəbistanı",
        "Ər-Riyad",
        "Qara dəniz",
        "Türkiyə"
      ],
      "positions": [
        "Ukrayna Prezidenti"
      ],
      "dates": []
    },
    "manually_verified": true,
    "annotator_notes": ""
  },
  {
    "article_id": "4036",
    "source": "report.az",
    "link": "https://report.az/region-xeberleri/lasa-maqradze-bbc-gurcustana-qarsi-meqsedyonlu-dezinformasiya-yayir",
    "pub_date": "2025-12-06 15:40:00.000",
    "title": "Laşa Maqradze: BBC Gürcüstana qarşı məqsədyönlü dezinformasiya yayır",
    "content": "BBC telekanalının Tbilisidə ötən ilin sonunda etirazçılara qarşı kimyəvi silahın tətbiq edilməsi barədə bəyanatı dezinformasiyadır.\n\n\"Report\"un Gürcüstan KİV-ə istinadən verdiyi məlumata görə, bunu ölkənin Dövlət Təhlükəsizlik Xidməti rəhbərinin müavini Laşa Maqradze brifinqdə bildirib.\n\n\"Araşdırma zamanı əldə edilən məlumatlar bizə birmənalı sübut edir ki, BBC-nin filmində Gürcüstanda etirazçılara qarşı \"Kamit\" adlı zəhərli maddənin istifadə edilməsi haqqında səsləndirilən məlumat məqsədyönlü dezinformasiyadır və Gürcüstanın maraqlarına zərər vurmaq məqsədi daşıyır\", - o qeyd edib.\n\nBu həftənin əvvəlində Gürcüstanın Baş naziri İrakli Kobaxidze jurnalistlərə bildirib ki, BBC Tbilisidəki nümayişçilərə qarşı Birinci Dünya müharibəsindən qalmış \"Kamit\" adlı kimyəvi maddənin tətbiq edilməsi barədə açıq şəkildə yalan məlumat yayıb.",
    "gold_entities": {
      "persons": [
        "Laşa Maqradze",
        "İrakli Kobaxidze"
      ],
      "organizations": [
        "BBC",
        "Report",
        "Gürcüstanın Dövlət Təhlükəsizlik Xidməti"
      ],
      "locations": [
        "Tbilisi",
        "Gürcüstan"
      ],
      "positions": [
        "Dövlət Təhlükəsizlik Xidməti rəhbərinin müavini",
        "Gürcüstanın Baş naziri"
      ],
      "dates": [
        "ötən ilin sonunda",
        "Bu həftənin əvvəlində"
      ]
    },
    "manually_verified": true,
    "annotator_notes": ""
  },
  {
    "article_id": "2004",
    "source": "report.az",
    "link": "https://report.az/diger-olkeler/abs-cine-cip-istehsalat-avadanliqlarinin-techizatini-qadagan-ede-biler",
    "pub_date": "2025-06-20 23:00:00.000",
    "title": "ABŞ Çinə çip istehsalat avadanlıqlarının təchizatını qadağan edə bilər",
    "content": "ABŞ hakimiyyəti böyük yarımkeçirici istehsalçılarına xəbərdarlıq edib ki, onlar ölkə istehsalı olan avadanlıqların Çindəki fabriklərə tədarükü üçün verilən icazələri ləğv etməyi düşünürlər.\n\n\"Report\"xəbər verir ki, bu barədə mənbələrə istinadən \"The Wall Street Journal\" (WSJ) məlumat yayıb.\n\nQeyd olunub ki, ABŞ Ticarət Nazirliyinin Sənaye və Təhlükəsizlik Bürosunun rəhbəri Ceffri Kessler şirkətlərə ABŞ-nin icazələri ləğv etmək istədiyini bildirib.\n\nHazırda \"Samsung Electronics\" və \"SK Hynix\", eləcə də \"TSMC\" indi hər bir iş üçün ayrıca lisenziya almadan Çindəki fabriklərinə ABŞ avadanlığı təqdim edə bilir.\n\nNəşr bildirib ki, sözügedən planlar həyata keçirilərsə, bu, diplomatik və iqtisadi nəticələrə gətirib çıxara bilər. Qəzetin yazdığına görə, Pekin bunu Londonda aparılan danışıqlar zamanı əldə olunmuş razılaşmaların pozulması kimi şərh edə bilər.",
    "gold_entities": {
      "persons": [
        "Ceffri Kessler"
      ],
      "organizations": [
        "Report",
        "The Wall Street Journal (WSJ)",
        "ABŞ Ticarət Nazirliyi",
        "Sənaye və Təhlükəsizlik Bürosu",
        "Samsung Electronics",
        "SK Hynix",
        "TSMC"
      ],
      "locations": [
        "ABŞ",
        "Çin",
        "London",
        "Pekin"
      ],
      "positions": [
        "ABŞ Ticarət Nazirliyinin Sənaye və Təhlükəsizlik Bürosunun rəhbəri"
      ],
      "dates": []
    },
    "manually_verified": true,
    "annotator_notes": ""
  },
  {
    "article_id": "3216",
    "source": "report.az",
    "link": "https://report.az/diger-olkeler/madaqaskarda-kutlevi-igtisaslar-zamani-22-nefer-olub",
    "pub_date": "2025-09-29 23:03:00.000",
    "title": "Madaqaskarda kütləvi iğtişaşlar zamanı 22 nəfər ölüb",
    "content": "Madaqaskarda iğtişaşlar zamanı azı 22 nəfər ölüb, 100-dən çox adam yaralanıb.\n\n\"Report\"xəbər verir ki, bu barədə BMT-nin insan haqları üzrə ali komissarı Volker Türk mənbəni açıqlamadan bildirib.\n\n\"Azı 22 nəfər ölüb, 100-dən çox insan yaralanıb. Həlak olanlar arasında təhlükəsizlik qüvvələrinin əməkdaşları tərəfindən öldürülən etirazçılar və ətrafdakılar, habelə iğtişaşlar və qarətlər zamanı həlak olanlar var\", - təşkilatın saytında bildirilib.\n\nXatırladaq ki, sentyabrın 25-də Madaqaskarda elektrik enerjisinin və suyun kəsilməsinə qarşı nümayişlər başlayıb və iğtişaşlara çevrilib. İğtişaşlar bu günə qədər fasilələrlə davam edir. Vəziyyəti sakitləşdirmək üçün yaradılmış Baş nazir Kristian Ntsayın sədrlik etdiyi Milli Konfransın müştərək orqanı sentyabrın 29-da Madaqaskar Universitetinin kampusunda dinc etirazçılar arasında silahlı şəxslərin də olduğu barədə bəyanat yayıb.",
    "gold_entities": {
      "persons": [
        "Volker Türk",
        "Kristian Ntsay"
      ],
      "organizations": [
        "Report",
        "BMT",
        "Madaqaskar Universiteti",
        "Milli Konfrans"
      ],
      "locations": [
        "Madaqaskar"
      ],
      "positions": [
        "BMT-nin insan haqları üzrə ali komissarı",
        "Baş nazir"
      ],
      "dates": [
        "sentyabrın 25-də",
        "sentyabrın 29-da"
      ]
    },
    "manually_verified": true,
    "annotator_notes": ""
  },
  {
    "article_id": "1216",
    "source": "report.az",
    "link": "https://report.az/diger-olkeler/mark-rutte-ukraynaya-planlasdirilmamis-sefer-edib",
    "pub_date": "2025-04-15 22:31:00.000",
    "title": "Mark Rutte Ukraynaya planlaşdırılmamış səfər edib",
    "content": "NATO-nun Baş katibi Mark Rutte aprelin 15-də planlaşdırılmamış səfərlə Ukraynaya gedib.\n\n“Report”“RBK-Ukrayna”ya istinadən xəbər verir ki, bu barədə Ukrayna Prezidenti Volodimir Zelenski və Ruttenin özü sosial şəbəkələrdə bildiriblər.\n\nRutte qeyd edib ki, Zelenski ilə birlikdə Odessa şəhərinə səfər edib.\n\n“Ukrayna xalqı çox şey yaşayıb. NATO-nun dəstəyi sarsılmazdır. Biz Ukraynaya kömək etməyə davam edəcəyik ki, bu gün özünü müdafiə edə və gələcək təcavüzün qarşısını ala bilsin, ədalətli və davamlı sülhü təmin etsin”, - o \"X\"də yazıb.\n\nEyni zamanda, Zelenski NATO Baş katibi ilə birlikdə ukraynalı hərbçilərin yaralandıqdan sonra bərpa prosesi keçdiyi xəstəxanaya baş çəkdiyi videonu paylaşıb.\n\n“Hərbi həkimləri də mükafatlandırdım. Onlar nəinki hər gün xəstəxanada əsgərlərimizə kömək edir, həm də Xerson, Xarkov və Nikolayev vilayətlərində atəş altında insanların həyatını xilas ediblər”, - Zelenski yazıb.",
    "gold_entities": {
      "persons": [
        "Mark Rutte",
        "Volodimir Zelenski"
      ],
      "organizations": [
        "Report",
        "NATO",
        "RBK-Ukrayna",
        "X"
      ],
      "locations": [
        "Ukrayna",
        "Odessa",
        "Xerson",
        "Xarkov",
        "Nikolayev"
      ],
      "positions": [
        "NATO-nun Baş katibi",
        "Ukrayna Prezidenti"
      ],
      "dates": [
        "aprelin 15-də"
      ]
    },
    "manually_verified": true,
    "annotator_notes": ""
  },
  {
    "article_id": "2955",
    "source": "report.az",
    "link": "https://report.az/hadise/semkirde-tecili-yardim-masini-korpuden-asib-xesaret-alanlar-var",
    "pub_date": "2025-09-07 21:54:00.000",
    "title": "Şəmkirdə ambulansın qəzaya uğraması nəticəsində xəsarət alanların vəziyyətləri açıqlanıb - YENİLƏNİB",
    "content": "Şəmkir rayon ərazisində təcili tibbi yardım maşınının qəzaya uğraması nəticəsində xəsarət alanların vəziyyətləri açıqlanıb.\n\n\"Report\"un Qərb bürosunun məlumatına görə, Şəmkir rayonunda \"Mersedes\" markalı avtomobillə ambulansın toqquşması nəticəsində tibb bacısı T. Ağayeva, təcili tibbi yardım avtomobilinin sürücüsü B.Əliyev və minik maşınının sürücüsü İ.Əliyev müxtəlif xəsarətlərlə Şəmkir rayon Mərkəzi Xəstəxanasına çatdırılıblar. Onlara ilkin yardım göstərildikdən sonra ambulator müalicə üçün evə buraxılıblar.\n\nQeyd edək ki, qəza nəticəsində həkimin xəsarət almadığı bildirilir.\n\nFaktla bağlı araşdırma aparılır.\n\n18:00\n\nŞəmkir rayon ərazisində təcili tibbi yardım maşını qəzaya uğrayıb.\n\n\"Report\"un Qərb bürosunun məlumatına görə, Kür qəsəbəsinə çağırışa gedən ambulans körpü üzərində idarəetmədən çıxaraq digər avtomobilə arxadan çırpılıb.\n\nQəza nəticəsində sürücü, həkim və tibb bacısı xəsarət alıb.\n\nFaktla bağlı araşdırma aparılır.",
    "gold_entities": {
      "persons": [
        "T. Ağayeva",
        "B.Əliyev",
        "İ.Əliyev"
      ],
      "organizations": [
        "Report",
        "Şəmkir rayon Mərkəzi Xəstəxanası"
      ],
      "locations": [
        "Şəmkir",
        "Şəmkir rayonu",
        "Kür qəsəbəsi"
      ],
      "positions": [
        "tibb bacısı",
        "təcili tibbi yardım avtomobilinin sürücüsü",
        "minik maşınının sürücüsü",
        "həkim"
      ],
      "dates": []
    },
    "manually_verified": true,
    "annotator_notes": ""
  },
  {
    "article_id": "2808",
    "source": "report.az",
    "link": "https://report.az/diger-olkeler/kiv-iran-ve-avropa-ucluyunun-cenevredeki-bugunku-gorusu-neticesiz-qalib",
    "pub_date": "2025-08-26 23:20:00.000",
    "title": "KİV: İran və \"Avropa Üçlüyü\"nün Cenevrədəki bugünkü görüşü nəticəsiz qalıb",
    "content": "İran və \"Avropa Üçlüyü\" nümayəndələrinin bu axşam Cenevrədəki görüşü nəzərəçarpacaq irəliləyiş olmadan baş tutub.\n\n\"Report\"xəbər verir ki, bu barədə \"Axios\"un jurnalisti Barak Devid \"X\" sosial şəbəkəsində yazıb.\n\nQeyd olunur ki, bu, Avropa güclərinin İranın nüvə proqramı ilə bağlı müəyyən etdiyi müddətə 5 gün qalmış baş verib.\n\nMənbələrin bildirdiyinə görə, İran tərəfi tələblərin yerinə yetirilməsi üçün konkret addımlar təklif etməyib: ABŞ ilə danışıqların bərpası, BMT müfəttişlərinin İsrailin hücumları nəticəsində zədələnmiş nüvə obyektlərinə çıxışının təmin edilməsi və İranda qalan 60 % zənginləşdirilmiş uran ehtiyatları.\n\n\"Axios\"un fikrincə, irəliləyişin olmaması tələblərin avqustun 31-dək yerinə yetirilməyəcəyi təqdirdə Avropa ölkələrinin \"Snapback\" mexanizmini işə salması ehtimalını xeyli artırır.\n\n\"Snapback\" 2015-ci il nüvə sazişinin bir hissəsi olan hüquqi mexanizmdir və sazişi pozarsa, BMT Təhlükəsizlik Şurasının İrana qarşı sanksiyalarına səbəb olur.",
    "gold_entities": {
      "persons": [
        "Barak Devid"
      ],
      "organizations": [
        "Report",
        "Axios",
        "X",
        "Avropa Üçlüyü",
        "BMT",
        "BMT Təhlükəsizlik Şurası",
        "Snapback"
      ],
      "locations": [
        "İran",
        "Cenevrə",
        "ABŞ",
        "İsrail"
      ],
      "positions": [
        "jurnalist"
      ],
      "dates": [
        "bu axşam",
        "avqustun 31-dək",
        "2015-ci il"
      ]
    },
    "manually_verified": true,
    "annotator_notes": ""
  },
  {
    "article_id": "2336",
    "source": "report.az",
    "link": "https://report.az/region-xeberleri/gurcustanda-qetl-hadisesi-bas-verib-iki-turkiye-vetendasi-saxlanilib",
    "pub_date": "2025-07-18 23:51:00.000",
    "title": "Gürcüstanda qətl hadisəsinə görə Türkiyə vətəndaşları saxlanılıb",
    "content": "Gürcüstanın Daxili İşlər Nazirliyi Batumi şəhərində baş verən qətllə bağlı Türkiyə vətəndaşlarının saxlanıldığını açıqlayıb.\n\n“Report”un yerli bürosu xəbər verir ki, nazirliyin yaydığı rəsmi məlumata görə, əməliyyat-axtarış tədbirləri nəticəsində Acarıstan Polis Şöbəsinin əməkdaşları 2003-cü il təvəllüdlü A.E. və 1998-ci il təvəllüdlü M.J-ni saxlayıb. Onlar odlu silahdan istifadə etməklə adam öldürməkdə və odlu silahı qanunsuz əldə edib saxlamaqda şübhəli bilinir.\n\nMəlumata əsasən, A.E. odlu silahla qətlə yetirdiyi şəxsi hadisə yerində tərk edərək qaçıb. Hadisənin şahidi olan M.J. isə cinayət barədə hüquq-mühafizə orqanlarına məlumat verməyib. İstintaq çərçivəsində hər iki şəxs barəsində təqsirləndirilən şəxs qismində həbs tədbiri görülüb.\n\nFaktla bağlı Cinayət Məcəlləsinin bir neçə maddəsi üzrə – 108 (qəsdən adam öldürmə), 236 (qanunsuz odlu silah əldə etmə və saxlama), 376 (ağır cinayət haqqında məlumat verməmə) və 344-cü (dövlət sərhədini qanunsuz keçmə) maddələri ilə istintaq aparılır.",
    "gold_entities": {
      "persons": [
        "A.E.",
        "M.J."
      ],
      "organizations": [
        "Report",
        "Gürcüstanın Daxili İşlər Nazirliyi",
        "Acarıstan Polis Şöbəsi",
        "Cinayət Məcəlləsi",
        "hüquq-mühafizə orqanları"
      ],
      "locations": [
        "Gürcüstan",
        "Batumi",
        "Acarıstan",
        "Türkiyə"
      ],
      "positions": [],
      "dates": [
        "2003-cü il",
        "1998-ci il"
      ]
    },
    "manually_verified": true,
    "annotator_notes": ""
  },
  {
    "article_id": "719",
    "source": "report.az",
    "link": "https://report.az/xarici-siyaset/erdogan-ilham-eliyevle-gorusunun-teessuratlarini-paylasib-regionumuzda-sadece-sulh-isteyirik",
    "pub_date": "2025-03-05 23:11:00.000",
    "title": "Ərdoğan İlham Əliyevlə görüşünün təəssüratlarını paylaşıb: Regionumuzda sadəcə sülh istəyirik",
    "content": "Türkiyə Prezidenti Rəcəb Tayyib Ərdoğan Azərbaycanın dövlət başçısı İlham Əliyevlə görüşünün təəssüratlarını paylaşıb.\n\n“Report”xəbər verir ki, bu barədə Türkiyə lideri sosial şəbəkədəpaylaşımedib.\n\n“Qardaşım, Azərbaycan Prezidenti cənab İlham Əliyevi Türkiyədə qonaq etməkdən çox məmnun oldum. “Bir millət – iki dövlət” şüarı ilə təcəssüm olunan qardaşlıq münasibətlərimizdə hər sahədə böyük irəliləyişlər əldə edirik. Ölkələrimiz arasında əlaqələr müdafiədən tutmuş ticarətə qədər bir çox sahələrdə daim inkişaf edir”, – Türkiyənin ölkə başçısı qeyd edib. O, bu əməkdaşlıqlar arasında enerji sektorunun ön sırada olduğunu da vurğulayıb.\n\nƏrdoğan Bakı və Ankaranın sadəcə sülh, əməkdaşlıq istədiyini vurğulayıb:\n\n“Bunu ifadə etmək istərdim: Türkiyə və Azərbaycan sülhün, əmin-amanlığın, firavanlığın tərəfindədir. Regionumuzda sadəcə sülh istəyirik, əməkdaşlıq istəyirik, birlikdə inkişaf etmək istəyirik. İnşallah, bundan sonra regional sülhə, rifaha və əmin-amanlığa yönəlmiş hər cür layihələri birlikdə həyata keçirmək əzmindəyik”.",
    "gold_entities": {
      "persons": [
        "Rəcəb Tayyib Ərdoğan",
        "İlham Əliyev"
      ],
      "organizations": [
        "Report"
      ],
      "locations": [
        "Türkiyə",
        "Azərbaycan",
        "Bakı",
        "Ankara"
      ],
      "positions": [
        "Türkiyə Prezidenti",
        "Azərbaycan Prezidenti"
      ],
      "dates": []
    },
    "manually_verified": true,
    "annotator_notes": ""
  },
  {
    "article_id": "3699",
    "source": "report.az",
    "link": "https://report.az/diger-olkeler/robert-fico-si-cinpinin-slovakiyaya-sefer-edeceyini-bildirib",
    "pub_date": "2025-11-08 22:56:00.000",
    "title": "Robert Fitso: Si Cinpin, Fridrix Merts və Mark Rutte Slovakiyaya səfər edəcək",
    "content": "Slovakiya Çin Sədri Si Cinpinin səfərini gözləyir.\n\n\"Report\"Slovakiyanın \"Pravda\" portalına istinadən xəbər verir ki, bu barədə Slovakiyanın Baş naziri Robert Fitso bildirib.\n\nLakin o, səfərin dəqiq tarixini açıqlamayıb.\n\nFitso, həmçinin qeyd edib ki, Almaniya kansleri Fridrix Merts və NATO-nun baş katibi Mark Ruttenin yaxın gələcəkdə Slovakiyaya səfərləri planlaşdırılır.\n\n\"Biz kansler Mertslə onun yaxın gələcəkdə Slovakiyaya səfəri barədə açıq razılığa gəlmişik. Düşünürəm ki, baş katib Mark Rutte də noyabrın 18-də burada olacaq və sonra mən Brüsselə gedəcəyəm\", - o deyib.\n\nFitso jurnalistlərlə söhbətində həmçinin Rusiyanın dondurulmuş aktivlərinin 140 milyard avroluq hissəsinin Ukraynanın yenidən qurulması və ya yardımı üçün istifadə edilməsi məsələsinə toxunub. Slovakiya hökumətinin başçısı bu aktivlərin Kiyev üçün müdafiə avadanlığı məqsədilə istifadəsi ideyasını dəstəkləməyib.\n\n\"Yəqin ki, silah və hərbi xərclərə 140 milyard avro xərcləsək, bunun heç vaxt geri qaytarılmayacağı qənaətinə gələcəyik. Slovakiya hərbi xərclərdə iştirak edə bilməz\", - o deyib.",
    "gold_entities": {
      "persons": [
        "Robert Fitso",
        "Si Cinpin",
        "Fridrix Merts",
        "Mark Rutte"
      ],
      "organizations": [
        "Report",
        "Pravda",
        "NATO"
      ],
      "locations": [
        "Slovakiya",
        "Çin",
        "Almaniya",
        "Brüssel",
        "Rusiya",
        "Ukrayna",
        "Kiyev"
      ],
      "positions": [
        "Slovakiyanın Baş naziri",
        "Çin Sədri",
        "Almaniya kansleri",
        "NATO-nun baş katibi"
      ],
      "dates": [
        "noyabrın 18-də",
        "yaxın gələcəkdə"
      ]
    },
    "manually_verified": true,
    "annotator_notes": ""
  },
  {
    "article_id": "1514",
    "source": "report.az",
    "link": "https://report.az/region-xeberleri/makron-qerbden-kiyeve-yardimin-ateskes-halinda-da-davam-edeceyini-aciqlayib",
    "pub_date": "2025-05-10 22:16:00.000",
    "title": "Makron Qərbdən Kiyevə yardımın atəşkəs halında da davam edəcəyini açıqlayıb",
    "content": "Fransa Prezidenti Emmanuel Makron hesab edir ki, Ukraynaya yardım, Avropa liderlərinin mayın 12-dən tətbiq etməyi təklif etdiyi 30 günlük atəşkəsdən asılı olmayaraq davam etməlidir.\n\n“Report”xəbər verir ki, bu barədə o, BFMTV telekanalının canlı yayımladığı Kiyevdəki mətbuat konfransında bildirib.\n\n“Biz bazar ertəsindən etibarən heç bir ilkin şərt olmadan atəşkəsin tətbiq ediləcəyindən çıxış edirik. Bundan sonra davamlı sülhün bütün şərtləri müzakirə olunacaq. Bu, məhz sülh haqqında müzakirəni strukturlaşdıracaq. Lakin bu, atəşkəs üçün ilkin şərt deyil”, – Makron vurğulayıb.\n\nOnun sözlərinə görə, Ukraynaya təcili yardım davam etdirilməlidir. “Sonra müəyyən mənada ilk təhlükəsizlik zəmanəti olan uzunmüddətli Ukrayna ordusunun qurulmasıdır”, – Fransa lideri qeyd edib.\n\nAtəşkəs təklifi barədə danışan Makron əlavə edib ki, “o, şərtsiz olmalıdır”. “Bu atəşkəs üçün nə ukraynalılar, nə də ruslar tərəfindən heç bir ilkin şərt olmalıdır. O, əsasən ABŞ-nin nəzarəti altında quruda, havada və dənizdə 30 gün davam etməlidir. Buna hazır olan bütün avropalılar bunda iştirak edəcəklər”, – Fransa Prezidenti söyləyib.",
    "gold_entities": {
      "persons": [
        "Emmanuel Makron"
      ],
      "organizations": [
        "Report",
        "BFMTV"
      ],
      "locations": [
        "Kiyev",
        "Ukrayna",
        "Avropa",
        "ABŞ",
        "Fransa"
      ],
      "positions": [
        "Fransa Prezidenti"
      ],
      "dates": [
        "mayın 12-dən",
        "30 gün"
      ]
    },
    "manually_verified": true,
    "annotator_notes": ""
  },
  {
    "article_id": "1677",
    "source": "report.az",
    "link": "https://report.az/diger-olkeler/zelenski-esir-mubadilesinin-ucuncu-merhelesi-mayin-25-de-bas-tutacaq",
    "pub_date": "2025-05-24 23:31:00.000",
    "title": "Zelenski: Əsir mübadiləsinin üçüncü mərhələsi mayın 25-də baş tutacaq",
    "content": "Ukrayna Prezidenti Volodimir Zelenski Rusiya ilə “1000-ə 1000” formatında hərbi əsirlərin mübadiləsinin üçüncü mərhələsinin bazar günü baş tutacağını açıqlayıb.\n\n“Report”“İnterfaks-Ukrayna”ya istinadən xəbər verir ki, o, bu barədə axşam videomüraciətində bildirib.\n\n\"Sabah üçüncü mərhələdir. Biz yaxın bir neçə gün ərzində min nəfərimizi azad etməliyik, lakin vəzifə hazırda Rusiyada saxlanılan hər kəsi tamamilə azad etməkdir. Bu da bizim baxışlarımız, diplomatlarımız, bütün dövlətimiz üçün ümumi vəzifədir”, - Zelenski bildirib.\n\nUkrayna lideri dünyada ölkəsinə kömək edən hər kəsə də təşəkkür edib:\n\n\"Bizim üçün həqiqətən çox vacibdir ki, tərəfdaşlarımız, hər bir lider, hər bir dövlət bu çətin işdə bizə dəstək oldu. Bir gün belə dayanmırıq\", - o qeyd edib.\n\nPrezidentin sözlərinə görə, mübadilə aparılan iki gün ərzində ümumilikdə 697 ukraynalı azad edilib. \"Onların əksəriyyəti Ukrayna Silahlı Qüvvələrinin hərbçiləridir. Həmçinin Milli Qvardiya, Dövlət Sərhəd Xidmətinin hərbçiləri də var. Bu şəxslərin 273-ü, çox hissəsi 2022-ci ildə Donetsk vilayətində əsir götürülüb. Həmçinin Xerson, Zaporojye, Xarkov, Luqansk vilayəti ərazisində\", - Zelenski vurğulayıb.",
    "gold_entities": {
      "persons": [
        "Volodimir Zelenski"
      ],
      "organizations": [
        "Report",
        "İnterfaks-Ukrayna",
        "Ukrayna Silahlı Qüvvələri",
        "Milli Qvardiya",
        "Dövlət Sərhəd Xidməti"
      ],
      "locations": [
        "Ukrayna",
        "Rusiya",
        "Donetsk vilayəti",
        "Xerson",
        "Zaporojye",
        "Xarkov",
        "Luqansk"
      ],
      "positions": [
        "Ukrayna Prezidenti"
      ],
      "dates": [
        "mayın 25-də",
        "bazar günü",
        "2022-ci ildə"
      ]
    },
    "manually_verified": true,
    "annotator_notes": ""
  },
  {
    "article_id": "3036",
    "source": "report.az",
    "link": "https://report.az/diger-olkeler/fidan-israilin-felestindeki-hereketleri-regional-ekspansionizme-cevrilib",
    "pub_date": "2025-09-14 23:24:00.000",
    "title": "Fidan: İsrailin Fələstindəki hərəkətləri regional ekspansionizmə çevrilib",
    "content": "\"İsrailin hərəkətləri Fələstin ərazilərindən kənara çıxıb və regional ekspansionizmə çevrilib\".\n\n\"Report\"bunu Türkiyənin xarici işlər naziri Hakan Fidan Qətərin \"Əl-Cəzirə\" və \"Qatar TV\" telekanallarına müsahibəsində deyib.\n\n\"Bu gün biz (Ərəb Liqası (ƏƏT) və İslam Əməkdaşlıq Təşkilatı (İƏT) – Qeyd) xarici işlər nazirlərinin iclasını keçirdik. Sabah liderlərimiz görüşəcək. Biz burada gördük ki, artıq məsələ təkcə Fələstinə və İsrailə aid deyil, bu, təkcə İsrailin Fələstini işğalı, Qəzzadakı soyqırımı problemi ilə məhdudlaşmır. Bu aspektlərlə yanaşı, hazırda məsələ İsrailin bölgədəki ekspansionizminə aiddir\", - deyə Fidan bildirib.\n\nOnun sözlərinə görə, İsrail ekspansionizmi məsələsi aydın formalaşdırıldıqdan sonra ərəb və islam ölkələri birləşməli və bu yeni problemin həllini tapmalıdır:\n\n\"Bizim regional təhlükəsizliyimiz daha güclü institusional təməl üzərində qurulmalıdır. Regionda heç kim heç kimə təhlükəsizliyə təhdid yaratmamalıdır. Lakin İsrailin indiki aqressiv siyasəti bütünlüklə buna yönəlib (regional dövlətlərə təhdidlər - Qeyd). Əmin ola bilərsiniz ki, bu gün keçirdiyimiz nazirlərin görüşündə bu məsələlər geniş müzakirə olunub və sabah liderlərin görüşündə də qaldırılacaq\", - XİN rəhbəri qeyd edib.",
    "gold_entities": {
      "persons": [
        "Hakan Fidan"
      ],
      "organizations": [
        "Report",
        "Əl-Cəzirə",
        "Qatar TV",
        "Ərəb Liqası (ƏƏT)",
        "İslam Əməkdaşlıq Təşkilatı (İƏT)"
      ],
      "locations": [
        "Fələstin",
        "İsrail",
        "Qəzza",
        "Türkiyə",
        "Qətər"
      ],
      "positions": [
        "Türkiyənin xarici işlər naziri"
      ],
      "dates": []
    },
    "manually_verified": true,
    "annotator_notes": ""
  },
  {
    "article_id": "1838",
    "source": "report.az",
    "link": "https://report.az/futbol-xeberleri/millinin-bas-mesqcisi-ortaya-qoyulan-xarakter-gosterdi-ki-azerbaycanda-yaxsi-futbolcular-var",
    "pub_date": "2025-06-06 22:44:00.000",
    "title": "Millinin baş məşqçisi: \"Ortaya qoyulan xarakter göstərdi ki, Azərbaycanda yaxşı futbolçular var\"",
    "content": "On yeddi yaşadək futbolçulardan ibarət Azərbaycan milli komandasının baş məşqçisi Aqil Nəbiyev Qəbələ şəhər stadionunda Qazaxıstanın müvafiq yaş qrupundan ibarət komandasına qalib gəldikləri yoxlama görüşünü (2:0) dəyərləndirib.\n\n\"Report\"xəbər verir ki, mütəxəssis bu barədə AFFA-nın Mətbuat xidmətinə açıqlama verib.\n\nO, komandanın çıxışından məmnun olduğunu vurğulayıb:\n\n“Çətin oyun oldu. Qəbələdə neçə gündür yağışın yağması da müəyyən təsir göstərdi. İspaniyanın “Marcet” komandasından dəvət edilən 9 futbolçumuz dünən gecə kollektivə qoşulublar. Komanda şəklində məşq edə bilməməyimiz bir qədər sıxıntı yaratdı.\n\nBu gün ortaya qoyulan xarakter göstərdi ki, Azərbaycanda yaxşı futbolçular var. İstər UEFA İnkişaf Turnirində, istərsə də son matçlarda bunu sübut etmişik. Sadəcə, düzgün istiqamət götürmək, bu uşaqlara güvənmək lazımdır. İnanıram ki, getdikcə daha yaxşı olacağıq. Bu kollektivlə martdan bir yerə yığılırıq. Bu, artıq üçüncü toplanışımızdır.\n\nRəsmi oyunlar öncəsi daha bir təlim-məşq toplanışımız olacaq. Avropa çempionatının seçmə mərhələsində Fransa, İsrail və Rumıniya ilə eyni qrupda çıxış edəcəyik. Rəqiblər güclü olsalar da, komandamıza inanırıq”.\n\nQeyd edək ki, Azərbaycanın U-17 millisi növbəti yoxlama oyununu iyunun 10-da Gürcüstan yığmasına qarşı keçirəcək.",
    "gold_entities": {
      "persons": [
        "Aqil Nəbiyev"
      ],
      "organizations": [
        "Report",
        "AFFA",
        "Azərbaycan U-17 millisi",
        "Qazaxıstan yığması",
        "Marcet",
        "UEFA İnkişaf Turniri",
        "Avropa çempionatı"
      ],
      "locations": [
        "Qəbələ",
        "Azərbaycan",
        "İspaniya",
        "Qazaxıstan",
        "Fransa",
        "İsrail",
        "Rumıniya",
        "Gürcüstan"
      ],
      "positions": [
        "baş məşqçi"
      ],
      "dates": [
        "iyunun 10-da"
      ]
    },
    "manually_verified": true,
    "annotator_notes": ""
  },
  {
    "article_id": "1783",
    "source": "report.az",
    "link": "https://report.az/region-xeberleri/rusiya-numayendeleri-ukrayna-ile-danisiqlar-ucun-turkiyeye-yola-dusub",
    "pub_date": "2025-06-01 21:39:00.000",
    "title": "Rusiya nümayəndə heyəti Ukrayna ilə bağlı danışıqlarda iştirak etmək üçün İstanbula gəlib - YENİLƏNİB",
    "content": "Rusiya nümayəndə heyəti Ukrayna tərəfi ilə iyunun 2-nə planlaşdırılan danışıqlarda iştirak etmək üçün İstanbula gəlib.\n\n“Report”xəbər verir ki, bu barədə TASS-dakı mənbə bildirib.\n\n\"Danışıqlar aparan qrup İstanbula gəlib\", - agentliyin mənbəsi deyib.\n\nRusiyanın xarici işlər naziri Sergey Lavrov bildirib ki, prezidentin köməkçisi Vladimir Medinskinin başçılıq etdiyi Rusiya nümayəndə heyəti iyunun 2-də Ukraynaya böhranın səbəblərini aradan qaldırmağın bütün aspektləri ilə bağlı memorandum təqdim etməyə hazırdır. Rusiya prezidentinin mətbuat katibi Dmitri Peskov vurğulayıb ki, hazırda əsas məsələ birbaşa danışıqlar prosesini davam etdirməkdir.\n\nİyunun 1-də Ukrayna Prezidenti Volodimir Zelenski bəyan edib ki, Umerov İstanbulda keçiriləcək danışıqlarda Ukrayna nümayəndə heyətinə rəhbərlik edəcək.\n\n17:04\n\nRusiyanın nümayəndə heyəti bazar günü günortadan sonra Ukrayna ilə danışıqlarda iştirak etmək üçün təyyarə ilə Türkiyənin İstanbul şəhərinə yola düşüb.\n\n\"Report\"un xəbərinə görə, bu barədə \"İnterfaks\" danışıqların hazırlanması ilə tanış olan mənbəyə istinadən xəbər verir.\n\n\"Rusiya Federasiyası Prezidentinin köməkçisi Vladimir Medinskinin rəhbərlik etdiyi nümayəndə heyəti bazar günü günortadan sonra təyyarə ilə İstanbula uçub\", - agentliyin müsahibi bildirib.\n\nO, qeyd edib ki, Rusiya nümayəndə heyəti iyunun 2-də səhər danışıqlara başlamağa hazır olacaq.",
    "gold_entities": {
      "persons": [
        "Sergey Lavrov",
        "Vladimir Medinski",
        "Dmitri Peskov",
        "Volodimir Zelenski",
        "Umerov"
      ],
      "organizations": [
        "Report",
        "TASS",
        "İnterfaks"
      ],
      "locations": [
        "Türkiyə",
        "İstanbul",
        "Rusiya",
        "Ukrayna"
      ],
      "positions": [
        "Rusiyanın xarici işlər naziri",
        "Rusiya Federasiyası Prezidentinin köməkçisi",
        "Rusiya prezidentinin mətbuat katibi",
        "Ukrayna Prezidenti"
      ],
      "dates": [
        "iyunun 2-nə",
        "İyunun 1-də",
        "bazar günü"
      ]
    },
    "manually_verified": true,
    "annotator_notes": ""
  },
  {
    "article_id": "149",
    "source": "report.az",
    "link": "https://report.az/region-xeberleri/gurcustan-polisi-batumi-ve-tbiliside-ondan-cox-etirazcini-saxlayib",
    "pub_date": "2025-01-12 21:57:00.000",
    "title": "Gürcüstan polisi Batumi və Tbilisidə bir neçə etirazçını saxlayıb",
    "content": "Bazar günü Gürcüstanın Batumi şəhərində etiraz aksiyası zamanı 8 nəfər saxlanılıb.\n\n“Report”xəbər verir ki, bu barədə Acarıstanın Batumi şəhər polis idarəsinin rəisi İrakli Dqebuadze jurnalistlərə bildirib.\n\nSaxlanılanların hamısı inzibati xətalarda - polis əməkdaşlarını təhqir etməkdə və müqavimət göstərməkdə ittiham olunurlar”, - Dqebuadze bildirib.\n\nGürcüstan mətbuatının məlumatına görə, Acarıstan Hökumət Evi yaxınlığında keçirilən etiraz aksiyasında vəziyyət Tbilisidən gələn müxalifət partiyası “Dəyişikliklər uğrunda Koalisiya”nın liderləri Yelena Xoştariya və Giorgi Kirtadzenin etirazçılara qoşularaq hökumətə tabe olmamağa çağırmasından sonra gərginləşib.\n\nXoştariya və Kirtadze polis tərəfindən saxlanılıb.\n\nBir gün əvvəl Batumidə hökumət siyasətinə qarşı etiraz aksiyasının 10 iştirakçısı da saxlanılıb, onlardan dördü yaxın günlərdə məhkəmə qarşısına çıxmaq üçün zaminə buraxılıb.\n\nBazar günü Tbilisidə hakimlərin korporativ iclasının keçirildiyi “Babilo” restoranının yaxınlığında polislə etirazçılar arasında toqquşmalar da baş verib.\n\nGürcüstanın Patrul Polisinin rəis müavini Sergi Bzişvilinin jurnalistlərə verdiyi məlumata görə, restoranın qarşısında etiraz aksiyasının bir neçə iştirakçısı saxlanılıb.\n\n“Saxlanılanlar qanunsuz olaraq yolu bağlayıb, polisə yumurta atıb və onları təhqir ediblər”, - Bzişvili bildirib.\n\nHazırda Tbilisinin Rustaveli prospektində Gürcüstan parlamentinin binası yaxınlığında etiraz aksiyası keçirilir.",
    "gold_entities": {
      "persons": [
        "İrakli Dqebuadze",
        "Yelena Xoştariya",
        "Giorgi Kirtadze",
        "Sergi Bzişvili"
      ],
      "organizations": [
        "Report",
        "Gürcüstan polisi",
        "Acarıstanın Batumi şəhər polis idarəsi",
        "Dəyişikliklər uğrunda Koalisiya",
        "Gürcüstanın Patrul Polisi",
        "Gürcüstan parlamenti",
        "Babilo"
      ],
      "locations": [
        "Gürcüstan",
        "Batumi",
        "Tbilisi",
        "Acarıstan",
        "Rustaveli prospekti"
      ],
      "positions": [
        "polis idarəsinin rəisi",
        "Patrul Polisinin rəis müavini"
      ],
      "dates": [
        "Bazar günü",
        "Bir gün əvvəl"
      ]
    },
    "manually_verified": true,
    "annotator_notes": ""
  },
  {
    "article_id": "1453",
    "source": "report.az",
    "link": "https://report.az/biznes-xeberleri/azerbaycan-belarus-biznes-forumunda-19-milyon-dollara-yaxin-muqavile-imzalanib",
    "pub_date": "2025-05-05 22:35:00.000",
    "title": "Azərbaycan-Belarus biznes forumunda 18,9 milyon dollarlıq müqavilə imzalanıb",
    "content": "Bakıda keçirilən Azərbaycan-Belarus biznes forumunun yekunları üzrə 18,9 milyon dollar dəyərində müqavilələr imzalanıb.\n\n“Report”xəbər verir ki, bu barədə Belarus Ticarət-Sənaye Palatasının sədri Mixail Myatlikov jurnalistlərə açıqlamasında bildirib.\n\nM.Myatlikovun sözlərinə görə, ümumilikdə 12 sənədə imza atılıb, onlardan üçü onlayn şəkildə qəbul olunub.\n\n\"Razılaşdığımız kimi, biz Azərbaycandan olan tərəfdaşlarımızı iyunda keçiriləcək \"Belagro\" sərgimizdə gözləyirik. Onlar iştiraklarını təsdiqləyiblər. Biz isə onların mayın 13-dən 16-dək \"Caspian Agro\" beynəlxalq sərgisində iştirak edəcəyik. Belarusdan olan 17 müəssisə artıq öz ərizələrini təsdiqləyib və onlar Bakıda yeni məhsullarını təqdim edəcəklər\", - o deyib.\n\nO qeyd edib ki, forum zamanı Belarus Universal Əmtəə Birjası ilə Azərbaycanın Kiçik və Orta Biznesin İnkişafı Agentliyi arasında memorandum, \"Mostovdrev\" və \"Sosna\" şirkətləri arasında məhsul tədarükünə dair üç müqavilə, \"Kamvol\" və \"Smart Style\" şirkətləri arasında məhsul tədarükünə dair müqavilə, \"Spartak\" və \"AZNUR\" şirkətləri arasında məhsul tədarükünə dair müqavilə, “Borkof-Aqro” MMC ilə “Stapri-Azərbaycan” MMC arasında rezin lövhələrin tədarükünə dair niyyət sazişi, “BelOMO” holdinqinin “LEMT” Elmi-Texniki Mərkəzi ilə “Azərbaycan Milli Aviasiya Akademiyası Hava Yolları” QSC arasında əməkdaşlıq müqaviləsi imzalanıb.\n\nBundan əlavə, forum çərçivəsində “Belşina” ASC, “Azərtexnika” MMC və “Azbelşin” MMC arasında 2025-2026-cı illərdə regiona şin məmulatlarının tədarükünü nəzərdə tutan əməkdaşlıq memorandumuna imza atılıb.",
    "gold_entities": {
      "persons": [
        "Mixail Myatlikov"
      ],
      "organizations": [
        "Report",
        "Belarus Ticarət-Sənaye Palatası",
        "Belagro",
        "Caspian Agro",
        "Belarus Universal Əmtəə Birjası",
        "Azərbaycanın Kiçik və Orta Biznesin İnkişafı Agentliyi",
        "Mostovdrev",
        "Sosna",
        "Kamvol",
        "Smart Style",
        "Spartak",
        "AZNUR",
        "Borkof-Aqro MMC",
        "Stapri-Azərbaycan MMC",
        "BelOMO",
        "LEMT Elmi-Texniki Mərkəzi",
        "Azərbaycan Milli Aviasiya Akademiyası Hava Yolları QSC",
        "Belşina ASC",
        "Azərtexnika MMC",
        "Azbelşin MMC"
      ],
      "locations": [
        "Bakı",
        "Azərbaycan",
        "Belarus"
      ],
      "positions": [
        "Belarus Ticarət-Sənaye Palatasının sədri"
      ],
      "dates": [
        "iyunda",
        "mayın 13-dən 16-dək",
        "2025-2026-cı illərdə"
      ]
    },
    "manually_verified": true,
    "annotator_notes": ""
  },
  {
    "article_id": "347",
    "source": "report.az",
    "link": "https://report.az/daxili-siyaset/sinayda-tapilan-alban-dilinde-315-sehifeli-palimpsest-ermeni-yalanlarini-ifsa-etdi-qerbi-azerbaycan-xronikasi",
    "pub_date": "2025-01-29 19:22:00.000",
    "title": "Qərbi Azərbaycan Xronikası: Ermənilər udilərdən qorxub, Alban kilsəsini tanımaq istəmirlər",
    "content": "Qərbi Azərbaycan Xronikası layihəsi çərçivəsində sənətşünaslıq üzrə fəlsəfə doktoru Elçin Əlibəylinin təqdimatında “Ermənilər udilərdən qorxub, Alban kilsəsini tanımaq istəmirlər” adlı veriliş efirə gedib.\n\n“Report” xəbər verir ki, verilişdə Alban-Udi Xristian Dini İcmasının sədri Robert Mobili ermənilərin Alban kilsələrini talan edərək saxtalaşdırmasından söz açıb.\n\nO bildirib ki, 1836-cı ildən sonra ermənilər Alban kilsələrini talamağa başlayıblar: “Onlar Alban kilsələrində olan tarixi, dini kitabları məhv etmək üçün rus çarından icazə alıblar. Albanlara aid mühüm tarixi sənədləri Eçmiədzin və Matenadaranda gizlədiblər”.\n\nDini İcma sədri diqqətə çatdırıb ki, Ermənistanda yaradılan qondarma Udi icmasında udilər yox, ermənilər yığışıb: “Udinlər vaxtı ilə ermənilərdən kömək istədi, amma onlar üz çevirdilər. Ermənilər udi adlarını, tarixini saxtalaşdırmaq, məhv etməyə çalışıblar”.\n\nR.Mobili vurğulayıb ki, erməniləri Alban kilsəsinin bərpası qorxuya salıb: “Erməni kilsəsinin Qafqaza aidiyyəti yoxdur. Qəbələnin Nic kəndindəki Alban kilsəsinə ən çox azərbaycanlılar gəlir”.\n\nXatırladaq ki, Qərbi Azərbaycan Xronikası layihəsinin məqsədi tarixi qədim torpaqlarımızın adının yaşadılması, tanıdılması, həmçinin azərbaycanlıların ermənilər tərəfindən deportasiyaya məruz qoyulması, həmin ərazilərdə mövcud olmuş, lakin adı silinən toponimlərin, saysız-hesabsız yeraltı və yerüstü maddi mədəniyyət nümunələri – qədim yaşayış məskənləri, nekropollar, kurqanlar, qala, saray və istehkam qalıqları, karvansaralar, körpülər, qəbirüstü sənduqələr, at-qoç heykəlləri, məbəd, kilsə, məscid, pir və ocaqların üzə çıxarılması, həmin ərazinin təmiz oğuz-türk məskənləri olduğunu təsdiq edən faktların dünya ictimaiyyətinə çatdırılmasıdır.",
    "gold_entities": {
      "persons": [
        "Elçin Əlibəyli",
        "Robert Mobili"
      ],
      "organizations": [
        "Report",
        "Qərbi Azərbaycan Xronikası",
        "Alban-Udi Xristian Dini İcması",
        "Eçmiədzin",
        "Matenadaran"
      ],
      "locations": [
        "Ermənistan",
        "Qəbələ",
        "Nic",
        "Qərbi Azərbaycan",
        "Qafqaz"
      ],
      "positions": [
        "sənətşünaslıq üzrə fəlsəfə doktoru",
        "təqdimatçı",
        "Dini İcmanın sədri"
      ],
      "dates": [
        "1836-cı ildən"
      ]
    },
    "manually_verified": true,
    "annotator_notes": ""
  },
  {
    "article_id": "431",
    "source": "report.az",
    "link": "https://report.az/region-xeberleri/esrin-felaketi-nden-iki-il-otur",
    "pub_date": "2025-02-05 20:00:00.000",
    "title": "“Əsrin fəlakəti”ndən iki il ötür",
    "content": "Türkiyədə53mindən çox insanın ölümünə səbəb olan dağıdıcı zəlzələlərdən iki il ötür.\n\n“Report” xatırladır ki, 2023-cü il fevralın 6-da ölkənin cənub-şərqindəki Kahramanmaraş vilayətində7,7və7,6bal gücündə zəlzələlər baş verib.\n\nYeraltı təkanlar ölkənin11əyalətində və qonşu dövlətlərdə hiss olunub. Türkiyə hakimiyyəti zəlzələni “əsrin fəlakəti” adlandırıb.\n\nBir neçə saat ara ilə sadəcə105saniyə davam edən iki zəlzələ nəticəsində53 537nəfər həlak olub,107 213nəfər isə müxtəlif xəsarətlər alıb. Yeraltı təkanlar zamanı39minə yaxın bina dağılıb. Bunlardan 26 minində axtarış-xilasetmə işləri aparılıb. Ölənlər arasında4azərbaycanlı tələbə də var idi.\n\nYeraltı təkanların gücündən Hatayda yer səddində400metr uzunluğunda nəhəng çat meydana gəlib, Qaziantepdə iki təpə birləşib, Qaziantepin Nurdağı vilayətində bir kənd iki hissəyə ayrılıb, Kahramanmaraşın Çiğli kəndi6,5, Değirmenkaya kəndi isə6metr sürüşüb.\n\nÖlkədə beynəlxalq yardım da daxil olmaqla,4-cü səviyyə həyəcan siqnalı verilib. Bunun ardından90ölkədən axtarış-xilasetmə qrupları zəlzələ bölgəsinə köməyə gəlib. Zəlzələdən sonra Türkiyəyə özünü çatdıran ilk xarici heyət isə Azərbaycan Fövqəladə Hallar Nazirliyinin nümayəndələri olub. Azərbaycan yardıma41-i tibb işçisi olmaqla725nəfər göndərib.\n\nKomandalar fevralın 6-da Türkiyəyə gedərək həm axtarış-xilasetmə, həm də digər fəaliyyətlərdə iştirak ediblər. Martın ilk həftəsinə kimi vəzifələrini davam etdirən azərbaycanlı axtarış-xilasetmə mütəxəssisləri Türkiyəni tərk edən sonuncu komanda olub. Nümayəndələrimiz53nəfəri dağıntılar altından xilas edib.\n\nZəlzələ bölgəsində2 302 000binada və6 227 000müstəqil evdə dəymiş ziyanın qiymətləndirilməsi aparılıb və indiyədək dağıntıların təmizlənməsi prosesinin91faizi tamamlanıb. Yeraltı təkanların baş verdiyi şəhər mərkəzləri və kəndlərdə307min binanın tikintisinə başlanılıb. Hazırda bölgədə inşa edilən evlərin açarları mərhələli şəkildə sahiblərinə təqdim edilir.",
    "gold_entities": {
      "persons": [],
      "organizations": [
        "Report",
        "Türkiyə hakimiyyəti",
        "Azərbaycan Fövqəladə Hallar Nazirliyi"
      ],
      "locations": [
        "Türkiyə",
        "Kahramanmaraş",
        "Hatay",
        "Qaziantep",
        "Nurdağı",
        "Çiğli",
        "Değirmenkaya",
        "Azərbaycan"
      ],
      "positions": [],
      "dates": [
        "2023-cü il fevralın 6-da",
        "Martın ilk həftəsi",
        "iki il"
      ]
    },
    "manually_verified": true,
    "annotator_notes": ""
  },
  {
    "article_id": "4031",
    "source": "report.az",
    "link": "https://report.az/xarici-siyaset/qudsi-osmanov-ruminiyanin-timisoara-seherinde-bir-sira-gorusler-kecirib",
    "pub_date": "2025-12-06 16:19:00.000",
    "title": "Qüdsi Osmanov Rumıniyanın Timişoara şəhərində bir sıra görüşlər keçirib",
    "content": "Azərbaycanın Rumıniyadakı səfiri Qudsi Osmanov Timişoaranın meri və hakim koalisiyada olan Rumıniya Xilaskarlar Birliyi Partiyasının (USR) sədri Dominik Frits ilə rəsmi görüş keçirib.\n\nAzərbaycan Rumıniyadakı səfirliyindən\"Report\"a verilən məlumata görə, görüşdə mümkün əməkdaşlıq imkanları, Timişoara ilə Azərbaycan arasında yeni əlaqələrin qurulması və ikitərəfli iqtisadi əməkdaşlığın inkişafı müzakirə olub.\n\nQ.Osmanov şəhərin multikultural xarakterini, beynəlxalq əməkdaşlığa açıqlığını, gənclərin ictimai həyatda fəallığını və özünəməxsus, unikal memarlığını vurğulayaraq bunun 2023-cü ildə Timişoaranın Avropanın Mədəniyyət Paytaxtı statusu alması, beynəlxalq səviyyədə tanınması və onun mədəni potensialının önə çıxmasına mühüm töhfə verməsini qeyd edib. O, Azərbaycan ilə Rumıniya əlaqələrinə toxunaraq iki ölkənin regionları arasında əməkdaşlığının qarşılıqlı faydasından danışıb.\n\nÖz növbəsində, mer Dominik Frits Timişoaranın \"şəhər diplomatiyası\" konsepsiyasına sadiqliyini və Azərbaycanla münasibətlərin möhkəmləndirilməsində marağını ifadə edib. Həmçinin şəhərin rəhbəri Timişoara şəhəri tərəfindən təsis olunan Avropa Dəyərləri Mükafatı və hər il təşkil olunan Timişoara Şəhər Sammiti barədə danışaraq bu tədbirlərin şəhərin Avropa dəyərləri və müzakirələri ilə əlaqələndirən təşəbbüslər adlandırıb.\n\nBundan əlavə, səfir Rumıniyada dövlət səviyyəsində qeyd olan Milad bayramı və bu ölkədə qeyd olan Müqəddəs Nikolay günü ərəfəsində XX əsrin ortalarında Timişoarada inşa olunmuş və Rumıniyanın ən mühüm dini məbədlərdən biri olan \"Müqəddəs Üç Hiyerarx\" kilsəsini də ziyarət edib.\n\nQüdsi Osmanov, eyni zamanda, Timişoaraya səfər çərçivəsində Timişoara Bələdiyyə Sosial Yardım İdarəsinin tabeliyində olan \"Inokentsiu Klein\" \"Qocalar Evi\"ni də ziyarət edib. Azərbaycanlı diplomat \"Qocalar evi\"nin sakinləri ilə söhbət aparıb, onlara Azərbaycanın Rumıniyadakı səfirliyi adından kiçik bayram hədiyyələri təqdim edib.\n\nQeyd edək ki, Timişoara Rumıniyanın ən inkişaf etmiş şəhər mərkəzlərindən biridir və rəqabətqabiliyyətli sənayesi, İT sektoru, memarlıq irsi və multikultural mədəniyyəti ilə tanınır. Şəhər əhali və ərazi baxımından ölkədə üçüncü yerdədir. Həmçinin Timişoara Rumıniyada azadlıq və demokratiyanın rəmzi sayılır, çünki ölkədə 1989-cu il inqilabı məhz bu şəhərdən başlayıb.",
    "gold_entities": {
      "persons": [
        "Qüdsi Osmanov",
        "Dominik Frits"
      ],
      "organizations": [
        "Report",
        "Azərbaycanın Rumıniyadakı səfirliyi",
        "Rumıniya Xilaskarlar Birliyi Partiyası (USR)",
        "Timişoara Bələdiyyə Sosial Yardım İdarəsi",
        "Inokentsiu Klein",
        "Müqəddəs Üç Hiyerarx kilsəsi",
        "Avropa Dəyərləri Mükafatı",
        "Timişoara Şəhər Sammiti"
      ],
      "locations": [
        "Rumıniya",
        "Timişoara"
      ],
      "positions": [
        "Azərbaycanın Rumıniyadakı səfiri",
        "Timişoaranın meri",
        "USR sədri"
      ],
      "dates": [
        "2023-cü ildə",
        "1989-cu il"
      ]
    },
    "manually_verified": true,
    "annotator_notes": ""
  },
  {
    "article_id": "3674",
    "source": "report.az",
    "link": "https://report.az/xarici-siyaset/sahibe-qafarova-turkiyenin-vitse-prezidenti-ile-cop29-un-nailiyyetlerini-muzakire-edib",
    "pub_date": "2025-11-06 22:55:00.000",
    "title": "Sahibə Qafarova Türkiyənin vitse-prezidenti ilə COP29-un nailiyyətlərini müzakirə edib - YENİLƏNİB",
    "content": "Milli Məclisin sədri Sahibə Qafarova Braziliyanın Belem şəhərində keçirilən BMT-nin İqlim Dəyişmələri üzrə Çərçivə Konvensiyasının Tərəflər Konfransının 30-cu sessiyası çərçivəsində Türkiyə Respublikasının vitse-prezidenti Cevdet Yılmazla görüşüb.\n\nBu barədə\"Report\"a Milli Məclisin Mətbuat və ictimaiyyətlə əlaqələr şöbəsindən bildirilib.\n\nGörüşdə ötən il COP29-un Bakıda yüksək səviyyədə təşkil olunduğunu söyləyən Cevdet Yılmaz, COP29 zamanı mühüm qərarların qəbul olunduğunu bildirib. O, qardaş Türkiyənin bu tədbirdə fəal iştirak etdiyini xatırladıb.\n\nTürkiyənin vitse-prezidenti 8 noyabr - Zəfər Günü münasibətilə təbriklərini çatdıraraq, bu böyük zəfər nəticəsində Azərbaycanın öz torpaqlarını işğaldan azad etdiyini söyləyib.\n\nMilli Məclisin sədri qeyd edib ki, dost və qardaş ölkələrimiz arasında münasibətlər Ulu Öndər Heydər Əliyevin \"Bir millət, iki dövlət\" prinsipi əsasında inkişaf edir və qardaş ölkələrimiz bütün məsələlərdə bir-birini daim dəstəkləyir. Söhbət zamanı əlaqələrin bu səviyyəyə gəlib çatmasında dövlət başçılarımızın müstəsna rolu qeyd edilərək, onların şəxsi dostluğunun və qardaşlığının, siyasi iradəsinin və qətiyyətinin münasibətlərin hazırki yüksək səviyyədə olmasını təmin etdiyi bildirilib.\n\nGörüşdə ölkələrimiz arasında yüksək səviyyəli münasibətlərin Türk Dövlətləri Təşkilatı çərçivəsində də əməkdaşlığın, o cümlədən, təşkilatın daha da gücləndirilməsinə töhfə verdiyi diqqətə çatdırılıb. Eyni zamanda, bu əlaqələrin fonunda Azərbaycan-Türkiyə-Pakistan üçtərəfli zirvəsinin önəmi qeyd edilib.\n\nTərəflər ikitərəfli münasibətlərin daha da dərinləşməsində parlamentlər arasında dialoqun vacib əhəmiyyət kəsb etdiyini vurğulayaraq, bu mənada qardaş ölkələrimizin qanunvericilik orqanları arasında əlaqələrin də yüksək səviyyədə olmasından məmnunluqlarını bildiriblər.\n\nSöhbət zamanı qeyd olunub ki, Azərbaycan və Ermənistan arasında normallaşma prosesi regiona uzunmüddətli sülh, sabitlik və rifahın gəlməsinə müsbət təsir göstərəcək.\n\n20:59\n\nAzərbaycanın Milli Məclisin sədri Sahibə Qafarova Braziliyanın Belem şəhərində keçirilən COP30 çərçivəsində Türkiyənin vitse- prezidenti Cevdet Yılmaz ilə görüşüb.\n\n\"Report\"xəbər verir ki, bu barədə Cevdet Yılmaz \"X\" hesabında paylaşım edib.\n\nO bildirib ki, Suriya Ərəb Respublikasının keçid dövrü Prezidenti Əhməd Əl Şaraa, Azərbaycan Milli Məclisinin sədri Sahibə Qafarova, İranın vitse-prezidenti Şina Ənsari və Rusiyanın vitse-prezidenti və iqlim dəyişikliyi üzrə xüsusi nümayəndəsi Ruslan Edelgeriyev ilə məhsuldar görüşlər keçirib:\n\n\"Görüşlərimiz zamanı biz iqlimlə bağlı fəaliyyət, COP29-un nailiyyətləri, COP31-ə ev sahibliyi etmək üçün namizədliyimiz, qlobal iqlim maliyyəsinin gücləndirilməsi, ikitərəfli əlaqələr, regional inkişaflar, ticarət, enerji, nəqliyyat, sərhəd təhlükəsizliyi və ətraf mühit məsələləri də daxil olmaqla genişspektrli ortaq gündəliyi müzakirə etdik.\n\nTürkiyə olaraq biz Azərbaycan, Suriya, İran və Rusiya ilə köklü və çoxvektorlu əlaqələrimizi və konstruktiv dialoqumuzu gücləndirməyə, regionumuzda sülh, sabitlik və davamlı inkişafı dəstəkləyən əməkdaşlıq mexanizmlərini inkişaf etdirməyə sadiqik. Qlobal miqyasda ədalətli, əhatəli və davamlı iqlim diplomatiyasına nail olmaq üçün bütün maraqlı tərəflərimizlə sıx məsləhətləşmələrimizi və həmrəyliyimizi davam etdirəcəyik\".",
    "gold_entities": {
      "persons": [
        "Sahibə Qafarova",
        "Cevdet Yılmaz",
        "Heydər Əliyev",
        "Əhməd Əl Şaraa",
        "Şina Ənsari",
        "Ruslan Edelgeriyev"
      ],
      "organizations": [
        "Report",
        "Milli Məclis",
        "COP30",
        "BMT-nin İqlim Dəyişmələri üzrə Çərçivə Konvensiyası",
        "COP29",
        "Türk Dövlətləri Təşkilatı",
        "Azərbaycan-Türkiyə-Pakistan üçtərəfli zirvəsi",
        "X"
      ],
      "locations": [
        "Braziliya",
        "Belem",
        "Azərbaycan",
        "Bakı",
        "Türkiyə",
        "Suriya",
        "İran",
        "Rusiya"
      ],
      "positions": [
        "Milli Məclisin sədri",
        "Türkiyə Respublikasının vitse-prezidenti",
        "Suriya Ərəb Respublikasının keçid dövrü Prezidenti",
        "İranın vitse-prezidenti",
        "Rusiyanın vitse-prezidenti"
      ],
      "dates": [
        "8 noyabr"
      ]
    },
    "manually_verified": true,
    "annotator_notes": ""
  },
  {
    "article_id": "2062",
    "source": "report.az",
    "link": "https://report.az/sehiyye-xeberler/suyun-mualicevi-gucu-nine-senses-de-yeni-texnologiya-saglamligin-berpasina-nece-komek-edir",
    "pub_date": "2025-06-25 23:36:00.000",
    "title": "Suyun müalicəvi gücü: \"Nine Senses\"də yeni texnologiya sağlamlığın bərpasına necə kömək edir?",
    "content": "Həyatın sürətli tempi və texnoloji tərəqqinin insanları təbii harmoniyadan getdikcə uzaqlaşdırdığı müasir dünyada sağlamlığın və daxili tarazlığın bərpası üzrə innovativ yanaşmalar böyük rol oynayır. Bu unikal ixtiralardan biri alman tədqiqatçısı Yakob Mayerin \"Alpha Omeqa Water\" (\"Alfa-Omeqa\") texnologiyası oldu. Onun yaradıcısının fikrincə, texnologiyanın təsiri müalicəvi və bərpaedici potensialı daşıyan sütun şəklində təcəssüm olunur.\n\nİndi ziyarətçilərə təkcə fiziki sağlamlaşdırmanı deyil, həm də dərin daxili yenilənməni təşviq edən seanslardan keçmək imkanı verilən \"Nine Senses\" incəsənət mərkəzinin məkanında \"Alpha Omega Water\"nin müalicəvi gücünə toxunmaq mümkündür.\n\n\"Report\"xəbər verir ki, Yakob Mayer texnologiyanın mahiyyətindən, elmi araşdırmalarından danışıb, həmçinin ixtirasının gətirdiyi transformasiya haqqında ruhlandırıcı hekayələri bölüşüb.\n\n- Bu unikal aləti yaratmağa sizi nə ilhamlandırdı?\n\n- Yəqin ki mənim əsas motivasiyam insanlara kömək etmək, faydalı olmaq istəyidir. Bu mənim həm gücüm, həm də zəifliyimdir. Mən təbii olaraq kömək etmək istəyirəm - məcbur olduğum üçün deyil, daxili ehtiyaca görə. Həqiqətən vacib və xoş olduğu yerdə kömək etmək.\n\nBəzən sadəcə başqasının ağrısını götürmək istəyirsən. Bəzən - sevinc bəxş etmək və ya kiminsə həyatını asanlaşdırmaq. Bu sadə, lakin dərin motivasiya məndə uşaqlıqdan yaşayır. O çıxış yolu axtaran nəbz, həyat titrəyişi kimidir, özünü təzahür etdirmək vasitəsidir. Məncə, çoxlarında belədir: kimsə kömək etmək istəyir, kimsə sadəcə həyatdan həzz almaq istəyir. Hər kəsin öz yolu, öz təbiəti var. Bununla belə, özünüzlə harmoniyada olmaq vacibdir. Mənim üçün həyatın özü bir ilhamdır. O əsas güc mənbəyidir.\n\nBu mövzu mənim üçün hələ 90-cı illərin sonlarında xüsusi əhəmiyyət kəsb etdi. Sonra suyun təmizlənməsi problemi haqqında ciddi düşündüm. Həmin illərdə müxtəlif xəstəliklərdən əziyyət çəkən insanlarla tez-tez ünsiyyətdə olurdum. Zamanla başa düşdüm ki, əsas səbəblərdən biri orqanizmin susuzlaşdırmasıdır. İnsanlar sadəcə olaraq kifayət qədər su içmirdilər.\n\nBu barədə məşhur iranlı tədqiqatçı Firudun Batmanxəlic \"Siz xəstə deyilsiniz - susuzsunuz!\" kitabında yazıb. Onun ideyaları böyük populyarlıq qazandı, çünki onlar sadə bir həqiqəti ehtiva edirdi: bir çox xəstəliklər əslində bədəndən su çatışmazlığı ilə bağlı bir siqnaldır. Bu kəşf mənim üçün dönüş nöqtəsi oldu: bir insana kömək etmək bəzən onu həyatın təbii əsaslarına qaytarmaq deməkdir.\n\nFirudun Batmanxəlicin hekayəsi məni çox təsirləndirdi. O, həbsxanada idi və orada olarkən məhbus yoldaşlarının müxtəlif xəstəliklərdən əziyyət çəkdiyinin şahidi oldu. Həkim və kömək etmək arzusunda olan bir insan kimi onların vəziyyətini yüngülləşdirməyin yollarını axtarmağa başladı. Halbuki həbsxanada dərman almaq imkanı yox idi və təklif oluna biləcək yeganə şey su idi.\n\nVaxt keçdikcə, Batmanxəlic məhbus yoldaşlarının sadəcə maye qəbulunu artırmaqla sağlamlığının yaxşılaşdığını gördü. Sonra o, belə qənaətə gəldi ki, bir çox xəstəliklərin səbəbi susuzlaşmadır. Həkimin daha sonra məşhur kitabında qeyd etdiyi konsepsiyası belə yarandı. Həbsdən çıxandan sonra bu mövzu onun missiyasına və bütün həyatın işinə çevrildi.\n\nBu hekayə məni ruhlandırdı. Düşünməyə başladım: həqiqətən də çoxları kifayət qədər su içmir. Üstəlik, hətta içdikləri su da çox vaxt \"ağır\" kimi qəbul edilir - mədədəki narahatlıqdan, sinədə gərginlikdən və ya boğazda xoşagəlməz hisslərdən şikayətlənirlər. Bu, mənə belə bir fikir verdi ki, söhbət təkcə kəmiyyətdən deyil, həm də həyatverici nəmin keyfiyyətindən gedir.\n\n- Araşdırmalarınız nədən başladı?\n\n- Mənim şəxsi yolum ən sadə şeylə başladı: mən kartriclə məişət filtrindən istifadə etməyə çalışdım. Nəticə gözlənilməz oldu - suyun dadı nəzərəçarpacaq dərəcədə yumşaq və yüngül oldu. Fikirləşdim: belə sadə filtrasiya artıq effekt verirsə, məsələni daha dərindən öyrənsəm nə olacaq?\n\nTədricən suyun təmizlənməsi və aktivləşdirilməsinin daha mürəkkəb üsullarını öyrənməyə başladım. Tezliklə mən strukturlaşdırılmış su konsepsi",
    "gold_entities": {
      "persons": [
        "Yakob Mayer",
        "Firudun Batmanxəlic"
      ],
      "organizations": [
        "Report",
        "Nine Senses",
        "Alpha Omeqa Water",
        "Alpha Omega Water"
      ],
      "locations": [
        "Almaniya",
        "İran"
      ],
      "positions": [
        "alman tədqiqatçısı",
        "iranlı tədqiqatçı",
        "həkim"
      ],
      "dates": [
        "90-cı illərin sonlarında"
      ]
    },
    "manually_verified": true,
    "annotator_notes": ""
  },
  {
    "article_id": "631",
    "source": "azerbaijan.az",
    "link": "https://azerbaijan.az/news/15956",
    "pub_date": "2025-05-16 00:00:00.000",
    "title": "Prezident İlham Əliyev “Avropa Siyasi Birliyi” 6-cı Zirvə toplantısının açılış plenar sessiyasında iştirak edib",
    "content": "Mayın 16-da Tiranada “Avropa Siyasi Birliyi” 6-cı Zirvə toplantısının açılış plenar sessiyası keçirilib.\n\nAZƏRTAC xəbər verir ki, Azərbaycan Respublikasının Prezidenti İlham Əliyev tədbirdə iştirak edib.",
    "gold_entities": {
      "persons": [
        "İlham Əliyev"
      ],
      "organizations": [
        "AZƏRTAC",
        "Avropa Siyasi Birliyi"
      ],
      "locations": [
        "Tirana"
      ],
      "positions": [
        "Azərbaycan Respublikasının Prezidenti"
      ],
      "dates": [
        "Mayın 16-da"
      ]
    },
    "manually_verified": true,
    "annotator_notes": ""
  },
  {
    "article_id": "51",
    "source": "azerbaijan.az",
    "link": "https://azerbaijan.az/news/17622",
    "pub_date": "2025-11-16 00:00:00.000",
    "title": "Prezident İlham Əliyev Daşkənddəki Konqres Mərkəzinə gəlib",
    "content": "Azərbaycan Respublikasının Prezidenti İlham Əliyev Özbəkistanın paytaxtı Daşkənddə Mərkəzi Asiya Dövlət Başçılarının \"Mərkəzi Asiya+Azərbaycan\" formatında 7-ci Məşvərət Görüşünün iclasında iştirak etmək üçün Konqres Mərkəzinə gəldi.\n\nAZƏRTAC xəbər verir ki, Özbəkistan Prezidenti Şavkat Mirziyoyev dövlətimizin başçısını qarşıladı.",
    "gold_entities": {
      "persons": [
        "İlham Əliyev",
        "Şavkat Mirziyoyev"
      ],
      "organizations": [
        "AZƏRTAC",
        "Mərkəzi Asiya Dövlət Başçıları",
        "\"Mərkəzi Asiya+Azərbaycan\" formatı",
        "Konqres Mərkəzi"
      ],
      "locations": [
        "Özbəkistan",
        "Daşkənd"
      ],
      "positions": [
        "Azərbaycan Respublikasının Prezidenti",
        "Özbəkistan Prezidenti"
      ],
      "dates": []
    },
    "manually_verified": true,
    "annotator_notes": ""
  },
  {
    "article_id": "646",
    "source": "azerbaijan.az",
    "link": "https://azerbaijan.az/news/15912",
    "pub_date": "2025-05-10 00:00:00.000",
    "title": "Prezident İlham Əliyev Ağdamın Kəngərli kəndində klub-icma mərkəzində yaradılan şəraitlə də tanış olub",
    "content": "Azərbaycan Respublikasının Prezidenti İlham Əliyev mayın 10-da Ağdam rayonunun Kəngərli kəndində klub-icma mərkəzində yaradılan şəraitlə də tanış olub.\n\nAZƏRTAC xəbər verir ki, ikimərtəbəli mərkəzdəki otaqlarda rəqs və digər dərnəklər fəaliyyət göstərəcək. Binadakı zalda əlamətdar günlərlə bağlı müxtəlif tədbirlərin, eyni zamanda, gənclərin toplantı və görüşlərinin keçirilməsi üçün hərtərəfli şərait var.",
    "gold_entities": {
      "persons": [
        "İlham Əliyev"
      ],
      "organizations": [
        "AZƏRTAC"
      ],
      "locations": [
        "Ağdam",
        "Kəngərli"
      ],
      "positions": [
        "Azərbaycan Respublikasının Prezidenti"
      ],
      "dates": [
        "mayın 10-da"
      ]
    },
    "manually_verified": true,
    "annotator_notes": ""
  },
  {
    "article_id": "188",
    "source": "azerbaijan.az",
    "link": "https://azerbaijan.az/news/17231",
    "pub_date": "2025-10-09 00:00:00.000",
    "title": "Azərbaycan Prezidenti İlham Əliyev Tacikistana səfərə gəlib",
    "content": "Azərbaycan Respublikasının Prezidenti İlham Əliyev Tacikistan Respublikasının Prezidenti Emoməli Rəhmonun dəvəti ilə MDB Dövlət Başçıları Şurasının iclasında iştirak etmək üçün oktyabrın 9-da Düşənbəyə səfərə gəlib.\n\nAZƏRTAC xəbər verir ki, Düşənbə Beynəlxalq Aeroportunda dövlətimizin başçısının şərəfinə fəxri qarovul dəstəsi düzülmüşdü.\n\nAzərbaycan Prezidentini Tacikistan Respublikası Ali Məclisi Milli Məclisinin sədri Rüstəm Emoməli və digər rəsmi şəxslər qarşıladılar.",
    "gold_entities": {
      "persons": [
        "İlham Əliyev",
        "Emoməli Rəhmon",
        "Rüstəm Emoməli"
      ],
      "organizations": [
        "AZƏRTAC",
        "MDB Dövlət Başçıları Şurası",
        "Düşənbə Beynəlxalq Aeroportu",
        "Tacikistan Respublikası Ali Məclisi Milli Məclisi"
      ],
      "locations": [
        "Tacikistan",
        "Düşənbə"
      ],
      "positions": [
        "Azərbaycan Respublikasının Prezidenti",
        "Tacikistan Respublikasının Prezidenti",
        "Milli Məclisinin sədri"
      ],
      "dates": [
        "oktyabrın 9-da"
      ]
    },
    "manually_verified": true,
    "annotator_notes": ""
  },
  {
    "article_id": "97",
    "source": "azerbaijan.az",
    "link": "https://azerbaijan.az/news/17491",
    "pub_date": "2025-11-05 00:00:00.000",
    "title": "Heydər Əliyev Fondunun vitse-prezidenti Leyla Əliyeva Bülbül adına Orta İxtisas Musiqi Məktəbində olub",
    "content": "Noyabrın 4-də Bülbül adına Orta İxtisas Musiqi Məktəbində Heydər Əliyev Fondunun vitse-prezidenti Leyla Əliyeva ilə görüş keçirilib.\n\nAZƏRTAC xəbər verir ki, görüş çərçivəsində Leyla Əliyeva məktəbin fəaliyyəti, tədris prosesi, musiqi otaqları və istedadlı şagirdlərin yaradıcı uğurları ilə tanış olub.\n\nSonra məktəbin şagirdlərinin iştirakı ilə bədii konsert proqramı təqdim edilib.\n\nKonsert proqramında Azərbaycan və dünya bəstəkarlarının əsərləri səsləndirilib.\n\nSonda Leyla Əliyeva məktəb kollektivi ilə xatirə şəkli çəkdirib.",
    "gold_entities": {
      "persons": [
        "Leyla Əliyeva"
      ],
      "organizations": [
        "AZƏRTAC",
        "Heydər Əliyev Fondu",
        "Bülbül adına Orta İxtisas Musiqi Məktəbi"
      ],
      "locations": [],
      "positions": [
        "Heydər Əliyev Fondunun vitse-prezidenti"
      ],
      "dates": [
        "Noyabrın 4-də"
      ]
    },
    "manually_verified": true,
    "annotator_notes": ""
  },
  {
    "article_id": "1047",
    "source": "azerbaijan.az",
    "link": "https://azerbaijan.az/news/14728",
    "pub_date": "2024-11-11 00:00:00.000",
    "title": "Heydər Əliyev Fondunun vitse-prezidenti Leyla Əliyeva və Prezidentin köməkçisi Anar Ələkbərov COP29 məkanındakı Azərbaycan pavilyonunu ziyarət ediblər",
    "content": "Bakıda BMT-nin İqlim Dəyişmələri üzrə Çərçivə Konvensiyasının Tərəflər Konfransının 29-cu sessiyası (COP29) davam edir.\n\nAZƏRTAC xəbər verir ki, Heydər Əliyev Fondunun vitse-prezidenti Leyla Əliyeva və Prezidentin köməkçisi Anar Ələkbərov tədbirin keçirildiyi məkana baş çəkib, burada yerləşən Azərbaycan pavilyonunu ziyarət ediblər.\n\nQeyd edək ki, noyabrın 11-22-də Bakı Stadionunda keçiriləcək COP29 Azərbaycanın bu günədək təşkil etdiyi ən nəhəng tədbirdir və regionda ilk dəfə ölkəmizdə baş tutur. COP29 çərçivəsində ən yüksəksəviyyəli tədbir – Dünya Liderlərinin İqlim Fəaliyyəti Sammiti noyabrın 12-13-də təşkil olunacaq.",
    "gold_entities": {
      "persons": [
        "Leyla Əliyeva",
        "Anar Ələkbərov"
      ],
      "organizations": [
        "AZƏRTAC",
        "Heydər Əliyev Fondu",
        "COP29",
        "BMT-nin İqlim Dəyişmələri üzrə Çərçivə Konvensiyası",
        "Azərbaycan pavilyonu",
        "Dünya Liderlərinin İqlim Fəaliyyəti Sammiti"
      ],
      "locations": [
        "Bakı",
        "Bakı Stadionu"
      ],
      "positions": [
        "Heydər Əliyev Fondunun vitse-prezidenti",
        "Prezidentin köməkçisi"
      ],
      "dates": [
        "noyabrın 11-22-də",
        "noyabrın 12-13-də"
      ]
    },
    "manually_verified": true,
    "annotator_notes": ""
  },
  {
    "article_id": "72",
    "source": "azerbaijan.az",
    "link": "https://azerbaijan.az/news/17553",
    "pub_date": "2025-11-11 00:00:00.000",
    "title": "Prezident İlham Əliyev Rəcəb Tayyib Ərdoğana zəng edib",
    "content": "Noyabrın 11-də Azərbaycan Respublikasının Prezidenti İlham Əliyev Türkiyə Respublikasının Prezidenti Rəcəb Tayyib Ərdoğana zəng edib.\n\nDövlətimizin başçısı Türkiyə Hərbi Hava Qüvvələrinə məxsus hərbi yük təyyarəsinin Gürcüstan ərazisində qəzaya uğraması ilə əlaqədar Türkiyə Respublikasının Prezidentinə, həlak olmuş hərbçilərin ailələrinə və yaxınlarına, qardaş Türkiyə xalqına dərin hüznlə başsağlığı verib.\n\nTürkiyə Respublikasının Prezidenti telefon zənginə və ifadə edilmiş başsağlığına görə Azərbaycan Respublikasının Prezidentinə təşəkkürünü bildirib.\n\nTelefon danışığı zamanı Azərbaycanın və Türkiyənin aidiyyəti dövlət qurumlarının qəza ilə əlaqədar təmasda olduqları qeyd edilib.",
    "gold_entities": {
      "persons": [
        "İlham Əliyev",
        "Rəcəb Tayyib Ərdoğan"
      ],
      "organizations": [
        "AZƏRTAC",
        "Türkiyə Hərbi Hava Qüvvələri"
      ],
      "locations": [
        "Azərbaycan",
        "Türkiyə",
        "Gürcüstan"
      ],
      "positions": [
        "Azərbaycan Respublikasının Prezidenti",
        "Türkiyə Respublikasının Prezidenti"
      ],
      "dates": [
        "Noyabrın 11-də"
      ]
    },
    "manually_verified": true,
    "annotator_notes": ""
  },
  {
    "article_id": "482",
    "source": "azerbaijan.az",
    "link": "https://azerbaijan.az/news/16397",
    "pub_date": "2025-07-16 00:00:00.000",
    "title": "Azərbaycanla Çin arasında viza rejiminin ləğvi ilə bağlı saziş qüvvəyə minib",
    "content": "Azərbaycan Prezidenti İlham Əliyevin Çinə apreldə dövlət səfəri zamanı imzalanmış “Azərbaycan Respublikası Hökuməti ilə Çin Xalq Respublikası Hökuməti arasında ümumvətəndaş pasportlarına malik vətəndaşların vizadan qarşılıqlı azad edilməsi haqqında Saziş” iyulun 16-da qüvvəyə minib.\n\nAZƏRTAC xəbər verir ki, sazişə əsasən, Azərbaycan Respublikasının etibarlı ümumvətəndaş pasportlarına malik vətəndaşları və Çin Xalq Respublikasının etibarlı ümumvətəndaş pasportlarına malik vətəndaşları digər ölkə ərazisinə daxil olmaq, oranı tərk etmək və yaxın tranzit keçmək üçün hər səfər ərzində otuz (30) gündən çox olmamaqla və hər yüz səksən (180) günlük dövr ərzində ümumilikdə doxsan (90) gün müddətini aşmamaqla viza tələbindən azad edilir.",
    "gold_entities": {
      "persons": [
        "İlham Əliyev"
      ],
      "organizations": [
        "AZƏRTAC",
        "Azərbaycan Respublikası Hökuməti",
        "Çin Xalq Respublikası Hökuməti"
      ],
      "locations": [
        "Azərbaycan",
        "Çin"
      ],
      "positions": [
        "Azərbaycan Prezidenti"
      ],
      "dates": [
        "apreldə",
        "iyulun 16-da",
        "30 gün",
        "180 gün",
        "90 gün"
      ]
    },
    "manually_verified": true,
    "annotator_notes": ""
  },
  {
    "article_id": "770",
    "source": "azerbaijan.az",
    "link": "https://azerbaijan.az/news/15542",
    "pub_date": "2025-03-25 00:00:00.000",
    "title": "Aleksandr Lukaşenko: Belarusla Azərbaycan arasındakı xoşniyyətli münasibətlər ikitərəfli əlaqələrin bundan sonra da genişlənməsinə kömək edəcək",
    "content": "Belarus Respublikasının Prezidenti Aleksandr Lukaşenko Novruz bayramı münasibətilə Azərbaycan Respublikasının Prezidenti İlham Əliyevi təbrik edib.\n\nAZƏRTAC xəbər verir ki, Belarus Prezidenti məktubunda bildirib: “Təbiətin oyanışının və həyatın yeni mərhələsinin başlanğıcının, daha yaxşı gələcəyə inamın rəmzi olan gözəl Novruz bayramı münasibətilə Sizi ürəkdən təbrik edirəm.\n\nƏminəm ki, Belarus ilə Azərbaycan arasında mövcud olan xoşniyyətli münasibətlər dövlətlərimizin xalqlarının rifahı naminə ikitərəfli əlaqələrin bütün sahələrdə bundan sonra da genişlənməsinə kömək edəcək”.\n\nAleksandr Lukaşenko bu əlamətdar bayram günündə dövlətimizin başçısına möhkəm cansağlığı və planlarının uğurla həyata keçməsində uğurlar, ölkəmizin əhalisinə sülh və əmin-amanlıq arzulayıb.",
    "gold_entities": {
      "persons": [
        "Aleksandr Lukaşenko",
        "İlham Əliyev"
      ],
      "organizations": [
        "AZƏRTAC",
        "Belarus Respublikası"
      ],
      "locations": [
        "Belarus",
        "Azərbaycan"
      ],
      "positions": [
        "Belarus Respublikasının Prezidenti",
        "Azərbaycan Respublikasının Prezidenti"
      ],
      "dates": [
        "Novruz bayramı"
      ]
    },
    "manually_verified": true,
    "annotator_notes": ""
  },
  {
    "article_id": "78",
    "source": "azerbaijan.az",
    "link": "https://azerbaijan.az/news/17547",
    "pub_date": "2025-11-08 00:00:00.000",
    "title": "Azərbaycan Prezidentinin, Türkiyə Prezidentinin və Pakistanın Baş nazirinin üçtərəfli görüşü olub",
    "content": "Noyabrın 8-də Azərbaycan Respublikasının Prezidenti İlham Əliyevin, Türkiyə Respublikasının Prezidenti Rəcəb Tayyib Ərdoğanın və Pakistan İslam Respublikasının Baş naziri Məhəmməd Şahbaz Şərifin üçtərəfli görüşü olub.\n\nAZƏRTAC xəbər verir ki, görüşdə Türkiyə Prezidenti və Pakistanın Baş naziri Vətən müharibəsində Qələbənin 5-ci ildönümü münasibətilə dövlətimizin başçısını bir daha təbrik edib, Bakıda keçirilən hərbi paradın yüksək səviyyədə təşkil olunduğunu vurğulayıblar.\n\nSöhbət zamanı Azərbaycanın, Türkiyənin və Pakistanın daim bir-birinin yanında olduqları qeyd edilib, ölkələrimiz arasında siyasi, iqtisadi, hərbi, mədəni-humanitar və digər sahələrdə əməkdaşlığın daha da inkişaf etdiyi bildirilib.\n\nLiderlər Azərbaycan-Türkiyə-Pakistan üçtərəfli formatının perspektivləri ilə bağlı fikir mübadiləsi aparıblar.",
    "gold_entities": {
      "persons": [
        "İlham Əliyev",
        "Rəcəb Tayyib Ərdoğan",
        "Məhəmməd Şahbaz Şərif"
      ],
      "organizations": [
        "AZƏRTAC"
      ],
      "locations": [
        "Bakı",
        "Azərbaycan",
        "Türkiyə",
        "Pakistan"
      ],
      "positions": [
        "Azərbaycan Respublikasının Prezidenti",
        "Türkiyə Respublikasının Prezidenti",
        "Pakistan İslam Respublikasının Baş naziri"
      ],
      "dates": [
        "Noyabrın 8-də",
        "Vətən müharibəsində Qələbənin 5-ci ildönümü"
      ]
    },
    "manually_verified": true,
    "annotator_notes": ""
  },
  {
    "article_id": "561",
    "source": "azerbaijan.az",
    "link": "https://azerbaijan.az/news/16165",
    "pub_date": "2025-06-18 00:00:00.000",
    "title": "Heydər Əliyev Sarayında “Muğam aləmi” VII Beynəlxalq Musiqi Festivalının açılışı olub",
    "content": "Heydər Əliyev Fondu və Mədəniyyət Nazirliyinin təşkilatçılığı, Elm və Təhsil Nazirliyi və Azərbaycan Milli Konservatoriyasının dəstəyi ilə iyunun 17-də Heydər Əliyev Sarayında “Muğam aləmi” VII Beynəlxalq Musiqi Festivalının açılış mərasimi keçirilib.\n\nAZƏRTAC xəbər verir ki, Azərbaycanın zəngin musiqi irsinin incisi olan muğam sənətinin beynəlxalq miqyasda təbliği və qorunması məqsədilə təşkil edilən festivalın açılışı “Bayatı” konsert-tamaşası ilə reallaşıb.\n\nFestivalda 25-dən çox ölkəni təmsil edən 50-dən artıq ifaçı, muğam tədqiqatçısı və qonaq iştirak edir.\n\nMüxtəlif ölkələrdən dəvət olunmuş ifaçılar və muğam ustadları festival günlərində səhnəyə çıxaraq tamaşaçılara muğam sənətinin ecazkar dünyasını yaşadacaqlar.\n\nQeyd edək ki, iyunun 17-dən 22-dək keçiriləcək “Muğam aləmi” VII Beynəlxalq Musiqi Festivalının bağlanış mərasimi Ağdamda təşkil olunacaq.",
    "gold_entities": {
      "persons": [],
      "organizations": [
        "AZƏRTAC",
        "Heydər Əliyev Fondu",
        "Mədəniyyət Nazirliyi",
        "Elm və Təhsil Nazirliyi",
        "Azərbaycan Milli Konservatoriyası",
        "Heydər Əliyev Sarayı",
        "“Muğam aləmi” VII Beynəlxalq Musiqi Festivalı"
      ],
      "locations": [
        "Bakı",
        "Ağdam"
      ],
      "positions": [],
      "dates": [
        "iyunun 17-də",
        "iyunun 17-dən 22-dək"
      ]
    },
    "manually_verified": true,
    "annotator_notes": ""
  },
  {
    "article_id": "1006",
    "source": "azerbaijan.az",
    "link": "https://azerbaijan.az/news/14854",
    "pub_date": "2024-11-29 00:00:00.000",
    "title": "Cəbrayılda daha 40 ailəyə evlərinin açarları təqdim olunub",
    "content": "Bu gün növbəti köç karvanı ilə Cəbrayıl şəhərinə çatan ailələrə evlərinin açarları təqdim olunub.\n\nAZƏRTAC-ın bölgə müxbiri xəbər verir ki, Cəbrayıla qədəm qoyan ailələr qarşılandıqdan sonra onlara ANAMA-nın əməkdaşları tərəfindən mina və partlamamış silah-sursatların təhlükəsi barədə ətraflı məlumat verilib. Tanımadıqları naməlum əşyalar və cisimlərdən uzaq durmaları, belə hallarla qarşılaşdıqları zaman aidiyyəti qurumlara xəbər vermələri tövsiyə olunub.\n\nAçarların təqdim edilməsi mərasimində Cəbrayıl, Qubadlı və Zəngilan rayonlarında Azərbaycan Respublikası Prezidentinin Xüsusi nümayəndəliyinin, Qaçqınların və Məcburi Köçkünlərin İşləri üzrə Dövlət Komitəsinin rəsmiləri və digər şəxslər iştirak ediblər.\n\nAilələr açarları təhvil alıb, evlərində məskunlaşıblar. Köçürülən ailələrin dövlətimizin başçısının göstərişi əsasında Cəbrayıl şəhərində yenidən tikilən evlərdə məskunlaşması üçün bütün şərait yaradılıb.",
    "gold_entities": {
      "persons": [],
      "organizations": [
        "AZƏRTAC",
        "ANAMA",
        "Cəbrayıl, Qubadlı və Zəngilan rayonlarında Azərbaycan Respublikası Prezidentinin Xüsusi nümayəndəliyi",
        "Qaçqınların və Məcburi Köçkünlərin İşləri üzrə Dövlət Komitəsi"
      ],
      "locations": [
        "Cəbrayıl",
        "Qubadlı",
        "Zəngilan"
      ],
      "positions": [],
      "dates": []
    },
    "manually_verified": true,
    "annotator_notes": ""
  },
  {
    "article_id": "713",
    "source": "azerbaijan.az",
    "link": "https://azerbaijan.az/news/15710",
    "pub_date": "2025-04-21 00:00:00.000",
    "title": "Xocalının Ballıca kəndinə daha 21 ailə köçürülüb",
    "content": "Bu gün növbəti köç karvanı ilə Xocalı rayonunun Ballıca kəndinə çatan ailələrə yeni mənzillərin açarları təqdim olunub.\n\nAZƏRTAC-ın bölgə müxbiri xəbər verir ki, 83 nəfərdən ibarət 21 ailə doğma yurduna qovuşub.\n\nAçarların təqdimetmə mərasimində çıxış edən Xankəndi şəhərində, Xocalı və Ağdərə rayonlarında Bərpa, Tikinti və İdarəetmə Xidmətinin icraçı direktoru Telman Kərimli bildirib ki, mərhələli şəkildə doğma torpaqlarına köç edən keçmiş məcburi köçkünlər üçün Ballıca kəndində hər cür şərait yaradılıb. Onların məşğulluq məsələləri diqqət mərkəzində saxlanılır.\n\nBallıca kəndinə köçən sakinlər hərtərəfli dövlət qayğısı ilə əhatə olunduqlarına görə minnətdarlıqlarını bildiriblər. Ailələr açarları təhvil alıb və öz evlərində məskunlaşıblar.\n\nQeyd edək ki, Ballıca kəndi elektrik enerjisi, təbii qaz, içməli su və yüksəksürətli internet xətti ilə təmin edilib. Bu gün köçürülənlər də daxil olmaqla, Ballıca kəndində 157 ailə (742 nəfər) məskunlaşıb.",
    "gold_entities": {
      "persons": [
        "Telman Kərimli"
      ],
      "organizations": [
        "AZƏRTAC",
        "Xankəndi şəhərində, Xocalı və Ağdərə rayonlarında Bərpa, Tikinti və İdarəetmə Xidməti"
      ],
      "locations": [
        "Xocalı",
        "Ballıca",
        "Xankəndi",
        "Ağdərə"
      ],
      "positions": [
        "icraçı direktor"
      ],
      "dates": [
        "Bu gün"
      ]
    },
    "manually_verified": true,
    "annotator_notes": ""
  },
  {
    "article_id": "31",
    "source": "azerbaijan.az",
    "link": "https://azerbaijan.az/news/17676",
    "pub_date": "2025-11-22 00:00:00.000",
    "title": "Leyla Əliyeva, Arzu Əliyeva və Alena Əliyeva Lənkəranda fermer təsərrüfatı ilə tanış olublar",
    "content": "Heydər Əliyev Fondunun vitse-prezidenti, IDEA İctimai Birliyinin təsisçisi və rəhbəri Leyla Əliyeva, Bakı Media Mərkəzinin rəhbəri Arzu Əliyeva və Alena Əliyeva Lənkəranda “Citrus Valley” fermer təsərrüfatına baxış keçiriblər.\n\nAZƏRTAC xəbər verir ki, təsərrüfatın sahibi Rəftarə Şükürova Azərbaycanın ilk aqro-qastro-ekoturizm məkanlarından biri olan “Citrus Valley”in yalnız 2024-cü il ərzində 15 mindən çox turist qəbul etdiyini deyib. Bildirib ki, burada qonaqlar üçün kənd təsərrüfatı proseslərini, xüsusilə meyvə yığımını izləmək, yerli mətbəxin təamlarını dadmaq və onların hazırlanmasını öyrənmək üçün ustad dərslərində iştirak etmək, eləcə də ətraf mühitlə yaxından tanış olmaq imkanı mövcuddur.\n\nLeyla Əliyeva, Arzu Əliyeva və Alena Əliyeva fermer təsərrüfatında yaradılan şəraitlə yaxından tanış olub, məhsullara baxış keçirib, burada çalışan əməkdaşlarla səmimi söhbət edib və onlara fəaliyyətlərində uğurlar arzulayıblar. Sonda təsərrüfatın kollektivi ilə xatirə fotoşəkilləri çəkdirilib.",
    "gold_entities": {
      "persons": [
        "Leyla Əliyeva",
        "Arzu Əliyeva",
        "Alena Əliyeva",
        "Rəftarə Şükürova"
      ],
      "organizations": [
        "AZƏRTAC",
        "Heydər Əliyev Fondu",
        "IDEA İctimai Birliyi",
        "Bakı Media Mərkəzi",
        "Citrus Valley"
      ],
      "locations": [
        "Lənkəran"
      ],
      "positions": [
        "Heydər Əliyev Fondunun vitse-prezidenti",
        "IDEA İctimai Birliyinin təsisçisi",
        "IDEA İctimai Birliyinin rəhbəri",
        "Bakı Media Mərkəzinin rəhbəri"
      ],
      "dates": [
        "2024-cü il"
      ]
    },
    "manually_verified": true,
    "annotator_notes": ""
  },
  {
    "article_id": "420",
    "source": "azerbaijan.az",
    "link": "https://azerbaijan.az/news/16575",
    "pub_date": "2025-08-07 00:00:00.000",
    "title": "Vaşinqtonda Azərbaycan Prezidenti İlham Əliyevin ABŞ Prezidentinin xüsusi elçisi Stiv Uitkoff ilə görüşü olub",
    "content": "Avqustun 7-də Azərbaycan Respublikasının Prezidenti İlham Əliyev Vaşinqtonda ABŞ Prezidentinin xüsusi elçisi Stiv Uitkoff ilə görüşüb.\n\nAZƏRTAC xəbər verir ki, əvvəlcə dövlətimizin başçısı İlham Əliyevin və ABŞ Prezidentinin xüsusi elçisi Stiv Uitkoffun iştirakı ilə SOCAR-la “ExxonMobil” şirkəti arasında “Əməkdaşlıq haqqında Memorandum” imzalanıb.\n\nSənədi Azərbaycan Respublikasının iqtisadiyyat naziri Mikayıl Cabbarov və “ExxonMobil” şirkətinin vitse-prezidenti Con Ardill imzalayıblar.\n\nSonra dövlətimizin başçısı İlham Əliyev ilə ABŞ Prezidentinin xüsusi elçisi Stiv Uitkoffun görüşü olub.\n\nGörüşdə Prezident İlham Əliyevin ABŞ Prezidenti Donald Trampın dəvəti ilə Vaşinqtona işgüzar səfərinin ikitərəfli münasibətlərimizin gündəliyinin və regional məsələlərin müzakirəsi üçün yaxşı fürsət yaratdığı bildirildi.\n\nSöhbət zamanı Azərbaycan Respublikası ilə Amerika Birləşmiş Ştatlarının strateji müstəvidə əməkdaşlığının inkişaf perspektivləri, Ermənistanla Azərbaycan arasında normallaşma prosesi və regiondakı sülh gündəliyinə dair fikir mübadiləsi aparıldı.",
    "gold_entities": {
      "persons": [
        "İlham Əliyev",
        "Stiv Uitkoff",
        "Mikayıl Cabbarov",
        "Con Ardill",
        "Donald Tramp"
      ],
      "organizations": [
        "AZƏRTAC",
        "SOCAR",
        "ExxonMobil",
        "Əməkdaşlıq haqqında Memorandum"
      ],
      "locations": [
        "Vaşinqton",
        "ABŞ",
        "Azərbaycan",
        "Ermənistan",
        "Amerika Birləşmiş Ştatları"
      ],
      "positions": [
        "Azərbaycan Respublikasının Prezidenti",
        "ABŞ Prezidentinin xüsusi elçisi",
        "Azərbaycan Respublikasının iqtisadiyyat naziri",
        "ExxonMobil şirkətinin vitse-prezidenti",
        "ABŞ Prezidenti"
      ],
      "dates": [
        "Avqustun 7-də"
      ]
    },
    "manually_verified": true,
    "annotator_notes": ""
  },
  {
    "article_id": "826",
    "source": "azerbaijan.az",
    "link": "https://azerbaijan.az/news/15378",
    "pub_date": "2025-03-01 00:00:00.000",
    "title": "Prezident İlham ƏIiyev “Barselona” Futbol Klubunun prezidentini qəbul edib",
    "content": "Azərbaycan Respublikasının Prezidenti İlham ƏIiyev martın 1-də “Barselona” Futbol Klubunun prezidenti Xuan Laportanı qəbul edib.\n\nAZƏRTAC xəbər verir ki, qəbula görə dövlətimizin başçısına minnətdarlığını bildirən Xuan Laporta Azərbaycana ilk dəfə COP29 zamanı səfər etdiyini xatırlayaraq, Bakıdakı inkişaf proseslərinin onda dərin təəssürat yaratdığını dedi, burada əməkdaşlıq üçün böyük potensial gördüyünü və məhz buna görə də qısa müddət ərzində ölkəmizə ikinci dəfə gəldiyini vurğuladı.\n\nSöhbət zamanı Azərbaycanda idman sahəsinə, o cümlədən futbolun inkişafına göstərilən dövlət qayğısına toxunuldu, ölkəmizdə nüfuzlu beynəlxalq idman yarışlarının, həmçinin dünya səviyyəli futbol oyunlarının ən yüksək standartlara uyğun təşkil edildiyi qeyd olundu.\n\nGörüşdə Azərbaycanda “Barselona” futbol akademiyasının yaradılması ilə bağlı sənədin imzalanacağı bildirildi, akademiyanın gələcək fəaliyyətinə dair məsələlər ətrafında fikir mübadiləsi aparıldı, ölkəmizdə uşaq futbolunun inkişafı sahəsində əməkdaşlıq məsələləri müzakirə olundu.\n\nXuan Laporta Azərbaycan Prezidentinə xatirə hədiyyəsi təqdim etdi.",
    "gold_entities": {
      "persons": [
        "İlham ƏIiyev",
        "Xuan Laporta"
      ],
      "organizations": [
        "AZƏRTAC",
        "COP29",
        "Barselona Futbol Klubu",
        "Barselona futbol akademiyası"
      ],
      "locations": [
        "Azərbaycan",
        "Bakı"
      ],
      "positions": [
        "Azərbaycan Respublikasının Prezidenti",
        "Barselona Futbol Klubunun prezidenti"
      ],
      "dates": [
        "martın 1-də",
        "COP29 zamanı"
      ]
    },
    "manually_verified": true,
    "annotator_notes": ""
  },
  {
    "article_id": "590",
    "source": "azerbaijan.az",
    "link": "https://azerbaijan.az/news/16081",
    "pub_date": "2025-05-30 00:00:00.000",
    "title": "Prezident İlham Əliyev Alman İqtisadiyyatının Şərq Komitəsinin sədrini qəbul edib",
    "content": "Azərbaycan Respublikasının Prezidenti İlham Əliyev mayın 30-da Alman İqtisadiyyatının Şərq Komitəsinin sədri Mixael Harmsı qəbul edib.\n\nAZƏRTAC xəbər verir ki, söhbət zamanı dövlətimizin başçısının Mixael Harmsla, həmçinin Almaniya biznes dairələri və şirkətlərinin nümayəndələri ilə görüşləri məmnunluqla xatırlandı, Almaniya Prezidentinin ölkəmizə səfərinin ikitərəfli münasibətlərimizin, o cümlədən iqtisadi sahədə əlaqələrimizin genişlənməsində rolu vurğulandı.\n\nAzərbaycanla Almaniya arasında müxtəlif sahələrdə, o cümlədən iqtisadi-ticari sahədə əməkdaşlığın inkişaf etdiyi bildirildi.\n\nMixael Harmsın ölkəmizə səfərinin səmərəli olacağına və iqtisadi əməkdaşlıqla bağlı gündəliyimizin müzakirəsi üçün yaxşı imkan yaradacağına ümidvarlıq ifadə edildi.\n\nQonaq bu gün qarşılıqlı iqtisadi layihələrlə bağlı AZPROMO ilə “Yol xəritəsi”nin imzalanacağını qeyd edərək, bu məsələdə Azərbaycan Prezidentinin siyasi dəstəyini vurğuladı.\n\nGörüşdə Azərbaycanda mövcud olan əlverişli investisiya şəraitinə toxunularaq, bu xüsusda alman iş adamlarının ölkəmizə sərmayə yatırmaları qeyd edildi və iqtisadi əlaqələrin perspektivlərinə dair fikir mübadiləsi aparıldı.",
    "gold_entities": {
      "persons": [
        "İlham Əliyev",
        "Mixael Harms"
      ],
      "organizations": [
        "AZƏRTAC",
        "Alman İqtisadiyyatının Şərq Komitəsi",
        "AZPROMO"
      ],
      "locations": [
        "Azərbaycan",
        "Almaniya"
      ],
      "positions": [
        "Azərbaycan Respublikasının Prezidenti",
        "Alman İqtisadiyyatının Şərq Komitəsinin sədri"
      ],
      "dates": [
        "mayın 30-da",
        "bu gün"
      ]
    },
    "manually_verified": true,
    "annotator_notes": ""
  },
  {
    "article_id": "5",
    "source": "azerbaijan.az",
    "link": "https://azerbaijan.az/news/17747",
    "pub_date": "2025-12-05 00:00:00.000",
    "title": "Bakıda “Mədəni irs və qayıdış hüququ” mövzusunda beynəlxalq konfrans keçirilir",
    "content": "Dekabrın 5-də Bakıda Qərbi Azərbaycan İcması tərəfindən “Mədəni irs və qayıdış hüququ: Ermənistandan didərgin salınmış azərbaycanlıların mədəni irsinin bərpası – ədalətə, barışığa və sülhə aparan yol kimi” mövzusunda III beynəlxalq konfrans keçirilir.\n\nAZƏRTAC xəbər verir ki, əvvəlcə Qərbi Azərbaycan İcmasının fəaliyyəti ilə bağlı videoçarx nümayiş olunub.\n\nDaha sonra Prezident Administrasiyasının Siyasi partiyalar və qanunvericilik hakimiyyəti ilə əlaqələr şöbəsinin müdiri Ədalət Vəliyev Prezident İlham Əliyevin konfrans iştirakçılarına müraciətini oxuyub.\n\nKonfransda Ermənistan ərazisindəki azərbaycanlılara məxsus mədəni irsin vəziyyəti, bu irsin qorunması və dirçəldilməsi, həmçinin qayıdış hüququnun beynəlxalq hüquq və mədəni irsin müdafiəsi kontekstində qiymətləndirilməsi müzakirə olunacaq.\n\nTədbirdə “Qayıdış hüququ və mədəni irs: hüquqi və mənəvi əsaslar”, “Maddi irs: qayıdışın fiziki təməllərinin qorunması”, “Qeyri-maddi irs: qayıdışın canlı əsaslarının dirçəldilməsi”, “Beynəlxalq əməkdaşlıq: qlobal dəstəyin səfərbər olunması” mövzularında panellər keçiriləcək.\n\nQeyd edək ki, 60-dan çox ölkədən 100-dən artıq xarici qonaq və yerli ekspertlər müzakirələrdə iştirak edir.",
    "gold_entities": {
      "persons": [
        "Ədalət Vəliyev",
        "İlham Əliyev"
      ],
      "organizations": [
        "AZƏRTAC",
        "Qərbi Azərbaycan İcması",
        "Prezident Administrasiyası"
      ],
      "locations": [
        "Bakı",
        "Ermənistan"
      ],
      "positions": [
        "Prezident Administrasiyasının Siyasi partiyalar və qanunvericilik hakimiyyəti ilə əlaqələr şöbəsinin müdiri",
        "Azərbaycan Prezidenti"
      ],
      "dates": [
        "Dekabrın 5-də"
      ]
    },
    "manually_verified": true,
    "annotator_notes": ""
  },
  {
    "article_id": "137",
    "source": "azerbaijan.az",
    "link": "https://azerbaijan.az/news/17381",
    "pub_date": "2025-10-24 00:00:00.000",
    "title": "Şarl Mişel: Sülh həmişə daha düzgün və daha ağıllı seçimdir",
    "content": "Mən əvvəlki fəaliyyətim dövründə Ermənistan ilə Azərbaycan arasında dialoqun bərpası istiqamətində müxtəlif təşəbbüsləri dəstəkləmiş, həmin prosesin nə qədər mürəkkəb, nə qədər həssas olduğunu yaxından müşahidə etmişəm. Buna görə də bu gün artıq əldə olunan irəliləyişləri və hər iki tərəfin atdığı cəsarətli addımları görmək mənim üçün böyük məmnunluq doğurur. Bu, gələcəyə ümidlə baxmaq üçün ciddi əsas yaradır. Çünki əgər hər iki tərəf bu cür cəsarətli və uzaqgörən qərarlar qəbul edirsə, bu, səmimi şəkildə daha çox irəliləyiş əldə etmək istəklərinin göstəricisidir.\n\nAZƏRTAC xəbər verir ki, bu fikirləri jurnalistlərə açıqlamasında Avropa İttifaqı Şurasının keçmiş Prezidenti Şarl Mişel bildirib.\n\nO bildirib ki, sülh həmişə daha düzgün və daha ağıllı seçimdir. “Sülh iqtisadi inkişafın, qarşılıqlı əməkdaşlığın və regional inteqrasiyanın yeganə zəmanətidir. Bu, təkcə Azərbaycan üçün deyil, bütövlükdə region üçün həyati əhəmiyyət daşıyır. Bu istiqamətdə atılan hər addım, əldə olunan istənilən nailiyyət yeni iqtisadi imkanların, sərmayə axınının və davamlı inkişafın əsasını qoyur. Mən inanıram ki, bu proses davam edəcək və regionun gələcəyi sabitlik, tərəqqi və əməkdaşlıq ruhu üzərində qurulacaq”, - deyə o qeyd edib.",
    "gold_entities": {
      "persons": [
        "Şarl Mişel"
      ],
      "organizations": [
        "AZƏRTAC",
        "Avropa İttifaqı Şurası"
      ],
      "locations": [
        "Azərbaycan",
        "Ermənistan",
        "Avropa"
      ],
      "positions": [
        "Avropa İttifaqı Şurasının keçmiş Prezidenti"
      ],
      "dates": []
    },
    "manually_verified": true,
    "annotator_notes": ""
  },
  {
    "article_id": "10",
    "source": "azerbaijan.az",
    "link": "https://azerbaijan.az/news/17732",
    "pub_date": "2025-12-03 00:00:00.000",
    "title": "Azərbaycan UNESCO-nun Silahlı Münaqişələr zamanı Mədəni Mülkiyyətin Qorunması üzrə Komitəsinə seçilib",
    "content": "Dekabrın 1-dən 2-dək Birləşmiş Millətlər Təşkilatının Təhsil, Elm və Mədəniyyət üzrə Təşkilatının (UNESCO) Silahlı münaqişələr zamanı mədəni mülkiyyətin mühafizəsi üzrə 1954-cü il Haaqa Konvensiyasının İkinci Protokoluna tərəf dövlətlərin 16-cı iclası keçirilib.\n\nAZƏRTAC xəbər verir ki, bu barədə Xarici İşlər Nazirliyindən məlumat verilib. İclas çərçivəsində Azərbaycan Respublikası UNESCO-nun Silahlı Münaqişələr zamanı Mədəni Mülkiyyətin Qorunması üzrə Komitəsinə 2025-2029-cu illər üzrə üzv seçilib.\n\n4 vakant yer uğrunda Azərbaycanla birgə 6 ölkə mübarizə aparıb. Rəqabət şəraitində keçirilmiş seçkilərin nəticəsində Azərbaycan səsvermənin ilk mərhələsində iştirak edən ölkələrin əksəriyyətinin səsini toplayıb.\n\nQeyd edək ki, sözügedən komitə silahlı münaqişələr zamanı mədəni mülkiyyətin qorunmasını təmin etmək, 1954-cü il Haaqa Konvensiyasının və onun İkinci Protokolunun tələblərinə əməl olunmasına nəzarət etmək, habelə dövlətlərə bu sahədə texniki, hüquqi və institusional dəstəyin göstərilməsini təşviq etmək məqsədilə yaradılıb.\n\nAzərbaycanın komitəyə üzv seçilməsi, ölkəmizin mədəni irsin qorunması sahəsində beynəlxalq aləmdə formalaşmış müsbət imicinin, beynəlxalq platformalarda nümayiş etdirdiyi fəallığın və apardığı ardıcıl siyasətin göstəricisidir.",
    "gold_entities": {
      "persons": [],
      "organizations": [
        "AZƏRTAC",
        "UNESCO",
        "Birləşmiş Millətlər Təşkilatı",
        "Xarici İşlər Nazirliyi",
        "1954-cü il Haaqa Konvensiyası",
        "UNESCO-nun Silahlı Münaqişələr zamanı Mədəni Mülkiyyətin Qorunması üzrə Komitəsi"
      ],
      "locations": [],
      "positions": [],
      "dates": [
        "Dekabrın 1-dən 2-dək",
        "1954-cü il",
        "2025-2029-cu illər"
      ]
    },
    "manually_verified": true,
    "annotator_notes": ""
  },
  {
    "article_id": "923",
    "source": "azerbaijan.az",
    "link": "https://azerbaijan.az/news/15100",
    "pub_date": "2025-01-14 00:00:00.000",
    "title": "Prezident İlham Əliyev Əbu-Dabi Dayanıqlılıq Həftəsinin açılış mərasimində iştirak edib",
    "content": "Yanvarın 14-də Birləşmiş Ərəb Əmirliklərinin paytaxtında Əbu-Dabi Dayanıqlılıq Həftəsinin rəsmi açılışı və Zayed Dayanıqlılıq Mükafatının təqdimat mərasimi keçirilib.\n\nAZƏRTAC xəbər verir ki, Azərbaycan Respublikasının Prezidenti İlham Əliyev tədbirdə iştirak edib.\n\nTədbirdə çıxış edən Birləşmiş Ərəb Əmirliklərinin sənaye və qabaqcıl texnologiyalar naziri Sultan Əhməd Əl-Cabir ölkəsinin dayanıqlılıq sahəsində həyata keçirdiyi siyasət və layihələr barədə məlumat verib, Əbu-Dabi Dayanıqlılıq Həftəsinin mühüm beynəlxalq platforma kimi rolunun artdığını qeyd edib.\n\nSonra Zayed Dayanıqlılıq Mükafatının təqdimat mərasimi olub.\n\nDaha sonra Zayed Dayanıqlılıq Mükafatının qalibləri ilə xatirə fotosu çəkdirilib.\n\nX X X\n\nQeyd edək ki, 2008-ci ildə təsis olunan Əbu-Dabi Dayanıqlılıq Həftəsi ötən illər ərzində dayanıqlı qlobal inkişaf baxımından önəmli müzakirələrin aparıldığı beynəlxalq platformaya çevrilib. Qlobal əməkdaşlıq və liderlik, iqtisadi inkişaf və texnologiya, eləcə də innovasiya prinsiplərini əsas istiqamətlər kimi müəyyənləşdirən Dayanıqlılıq Həftəsi dövlət və hökumət başçılarını, siyasətçiləri, sənaye liderlərini, iş adamlarını və gəncləri bir araya gətirir. Budəfəki Dayanıqlılıq Həftəsində 13 dövlət və hökumət başçısı, eləcə də 140-dan çox nazir və digər rəsmi şəxslər iştirak edir.",
    "gold_entities": {
      "persons": [
        "İlham Əliyev",
        "Sultan Əhməd Əl-Cabir"
      ],
      "organizations": [
        "AZƏRTAC",
        "Əbu-Dabi Dayanıqlılıq Həftəsi",
        "Zayed Dayanıqlılıq Mükafatı",
        "Birləşmiş Ərəb Əmirlikləri"
      ],
      "locations": [
        "Birləşmiş Ərəb Əmirlikləri",
        "Əbu-Dabi"
      ],
      "positions": [
        "Azərbaycan Respublikasının Prezidenti",
        "Birləşmiş Ərəb Əmirliklərinin sənaye və qabaqcıl texnologiyalar naziri"
      ],
      "dates": [
        "Yanvarın 14-də",
        "2008-ci ildə"
      ]
    },
    "manually_verified": true,
    "annotator_notes": ""
  },
  {
    "article_id": "492",
    "source": "azerbaijan.az",
    "link": "https://azerbaijan.az/news/16369",
    "pub_date": "2025-07-11 00:00:00.000",
    "title": "Azərbaycanın daha iki abidəsi UNESCO-nun Dünya İrsinin İlkin Siyahısına daxil edilib",
    "content": "Fransanın paytaxtı Parisdə UNESCO-nun Baş Qərargahında Dünya İrsi Komitəsinin 47-ci sessiyası keçirilir.\n\nAZƏRTAC xəbər verir ki, sessiyanın gündəliyinə uyğun olaraq, iyulun 11-də Dünya İrsinin İlkin Siyahısına təqdim olunan nominasiya fayllarının müzakirəsi aparılıb.\n\nAzərbaycan tərəfindən təqdim olunmuş “Qədim Qəbələ şəhəri” və “Gəmiqaya və Göygöl Tarixi-Mədəni və Təbii Kompleksi” UNESCO-nun Dünya İrsinin İlkin Siyahısına daxil edilib.\n\nQeyd edək ki, Ordubad rayonu ərazisində, Zəngəzur silsiləsinin suayırıcı hissəsində, 3725 metr yüksəklikdə yerləşən Gəmiqaya, Azərbaycan mədəniyyətinin ən qədim nümunələrindən biridir. Bu ərazi Tunc dövrünün müxtəlif mərhələlərinə, Dəmir dövrünə və Orta əsrlərə aid zəngin qayaüstü təsvirlərlə diqqət çəkir.\n\nTarixi mənbələrə əsasən, eramızdan əvvəl IV əsrdən etibarən Azərbaycanın iqtisadi, siyasi və mədəni həyatında mühüm rol oynamış, eramızın I əsrindən yazılı mənbələrdə adıçəkilən Qədim Qəbələ Qafqaz Albaniyasının ilk paytaxtı olmuşdur. Təxminən 2500 illik tarixə malik bu şəhər uzun müddət regionun mühüm siyasi, iqtisadi və ticarət mərkəzlərindən biri olmuşdur.\n\nHər iki abidənin gələcəkdə UNESCO-nun Dünya İrsinin Əsas Siyahısına daxil edilməsi məqsədilə zəruri elmi və təşkilati işlər davam etdiriləcəkdir.\n\nUNESCO-nun Baş Qərargahında Dünya İrsi Komitəsinin 47-ci sessiyası iyulun 16-dək davam edəcək.",
    "gold_entities": {
      "persons": [],
      "organizations": [
        "AZƏRTAC",
        "UNESCO",
        "Dünya İrsi Komitəsi",
        "UNESCO-nun Baş Qərargahı"
      ],
      "locations": [
        "Paris",
        "Fransa",
        "Qəbələ",
        "Göygöl",
        "Gəmiqaya",
        "Ordubad",
        "Zəngəzur",
        "Qafqaz Albaniyası"
      ],
      "positions": [],
      "dates": [
        "iyulun 11-də",
        "iyulun 16-dək",
        "Tunc dövrü",
        "Dəmir dövrü",
        "Orta əsrlər",
        "eramızdan əvvəl IV əsr",
        "eramızın I əsri",
        "təxminən 2500 illik"
      ]
    },
    "manually_verified": true,
    "annotator_notes": ""
  },
  {
    "article_id": "59",
    "source": "azerbaijan.az",
    "link": "https://azerbaijan.az/news/17599",
    "pub_date": "2025-11-14 00:00:00.000",
    "title": "Prezident İlham Əliyev Asiya İnkişaf Bankının nümayəndə heyətini qəbul edib",
    "content": "Azərbaycan Respublikasının Prezidenti İlham Əliyev noyabrın 14-də Asiya İnkişaf Bankının prezidenti Masato Kandanın rəhbərlik etdiyi nümayəndə heyətini qəbul edib.\n\nAZƏRTAC xəbər verir ki, görüşdə Azərbaycan ilə Asiya İnkişaf Bankı arasında səmərəli əməkdaşlığa toxunuldu, birgə layihələrin uğurlu icrası qeyd edildi. 1999-cu ildən indiyədək Asiya İnkişaf Bankı tərəfindən nəqliyyat, su təchizatı, enerji, maliyyə, təhsil, səhiyyə və digər sahələri əhatə edən 145 kredit, qrant, investisiya və texniki yardım layihələri üzrə Azərbaycana 5,5 milyard dollar dəyərində maliyyə dəstəyinin göstərildiyi vurğulandı.\n\nAsiya İnkişaf Bankının Azərbaycan dövləti ilə yanaşı, özəl sektorla da uğurlu əməkdaşlıq etdiyi qeyd olundu. Bu xüsusda neft-qaz, elektrik enerjisi, yol, dəmir yolu, kənd təsərrüfatı, su təchizatı, çirkab suların axıdılması və digər istiqamətlərdə icra olunan birgə layihələrə toxunuldu.\n\nSöhbət zamanı Azərbaycanla Ermənistan arasında sülh gündəliyinin irəli aparılması istiqamətində Vaşinqtonda əldə edilmiş nailiyyətlərin regionun nəqliyyat-tranzit imkanlarının genişləndirilməsi üçün də böyük imkanlar yaratdığı diqqətə çatdırıldı.\n\nGörüşdə Mərkəzi Asiya-Azərbaycan-Avropa marşrutu üzrə bağlantıların önəmi qeyd edildi. Həmçinin ölkəmizlə bank arasında yeni layihələrə toxunuldu, bu xüsusda dəmir yolu, metro şəbəkəsinin genişləndirilməsi və su təchizatı ilə bağlı əməkdaşlıq məsələləri müzakirə olundu.",
    "gold_entities": {
      "persons": [
        "İlham Əliyev",
        "Masato Kanda"
      ],
      "organizations": [
        "AZƏRTAC",
        "Asiya İnkişaf Bankı"
      ],
      "locations": [
        "Azərbaycan",
        "Ermənistan",
        "Vaşinqton",
        "Mərkəzi Asiya",
        "Avropa"
      ],
      "positions": [
        "Azərbaycan Respublikasının Prezidenti",
        "Asiya İnkişaf Bankının prezidenti"
      ],
      "dates": [
        "noyabrın 14-də",
        "1999-cu ildən"
      ]
    },
    "manually_verified": true,
    "annotator_notes": ""
  },
  {
    "article_id": "197",
    "source": "azerbaijan.az",
    "link": "https://azerbaijan.az/news/17204",
    "pub_date": "2025-10-07 00:00:00.000",
    "title": "Azərbaycan Prezidenti İlham Əliyev Qəbələdə Türkmənistan Xalq Məsləhətinin Sədri ilə görüşüb",
    "content": "Azərbaycan Respublikasının Prezidenti İlham Əliyev oktyabrın 7-də Qəbələdə Türkmənistan Xalq Məsləhətinin Sədri Qurbanqulu Berdiməhəmmədov ilə görüşüb.\n\nAZƏRTAC xəbər verir ki, Qurbanqulu Berdiməhəmmədov Türkmənistan Prezidenti Sərdar Berdiməhəmmədovun salamlarını dövlətimizin başçısına çatdırdı.\n\nPrezident İlham Əliyev salamlara görə minnətdarlığını bildirdi, onun da salamlarını Türkmənistan dövlətinin başçısına çatdırmağı xahiş etdi.\n\nSöhbət zamanı Azərbaycan Prezidentinin Türkmənistan Xalq Məsləhətinin Sədri ilə görüşləri, həmçinin onun bu ilin iyulunda ölkəmizə səfəri məmnunluqla xatırlandı.\n\nTürk Dövlətləri Təşkilatının Dövlət Başçıları Şurasının Qəbələdə keçiriləcək 12-ci Zirvə Görüşünün əhəmiyyətinə toxunuldu, bu sammitin türk dövlətləri arasında əməkdaşlığın dərinləşdirilməsi və xalqlararası əlaqələrin daha da inkişaf etdirilməsində rolu vurğulandı.\n\nGörüşdə qardaşlıq, mehriban qonşuluq və əməkdaşlıq prinsiplərinə əsaslanan Azərbaycan-Türkmənistan dövlətlərarası əlaqələrinin hazırkı səviyyəsi yüksək qiymətləndirildi, xalqlarımızı dərin qardaşlıq ənənələrinin birləşdirdiyi qeyd olundu. Siyasi, iqtisadi, nəqliyyat, energetika, parlamentlərarası, humanitar, mədəni, təhsil və digər sahələrdə əlaqələrimizin uğurla inkişaf etdiyi vurğulandı, ölkələrimizin beynəlxalq təşkilatlarda səmərəli əməkdaşlığına toxunuldu.\n\nAzərbaycan Prezidenti və Türkmənistan Xalq Məsləhətinin Sədri əməkdaşlığımızın perspektivləri ilə bağlı fikir mübadiləsi apardılar.",
    "gold_entities": {
      "persons": [
        "İlham Əliyev",
        "Qurbanqulu Berdiməhəmmədov",
        "Sərdar Berdiməhəmmədov"
      ],
      "organizations": [
        "AZƏRTAC",
        "Türk Dövlətləri Təşkilatı",
        "Türkmənistan Xalq Məsləhəti"
      ],
      "locations": [
        "Qəbələ",
        "Azərbaycan",
        "Türkmənistan"
      ],
      "positions": [
        "Azərbaycan Respublikasının Prezidenti",
        "Türkmənistan Xalq Məsləhətinin Sədri",
        "Türkmənistan Prezidenti"
      ],
      "dates": [
        "oktyabrın 7-də",
        "bu ilin iyulunda",
        "12-ci Zirvə Görüşü"
      ]
    },
    "manually_verified": true,
    "annotator_notes": ""
  },
  {
    "article_id": "761",
    "source": "azerbaijan.az",
    "link": "https://azerbaijan.az/news/15563",
    "pub_date": "2025-04-01 00:00:00.000",
    "title": "Almaniya Prezidenti Administrasiyası bu ölkənin Prezidentinin sosial media profilində yerləşdirilmiş postla bağlı Azərbaycan tərəfinə üzrxahlıq edib",
    "content": "Almaniya Prezidentinin sosial media profilində artıq keçmişin qalığı olan qondarma rejimin bayrağının yerləşdirilməsi və onun altında yazılan mətn Azərbaycan tərəfinin ciddi narazılığına səbəb olub. Dərhal iki ölkənin Prezident administrasiyaları və Xarici İşlər nazirlikləri arasında təmaslar başlayıb. Almaniya tərəfi bu postun səhvən yerləşdirildiyini etiraf edərək onu dərhal çıxarıb. Almaniya Prezidenti Administrasiyasının rəhbəri adından ünvanlanmış məktubda baş vermiş bu hadisəyə görə üzrxahlıq ifadə olunaraq, məktubun mediaya verilməsinə razılıq bildirilib.\n\nAZƏRTAC məktubu və onun Azərbaycan dilində tərcüməsini təqdim edir.\n\nAlmaniya Federativ RespublikasınınPrezidenti Administrasiyasının rəhbəriDövlət katibi Dörte Dinger\n\n31 mart 2025-ci il\n\nAzərbaycan Respublikası Prezidentinin köməkçisi Hikmət Hacıyevə\n\nHörmətli Hikmət Hacıyev.\n\nFederal Prezidentin sosial media hesabında qısa müddət ərzində Azərbaycanın bir regionuna aid bayrağın yanlış təsviri və onunla bağlı mətn dərc olunub. Səhv aşkar edildikdən sonra paylaşım dərhal silinib.\n\nBu paylaşım texniki səhv səbəbindən dərc edilib və Almaniyanın Azərbaycanın ərazi bütövlüyünə dair məlum mövqeyi ilə bağlı heç bir məna kəsb etmir.\n\nBelə bir səhvə yol verilməsinə görə çox məyusam. Paylaşımın Azərbaycanda bəzi insanlarda yaratdığı yanlış təəssürata görə səmimi-qəlbdən üzr istəyirəm.\n\nFederal Prezidentin qarşıdan gələn səfəri Azərbaycan-Almaniya tərəfdaşlığını möhkəmləndirmək və regionda davam edən sülh prosesinə dəstək vermək məqsədi daşıyır.\n\nHörmətlə,\n\nD. Dinger",
    "gold_entities": {
      "persons": [
        "Dörte Dinger",
        "Hikmət Hacıyev"
      ],
      "organizations": [
        "AZƏRTAC",
        "Almaniya Federativ Respublikası",
        "Almaniya Federativ Respublikasının Prezidenti Administrasiyası",
        "Federal Prezident"
      ],
      "locations": [
        "Almaniya",
        "Azərbaycan"
      ],
      "positions": [
        "Dövlət katibi",
        "Azərbaycan Respublikası Prezidentinin köməkçisi",
        "Prezident Administrasiyasının rəhbəri"
      ],
      "dates": [
        "31 mart 2025-ci il"
      ]
    },
    "manually_verified": true,
    "annotator_notes": ""
  },
  {
    "article_id": "517",
    "source": "azerbaijan.az",
    "link": "https://azerbaijan.az/news/16294",
    "pub_date": "2025-07-03 00:00:00.000",
    "title": "Prezident İlham Əliyev “Xankəndi” Biznes Mərkəzinin açılışında iştirak edib",
    "content": "Azərbaycan Respublikasının Prezidenti İlham Əliyev iyulun 3-də “Xankəndi” Mehmanxana Kompleksinə aid olan “Xankəndi” Biznes Mərkəzinin açılışında iştirak edib.\n\nAZƏRTAC xəbər verir ki, Azərbaycan Respublikası Prezidentinin İşlər müdiri Ramin Quluzadə dövlətimizin başçısına Mərkəzdə yaradılan şərait barədə məlumat verdi.\n\nDiqqətə çatdırıldı ki, dörd mərtəbədən ibarət “Xankəndi” Biznes Mərkəzi ümumilikdə 4500 kvadratmetrdən artıq sahəni əhatə edir. Burada 24 ofis sahəsi, 6 iclas otağı mövcuddur. Bundan əlavə, Mərkəzdə 120 nəfər qonaq üçün nəzərdə tutulan “Zefir Cafe & Terrace” restoranı, həmçinin dəftərxana və mətbəə məhsullarının satışı, kimyəvi təmizləmə və camaşırxana xidmətləri fəaliyyət göstərəcək.\n\nBildirildi ki, işğaldan azad edilmiş ərazilərdə həyata keçirilən yenidənqurma proseslərinin bir hissəsi olan bu Mərkəz funksional idarəetmə prinsiplərinə və yüksək xidmət meyarlarına cavab verəcək. “Xankəndi” Biznes Mərkəzi rezident şirkətlər üçün müasir və rahat işgüzar mühit təklif edəcək. Müxtəlif sahibkarlıq subyektləri və korporativ strukturlar üçün nəzərdə tutulmuş bu Mərkəz, eyni zamanda, məşğulluğun artırılmasına da töhfə verəcək. İlkin mərhələdə Biznes Mərkəzində 20 nəfər işləyəcək ki, onlardan da 12-si Xankəndi, Xocalı, Şuşa və işğaldan azad olunmuş digər ərazilərin sakinləri, 1-i isə Vətən müharibəsi veteranıdır.\n\nQeyd edək ki, bu cür müasir Mərkəzin fəaliyyətə başlaması Azərbaycanın tarixi şəhəri olan Xankəndinin işğaldan azad edilməsindən sonra burada biznes mühitinin yaradılması, yeni iş yerlərinin açılması və ümumilikdə şəhərin inkişafında mühüm rol oynayacaq.",
    "gold_entities": {
      "persons": [
        "İlham Əliyev",
        "Ramin Quluzadə"
      ],
      "organizations": [
        "AZƏRTAC",
        "Xankəndi Biznes Mərkəzi",
        "Xankəndi Mehmanxana Kompleksi",
        "Zefir Cafe & Terrace"
      ],
      "locations": [
        "Xankəndi",
        "Xocalı",
        "Şuşa"
      ],
      "positions": [
        "Azərbaycan Respublikasının Prezidenti",
        "Azərbaycan Respublikası Prezidentinin İşlər müdiri"
      ],
      "dates": [
        "iyulun 3-də"
      ]
    },
    "manually_verified": true,
    "annotator_notes": ""
  },
  {
    "article_id": "927",
    "source": "azerbaijan.az",
    "link": "https://azerbaijan.az/news/15088",
    "pub_date": "2025-01-09 00:00:00.000",
    "title": "Papa Fransisk COP29-un əhəmiyyətindən danışıb",
    "content": "Roma Katolik Kilsəsinin rəhbəri Papa Fransisk Bakının ev sahibliyi etdiyi BMT-nin İqlim Dəyişmələri üzrə Çərçivə Konvensiyasının Tərəflər Konfransının 29-cu sessiyasının (COP29) əhəmiyyətini vurğulayıb.\n\nAZƏRTAC xəbər verir ki, Papa Fransisk yanvarın 9-da Müqəddəs Taxt-Tacda akkreditə olunmuş diplomatik korpusun rəhbərləri üçün təşkil edilən ənənəvi illik görüşdə Bakıda keçirilən COP29-da iqlimlə bağlı tədbirlər üçün daha çox maliyyə resurslarının təmin edilməsinə dair qərarlar qəbul olunduğunu xatırladıb.\n\n“Mən inanıram ki, bunlar iqlim böhranından çox təsirlənən və böyük iqtisadi borc yükü altında olan bir çox ölkə üçün resursların bölüşdürülməsinə imkan verəcək. Bunu nəzərə alaraq, varlı xalqlardan xahiş edirəm ki, borclarını heç vaxt ödəyə bilməyəcək ölkələrin borclarını bağışlasınlar. Bu, sadəcə olaraq, həmrəylik və ya səxavətlilik deyil, hər şeydən əvvəl, bu gün getdikcə daha çox dərk etdiyimiz bərabərsizliyin yeni forması fonunda ədalət aktıdır: xüsusilə qlobal Şimal ilə Cənub arasında mövcud olan “ekoloji borc”. Həmçinin bu “ekoloji borc”un işığında yoxsul ölkələrin xarici borclarını insan inkişafının inteqral inkişafını təşviq etmək üçün effektiv, yaradıcı və məsuliyyətli siyasət və proqramlara çevirməyin effektiv yollarını tapmaq vacibdir”, - deyə Roma Papası qeyd edib.\n\nPontifik müqəddəs Taxt-Tacın bu prosesi müşayiət etməyə hazır olduğunu vurğulayaraq bildirib: “Bilirik ki, artıq arxasında gizlənə biləcəyimiz heç bir sərhəd, yaxud siyasi və sosial maneə yoxdur”.\n\nGörüşdə ölkəmizin Müqəddəs Taxt-Tacdakı səfiri İlqar Muxtarov da iştirak edib.\n\nQeyd edək ki, Fransiskin iştirakçılara müraciətini Vatikanın əməkdaşı oxuyub.",
    "gold_entities": {
      "persons": [
        "Papa Fransisk",
        "İlqar Muxtarov"
      ],
      "organizations": [
        "AZƏRTAC",
        "Roma Katolik Kilsəsi",
        "COP29",
        "BMT-nin İqlim Dəyişmələri üzrə Çərçivə Konvensiyası",
        "Müqəddəs Taxt-Tac",
        "Vatikan"
      ],
      "locations": [
        "Bakı",
        "Müqəddəs Taxt-Tac",
        "Vatikan"
      ],
      "positions": [
        "Roma Katolik Kilsəsinin rəhbəri",
        "Azərbaycanın Müqəddəs Taxt-Tacdakı səfiri"
      ],
      "dates": [
        "yanvarın 9-da"
      ]
    },
    "manually_verified": true,
    "annotator_notes": ""
  },
  {
    "article_id": "640",
    "source": "azerbaijan.az",
    "link": "https://azerbaijan.az/news/15930",
    "pub_date": "2025-05-12 00:00:00.000",
    "title": "Leyla Əliyevanın təşəbbüsü ilə uşaq və yeniyetmələrə velosipedlər hədiyyə olunub",
    "content": "Mayın 11-də Xızı, Quba, Qax və Yevlax rayonlarında yaşayan uşaq və yeniyetmələr üçün Heydər Əliyev Fondunun vitse-prezidenti, IDEA İctimai Birliyinin təsisçisi və rəhbəri Leyla Əliyevanın təşəbbüsü ilə xüsusi sosial aksiya keçirilib.\n\nIDEA İctimai Birliyinin mətbuat xidmətindən AZƏRTAC-a verilən məlumata görə, Azərbaycan Velosiped İdmanı Federasiyasının dəstəyi ilə keçirilən aksiya çərçivəsində hər rayondan 50 nəfər olmaqla, 6–18 yaş arası ümumilikdə 200 uşaq və yeniyetməyə velosipedlər, onlara uyğun təhlükəsizlik ləvazimatları hədiyyə olunub.\n\nMütəmadi olaraq icra edilən bu təşəbbüsün əsas məqsədi regionlarda yaşayan uşaqların asudə vaxtlarını daha səmərəli şəkildə keçirmələrinə şərait yaratmaq, onların idmana və sağlam həyat tərzinə marağını artırmaq, fiziki aktivliyi təşviq etmək, eləcə də ekoloji nəqliyyat vasitəsi kimi velosiped istifadəsini təşviq etməkdir. Tədbirdə iştirak edən uşaqlar hədiyyələri böyük sevinclə qarşılayıb, təşəbbüsə görə təşkilatçılara minnətdarlıqlarını bildiriblər.\n\nQeyd edək ki, Heydər Əliyev Fondunun vitse-prezidenti, IDEA İctimai Birliyinin təsisçisi və rəhbəri Leyla Əliyevanın təşəbbüsü ilə həm ölkəmizin müxtəlif regionlarında, həm də dünyanın bir sıra ölkələrində humanitar, təhsil, səhiyyə, sosial, ekoloji və digər sahələri əhatə edən genişmiqyaslı layihələr mütəmadi olaraq həyata keçirilir. Müxtəlif hədəf və yaş qruplarını əhatə edən bu təşəbbüslər insanların sosial rifahının yaxşılaşdırılmasına, onların həyat keyfiyyətinin yüksəldilməsinə, təbiətin və biomüxtəlifliyin qorunmasına, ekoloji tarazlığın bərpasına mühüm töhfələr verir. Bu layihələr yüz minlərlə insanın həyatına bilavasitə müsbət təsir göstərərək, həm cəmiyyətin rifahına, həm də planetimizin davamlı inkişafına xidmət edir.",
    "gold_entities": {
      "persons": [
        "Leyla Əliyeva"
      ],
      "organizations": [
        "AZƏRTAC",
        "Heydər Əliyev Fondu",
        "IDEA İctimai Birliyi",
        "Azərbaycan Velosiped İdmanı Federasiyası"
      ],
      "locations": [
        "Xızı",
        "Quba",
        "Qax",
        "Yevlax",
        "Azərbaycan"
      ],
      "positions": [
        "Heydər Əliyev Fondunun vitse-prezidenti",
        "IDEA İctimai Birliyinin təsisçisi",
        "IDEA İctimai Birliyinin rəhbəri"
      ],
      "dates": [
        "Mayın 11-də",
        "6–18 yaş"
      ]
    },
    "manually_verified": true,
    "annotator_notes": ""
  },
  {
    "article_id": "362",
    "source": "azerbaijan.az",
    "link": "https://azerbaijan.az/news/16744",
    "pub_date": "2025-08-25 00:00:00.000",
    "title": "IX “Muğam” Televiziya Müsabiqəsinə Laçında yekun vurulub",
    "content": "Heydər Əliyev Fondunun dəstəyi, Mədəniyyət Nazirliyinin və Azərbaycan Televiziyasının təşkilatçılığı ilə ərsəyə gələn IX “Muğam” Televiziya Müsabiqəsinin final mərhələsi Laçın şəhərində keçirilib.\n\nAZƏRTAC-ın bölgə müxbiri xəbər verir ki, müsabiqənin final mərhələsində gənc xanəndələr Rəis Niftəliyev, Kənan Novruzov, Nərmin Mirzəyeva, Əli Rəşidi, Aycan Şükürlü, Yusif Cəfərbəyli, Aytac Bəybalayeva və azyaşlı ifaçılar Əhəd Ağayev, Kənan Tağızadə, Yusif Mustafayev, Mətləb Əhmədzadə, Murad Nəbizadənin çıxışları dinlənilib. Müsabiqəyə Xalq artistləri Mələkxanım Əyyubova, Mənsum İbrahimov, Nəzakət Teymurova, Sərdar Fərəcov, Vamiq Məmmədəliyev, Əməkdar mədəniyyət işçisi İlqar Fəhmi münsiflik edib.\n\nMünsiflər heyətinin məşvərətindən sonra qaliblərin adı elan olunub.\n\nYeniyetmə ifaçılar arasında birinci yerə Əhəd Ağayev, ikinci yerə Murad Nəbizadə, üçüncü yerə isə Kənan Tağızadə layiq görülüblər.\n\nGənc xanəndələr arasında isə birinci yeri Aytac Bəybalayeva, ikinci yeri Nərmin Mirzəyeva və üçüncü yeri Rəis Niftəliyev tutublar.\n\nYeniyetmə və gənclər arasında ilk üç yerin qaliblərinə Heydər Əliyev Fondunun mükafatları və diplomlar təqdim olunub.\n\nMüsabiqənin digər iştirakçılarına da diplomlar verilib.\n\nTamaşaçılar Əməkdar artist Ehtiram Hüseynovun ifasını dinləyiblər. Sonra qaliblərin ifasında “Qarabağ şikəstəsi” səsləndirilib.\n\nQeyd edək ki, “Muğam” Televiziya Müsabiqəsi Heydər Əliyev Fondunun dəstəyi ilə 2005-ci ildən keçirilir. Azərbaycan Respublikasının Birinci vitse-prezidenti, Heydər Əliyev Fondunun prezidenti Mehriban Əliyevanın təşəbbüsü və dəstəyi ilə keçirilən muğam müsabiqələri gənc ifaçıların yaradıcılıq potensialının üzə çıxarılmasına, xalq musiqisinin yaşadılaraq yeni nəsillərə ötürülməsinə və Azərbaycanın muğam sənətinin beynəlxalq aləmdə tanıdılmasına mühüm töhfə verib.",
    "gold_entities": {
      "persons": [
        "Rəis Niftəliyev",
        "Kənan Novruzov",
        "Nərmin Mirzəyeva",
        "Əli Rəşidi",
        "Aycan Şükürlü",
        "Yusif Cəfərbəyli",
        "Aytac Bəybalayeva",
        "Əhəd Ağayev",
        "Kənan Tağızadə",
        "Yusif Mustafayev",
        "Mətləb Əhmədzadə",
        "Murad Nəbizadə",
        "Mələkxanım Əyyubova",
        "Mənsum İbrahimov",
        "Nəzakət Teymurova",
        "Sərdar Fərəcov",
        "Vamiq Məmmədəliyev",
        "İlqar Fəhmi",
        "Ehtiram Hüseynov",
        "Mehriban Əliyeva"
      ],
      "organizations": [
        "AZƏRTAC",
        "Heydər Əliyev Fondu",
        "Mədəniyyət Nazirliyi",
        "Azərbaycan Televiziyası",
        "IX “Muğam” Televiziya Müsabiqəsi"
      ],
      "locations": [
        "Laçın",
        "Azərbaycan"
      ],
      "positions": [
        "Azərbaycan Respublikasının Birinci vitse-prezidenti",
        "Heydər Əliyev Fondunun prezidenti",
        "Xalq artisti",
        "Əməkdar mədəniyyət işçisi",
        "Əməkdar artist"
      ],
      "dates": [
        "2005-ci ildən"
      ]
    },
    "manually_verified": true,
    "annotator_notes": ""
  },
  {
    "article_id": "1072",
    "source": "azerbaijan.az",
    "link": "https://azerbaijan.az/news/14653",
    "pub_date": "2024-10-25 00:00:00.000",
    "title": "Azərbaycan Prezidenti: Qardaş Qazaxıstanla birgə layihələrin reallaşdırılmasında maraqlıyıq",
    "content": "Azərbaycan qardaş Qazaxıstanla iqtisadiyyat, nəqliyyat-logistika, rəqəmsallaşma, infrastruktur, enerji, humanitar və qarşılıqlı maraq doğuran digər sahələrdə səmərəli tərəfdaşlığın inkişaf etdirilməsində və birgə layihələrin reallaşdırılmasında maraqlıdır.\n\nAZƏRTAC xəbər verir ki, bu fikirlər Azərbaycan Prezidenti İlham Əliyevin Qazaxıstan Prezidenti Kasım-Jomart Tokayevə bu ölkənin milli bayramı – Respublika Günü münasibətilə ünvanladığı təbrik məktubunda yer alıb.\n\nMəktubunda Azərbaycan xalqı adından ən xoş arzularını çatdıran Prezident İlham Əliyev qeyd edib: “Sizin qardaş Qazaxıstanın hərtərəfli inkişafına yönəlmiş qətiyyətli siyasətiniz və həyata keçirdiyiniz islahatlar nəticəsində ölkəniz mühüm nailiyyətlər və uğurlar əldə etmiş, beynəlxalq aləmdə yüksək nüfuz qazanmışdır. Qazaxıstana hər səfərimdə çiçəklənən və müasir bir diyara çevrilmiş ölkənizi görməkdən böyük qürur duyuram”.\n\nXalqlarımızın ortaq tarixi-mədəni köklərindən güc alan, qarşılıqlı inam və dəstəyə əsaslanan Azərbaycan-Qazaxıstan əlaqələrinin və əməkdaşlığının gündən-günə genişlənərək yeni məzmunla zənginləşməsinin məmnunluq doğurduğunu vurğulayan dövlətimizin başçısı əlavə edib: “Qarşılıqlı ali və yüksək səviyyəli səfərlər, müntəzəm təmaslar, müxtəlif sahələrdə imzalanan çoxsaylı sənədlər, həyata keçirdiyimiz birgə layihələr çoxşaxəli əməkdaşlığımızın inkişafında əhəmiyyətli rol oynayır. Bu mənada cari ilin martında Azərbaycana dövlət səfərinizi xüsusi qeyd etmək istərdim”.\n\nPrezident İlham Əliyev əmin olduğunu bildirib ki, Azərbaycan-Qazaxıstan əlaqələrinin həm ikitərəfli, həm də çoxtərəfli müstəvidə genişləndirilməsi, xalqlarımızın firavanlığı, ölkələrimizin və regionumuzun rifahı naminə əməkdaşlığımızın bütün sahələrdə dərinləşdirilməsi, strateji tərəfdaşlığımızın və müttəfiqliyimizin daha da möhkəmləndirilməsi istiqamətində birgə səylər bundan sonra da uğurla davam etdiriləcək.",
    "gold_entities": {
      "persons": [
        "İlham Əliyev",
        "Kasım-Jomart Tokayev"
      ],
      "organizations": [
        "AZƏRTAC"
      ],
      "locations": [
        "Azərbaycan",
        "Qazaxıstan"
      ],
      "positions": [
        "Azərbaycan Prezidenti",
        "Qazaxıstan Prezidenti"
      ],
      "dates": [
        "Respublika Günü",
        "cari ilin martında"
      ]
    },
    "manually_verified": true,
    "annotator_notes": ""
  },
  {
    "article_id": "274",
    "source": "azerbaijan.az",
    "link": "https://azerbaijan.az/news/16993",
    "pub_date": "2025-09-18 00:00:00.000",
    "title": "Prezident İlham Əliyev Avropa İttifaqının Genişlənmə üzrə komissarını qəbul edib",
    "content": "Azərbaycan Respublikasının Prezidenti İlham Əliyev sentyabrın 18-də Avropa İttifaqının Genişlənmə üzrə komissarı Marta Kosu qəbul edib.\n\nAZƏRTAC xəbər verir ki, Marta Kos Ermənistanla Azərbaycan arasında münasibətlərin normallaşması və sülh gündəliyinin irəlilədilməsi istiqamətində əldə edilmiş nailiyyətlər münasibətilə dövlətimizin başçısına təbriklərini çatdırdı. Qonaq dedi ki, Avropa İttifaqı regionda davamlı sülhün təmin olunmasına yönəlmiş səylərə və Azərbaycanın humanitar minatəmizləmə sahəsindəki fəaliyyətinə dəstəyini bundan sonra da davam etdirəcək.\n\nKomissar Marta Kos Avropa İttifaqı ilə Azərbaycan arasında enerji sahəsində uğurlu əməkdaşlığın qurulduğunu deyərək, həmçinin nəqliyyat sahəsində əməkdaşlığın daha da inkişaf etdirilməsi üçün böyük perspektivlərin olduğunu vurğuladı.\n\nPrezident İlham Əliyev bu ilin mayında Tiranada Avropa İttifaqı Şurasının Prezidenti Antonio Koşta və Avropa Komissiyasının Prezidenti Ursula Fon der Lyayen ilə görüşünü məmnunluqla xatırladı.\n\nDövlətimizin başçısı təbriklərə görə təşəkkürünü bildirərək, Azərbaycanın regionda sülh gündəliyinin irəli aparılması üçün səylərini bundan sonra da davam etdirəcəyini vurğuladı. Regionda nəqliyyat bağlantılarının yaradılması üçün yaxşı imkanların olduğunu deyən Prezident İlham Əliyev işğaldan azad edilmiş ərazilərimizdə yol-nəqliyyat infrastrukturunun qurulması ilə bağlı Azərbaycanın intensiv işlər gördüyünü qeyd etdi. Bu xüsusda Zəngilana gedən avtomobil və dəmir yolu xətlərinin əhəmiyyətini vurğuladı.\n\nÖlkəmizin Avropanın enerji təhlükəsizliyinə verdiyi töhfəyə toxunan dövlətimizin başçısı Azərbaycan qazının hazırda Avropanın 10 ölkəsinə, o cümlədən Avropa İttifaqına üzv 8 dövlətə ixrac olunduğu dedi və ixrac coğrafiyasının genişləndiyini qeyd etdi.\n\nGörüşdə Orta Dəhliz ilə Mərkəzi Asiyadan Azərbaycana gələn yüklərin həcmində əsaslı dərəcədə artımın müşahidə olunduğu bildirildi və qarşılıqlı maraq doğuran məsələlər ətrafında fikir mübadiləsi aparıldı.",
    "gold_entities": {
      "persons": [
        "İlham Əliyev",
        "Marta Kos",
        "Antonio Koşta",
        "Ursula Fon der Lyayen"
      ],
      "organizations": [
        "AZƏRTAC",
        "Avropa İttifaqı",
        "Avropa Komissiyası",
        "Orta Dəhliz",
        "ANAMA"
      ],
      "locations": [
        "Azərbaycan",
        "Ermənistan",
        "Tirana",
        "Zəngilan",
        "Avropa",
        "Mərkəzi Asiya"
      ],
      "positions": [
        "Azərbaycan Respublikasının Prezidenti",
        "Avropa İttifaqının Genişlənmə üzrə komissarı",
        "Avropa İttifaqı Şurasının Prezidenti",
        "Avropa Komissiyasının Prezidenti"
      ],
      "dates": [
        "sentyabrın 18-də",
        "bu ilin mayında"
      ]
    },
    "manually_verified": true,
    "annotator_notes": ""
  },
  {
    "article_id": "423",
    "source": "azerbaijan.az",
    "link": "https://azerbaijan.az/news/16566",
    "pub_date": "2025-08-07 00:00:00.000",
    "title": "Avazada Xəzərin dayazlaşması müzakirə edilib",
    "content": "BMT-nin Dənizə çıxışı olmayan inkişaf etməkdə olan ölkələr üzrə Üçüncü Konfransı çərçivəsində Xəzəryanı dövlətlərin hökumət rəsmiləri səviyyəsində iclası keçirilib.\n\nAzərbaycan Respublikasının Nazirlər Kabinetindən AZƏRTAC-a bildirilib ki, görüşdə Xəzər dənizinin dayazlaşmasının mənfi təsirlərini azaltmaq üçün birgə fəaliyyətin əsas istiqamətləri müzakirə olunub.\n\nİclasda çıxış edən Baş nazirin müavini Şahin Mustafayev Xəzəryanı dövlətlər arasında ticarət dövriyyəsinin dayanıqlı artım dinamikasını qeyd edərək, bunun həm ikitərəfli, həm də çoxtərəfli formatlarda əməkdaşlığın dərinləşməsi üçün möhkəm zəmin yaratdığını bildirib.\n\nBaş nazirin müavini cari ilin fevralında Tehranda keçirilmiş III Xəzər İqtisadi Forumunun ticarət və qarşılıqlı investisiya həcmlərinin genişlənməsi, enerji və nəqliyyat-logistika sahələrində əməkdaşlığın dərinləşdirilməsi baxımından əhəmiyyətli olduğunu qeyd edib.\n\nÇıxışında ekoloji çağırışlara da toxunan Şahin Mustafayev su səviyyəsinin aşağı düşməsinin bütün regionda narahatlıq doğurduğunu, bu problemin hələ 2022-ci il Aşqabad Sammitində Azərbaycan Prezidenti tərəfindən qaldırıldığını və Bakıda beştərəfli ekspert qrupunun ilk toplantısının təşkilinə hazırlıqların davam etdiyini vurğulayıb.\n\nƏlavə olaraq, tədbirdə Xəzər dənizinin ekosistemində baş verən dəyişikliklərin sosial-iqtisadi və ekoloji aspektləri geniş şəkildə müzakirə olunub. Su səviyyəsindəki dəyişikliklərin sahilyanı ərazilərdəki həyat şəraitinə və regional inkişaf proseslərinə mümkün təsirləri diqqət mərkəzində olub.\n\nBaş nazirin müavini Şahin Mustafayev qeyd edib ki, səviyyə dəyişikliklərinin mənfi təsirlərinin minimuma endirilməsi üçün elmi-tədqiqat əməkdaşlığının genişləndirilməsi, balıqçılığın, gəmiçiliyin və biomüxtəlifliyin qorunması sahəsində birgə proqramların həyata keçirilməsi zəruridir.\n\nİclas zamanı Xəzər dənizində baş verən dəyişikliklərin öyrənilməsi üçün ümumi standartlar və yanaşmalar formalaşdırmağa imkan verəcək çoxtərəfli qarşılıqlı fəaliyyət mexanizminin işə salınması təşəbbüsü irəli sürülüb.",
    "gold_entities": {
      "persons": [
        "Şahin Mustafayev"
      ],
      "organizations": [
        "AZƏRTAC",
        "BMT",
        "Nazirlər Kabineti",
        "III Xəzər İqtisadi Forumu"
      ],
      "locations": [
        "Avaza",
        "Xəzər dənizi",
        "Tehran",
        "Aşqabad",
        "Bakı"
      ],
      "positions": [
        "Baş nazirin müavini"
      ],
      "dates": [
        "cari ilin fevralında",
        "2022-ci il"
      ]
    },
    "manually_verified": true,
    "annotator_notes": ""
  },
  {
    "article_id": "24",
    "source": "azerbaijan.az",
    "link": "https://azerbaijan.az/news/17695",
    "pub_date": "2025-11-25 00:00:00.000",
    "title": "Ceyhun Bayramov Vatikanda Müqəddəs Taxt-Tacın dövlət katibi ilə görüşüb",
    "content": "Noyabrın 25-də Azərbaycan Respublikasının xarici işlər naziri Ceyhun Bayramov Vatikana rəsmi səfəri çərçivəsində Müqəddəs Taxt-Tacın dövlət katibi kardinal Pietro Parolin ilə görüşüb.\n\nXarici İşlər Nazirliyinin Mətbuat xidməti idarəsindən AZƏRTAC-a bildirilib ki, görüşdə Azərbaycan Respublikası ilə Müqəddəs Taxt-Tac arasında ikitərəfli münasibətlərin mövcud gündəliyi, habelə qarşılıqlı maraq doğuran regional və beynəlxalq məsələlər müzakirə olunub.\n\nAzərbaycanın Müqəddəs Taxt-Tac ilə münasibətlərin inkişafına böyük əhəmiyyət verdiyi diqqətə çatdırılıb, son zamanlar Azərbaycandan Müqəddəs Taxt-Taca baş tutan çoxsaylı yüksəksəviyyəli səfərlərin bunun bariz nümunəsi olduğu bildirilib.\n\nBu çərçivədə Azərbaycan Respublikasının Birinci vitse-prezidenti Mehriban Əliyevanın Müqəddəs Taxt-Taca cari ilin oktyabr ayında həyata keçirilmiş səfərinin əlaqələrimizin qarşılıqlı anlaşma və ortaq dəyərlər əsasında daha da möhkəmlənməsinə təkan verdiyi vurğulanıb. Mehriban xanım Əliyevanın təşəbbüsü və Heydər Əliyev Fondunun dəstəyi ilə Müqəddəs Taxt-Tacda həyata keçirilən mühafizə və bərpa layihələrinin humanitar sahədə əməkdaşlığımız üçün körpü rolunu oynadığı qeyd edilib.\n\nAzərbaycan ərazisində yaşayan bütün etnik və dini icmaların hüquq və təhlükəsizliyinin təmin edildiyi bildirilib, ölkəmizin çoxəsrlik multikulturalizm və tolerantlıq ənənələrindən danışılıb.\n\nDini etiqadların universal insani dəyərlər və qlobal həmrəyliyin təşviqindəki mühüm roluna toxunulub, bu çərçivədə dinlərarası dialoqun daha da dərinləşdirilməsinin, eləcə də mədəni-humanitar sahədə müştərək layihələrin təşviqinin həm ikitərəfli, həm də çoxtərəfli formatlarda dostluq və anlaşma əlaqələrinin gücləndirilməsinə töhfə verdiyi ifadə olunub.\n\nNazir Ceyhun Bayramov görüş zamanı qarşı tərəfə Azərbaycan-Ermənistan normallaşma prosesi, tarixi Vaşinqton Zirvəsi zamanı əldə edilmiş razılaşmalar və onların icrası istiqamətində həyata keçirilən əməli tədbirlər, münaqişədən sonra regionumuzdakı inkişaflar barədə ətraflı məlumat verib.\n\nGörüşdə, həmçinin qarşılıqlı maraq doğuran digər məsələlər ətrafında fikir mübadiləsi aparılıb.",
    "gold_entities": {
      "persons": [
        "Ceyhun Bayramov",
        "Pietro Parolin",
        "Mehriban Əliyeva"
      ],
      "organizations": [
        "AZƏRTAC",
        "Xarici İşlər Nazirliyi",
        "Müqəddəs Taxt-Tac",
        "Heydər Əliyev Fondu"
      ],
      "locations": [
        "Vatikan",
        "Azərbaycan",
        "Ermənistan",
        "Vaşinqton"
      ],
      "positions": [
        "Azərbaycan Respublikasının xarici işlər naziri",
        "Müqəddəs Taxt-Tacın dövlət katibi",
        "kardinal",
        "Azərbaycan Respublikasının Birinci vitse-prezidenti"
      ],
      "dates": [
        "Noyabrın 25-də",
        "cari ilin oktyabr ayında"
      ]
    },
    "manually_verified": true,
    "annotator_notes": ""
  },
  {
    "article_id": "994",
    "source": "azerbaijan.az",
    "link": "https://azerbaijan.az/news/14890",
    "pub_date": "2024-12-05 00:00:00.000",
    "title": "Qərbi Azərbaycan İcmasının Fəxri üzvlük sertifikatları təqdim edilib",
    "content": "“Qayıdış hüququ: Ermənistandan zorla çıxarılmış azərbaycanlılar üçün ədalətin təmin edilməsi” mövzusunda II beynəlxalq konfransda Qərbi Azərbaycan İcmasının Fəxri üzvlük sertifikatları təqdim olunub.\n\nAZƏRTAC xəbər verir ki, sertifikatlar aşağıdakı şəxslərə verilib:\n\n1. Türkiyənin sabiq xarici işlər naziri, Türkiyə Böyük Millət Məclisinin NATO PA-da nümayəndə heyətinin rəhbəri Mövlud Çavuşoğlu;\n\n2. İrəvan xanı Hüseynəli xanın nəslinin nümayəndəsi Əmir Əli Sərdar İrəvani;\n\n3. Türkiyə Böyük Millət Məclisinin üzvü, Ədalət və İnkişaf Partiyasının sədr müavini Zafer Sırakaya;\n\n4. Qərargahı Brüsseldə yerləşən Ümumdünya Pan-Afrika Qadın Liderləri Hərəkatının Baş katibi Aişa Başa;\n\n5. Türkiyə Böyük Millət Məclisinin üzvü, Türkiyə-Azərbaycan parlamentlərarası dostluq qrupunun sədri Şamil Ayrım;\n\n6. İsveçrədə fəaliyyət göstərən Su, Ətraf Mühit və Sağlamlıq Qlobal İnstitutunun təsisçisi və baş direktoru, İsveçrə Su Tərəfdaşlığı və Asiya Su Şurasının üzvü Nidal Salim;\n\n7. Türkiyə Böyük Millət Məclisinin üzvü Cantürk Alagöz;\n\n8. Amerikan Dini Azadlıq Mərkəzinin rəhbəri Cannah Skott;\n\n9. Türkiyə Böyük Millət Məclisinin üzvü, Türkiyə-Azərbaycan parlamentlərarası dostluq qrupunun sədr müavini Orhan Erdem;\n\n10. Rumıniyada fəaliyyət göstərən İncəsənət və İrs Assosiasiyasının prezidenti Nikoleta Zaqura;\n\n11. Şimali Kipr Türk Cümhuriyyəti Prezidentinin beynəlxalq əlaqələr və diplomatiya üzrə xüsusi müşaviri Hüseyin İşıksal;\n\n12. Qazaxıstanın Mədəniyyət və Turizm Nazirliyi nəzdində Tətbiqi Etnosiyasi Tədqiqatlar İnstitutunun direktoru, keçmiş səfir Talqat Kaliyev;\n\n13. Suxumi Dövlət Universitetinin elmi jurnalının redaktoru, AMEA-nın A.Bakıxanov adına Tarix və Etnologiya İnstitutunun fəxri doktoru, Azərbaycan Respublikasının Prezidenti tərəfindən “Tərəqqi” medalı ilə təltif olunan Quram Marxuli;\n\n14. Türkiyədə Heydər Əliyev Avrasiya Araşdırmaları Mərkəzinin müdiri Yaşar Sarı;\n\n15. “Economyfirst Limited London” şirkətinin direktoru, tanınmış jurnalist Klaus Peter Ralf Yürgens;\n\n16. İtaliyanın beynəlxalq məsələlər üzrə “Opinio Juris - Hüquq və Siyasət İcmalı” jurnalının baş redaktoru və Strasburqda Avropa Gəncləri Beyin Mərkəzinin tədqiqatçısı Valentina Chabert.",
    "gold_entities": {
      "persons": [
        "Mövlud Çavuşoğlu",
        "Əmir Əli Sərdar İrəvani",
        "Zafer Sırakaya",
        "Aişa Başa",
        "Şamil Ayrım",
        "Nidal Salim",
        "Cantürk Alagöz",
        "Cannah Skott",
        "Orhan Erdem",
        "Nikoleta Zaqura",
        "Hüseyin İşıksal",
        "Talqat Kaliyev",
        "Quram Marxuli",
        "Yaşar Sarı",
        "Klaus Peter Ralf Yürgens",
        "Valentina Chabert"
      ],
      "organizations": [
        "AZƏRTAC",
        "Qərbi Azərbaycan İcması",
        "NATO PA",
        "Türkiyə Böyük Millət Məclisi",
        "Ədalət və İnkişaf Partiyası",
        "Ümumdünya Pan-Afrika Qadın Liderləri Hərəkatı",
        "Amerikan Dini Azadlıq Mərkəzi",
        "İncəsənət və İrs Assosiasiyası",
        "Su, Ətraf Mühit və Sağlamlıq Qlobal İnstitutu",
        "İsveçrə Su Tərəfdaşlığı",
        "Asiya Su Şurası",
        "Suxumi Dövlət Universiteti",
        "AMEA-nın A.Bakıxanov adına Tarix və Etnologiya İnstitutu",
        "Heydər Əliyev Avrasiya Araşdırmaları Mərkəzi",
        "Economyfirst Limited London",
        "Opinio Juris - Hüquq və Siyasət İcmalı",
        "Avropa Gəncləri Beyin Mərkəzi"
      ],
      "locations": [
        "Brüssel",
        "İsveçrə",
        "Rumıniya",
        "Şimali Kipr Türk Cümhuriyyəti",
        "Qazaxıstan",
        "London",
        "Strasburq",
        "İtaliya",
        "Ermənistan"
      ],
      "positions": [
        "Türkiyənin sabiq xarici işlər naziri",
        "Baş katib",
        "baş direktor",
        "xüsusi müşavir",
        "keçmiş səfir",
        "direktor",
        "baş redaktor"
      ],
      "dates": []
    },
    "manually_verified": true,
    "annotator_notes": ""
  },
  {
    "article_id": "117",
    "source": "azerbaijan.az",
    "link": "https://azerbaijan.az/news/17437",
    "pub_date": "2025-10-28 00:00:00.000",
    "title": "Prezident İlham Əliyev Zəngilanın Ağalı kəndinin 2-ci mərhələsinin və Məmmədbəyli kəndinin açılışlarında iştirak edib",
    "content": "Azərbaycan Respublikasının Prezidenti İlham Əliyev oktyabrın 28-də Zəngilan rayonunun Ağalı kəndinin 2-ci mərhələsinin və Məmmədbəyli kəndinin açılışlarında iştirak edib.\n\nAZƏRTAC xəbər verir ki, Ağalı kəndinin ikinci mərhələsində istifadəyə veriləcək evlərin sayı 103 ədəddir. Bunlar 55-i ikiotaqlı fərdi evlərdən, 3-ü isə üçmərtəbəli 2 bloklu “Townhouse” tipli binalardakı mənzillərdən ibarətdir. 36 ədəd birotaqlı, 12 ədəd isə ikiotaqlı mənzil inşa edilib. Kənddə bütün evlərə kommunikasiya xətləri çəkilib, yaşayış və qeyri-yaşayış binalarının hamısı qazla təmin edilib, evlərdə kombilər quraşdırılıb. Burada ümumi sahəsi 2 hektardan çox olan park salınıb. Park Ağalı və Məmmədbəyli kənd sakinləri, eləcə də qonaqlar üçün açıq istirahət və əyləncə zonası kimi fəaliyyət göstərəcək. Parkın ərazisi 5 funksional zonaya bölünüb. Bu zonalarda uşaqların istirahəti, idman fəaliyyəti və əyləncəsi üçün bütün şərait yaradılıb. Ərazidə müxtəlif ağac və kol bitkiləri əkilib.\n\nx x x\n\nSonra Prezident İlham Əliyev Məmmədbəyli kəndinin açılışında iştirak edib.\n\nDövlətimizin başçısına kənddə yaradılan şərait barədə məlumat verildi.\n\nBildirildi ki, kəndin ümumi sahəsi 51,6 hektardır. Kənddə 188 fərdi ev inşa edilib ki, onlardan 39-u iki, 55-i üç, 55-i dörd və 39-u beşotaqlıdır. Hər bir ev üçün həyətyanı ərazi nəzərə alınaraq hasarlanıb. Evlərdə Günəş panelləri quraşdırılıb, onlar su, işıq, qaz, yüksəksürətli internet şəbəkəsi ilə təmin olunub. Kənddaxili yollar asfaltlanıb. Kənddə çoxfunksiyalı 2 qeyri-yaşayış binası da inşa olunub. İnzibati binalarda, eləcə də keçid və istinad divarlarında zövqlə işlənmiş rəsmlər çəkilib. Bu isə kəndin ümumi görünüşünə əlavə çalarlar qatır. Məmmədbəyli kəndi Ağalı kəndinə çox yaxın məsafədə yerləşdiyindən iqtisadi səmərəliliyin təmin olunması məqsədilə bu kəndləri birləşdirən keçid inşa edilib ki, bu da 360 şagird yerlik Ağalı kənd tam orta məktəbindən, 60 yerlik uşaq bağçasından, Ailə sağlamlıq mərkəzindən, məişət xidməti obyektindən, xidmətlər mərkəzindən, aptekdən, bazar kompleksindən və digər qeyri-yaşayış təyinatlı obyektlərdən istifadənin rahatlığını təmin edəcək.\n\nKənddə yaradılmış şəraitlə tanış olandan sonra dövlətimizin başçısı Məmmədbəyli və Ağalı kəndlərinə köçən sakinlərlə görüşüb, onlara mənzillərin açarlarını təqdim edib.",
    "gold_entities": {
      "persons": [
        "İlham Əliyev"
      ],
      "organizations": [
        "AZƏRTAC"
      ],
      "locations": [
        "Zəngilan",
        "Ağalı",
        "Məmmədbəyli"
      ],
      "positions": [
        "Azərbaycan Respublikasının Prezidenti"
      ],
      "dates": [
        "oktyabrın 28-də"
      ]
    },
    "manually_verified": true,
    "annotator_notes": ""
  },
  {
    "article_id": "311",
    "source": "azerbaijan.az",
    "link": "https://azerbaijan.az/news/16882",
    "pub_date": "2025-09-11 00:00:00.000",
    "title": "Pakistanda “ASAN xidmət” konsepsiyası tətbiq ediləcək",
    "content": "Sentyabrın 8-dən 10-dək Azərbaycan Respublikasının Prezidenti yanında Vətəndaşlara Xidmət və Sosial İnnovasiyalar üzrə Dövlət Agentliyinin sədri Ülvi Mehdiyevin rəhbərlik etdiyi nümayəndə heyəti Pakistan Hökumətinin dəvəti əsasında İslamabad şəhərində səfərdə olub.\n\nDövlət Agentliyinin İctimaiyyətlə əlaqələr şöbəsindən AZƏRTAC-a verilən məlumata görə, səfər çərçivəsində Pakistanın Baş naziri Məhəmməd Şahbaz Şərif Dövlət Agentliyinin sədri Ülvi Mehdiyevin rəhbərlik etdiyi nümayəndə heyətini qəbul edərək “ASAN xidmət” mərkəzinin yaradılması ilə bağlı Pakistan Hökumətinin iclasını keçirib.\n\nİclas zamanı Pakistanda yaradılacaq “ASAN xidmət” konsepsiyasının təqdimatı olub.\n\nPakistanın Baş naziri Azərbaycan Prezidentinin təşəbbüsü ilə yaradılmış “ASAN xidmət” mərkəzinin onda yüksək təəssürat yaratdığını bildirirək, analoji konsepsiyanın Pakistanda dövlət xidmətlərinin göstərilməsinin təkmilləşdirilməsində inqilabi addım olacağını bildirib. Baş nazir “ASAN xidmət” təşəbbüsünün Pakistan Hökumətinin “nağdsız iqtisadiyyat” siyasətini də inkişaf etdirəcəyini və paytaxt İslamabaddan sonra digər şəhər və vilayətlərdə tətbiq olunacağını diqqətə çatdırıb.\n\nPakistanda “ASAN xidmət” mərkəzinin yaradılması prosesində göstəriləcək dəstəyə görə Azərbaycan Prezidentinə minnətdarlığını bildirən Baş nazir müvafiq layihənin iki ölkə arasında iqtisadi əməkdaşlığı daha da gücləndirəcəyini bildirib.\n\nGörüşdən sonra Pakistanın Baş naziri Məhəmməd Şahbaz Şərifin iştirakı ilə “Azərbaycan Respublikası Hökuməti ilə Pakistan İslam Respublikası Hökuməti arasında Pakistan İslam Respublikasında “ASAN xidmət” təcrübəsinin tətbiqi istiqamətində əməkdaşlığa dair Saziş” imzalanıb.\n\nSazişin icrası çərçivəsində qısa müddətdə “ASAN xidmət” mərkəzinin Pakistanda fəaliyyətə başlaması nəzərdə tutulur.\n\nSəfər proqramı çərçivəsində Dövlət Agentliyinin sədri ilə Pakistanın informasiya texnologiyaları və telekommunikasiya naziri arasında görüş olub. Həmçinin “ASAN xidmət” mərkəzinin fəaliyyət göstərməsi nəzərdə tutulan bina infrastrukturlarına baxış keçirilib.\n\nPakistana səfər zamanı Dövlət Agentliyinin sədri Azərbaycanın Pakistandakı səfirliyini ziyarət edib və Azərbaycan xalqının Ümummilli Lideri Heydər Əliyevin abidəsi önünə gül dəstələri qoyub.\n\nSəfər zamanı keçirilən tədbir və görüşlərdə Azərbaycanın Pakistandakı fövqəladə və səlahiyyətli səfiri Xəzər Fərhadov da iştirak edib.",
    "gold_entities": {
      "persons": [
        "Ülvi Mehdiyev",
        "Məhəmməd Şahbaz Şərif",
        "Xəzər Fərhadov",
        "İlham Əliyev"
      ],
      "organizations": [
        "AZƏRTAC",
        "Vətəndaşlara Xidmət və Sosial İnnovasiyalar üzrə Dövlət Agentliyi",
        "ASAN xidmət",
        "Pakistan Hökuməti",
        "Azərbaycan Respublikası Hökuməti",
        "Pakistan İslam Respublikası Hökuməti"
      ],
      "locations": [
        "Pakistan",
        "İslamabad",
        "Azərbaycan"
      ],
      "positions": [
        "Dövlət Agentliyinin sədri",
        "Pakistanın Baş naziri",
        "Azərbaycanın Pakistandakı fövqəladə və səlahiyyətli səfiri",
        "Azərbaycan Respublikasının Prezidenti"
      ],
      "dates": [
        "Sentyabrın 8-dən 10-dək"
      ]
    },
    "manually_verified": true,
    "annotator_notes": ""
  },
  {
    "article_id": "840",
    "source": "azerbaijan.az",
    "link": "https://azerbaijan.az/news/15338",
    "pub_date": "2025-02-25 00:00:00.000",
    "title": "Heydər Əliyev Fondunun vitse-prezidenti Leyla Əliyeva 4-cü Ər-Riyad Beynəlxalq Humanitar Forumunda iştirak edir",
    "content": "Heydər Əliyev Fondunun vitse-prezidenti Leyla Əliyeva fevralın 24-də işinə başlayan 4-cü Ər-Riyad Beynəlxalq Humanitar Forumunda iştirak edir.\n\nAZƏRTAC xəbər verir ki, Kral Salman Humanitar Yardım və Qayğı Mərkəzinin rəhbəri Abdullah Ər-Rabiənin dəvəti ilə Forumda təmsil olunan Leyla Əliyeva “Qlobal humanitar könüllülük: perspektivlər və hədəflər” adlı paneldə çıxış edərək Heydər Əliyev Fondu tərəfindən Azərbaycanda və digər ölkələrdə həyata keçirilən humanitar layihələr barədə məlumat verib.\n\nƏr-Riyad şəhərində iki Müqəddəs Ocağın Xadimi, Səudiyyə Ərəbistanının Kralı Əlahəzrət Salman bin Əbdüləziz Al Səudanın himayəsi altında, Kral Salman Humanitar Yardım və Qayğı Mərkəzinin təşkilatçılığı ilə keçirilən forumda münaqişələr zamanı humanitar diplomatiya, fövqəladə hallarda media və kommunikasiya strategiyası, süni intellektin humanitar yardım fəaliyyətində rolu, beynəlxalq hüquq çərçivəsində humanitar yardım sahəsində mövcud problemlər və gələcək imkanlar müzakirə edilir.\n\nLeyla Əliyeva forumun gündəliyindəki məsələlərin qlobal əhəmiyyətini vurğulayaraq, Azərbaycanın müstəqilliyini yenidən əldə etdikdən sonra aparılan uğurlu siyasət nəticəsində humanitar yardım alan dövlətdən donor dövlətə çevrildiyini bildirib. Heydər Əliyev Fondunun regionun nəhəng qeyri-hökumət təşkilatı kimi 2004-cü ildən genişmiqyaslı humanitar layihələr həyata keçirdiyini qeyd edib. Fondun bir sıra istiqamətlərdə fəaliyyətini önə çəkən Leyla Əliyeva təhsil, səhiyyə və sosial sahələr üzrə layihələrin beynəlxalq səviyyəni əhatə etdiyini, bu fəaliyyətin tərəfdaş təşkilatlar və ölkələr tərəfindən yüksək qiymətləndirildiyini bildirib.\n\nLeyla Əliyeva müasir dünyada iqlim dəyişiklikləri kimi böhrana diqqət çəkərək ətraf mühitin və təbiətin qorunması istiqamətində, eləcə də aclığın aradan qaldırılması kimi problemlə üzləşən ölkələrə yardım sahəsində güclərin səfərbər olmasının vacibliyini vurğulayıb.\n\nHeydər Əliyev Fondunun vitse-prezidenti Azərbaycanın könüllülük fəaliyyəti üzrə uğurlu modelə sahib olduğunu bildirərək mövcud humanitar problemlərin həllində könüllülük proqramlarının inkişaf etdirilməsinin əhəmiyyətini qeyd edib.\n\nQeyd edək ki, fevralın 24-25-də keçirilən forumda bir sıra ölkələrin yüksək səviyyəli rəsmiləri, Ümumdünya Səhiyyə Təşkilatı, Beynəlxalq Miqrasiya Təşkilatı, Beynəlxalq Qırmızı Xaç Cəmiyyəti, BMT-nin Ərzaq və Kənd Təsərrüfatı Təşkilatı, BMT-nin Uşaq Fondu və digər nüfuzlu beynəlxalq təşkilatların rəhbərləri, donor təşkilatlar, beynəlxalq ekspertlər və tədqiqatçılar təmsil olunur.",
    "gold_entities": {
      "persons": [
        "Leyla Əliyeva",
        "Abdullah Ər-Rabia",
        "Salman bin Əbdüləziz Al Səud",
        "Papa Fransisk",
        "Mehriban Əliyeva"
      ],
      "organizations": [
        "AZƏRTAC",
        "Heydər Əliyev Fondu",
        "Kral Salman Humanitar Yardım və Qayğı Mərkəzi",
        "Ümumdünya Səhiyyə Təşkilatı",
        "Beynəlxalq Miqrasiya Təşkilatı",
        "Beynəlxalq Qırmızı Xaç Cəmiyyəti",
        "BMT-nin Ərzaq və Kənd Təsərrüfatı Təşkilatı",
        "BMT-nin Uşaq Fondu"
      ],
      "locations": [
        "Ər-Riyad",
        "Səudiyyə Ərəbistanı",
        "Azərbaycan"
      ],
      "positions": [
        "Heydər Əliyev Fondunun vitse-prezidenti",
        "Kral Salman Humanitar Yardım və Qayğı Mərkəzinin rəhbəri",
        "Səudiyyə Ərəbistanının Kralı",
        "Roma Papası",
        "Heydər Əliyev Fondunun prezidenti"
      ],
      "dates": [
        "fevralın 24-də",
        "fevralın 24-25-də",
        "2004-cü ildən"
      ]
    },
    "manually_verified": true,
    "annotator_notes": ""
  },
  {
    "article_id": "1058",
    "source": "azerbaijan.az",
    "link": "https://azerbaijan.az/news/14695",
    "pub_date": "2024-11-04 00:00:00.000",
    "title": "Vatikan rəsmisi ilə Heydər Əliyev Fondunda görüş keçirilib",
    "content": "Azərbaycan Respublikası Prezidentinin köməkçisi, Heydər Əliyev Fondunun icraçı direktoru Anar Ələkbərov Müqəddəs Taxt-Tacın Şərq kilsələri üzrə dikasteriyasının prefekti kardinal Klaudio Qucerotti ilə görüşüb.\n\nAZƏRTAC xəbər verir ki, görüşdə Azərbaycan və Vatikan arasında mövcud əlaqələr, Heydər Əliyev Fondu ilə əməkdaşlıq çərçivəsində layihələr müzakirə olunub.\n\nKlaudio Qucerotti Heydər Əliyev Fondunun Vatikandakı layihələrini yüksək qiymətləndirib və daimi dəstəyə görə Fondun prezidenti Mehriban Əliyevaya Roma Papası Fransiskin xüsusi minnətdarlığını çatdırıb.\n\nGörüşdə Heydər Əliyev Fondunun Vatikanda katakombaların bərpası, Vatikan muzeyi və Apostol kitabxanası ilə sıx əməkdaşlığı, arxiv əlyazmalarının rəqəmsallaşdırılması, Vatikan arxeoloqlarının Azərbaycana tarixi və dini abidələrin bərpası məqsədilə tanışlıq səfəri və təcrübə mübadiləsi xüsusi qeyd olunub, gələcəkdə yeni layihələrin icrasının vacibliyi vurğulanıb.\n\nKardinal Qucerotti bu tədbirləri yüksək qiymətləndirərək Azərbaycan hökuməti və Heydər Əliyev Fondunun dəstəyi ilə Bakıda yeni katolik kilsəsinin tikintisinin ölkəmizin multikultural siyasətinin bariz nümunəsi olduğunu bildirib.\n\nQonaq dünyada dini zəmində baş verən münaqişələrin genişlənməsi fonunda Azərbaycan hökumətinin həyata keçirdiyi multikulturalizm siyasəti, ölkədə müxtəlif dinlərin sülh şəraitində yaşaması, dini etiqad azadlığının sülhə ən böyük töhfə olduğunu vurğulayıb.\n\nHeydər Əliyev Fondunun icraçı direktoru Anar Ələkbərov Fondun prezidenti Mehriban Əliyevanın Vatikanla münasibətlərə hər zaman xüsusi önəm verdiyini deyib və gələcəkdə də bu əməkdaşlığın inkişaf etdiriləcəyinə əminliyini ifadə edib. Vatikan şəhər dövləti üzrə qubernatorluğu ilə Heydər Əliyev Fondu arasında Müqəddəs Pavel Bazilikasında həyata keçiriləcək bərpa işləri ilə bağlı imzalanmış əməkdaşlıq müqaviləsi tərəflər arasındakı sıx əməkdaşlığın göstəricisi kimi qeyd olunub.\n\nMüqəddəs Taxt-Tacın nümayəndəsi Heydər Əliyev Fondu ilə gələcək layihələr sırasında Vatikanda Azərbaycanın mədəniyyət günlərinin keçirilməsi, sərgi və konsert proqramının təşkil edilməsi və müxtəlif sahələrdə mütəxəssislər arasında qarşılıqlı mübadilə aparılması təklifini də irəli sürüb.\n\nGörüş zamanı Klaudio Qucerottiyə noyabrın 11-dən 22-dək Bakıda keçiriləcək BMT-nin İqlim Dəyişmələri üzrə Çərçivə Konvensiyasının Tərəflər Konfransının 29-cu sessiyasına hazırlıq işləri barədə də məlumat verilib. Qonaq COP29 ərəfəsində “Dünya dinləri yaşıl planet naminə” devizi altında keçiriləcək Dini Liderlərin Qlobal Sammitinin dinlərarası münasibətlərin daha da inkişafına və beynəlxalq konfransın uğuruna töhfə verəcəyinə əminliyini bildirib.",
    "gold_entities": {
      "persons": [
        "Anar Ələkbərov",
        "Klaudio Qucerotti",
        "Mehriban Əliyeva",
        "Papa Fransisk"
      ],
      "organizations": [
        "AZƏRTAC",
        "Heydər Əliyev Fondu",
        "Müqəddəs Taxt-Tac",
        "Vatikan",
        "Vatikan muzeyi",
        "Apostol kitabxanası",
        "Müqəddəs Pavel Bazilikası",
        "COP29",
        "Dünya dinləri yaşıl planet naminə",
        "Dini Liderlərin Qlobal Sammiti"
      ],
      "locations": [
        "Bakı",
        "Vatikan",
        "Azərbaycan"
      ],
      "positions": [
        "Azərbaycan Respublikası Prezidentinin köməkçisi",
        "Heydər Əliyev Fondunun icraçı direktoru",
        "kardinal",
        "prefekt",
        "Heydər Əliyev Fondunun prezidenti"
      ],
      "dates": [
        "noyabrın 11-dən 22-dək"
      ]
    },
    "manually_verified": true,
    "annotator_notes": ""
  },
  {
    "article_id": "438",
    "source": "azerbaijan.az",
    "link": "https://azerbaijan.az/news/16525",
    "pub_date": "2025-07-30 00:00:00.000",
    "title": "XIV Qəbələ Beynəlxalq Musiqi Festivalı başa çatıb",
    "content": "Heydər Əliyev Fondunun təşəbbüsü və təşkilatçılığı, Azərbaycan Respublikasının Mədəniyyət Nazirliyi, Üzeyir Hacıbəyli adına Bakı Musiqi Akademiyası və “Gilan”nın dəstəyi ilə keçirilən XIV Qəbələ Beynəlxalq Musiqi Festivalı başa çatıb. Gözəl ənənəyə çevrilən festival bu dəfə də möhtəşəmliyi ilə musiqisevərlərin diqqətini Qəbələyə cəlb edə bilib. İyulun 24-də başlanan və altı gün davam edən musiqi bayramında Azərbaycanla yanaşı, Latın Amerikası, Gürcüstan və Litvadan görkəmli musiqiçilər, ifaçılar, tanınmış musiqi kollektivləri iştirak ediblər. Budəfəki Qəbələ Beynəlxalq Musiqi Festivalı dahi bəstəkar Üzeyir Hacıbəylinin 140 illik yubileyinə həsr olunmuşdu.\n\nAZƏRTAC-ın bölgə müxbiri xəbər verir ki, festivalın davam etdiyi günlərdə musiqisevərlər və Qəbələnin qonaqları Azərbaycan Dövlət Xalq Çalğı Alətləri Orkestri və Fikrət Əmirov adına Əməkdar Kollektiv Azərbaycan Dövlət Mahnı və Rəqs Ansamblının Xor qrupunun, “Mercadonegro ” musiqi qrupunun (Latın Amerikası), “Tbilisi Big Band” orkestrinin (Gürcüstan), “Ciurlionis” kvartetinin (Litva), həmçinin “Gənclərə dəstək” layihəsi iştirakçılarının, Q.Qarayev adına Azərbaycan Dövlət Kamera Orkestri və “Xarıbülbül” muğam qrupunun iştirakı ilə Xalq artisti Nəzakət Teymurovanın, “Detaşe-Sabah” violinoçular ansamblının, Ü.Hacıbəyli adına Bakı Musiqi Akademiyasının tələbələrinin, tanınmış musiqiçilərin çıxışlarını izləmək imkanı qazanıblar.\n\nXIV Qəbələ Beynəlxalq Musiqi Festivalının bağlanış mərasimi və yekun konsertində Ü.Hacıbəyli adına Azərbaycan Dövlət Simfonik Orkestrinin iştirakı ilə tamaşaçılara “Viva opera” konsert proqramı təqdim olunub. Konsert görkəmli musiqi xadimləri Vasif Adıgözəlovun 90, Rauf Atakişiyevin 100 illik yubileylərinə həsr olunub. Xalq artisti Yalçın Adıgözəlovun dirijorluğu ilə keçən konsertin birinci hissəsində görkəmli bəstəkar Vasif Adıgözəlovun “Bayram uvertürası”, “Piano və orkestr üçün 4 nömrəli konsert”, “Qərənfil” romansı, “Çanaqqala 1915” oratoriyasından türkülər və “Bakı haqqında mahnı” səsləndirilib. Solistlər Murad Adıgözəlzadə (piano), Afaq Abbasova (soprano), Selcan Fermor-Hesketh (soprano) və Əvəz Abdulladır (bariton).\n\nKonsertin ikinci hissəsi Azərbaycan Dövlət Simfonik Orkestrinin bədii rəhbəri və baş dirijoru, Əməkdar artist Fuad İbrahimovun dirijorluğu ilə keçib. Solistlər Xalq artisti Yusif Eyvazov (tenor), Afaq Abbasova (soprano), Aytac Şıxəlizadə (mezzo soprano), Yusif Eyvazov (tenor) və Əvəz Abdullanın (bariton) ifaları tamaşaçılar tərəfindən alqışlarla qarşılanıb.\n\nKonsertin sonunda bütün solistlər birlikdə C.Verdinin “Traviata” operasından “Brindisi” ifa ediblər.\n\nQəbələ Beynəlxalq Musiqi Festivalının Azərbaycanın mədəni həyatında mühüm rolu var. Klassik musiqi vurğunu olan hər bir insanın səbirsizliklə gözlədiyi bu festival həm də yeni istedadların aşkar edilməsinə, bu sahədə bilik mübadiləsinə xidmət edir.",
    "gold_entities": {
      "persons": [
        "Üzeyir Hacıbəyli",
        "Fikrət Əmirov",
        "Nəzakət Teymurova",
        "Vasif Adıgözəlov",
        "Rauf Atakişiyev",
        "Yalçın Adıgözəlov",
        "Murad Adıgözəlzadə",
        "Afaq Abbasova",
        "Selcan Fermor-Hesketh",
        "Əvəz Abdulla",
        "Fuad İbrahimov",
        "Yusif Eyvazov",
        "Aytac Şıxəlizadə"
      ],
      "organizations": [
        "AZƏRTAC",
        "Heydər Əliyev Fondu",
        "Mədəniyyət Nazirliyi",
        "Üzeyir Hacıbəyli adına Bakı Musiqi Akademiyası",
        "Gilan",
        "XIV Qəbələ Beynəlxalq Musiqi Festivalı",
        "Azərbaycan Dövlət Xalq Çalğı Alətləri Orkestri",
        "Fikrət Əmirov adına Azərbaycan Dövlət Mahnı və Rəqs Ansamblı",
        "Mercadonegro",
        "Tbilisi Big Band",
        "Ciurlionis kvarteti",
        "Q.Qarayev adına Azərbaycan Dövlət Kamera Orkestri",
        "Xarıbülbül muğam qrupu",
        "Ü.Hacıbəyli adına Azərbaycan Dövlət Simfonik Orkestri"
      ],
      "locations": [
        "Qəbələ",
        "Bakı",
        "Latın Amerikası",
        "Gürcüstan",
        "Litva",
        "Azərbaycan"
      ],
      "positions": [
        "Xalq artisti",
        "Əməkdar artist",
        "baş dirijor",
        "dirijor"
      ],
      "dates": [
        "iyulun 24-də",
        "altı gün",
        "Üzeyir Hacıbəylinin 140 illik yubileyi"
      ]
    },
    "manually_verified": true,
    "annotator_notes": ""
  },
  {
    "article_id": "507",
    "source": "azerbaijan.az",
    "link": "https://azerbaijan.az/news/16324",
    "pub_date": "2025-07-04 00:00:00.000",
    "title": "Xankəndidə Azərbaycan Prezidenti İlham Əliyevlə İran Prezidenti Məsud Pezeşkianın görüşü olub",
    "content": "İyulun 4-də Xankəndidə Azərbaycan Respublikasının Prezidenti İlham Əliyevlə İran İslam Respublikasının Prezidenti Məsud Pezeşkianın görüşü olub.\n\nAZƏRTACxəbər verir ki, dövlət başçıları söhbət zamanı Azərbaycanla İranın dost, qonşu, qardaş ölkələr olduqlarını vurğulayaraq, ölkələrimiz arasında mədəni, etiqad, ənənələr, etnik baxımdan qohumluq və qardaşlıq əlaqələrinin mövcudluğunu qeyd etdilər.\n\nDövlətimizin başçısı dəvəti qəbul edib İqtisadi Əməkdaşlıq Təşkilatının 17-ci Zirvə görüşündə iştirakına görə İran İslam Respublikasının Prezidenti Məsud Pezeşkiana təşəkkürünü bildirdi, onun bu səfərinin və keçirilən görüşün Azərbaycan-İran ikitərəfli əlaqələrinin, həmçinin İqtisadi Əməkdaşlıq Təşkilatı çərçivəsində əməkdaşlıq məsələlərinin müzakirəsi baxımından əhəmiyyətli olduğunu dedi.\n\nMəsud Pezeşkianın bu ilin aprelində ölkəmizə rəsmi səfərinin ikitərəfli əlaqələrimizdə yeni səhifə açdığını vurğulayan Prezident İlham Əliyev həmin səfər zamanı müzakirə olunan mövzuların həyata keçirilməsi üçün hökumətlərarası komissiyanın rəhbərləri və aidiyyəti dövlət qurumları tərəfindən ardıcıl surətdə işlərin aparıldığını qeyd etdi.\n\nDövlətimizin başçısı İsraillə İran arasında qarşıdurmanın baş verməsindən dərhal sonra İrana qarşı olan bu hərəkətlərin Azərbaycan Respublikası Xarici İşlər Nazirliyi tərəfindən qınanıldığını bildirdi. Prezident İlham Əliyev bu qarşıdurmada İranın rəsmi və mülki şəxslərinin həlak olması ilə əlaqədar bir daha Azərbaycan tərəfinin İran xalqına başsağlığını çatdırdı, Azərbaycan dövlətinin və xalqının İran dövləti və xalqı ilə həmrəyliyini, dəstəyini ifadə etdi. Dövlətimizin başçısı Azərbaycanın həmişə haqq-ədalətin tərəfdarı olduğunu vurğuladı. Prezident İlham Əliyev qeyd etdi ki, müsəlman ölkələri, o cümlədən qonşu dövlətlər ilə əlaqələrin inkişaf etdirilməsi Azərbaycanın xarici siyasətində prioritet istiqamətlərdən biridir.\n\nİqtisadi Əməkdaşlıq Təşkilatının Zirvə görüşünün Azərbaycanda, Xankəndi şəhərində təşkil edilməsini və gələn il İslam Əməkdaşlıq Təşkilatının Zirvə görüşünün ölkəmizdə keçiriləcəyini vurğulayan dövlətimizin başçısı bütün bunları İslam dünyası tərəfindən ölkəmizə olan etimadın və hörmətin növbəti nümunəsi kimi qiymətləndirdi.\n\nİran İslam Respublikasının Prezidenti də İqtisadi Əməkdaşlıq Təşkilatının Zirvə görüşünün yüksək səviyyədə təşkilinə görə təbriklərini çatdırdı.\n\nAzərbaycana rəsmi səfərini və keçirilmiş görüşləri məmnunluqla xatırlayan Məsud Pezeşkian səfərin nəticəsi olaraq Azərbaycan-İran əlaqələrində yeni səhifənin açıldığını vurğuladı, bu xüsusda, artıq Bakı ilə Tehran, Bakı ilə Təbriz arasında təyyarə reyslərinin artırılmasını, Ağbənd-Kəlalə avtomobil yolu körpüsünün tikintisi istiqamətində işlərin aparılmasını qeyd etdi və digər sahələrdə əməkdaşlıq məsələlərinə toxundu.\n\nİran Prezidenti İsraillə baş vermiş qarşıdurma zamanı Azərbaycanın göstərdiyi dəstəyə və həmrəyliyə görə minnətdarlığını bildirdi.\n\nGörüşdə qarşılıqlı maraq doğuran məsələlərə, həmçinin ECO çərçivəsində əlaqələrin genişləndirilməsinə dair ətraflı fikir mübadiləsi aparıldı.",
    "gold_entities": {
      "persons": [
        "İlham Əliyev",
        "Məsud Pezeşkian"
      ],
      "organizations": [
        "AZƏRTAC",
        "İqtisadi Əməkdaşlıq Təşkilatı (ECO)",
        "Azərbaycan Respublikası Xarici İşlər Nazirliyi",
        "İran İslam Respublikası"
      ],
      "locations": [
        "Xankəndi",
        "Azərbaycan",
        "İran",
        "Bakı",
        "Tehran",
        "Təbriz",
        "Ağbənd-Kəlalə"
      ],
      "positions": [
        "Azərbaycan Respublikasının Prezidenti",
        "İran İslam Respublikasının Prezidenti"
      ],
      "dates": [
        "İyulun 4-də",
        "bu ilin aprelində",
        "17-ci Zirvə görüşü",
        "gələn il"
      ]
    },
    "manually_verified": true,
    "annotator_notes": ""
  },
  {
    "article_id": "12",
    "source": "azerbaijan.az",
    "link": "https://azerbaijan.az/news/17728",
    "pub_date": "2025-12-02 00:00:00.000",
    "title": "Otuz iki ildən sonra Horovluda məktəb 103 şagirdlə fəaliyyətə başlayıb",
    "content": "Dekabrın 1-də Cəbrayıl rayonu Horovlu kənd tam orta ümumtəhsil məktəbinin fəaliyyətə başlaması münasibətilə tədbir keçirilib.\n\nŞərqi Zəngəzur Regional Təhsil İdarəsindən AZƏRTAC-ın bölgə müxbirinə verilən məlumata görə, tədbirdə Cəbrayıl, Qubadlı və Zəngilan rayonlarında Azərbaycan Respublikası Prezidentinin xüsusi nümayəndəliyinin əməkdaşları, Şərqi Zəngəzur Regional Təhsil İdarəsinin müdiri Fuad Bədəlov, məktəb kollektivi, şagirdlər, valideynlər və digər qonaqlar iştirak ediblər.\n\nTədbir Dövlət Himninin səsləndirilməsi ilə başlayıb, ardınca şəhidlərin xatirəsi bir dəqiqəlik sükutla yad edilib. Daha sonra çıxış edən Şərqi Zəngəzur Regional Təhsil İdarəsinin müdiri Fuad Bədəlov məktəbin fəaliyyətə başlaması münasibətilə müəllimləri, şagirdləri və valideynləri təbrik edib. O, işğaldan azad olunmuş ərazilərdə tədris prosesinin qısa müddətdə bərpasının ölkəmizdə təhsilə göstərilən yüksək diqqət və qayğının bariz nümunəsi olduğunu vurğulayıb, həmçinin cari tədris ilində qarşıda duran vəzifələr barədə danışıb.\n\nDigər qonaqlar da çıxış edərək sevinclərini ifadə edib və məktəbin fəaliyyətə başlamasını əlamətdar hadisə kimi dəyərləndiriblər.\n\nTədbir bədii hissə ilə davam edib.\n\nDaha sonra iştirakçılar yeni tikilmiş məktəbdə yaradılan şərait və tədris prosesi ilə yaxından tanış olublar.\n\nMəktəbin müəllimi Lalə Əhmədova 1993-cü ildə işğal zamanı cəmi 2-ci sinif şagirdi ikən tərk etdiyi doğma kəndinə bu gün müəllim kimi qayıtdığını deyib. Onun sözlərinə görə, illər sonra yenidən Horovluda olmaq, doğulduğu məktəbdə çalışmaq böyük qürur və sevinc hissidir. \"Bu məktəbdə öz vəzifə borcumu həm də sevərək yerinə yetirəcəyəm. Bizə bu günü yaşadan Ali Baş Komandan İlham Əliyevə təşəkkür edirəm. Allah şəhidlərimizə rəhmət etsin, qazilərimizə cansağlığı versin. Horovlu kəndində inşa olunan yeni məktəb müasir standartlara tam cavab verir. Mən gözlədiyimdən də mükəmməl şəraitli bir məktəbə gəldim. İnanıram ki, burada yüksək nəticələr göstərəcək şagirdlərin sayı çox olacaq. Ən böyük arzumuz doğma kəndimizdə şagirdlərə təhsil vermək idi və bu arzu artıq gerçəyə çevrilib. Kənd ümumiyyətlə bizi çox gözəl abad şəkildə qarşıladı. Yeni evlər tikilib, yollar salınıb, bütün lazım olan infrastruktur yaradılıb. Kəndimizin mərkəzində gözoxşayan istirahət parkı inşa olunub. Həm də kəndimizin kəhrizlərinin bərpa olunması məni çox sevindirdi. Uşaqlıq xatirələrim canlandı, səhənglə kəhrizdən su götürməyimiz gözümün önünə gəldi. Horovluda xoşbəxt günlərimiz yenidən başlayıb\", - deyə Lalə müəllimə bildirib.\n\nMəktəb direktoru Zamiq Həmzəyev deyib: “Çox qürurluyam, sevincimin həddi-hüdudu yoxdur, bir vaxtlar şagird kimi çıxdığım məktəbə müəllim olaraq qayıtdım. Horovluya doğma kəndimizə qovuşmaq mənim üçün yenidən dünyaya gəlməyə bərabərdir. Bu xoşbəxtliyi bizə bəxş edən şəhidlərimizə Allahdan rəhmət diləyirəm, qazilərimizə şəfa arzu edirəm. Azərbaycanın müzəffər Ordusu Ali Baş Komandan İlham Əliyevin rəhbərliyi ilə sözün əsl mənasında yeni tarix yazdı. Torpaqlarımızın hər qarışı azad edildi. Artıq bu torpaqlarda həyat yenidən canlanır. Bizim kəndimiz də yenidən qurulub, evlər inşa olunub, müasir standartlara uyğun məktəb tikilib. İnanıram ki, məktəbimizin uğurları daimi olacaq\".\n\nQeyd edək ki, cari tədris ilində Horovlu kənd tam orta ümumtəhsil məktəbində 103 şagirddən ibarət 11 sinif formalaşdırılıb və 17 müəllim tədris aparacaq.",
    "gold_entities": {
      "persons": [
        "Fuad Bədəlov",
        "Lalə Əhmədova",
        "Zamiq Həmzəyev",
        "İlham Əliyev"
      ],
      "organizations": [
        "AZƏRTAC",
        "Şərqi Zəngəzur Regional Təhsil İdarəsi",
        "Şərqi Zəngəzur Regional Təhsil İdarəsi",
        "Cəbrayıl, Qubadlı və Zəngilan rayonlarında Azərbaycan Respublikası Prezidentinin xüsusi nümayəndəliyi"
      ],
      "locations": [
        "Cəbrayıl",
        "Horovlu",
        "Şərqi Zəngəzur",
        "Qubadlı",
        "Zəngilan"
      ],
      "positions": [
        "Şərqi Zəngəzur Regional Təhsil İdarəsinin müdiri",
        "məktəb direktoru",
        "məktəbin müəllimi",
        "Ali Baş Komandan"
      ],
      "dates": [
        "Dekabrın 1-də",
        "1993-cü ildə",
        "cari tədris ili"
      ]
    },
    "manually_verified": true,
    "annotator_notes": ""
  },
  {
    "article_id": "245",
    "source": "azerbaijan.az",
    "link": "https://azerbaijan.az/news/17075",
    "pub_date": "2025-09-25 00:00:00.000",
    "title": "Azərbaycan Prezidenti İlham Əliyev BMT-nin Baş katibi Antonio Quterreş ilə görüşüb",
    "content": "Sentyabrın 25-də BMT-nin mənzil-qərargahında Azərbaycan Respublikasının Prezidenti İlham Əliyev Birləşmiş Millətlər Təşkilatının Baş katibi Antonio Quterreş ilə görüşüb.\n\nAZƏRTAC xəbər verir ki, əvvəlcə dövlətimizin başçısı BMT-nin fəxri qonaqlar kitabını imzaladı.\n\nSonra Azərbaycan Prezidenti İlham Əliyev və BMT-nin Baş katibi Antonio Quterreş birgə foto çəkdirdilər.\n\nBaş katib Ermənistanla Azərbaycan arasında sülh gündəliyinin irəlilədilməsi və əldə olunmuş tarixi nəticələr münasibətilə dövlətimizin başçısına təbriklərini çatdırdı.\n\nBMT-nin Qaçqınlar üzrə Ali Komissarı vəzifəsində Azərbaycana səfərini xatırlayan Antonio Quterreş həmin vaxt ölkəmizdə qaçqın və məcburi köçkünlərin ağır vəziyyəti ilə yerində tanış olduğunu dedi. O, bütün bu məsələlərin artıq keçmişdə qaldığını sevinc hissi ilə vurğulayaraq, Azərbaycan hökuməti tərəfindən məcburi köçkünlərin öz doğma yurdlarına qayıtmaları ilə əlaqədar böyükmiqyaslı layihələr həyata keçirdiyini qeyd etdi.\n\nBMT-nin Baş katibi COP29-un Azərbaycanda uğurla keçirilməsi və beynəlxalq iqlim gündəliyinin irəli aparılması baxımından əldə olunmuş nailiyyətlər münasibətilə də dövlətimizin başçısını təbrik etdi və bu tədbirin yüksək səviyyədə keçirilməsi ilə bağlı təşəkkürünü çatdırdı.\n\nAntonio Quterreş BMT ilə Azərbaycan arasında əməkdaşlığın inkişafından məmnunluğunu ifadə edərək, hazırda ölkəmizin bu təşkilatın digər regionlarda fəaliyyətini dəstəklədiyinə görə minnətdarlığını bildirdi, beynəlxalq böhranların aradan qaldırılmasında Azərbaycanla BMT arasında əməkdaşlıq üçün böyük perspektivlərin olduğunu qeyd etdi.\n\nAzərbaycanın çoxtərəfli diplomatiyada fəal roluna toxunan BMT-nin Baş katibi Qoşulmama Hərəkatında ölkəmizin uğurlu sədrliyini də vurğuladı, Azərbaycanın artıq donor ölkə olaraq BMT-nin müxtəlif institutlarının fəaliyyətinə göstərdiyi dəstəyin yüksək qiymətləndirildiyini bildirdi.\n\nBMT-nin Baş katibi ölkəmizin regional əməkdaşlıq layihələrinin inkişafındakı, həmçinin Mərkəzi Asiya ilə regional nəqliyyat bağlantılarının yaradılmasındakı rolunu qeyd etdi.\n\nDövlətimizin başçısı təbriklərə görə minnətdarlığını bildirdi.\n\nPrezident İlham Əliyev Ermənistanla Azərbaycan arasında münasibətlərin normallaşdırılması və sülh gündəliyi ilə bağlı əldə olunmuş nəticələrin tarixi əhəmiyyət daşıdığını vurğuladı. İki ölkə arasındakı münasibətlərin və regiondakı vəziyyətin tamamilə dəyişdiyini deyən dövlətimizin başçısı bildirdi ki, Azərbaycan və Ermənistan müstəqilliklərini əldə edəndən bəri regionda sülh olmayıb. Hazırda isə bölgədə sülh mövcuddur. Hər iki ölkənin sülh şəraitində yaşamağa öyrəşdiklərini vurğulayan Prezident İlham Əliyev bunun həm Azərbaycan, həm də Ermənistan üçün mühüm və tarixi önəm kəsb etdiyini diqqətə çatdırdı.\n\nDövlətimizin başçısı da öz növbəsində işğaldan azad olunmuş ərazilərimizdə görülən genişmiqyaslı bərpa və quruculuq işlərini qeyd etdi. Bu xüsusda Prezident İlham Əliyev 53 mindən artıq keçmiş məcburi köçkünün öz doğma torpaqlarına qayıtdığını, Azərbaycanın “Böyük Qayıdış” Proqramına uyğun olaraq genişmiqyaslı bərpa və quruculuq işlərini həyata keçirdiyini bildirdi.\n\nDövlətimizin başçısı Azərbaycanın donor kimi COVID-19 zamanı 80-dən çox ölkəyə yardım göstərdiyini qeyd etdi və bundan sonra da regional, həmçinin beynəlxalq sülh gündəliyini dəstəkləyərək bu işə öz töhfəsini verəcəyini dedi.\n\n2026-cı ildə ölkəmizdə BMT-nin Ümumdünya Şəhərsalma Forumu kimi böyük tədbirinin keçiriləcəyinə toxunan Prezident İlham Əliyev vurğuladı ki, bu tədbir Azərbaycanın şəhərsalma, xüsusən də postmünaqişə şəraitində şəhərsalma sahəsində əldə etdiyi zəngin təcrübəsinin beynəlxalq ictimaiyyətlə bölüşməsi üçün yaxşı fürsət yaradır.",
    "gold_entities": {
      "persons": [
        "İlham Əliyev",
        "Antonio Quterreş"
      ],
      "organizations": [
        "AZƏRTAC",
        "BMT",
        "BMT-nin Qaçqınlar üzrə Ali Komissarlığı",
        "COP29",
        "Qoşulmama Hərəkatı",
        "Böyük Qayıdış Proqramı"
      ],
      "locations": [
        "BMT-nin mənzil-qərargahı",
        "Azərbaycan",
        "Ermənistan",
        "Mərkəzi Asiya"
      ],
      "positions": [
        "Azərbaycan Respublikasının Prezidenti",
        "BMT-nin Baş katibi"
      ],
      "dates": [
        "Sentyabrın 25-də",
        "2026-cı ildə",
        "COVID-19 zamanı"
      ]
    },
    "manually_verified": true,
    "annotator_notes": ""
  },
  {
    "article_id": "414",
    "source": "azerbaijan.az",
    "link": "https://azerbaijan.az/news/16593",
    "pub_date": "2025-08-09 00:00:00.000",
    "title": "Azərbaycan Prezidentinin və Ermənistanın Baş nazirinin Vaşinqton şəhərində keçirilmiş görüşünə dair Birgə Bəyannamə imzalanıb",
    "content": "Avqustun 8-də Azərbaycan Respublikasının Prezidenti İlham Əliyev, Amerika Birləşmiş Ştatlarının Prezidenti Donald Tramp və Ermənistan Respublikasının Baş naziri Nikol Paşinyan Azərbaycan Respublikasının Prezidentinin və Ermənistan Respublikasının Baş nazirinin Amerika Birləşmiş Ştatlarının Vaşinqton şəhərində keçirilmiş görüşünə dair Birgə Bəyannaməni imzaladılar.\n\nAZƏRTAC Bəyannaməni təqdim edir.\n\nAzərbaycan Respublikasının Prezidenti və Ermənistan Respublikasının Baş nazirinin Amerika Birləşmiş Ştatlarının Vaşinqton şəhərində keçirilmiş görüşünün nəticələrinə dair\n\nBİRGƏ BƏYANNAMƏ\n\nBiz, Azərbaycan Respublikasının Prezidenti və Ermənistan Respublikasının Baş Naziri 8 avqust 2025-ci il tarixində Amerika Birləşmiş Ştatlarının Vaşinqton şəhərində görüşərək, aşağıdakıları bəyan edirik:\n\n1. Biz və Amerika Birləşmiş Ştatlarının Prezidenti Donald Tramp “Azərbaycan Respublikası və Ermənistan Respublikası arasında sülhün və dövlətlərarası münasibətlərin təsis olunması haqqında Saziş”in razılaşdırılmış mətninin tərəflərin xarici işlər nazirləri tərəfindən paraflanmasına şahidlik etdik. Bu kontekstdə, biz Sazişin imzalanması və yekun olaraq ratifikasiyası üçün əlavə tədbirlərin görülməsinin davam etdirilməsinə ehtiyac olduğunu qəbul etdik və ölkələrimiz arasında sülhün təmin edilməsi və gücləndirilməsinin vacibliyini vurğuladıq;\n\n2. Biz, həmçinin Avropada Təhlükəsizlik və Əməkdaşlıq Təşkilatının (ATƏT) Minsk Prosesi və onunla əlaqəli strukturlarının bağlanmasına dair Azərbaycan Respublikasının xarici işlər naziri və Ermənistan Respublikasının xarici işlər naziri tərəfindən ATƏT-ə birgə müraciətin imzalanmasına şahidlik etdik. Biz ATƏT-in bütün iştirakçı dövlətlərini bu qərarı qəbul etməyə çağırırıq;\n\n3. Biz regionda və onun qonşuluğunda dövlətlərin suverenliyi, ərazi bütövlüyü və yurisdiksiyasına hörmət əsasında sülhün, sabitliyin və rifahın təşviqi üçün iki ölkə arasında ölkədaxili, ikitərəfli və beynəlxalq nəqliyyatın təmini məqsədilə kommunikasiyaların açılmasının əhəmiyyətini bir daha təsdiq etdik. Bu səylər Azərbaycan Respublikasının əsas hissəsi və onun Naxçıvan Muxtar Respublikası arasında maneəsiz bağlantını və Ermənistan Respublikası üçün beynəlxalq və ölkədaxili bağlantılar üzrə qarşılıqlı faydaları ehtiva edir;\n\n4. Ermənistan Respublikası Ermənistan Respublikasının ərazisində “Beynəlxalq Sülh və Rifah naminə Tramp Marşrutu” (TRIPP) bağlantı layihəsi üçün çərçivənin müəyyən edilməsi məqsədilə Amerika Birləşmiş Ştatları və qarşılıqlı müəyyən edilmiş üçüncü tərəflər ilə əməkdaşlıq edəcəkdir. Biz bu məqsədə ən qısa zamanda nail olmaq üçün xoş niyyətlə səy göstərməyə dair qətiyyətimizi təsdiq edirik;\n\n5. Biz BMT Nizamnaməsi və 1991-ci il Almatı Bəyannaməsinə uyğun olaraq, keçmiş münaqişənin əsiri olmayan parlaq gələcək yoluna qədəm qoyulmasına olan ehtiyacı qəbul edirik. Dərin insan iztirablarına səbəb olmuş münaqişədən sonra nəhayət ki, beynəlxalq sərhədlərin toxunulmazlığı və ərazi əldə olunması üçün güc tətbiq etmənin yolverilməzliyi əsasında dövlətlərimizin qonşuluq münasibətlərinin qurulmasına başlaması üçün şərtlər yaradılmışdır. Yenidən təftiş mövzusu olmayan və heç bir zaman olmayacaq bu reallıq dövlətlərimiz arasında düşmənçilik səhifəsinin bağlanmasına yol açır. Biz indi və gələcəkdə hər hansı bir qisas cəhdini qətiyyətlə rədd edir və istisna edirik;\n\n6. Biz bu Zirvə görüşünün regionda qarşılıqlı hörmət və sülhün irəlilədilməsi üçün möhkəm təməl təşkil edəcəyinə əminliyimizi ifadə edirik;\n\n7. Biz bu vacib Zirvə görüşünə ev sahibliyi çərçivəsində səmimi qonaqpərvərliyə və Azərbaycan Respublikası ilə Ermənistan Respublikası arasında ikitərəfli əlaqələrin normallaşdırılmasının irəlilədilməsinə vacib töhfələrinə görə Amerika Birləşmiş Ştatlarının Prezidenti Donald Trampa dərin minnətdarlığımızı ifadə edirik.\n\nBu Bəyannamə 8 avqust 2025-ci il tarixində Amerika Birləşmiş Ştatlarının Vaşinqton şəhərində imzalanmışdır.\n\nİlham ƏLİYEV                                                                                    Nikol PAŞİNYAN",
    "gold_entities": {
      "persons": [
        "İlham ƏLİYEV",
        "Donald Tramp",
        "Nikol PAŞİNYAN"
      ],
      "organizations": [
        "AZƏRTAC",
        "ATƏT",
        "ATƏT-in Minsk Prosesi",
        "TRIPP",
        "BMT Nizamnaməsi",
        "Almatı Bəyannaməsi"
      ],
      "locations": [
        "ABŞ",
        "Vaşinqton",
        "Azərbaycan",
        "Ermənistan",
        "Naxçıvan Muxtar Respublikası",
        "Amerika Birləşmiş Ştatları"
      ],
      "positions": [
        "Azərbaycan Respublikasının Prezidenti",
        "ABŞ Prezidenti",
        "Ermənistan Respublikasının Baş naziri"
      ],
      "dates": [
        "8 avqust 2025-ci il"
      ]
    },
    "manually_verified": true,
    "annotator_notes": ""
  },
  {
    "article_id": "129",
    "source": "azerbaijan.az",
    "link": "https://azerbaijan.az/news/17401",
    "pub_date": "2025-10-27 00:00:00.000",
    "title": "Vyanada “Beynəlxalq sülh və təhlükəsizlikdə neytral və bloklara qoşulmayan dövlətlərin rolu” mövzusunda beynəlxalq konfrans keçirilib",
    "content": "Vyana Diplomatiya Akademiyasında “Beynəlxalq sülh və təhlükəsizlikdə neytral və bloklara qoşulmayan dövlətlərin rolu” mövzusunda beynəlxalq konfrans keçirilib.\n\nAZƏRTAC xəbər verir ki, Azərbaycanın Avstriyadakı səfirliyinin dəstəyi ilə Beynəlxalq Münasibətlərin Təhlili Mərkəzi (AIR Center), Müharibə nəticələrinin araşdırılması üzrə Lüdviq Boltsmann İnstitutu və Vyana Diplomatiya Akademiyasının birgə təşkil etdiyi konfransda neytral və bloklara qoşulmayan dövlətlərin, xüsusilə də Azərbaycan və Avstriyanın siyasəti, onların təhlükəsizlik təminatçısı kimi rolu və sülhə, sabitliyə, həmçinin mövcud və yeni yaranan transmilli çağırışların həllinə verdikləri töhfələri müzakirə olunub.\n\nVyana Diplomatiya Akademiyasının direktor müavini Martina Şubert və Azərbaycanın Avstriyadakı səfiri Rövşən Sadıqbəyli konfransa açılış nitqi ilə çıxış ediblər. R. Sadıqbəyli bildirib ki, hazırda Avropada və dünyada müşahidə olunan təhlükəsizlik böhranı – beynəlxalq hüququn əsas prinsiplərinin pozulması, etimadın və inamın aşınması, siyasi-hərbi bloklar arasında dərinləşən uçurumlar, eləcə də qlobal dinamikaların və ittifaqların dəyişməsi dünyanın gələcək təhlükəsizlik və sabitlik mənzərəsinə dair qeyri-müəyyənliyi artırır. Bu dəyişkən təhlükəsizlik mühiti, həmçinin neytral və bloklara qoşulmayan dövlətlər üçün çətinliklər yaradır. Çünki onlar təhlükəsizliklərini siyasi-hərbi bloklara üzvlük vasitəsilə təmin edə bilmirlər və bu bloklardan təhlükəsizlik zəmanətlərinə ehtiyac duyurlar.\n\nDiqqətə çatdırılıb ki, bu il Azərbaycanın Konstitusiyasının qəbulunun 30 illiyi və Avstriyanın əbədi neytrallığının elan olunduğu Dövlət Müqaviləsinin 70 illiyi qeyd edilir. Avstriya 1955-ci ildə neytrallığını elan edərək, hərbi ittifaqlara qoşulmamaq qərarı verib. Azərbaycan isə 1991-ci ildə müstəqilliyini bərpa etdikdən sonra heç bir siyasi-hərbi bloka qoşulmadan bütün ölkələrlə dost münasibətlər qurmağa çalışan çoxşaxəli xarici siyasət yürüdüb. Azərbaycanın “Qoşulmayan” statusu beynəlxalq səviyyədə tanınıb və ölkə 2011-ci ilin may ayında Qoşulmama Hərəkatının tamhüquqlu üzvünə çevrilib.\n\nKonfransın sessiyalarında neytrallıq və strateji müstəqilliyə yeni baxışlar, yeni geosiyasi kontekstdə bloklara qoşulmadan xarici siyasətin həyata keçirilməsi mövzularında çıxışlar dinlənilib, fikir mübadiləsi aparılıb. Sessiyalarda BMTM-in İdarə Heyətinin sədri Fərid Şəfiyev, Avropa və Təhlükəsizlik Siyasəti üzrə Avstriya İnstitutunun baş məsləhətçiləri Frants Tsede və Martin Saydik, hərbi tarixçi Ervin Şmidl, Ludviq Boltsmann İnstitutunun təmsilçisi Anna Qraf-Ştayner, Vyana Universitetinin müəllimi Ralf Yanik, Strateji Analizlər üzrə Mərkəzin prezidenti Valter Fayxtinqer və digər məruzəçilər çıxış ediblər.\n\nBMTM-in İdarə Heyətinin sədri Fərid Şəfiyev vurğulayıb ki, 2011-ci ildə Azərbaycanın Qoşulmama Hərəkatına qoşulması ölkəmizin “Bandunq Prinsipləri”nə sadiqliyini nümayiş etdirib. Bu siyasi xətt hazırda da davam etdirilir və Azərbaycan regional əməkdaşlıqla yanaşı, ikitərəfli münasibətlərə, xüsusilə Türkiyə ilə müttəfiqlik əlaqələrinin dərinləşdirilməsinə xüsusi önəm verir.\n\nBMTM rəhbərinin sözlərinə görə, “soyuq müharibə”dən sonra Azərbaycan müxtəlif istiqamətlərdə - həm Müstəqil Dövlətlər Birliyi (MDB), həm də Avrointeqrasiya çərçivəsində əməkdaşlıq imkanlarını dəyərləndirsə də, mövcud geosiyasi vəziyyət ölkəmizi balanslaşdırılmış və praqmatik xarici siyasət xətti yürütməyə səbəb olub.\n\n\"2019-2023-cü illərdə Hərəkata sədrliyimiz dövründə Azərbaycan beynəlxalq həmrəyliyin gücləndirilməsi, pandemiya dövründə ədalətli vaksin bölgüsünün təşviqi, eləcə də Qoşulmama Hərəkatı Gənclər Təşkilatının və Parlament Şəbəkəsinin yaradılması kimi vacib təşəbbüslərlə çıxış edib.\n\nF. Şəfiyev bildirib ki, ölkəmiz beynəlxalq hüququn əsas norma və prinsiplərinin, xüsusilə dövlətlərin suverenliyi və ərazi bütövlüyü prinsipinin qorunmasını hər zaman prioritet hesab edib. Qoşulmama Hərəkatına üzv ölkələrin əksəriyyətinin İkinci Qarabağ müharibəsində Azərbaycanın suverenliyini dəstəkləməsi hərəkat daxili",
    "gold_entities": {
      "persons": [
        "Martina Şubert",
        "Rövşən Sadıqbəyli",
        "Fərid Şəfiyev",
        "Frants Tsede",
        "Martin Saydik",
        "Ervin Şmidl",
        "Anna Qraf-Ştayner",
        "Ralf Yanik",
        "Valter Fayxtinqer"
      ],
      "organizations": [
        "AZƏRTAC",
        "Vyana Diplomatiya Akademiyası",
        "Beynəlxalq Münasibətlərin Təhlili Mərkəzi (BMTM / AIR Center)",
        "Müharibə nəticələrinin araşdırılması üzrə Lüdviq Boltsmann İnstitutu",
        "Azərbaycanın Avstriyadakı səfirliyi",
        "Qoşulmama Hərəkatı",
        "MDB"
      ],
      "locations": [
        "Vyana",
        "Avstriya",
        "Azərbaycan",
        "Avropa"
      ],
      "positions": [
        "direktor müavini",
        "səfir",
        "İdarə Heyətinin sədri",
        "baş məsləhətçi",
        "hərbi tarixçi"
      ],
      "dates": [
        "1955-ci il",
        "1991-ci il",
        "2011-ci ilin may ayında",
        "2019-2023-cü illər"
      ]
    },
    "manually_verified": true,
    "annotator_notes": ""
  },
  {
    "article_id": "926",
    "source": "azerbaijan.az",
    "link": "https://azerbaijan.az/news/15091",
    "pub_date": "2025-01-10 00:00:00.000",
    "title": "Gənclər və İdman Nazirliyi ilin ən yaxşılarını mükafatlandırıb",
    "content": "Gənclər və İdman Nazirliyi ilin idman yekunları ilə bağlı yanvarın 9-da qala mərasimi təşkil edib.\n\nAZƏRTAC xəbər verir ki, tədbirə idman təşkilatlarının, federasiyaların, media qurumlarının rəhbərləri, idmançılar, məşqçilər və idman ictimaiyyətinin nümayəndələri qatılıblar.\n\nHeydər Əliyev Fondunun vitse-prezidenti Leyla Əliyeva və Bakı Media Mərkəzinin rəhbəri Arzu Əliyeva da mərasimdə iştirak ediblər.\n\nQala mərasimi Azərbaycan Respublikasının Dövlət Himninin səsləndirilməsi ilə başlayıb.\n\nGənclər və idman naziri Fərid Qayıbov 2024-cü ilin Azərbaycan idmanı üçün uğurlu keçdiyini qeyd edib və bu münasibətlə federasiya rəhbərlərini, idmançıları, məşqçiləri, idman ictimaiyyətini təbrik edib. Nazir Prezident İlham Əliyevin ötən ilin idman yekunları ilə bağlı olan tədbirdə idman ictimaiyyətinin bir sıra nümayəndələrini mükafatlandırdığını diqqətə çatdırıb. O, bu addımın idmançılara stimul verdiyini bildirib. F.Qayıbov 2025-ci ilin idmanımız üçün daha da uğurlu olacağına inandığını bildirib.\n\nDaha sonra 2024-cü ilin idman yekunları barədə hesabat videoçarxı təqdim edilib. Ardınca federasiyalar, idman jurnalistləri arasında və sosial mediada aparılmış sorğu əsasında müəyyənləşmiş müxtəlif nominasiyalar üzrə ilin qaliblərinin mükafatlandırılması mərasimi olub.\n\nMərasimdə ilin ən yaxşı media qurumları da açıqlanıb. Birinci yerə “CBC Sport” layiq görülüb. İkinci isə Azərbaycan Dövlət İnformasiya Agentliyi (AZƏRTAC) olub. AZƏRTAC-a mükafatı Azərbaycan Respublikası Prezidentinin köməkçisi və Azərbaycan Avtomobil Federasiyasının prezidenti Anar Ələkbərov təqdim edib. Üçüncü sıranı isə İdman.biz tutub.\n\nİlin ədalətli oyun (“fair-play”) mükafatçısı\n\n1) Qaşım Maqomedov (Taekvondo)\n\n2) Leyla Abidinova (Atletika)\n\n3) Nərmin Şərifova (Badminton)\n\nİlin ən yaxşı idman tədbiri\n\n1) Formula 1 Azərbaycan Qran-Prisi (Bakı)\n\n2) Beynəlxalq Avarçəkmə Reqatası (Füzuli və Mingəçevir)\n\n3) Cüdo üzrə \"Böyük Dəbilqə\" turniri (Bakı)\n\nİlin ən yaxşı Uşaq-Gənclər İdman Məktəbi\n\n1) “Ulduz” Futbol Akademiyası\n\n2) ROEQİUG Velosiped məktəbi\n\n3) Masallı Rayon Uşaq və Gənclər Məktəbi\n\nİlin idman mövzusunda ən yaxşı videoçarxı\n\n1) “Bir də gəlsəm” - Azərbaycan Cüdo Federasiyası\n\n2) “Doğru hədəfə yönəl” - ATV\n\n3) Güləşçilərin musiqi testi - Azərbaycan Güləş Federasiyası\n\nİlin ən yaxşı idman fotoqrafı\n\n1) Zaur Mustafayev (Trend.az)\n\n2) Nadejda Cavad\n\n3) İslam Atakişiyev (İdman.biz)\n\nİlin ən yaxşı media qurumu\n\n1) “CBC Sport”\n\n2) AZƏRTAC\n\n3) İdman.biz\n\nİlin ən yaxşı idman jurnalisti\n\n1) Elmir Əliyev (Haqqın.az)\n\n2) Kənan Hakimov (İctimai TV)\n\n3) Nazilə Əhmədova (Real TV)\n\nİlin ən yaxşı idman klubu\n\n1) “Ocaq Sport” İdman Klubu\n\n2) “Neftçi” İdman Klubu\n\n3) “Volan” Badminton Klubu\n\nİlin ən yaxşı idman qurğusu\n\n1) Milli Gimnastika Arenası\n\n2) Bakı Su İdmanı Sarayı\n\n3) “Kür” Olimpiya Tədris-İdman Mərkəzi\n\nİlin ən yaxşı Olimpiya İdman Kompleksi\n\n1) Quba Olimpiya İdman Kompleksi\n\n2) Goranboy Olimpiya İdman Kompleksi\n\n3) Ağdaş Olimpiya İdman Kompleksi\n\nİlin ən yaxşı tibb personalı\n\n1) Aydın Ağaliyev (Gimnastika)\n\n2) Nigar Heydərova (MİTRİ)\n\n3) Ramil Vəliyev (Cüdo)\n\nİlin ən yaxşı idman hakimi\n\n1) Emil Qurbanəliyev (Boks)\n\n2) Nataliya Bulanova (Gimnastika)\n\n3) Asif Şirəliyev (Güləş)\n\n2024-cü ildə uğurlu beynəlxalq fəaliyyətə görə\n\n1) Azərbaycan Atçılıq Federasiyası\n\n2) Azərbaycan Atıcılıq Federasiyası\n\n3) Azərbaycan Ağırlıqqaldırma Federasiyası\n\nİlin ən yaxşı idman federasiyası\n\n1) Azərbaycan Cüdo Federasiyası\n\n2) Azərbaycan Gimnastika Federasiyası\n\n3) Azərbaycan Güləş Federasiyası\n\nİlin kişilərdən ibarət ən yaxşı klub komandası (oyun idman növləri)\n\n1) “Qarabağ” Futbol Komandası\n\n2) “Azərreyl” çimərlik voleybol komandası\n\n3) “Birbaşa Bakı” Minifutbol komandası\n\nİlin qadınlardan ibarət ən yaxşı klub komandası (oyun idman növləri)\n\n1) “Azərreyl” çimərlik voleybol komandası\n\n2) “Neftçi” 3x3 basketbol komandası\n\n3) “Qarabağ” həndbol komandası\n\nİlin kişilərdən ibarət ən yaxşı milli komandası\n\n1) Yunan-Roma güləşi üzrə milli komanda\n\n2) Cüdo üzrə milli komanda\n\n3) Sərbəst güləş üzrə milli ",
    "gold_entities": {
      "persons": [
        "Leyla Əliyeva",
        "Arzu Əliyeva",
        "Fərid Qayıbov",
        "İlham Əliyev",
        "Anar Ələkbərov",
        "Zaur Mustafayev",
        "Nadejda Cavad",
        "İslam Atakişiyev"
      ],
      "organizations": [
        "AZƏRTAC",
        "Gənclər və İdman Nazirliyi",
        "Bakı Media Mərkəzi",
        "CBC Sport",
        "Azərbaycan Avtomobil Federasiyası",
        "Formula 1 Azərbaycan Qran-Prisi",
        "İdman.biz"
      ],
      "locations": [
        "Bakı",
        "Füzuli",
        "Mingəçevir"
      ],
      "positions": [
        "Gənclər və idman naziri",
        "Heydər Əliyev Fondunun vitse-prezidenti",
        "Bakı Media Mərkəzinin rəhbəri",
        "Azərbaycan Respublikası Prezidentinin köməkçisi",
        "Azərbaycan Avtomobil Federasiyasının prezidenti"
      ],
      "dates": [
        "yanvarın 9-da",
        "2024-cü il",
        "2025-ci il"
      ]
    },
    "manually_verified": true,
    "annotator_notes": ""
  },
  {
    "article_id": "1054",
    "source": "azerbaijan.az",
    "link": "https://azerbaijan.az/news/14707",
    "pub_date": "2024-11-06 00:00:00.000",
    "title": "Bişkekdə Türk Dövlətləri Təşkilatı Dövlət Başçılarının 11-ci Zirvə görüşü keçirilir Prezident İlham Əliyev Dövlət Başçıları Şurasının iclasında çıxış edib",
    "content": "Noyabrın 6-da Qırğızıstanın paytaxtı Bişkekdə Türk Dövlətləri Təşkilatı (TDT) Dövlət Başçılarının 11-ci Zirvə görüşü keçirilib.\n\nAZƏRTAC xəbər verir ki, Azərbaycan Respublikasının Prezidenti İlham Əliyev tədbirdə iştirak etmək üçün Prezident Administrasiyasına gəldi.\n\nQırğız Respublikasının Prezidenti Sadır Japarov Prezident İlham Əliyevi, digər dövlət və hökumət başçılarını qarşıladı.\n\nSonra birgə foto çəkdirildi.\n\nDaha sonra Türk Dövlətləri Təşkilatı Dövlət Başçıları Şurasının iclası keçirildi.\n\nQırğız Respublikasının Prezidenti Sadır Japarov Zirvə görüşünün işinə uğurlar arzuladı. S.Japarov çıxışında yaxın günlərdə Azərbaycanda keçiriləcək COP 29 konfransına diqqət çəkərək dedi: “Tezliklə Azərbaycanda BMT-nin İqlim Dəyişikliyi üzrə Çərçivə Konvensiyasının Tərəflər Konfransının 29-cu sessiyası - COP29 keçiriləcək. Hörmətli Azərbaycan Prezidenti belə bir böyük Zirvə toplantısına ev sahibliyi edəcək və biz Azərbaycan hökumətinə bu mövzu ilə bağlı hər cür dəstək göstərməyə hazırıq”.\n\nQazaxıstan Respublikasının Prezidenti Kasım-Jomart Tokayev Türk Dövlətləri Təşkilatının türk xalqlarını daha da yaxınlaşdırdığını bildirdi. Kasım-Jomart Tokayev ortaq türk əlifbasının yaradılması, iqtisadi-ticari əlaqələrin daha da genişləndirilməsi istiqamətində görülən işlərin əhəmiyyətini vurğuladı.\n\nSonra Azərbaycan Prezidenti İlham Əliyev iclasda çıxış etdi.\n\nPrezident İlham Əliyevinçıxışı\n\n-Hörmətli Sadır Nurqojoyeviç.\n\nHörmətli dövlət və hökumət başçıları.\n\nİlk növbədə, qonaqpərvərliyə və tədbirin yüksək səviyyədə təşkilinə görə Qırğız Respublikasının Prezidenti Sadır Nurqojoyeviç Japarova təşəkkür edirəm.\n\nBu, mənim son iki ildə Qırğız Respublikasına üçüncü səfərimdir. Hər səfərimdə Sadır Nurqojoyeviçin rəhbərliyi ilə ölkədə inkişafın şahidi oluram. Əldə edilmiş bütün uğurlar münasibətilə qardaş Qırğızıstanı təbrik edirəm.\n\nHəmçinin Türk Dövlətləri Təşkilatına uğurlu sədrliyinə görə Qazaxıstanı təbrik edirəm.\n\nBu il Türk Dövlətləri Təşkilatının əsasını qoymuş Naxçıvan Sazişinin 15-ci ildönümüdür. Təşkilatımız bu dövr ərzində uğurlu inkişaf yolu keçib. İyul ayında Şuşa şəhərində keçirilmiş Dövlət başçılarının qeyri-rəsmi Zirvə görüşündə imzalanmış Qarabağ Bəyannaməsi əməkdaşlığın daha da dərinləşməsinə töhfə verir.\n\nAzərbaycan Türk Dövlətləri Təşkilatının möhkəmlənməsi istiqamətində səylərini bundan sonra da davam etdirəcək.\n\nTürk Dövlətləri Təşkilatının mövcud büdcəsi qarşıya qoyduğumuz hədəflərin həyata keçirilməsi üçün yetərli deyil. Ümid edirəm ki, Azərbaycanın Türk Dövlətləri Təşkilatının Katibliyinə 2 milyon və Ağsaqqallar Şurasına 100 min ABŞ dolları məbləğində maliyyə dəstəyi təşkilatın potensialının daha da güclənməsinə töhfə verəcək.\n\nHazırda dünyada artan təhlükələri nəzərə alaraq müdafiə, təhlükəsizlik və müdafiə sənayesi sahələrində əməkdaşlığımız böyük əhəmiyyət daşıyır. Son dövrlər hüquq-mühafizə və təhlükəsizlik orqanlarımız arasında əməkdaşlıq daha da genişlənib.\n\nÖlkələrimizin silahlı qüvvələrinin iştirakı ilə hərbi təlimlər keçirilir. Hərbi təhsil müəssisələrimizdə qardaş ölkələrin müdavimlərinin təhsil alması qarşılıqlı etimadın və dostluğun göstəricisidir.\n\nSon dövrlər Şərq-Qərb nəqliyyat dəhlizi ilə Azərbaycan ərazisi üzrə daşımalar daha da artıb. Mərkəzi Asiya ölkələri ilə Türkiyəni Azərbaycan üzərindən bağlayan bu dəhlizin ötürmə qabiliyyətinin yüksəldilməsi üçün Azərbaycan öz sərmayələrini artırır.\n\n2023-cü ilin müvafiq dövrü ilə müqayisədə 2024-cü ilin yanvar-sentyabr aylarında üzv və müşahidəçi dövlətlər ilə tranzit daşımalarının həcmində 15 faizə yaxın artım müşahidə edilir.\n\nHazırda Orta Dəhlizin rəqəmsallaşdırılması və ticarətin asanlaşdırılması istiqamətində bir sıra layihələr icra olunur. Bu layihələr logistika səmərəliliyinin artırılmasına və xərclərin azaldılmasına təsir edəcək.\n\nÖtən ilin sentyabr ayında Azərbaycan öz suverenliyini tam bərpa etdi. Ermənistan 30 il davam edən işğal dövründə bu ərazilərdə 9 şəhərimizi və yüzlərlə kəndimizi tamamilə məhv edib. İşğaldan azad olunan ərazilərdə indi genişmiqyaslı",
    "gold_entities": {
      "persons": [
        "İlham Əliyev",
        "Sadır Japarov",
        "Kasım-Jomart Tokayev"
      ],
      "organizations": [
        "AZƏRTAC",
        "Türk Dövlətləri Təşkilatı (TDT)",
        "COP29",
        "BMT-nin İqlim Dəyişikliyi üzrə Çərçivə Konvensiyası",
        "Naxçıvan Sazişi",
        "Qarabağ Bəyannaməsi",
        "Türk Dövlətləri Təşkilatının Katibliyi",
        "Ağsaqqallar Şurası",
        "Orta Dəhliz"
      ],
      "locations": [
        "Bişkek",
        "Qırğızıstan",
        "Azərbaycan",
        "Şuşa",
        "Naxçıvan"
      ],
      "positions": [
        "Azərbaycan Respublikasının Prezidenti",
        "Qırğız Respublikasının Prezidenti",
        "Qazaxıstan Respublikasının Prezidenti"
      ],
      "dates": [
        "Noyabrın 6-da",
        "iyul ayında",
        "2023-cü ilin sentyabr ayında",
        "2024-cü ilin yanvar-sentyabr aylarında"
      ]
    },
    "manually_verified": true,
    "annotator_notes": ""
  },
  {
    "article_id": "620",
    "source": "azerbaijan.az",
    "link": "https://azerbaijan.az/news/15989",
    "pub_date": "2025-05-21 00:00:00.000",
    "title": "Türk Dövlətləri Təşkilatının Dövlət başçılarının qeyri-rəsmi Zirvə görüşündə Bəyannamə imzalanıb",
    "content": "Mayın 21-də Macarıstanın paytaxtı Budapeştdə keçirilən Türk Dövlətləri Təşkilatının (TDT) Dövlət başçılarının qeyri-rəsmi Zirvə görüşündə Bəyannamə imzalanıb.\n\nAZƏRTAC xəbər verir ki, Azərbaycan Respublikasının Prezidenti İlham Əliyev, Qazaxıstan Respublikasının Prezidenti Kasım-Jomart Tokayev, Qırğız Respublikasının Prezidenti Sadır Japarov, Türkiyə Respublikasının Prezidenti Rəcəb Tayyib Ərdoğan, Özbəkistan Respublikasının Prezidenti Şavkat Mirziyoyev və TDT-nin Baş katibi Kubanıçbek Ömüralıyev tərəfindən imzalanmış Bəyannamə 71 bənddən ibarətdir.\n\nTürk xalqlarının tarix boyu dünya sivilizasiyasına mühüm töhfələrini, o cümlədən Avropa və Asiyanın mədəni və siyasi cəhətdən formalaşmasında davamlı irsini, Türk dövlətlərinin dünyada müasir siyasi, iqtisadi və sosial tərəqqiyə, o cümlədən regional və qlobal sülh və təhlükəsizliyə təsir göstərməkdə mühüm rolunu vurğulayan dövlət başçıları TDT-nin təşkilatın institusional əsasını qoyan tarixi Naxçıvan Sazişinin prinsiplərinə, məqsədlərinə və ruhuna sarsılmaz sadiqliyini bir daha təsdiqləyiblər.\n\nTürk dövlətlərinin regionda və onun hüdudlarından kənarda rolunu artıran siyasi, iqtisadi, ekoloji, sosial və mədəni nailiyyətləri təqdir edən prezidentlər “Türk Dünyası Xartiyası”nı türk xalqlarının ortaq mədəniyyətinin, adət-ənənələrinin, dilinin və tarixinin əsas ifadəsi və onların ortaq türk kimliyinin möhkəmləndirilməsi üçün birləşdirici çərçivə kimi tanıyıblar.\n\nQırğız Respublikasının sədrliyinin və Macarıstanın TDT-yə üzv dövlətlər arasında çoxşaxəli əməkdaşlığın daha da gücləndirilməsinə olan əzminin yüksək qiymətləndirildiyi Bəyannamədə müşahidəçi ölkə Macarıstan tərəfindən ilk dəfə keçirilən TDT-nin qeyri-rəsmi Zirvə görüşünə verilən böyük dəyər xüsusi vurğulanır.\n\nTərəflər Türk dövlətləri arasındakı böyük potensialdan və imkanlardan istifadə edərək, bütün sahələrdə həmrəyliyi, əməkdaşlığı və koordinasiyanı daha da gücləndirmək əzmində olduqlarını bildirir, Macarıstan, Türkmənistan və Şimali Kipr Türk Cümhuriyyətinin müşahidəçi qismində təşkilatın işinə dəyərli töhfələrini alqışlayırlar. Eyni zamanda, Kipr məsələsinin danışıqlar yolu ilə, qarşılıqlı məqbul və həyat qabiliyyətli həllinə nail olunmasının zəruriliyi qeyd edilir.\n\nÜzv dövlətlərin birliyini və həmrəyliyini pozmağa yönəlmiş hər hansı hərəkət və təhdidlərin qarşısının alınmasının vacibliyi diqqətə çatdırılır.\n\nTəşkilatın üzvləri regionda və onun hüdudlarından kənarda sülh və təhlükəsizliyə təhdid və çağırışlar yaradan terrorizm və transmilli mütəşəkkil cinayətkarlığın bütün formaları, terrorizmin maliyyələşdirilməsi və kibercinayətkarlıqla mübarizədə birgə səyləri davam etdirməyə sadiqliklərini bir daha təsdiqləyirlər. Bu kontekstdə Suriyanın ərazi bütövlüyü və birliyi əsasında təhlükəsizliyin və sabitliyin bərqərar olması, ona qarşı sanksiyaların aradan qaldırılması istiqamətində Türkiyənin konstruktiv rolu yüksək qiymətləndirilir.\n\nQəzzadakı fəlakətli humanitar vəziyyətdən dərin narahatlıq ifadə olunur, daimi və hərtərəfli atəşkəs, girovların, məhbusların azad edilməsi və Qəzzaya humanitar yardımların maneəsiz çatdırılması istiqamətində danışıqlara dəstək bir daha təsdiqlənir. İsrail-Fələstin münaqişəsinin BMT-nin müvafiq qətnamələrinə uyğun olaraq ikidövlətli həlli variantının zəruriliyi qeyd edilir. Həmçinin Əfqanıstanla bağlı məsələlər üzrə TDT-nin İşçi Qrupunun yaradılması təqdir olunur.\n\nTDT çərçivəsində müdafiə sənayesi sahəsində məhsuldar çoxtərəfli əməkdaşlığı genişləndirmək niyyəti bir daha bəyan olunur və üzv dövlətlərin müvafiq orqanlarına bu məqsədlə səylərini sürətləndirmək tapşırılır.\n\nİrqçiliyin, ayrı-seçkiliyin, ksenofobiyanın, İslama qarşı nifrətin, nifrət nitqinin və dezinformasiyanın bütün formaları ilə mübarizədə əməkdaşlığın davam etdirilməsi məqsədilə beynəlxalq platformalarda səylərin əlaqələndirilməsi öhdəliyi xatırladılır.\n\nQlobal miqyasda mədəniyyətlərarası dialoqun təşviqində qabaqcıl təşəbbüs kimi “Bakı Prosesi”nin uğuru yüksək qiymətləndirilir və Azərbaycan bu istiqamətdə davamlı liderliyi",
    "gold_entities": {
      "persons": [
        "İlham Əliyev",
        "Kasım-Jomart Tokayev",
        "Sadır Japarov",
        "Rəcəb Tayyib Ərdoğan",
        "Şavkat Mirziyoyev",
        "Kubanıçbek Ömüralıyev"
      ],
      "organizations": [
        "AZƏRTAC",
        "Türk Dövlətləri Təşkilatı (TDT)",
        "Türk Dünyası Xartiyası",
        "Naxçıvan Sazişi",
        "Bakı Prosesi",
        "BMT"
      ],
      "locations": [
        "Budapeşt",
        "Macarıstan",
        "Azərbaycan",
        "Qazaxıstan",
        "Qırğızıstan",
        "Türkiyə",
        "Özbəkistan",
        "Şimali Kipr Türk Cümhuriyyəti",
        "Qəzza",
        "Suriya",
        "Əfqanıstan"
      ],
      "positions": [
        "Azərbaycan Respublikasının Prezidenti",
        "Qazaxıstan Respublikasının Prezidenti",
        "Qırğız Respublikasının Prezidenti",
        "Türkiyə Respublikasının Prezidenti",
        "Özbəkistan Respublikasının Prezidenti",
        "TDT-nin Baş katibi"
      ],
      "dates": [
        "Mayın 21-də"
      ]
    },
    "manually_verified": true,
    "annotator_notes": ""
  },
  {
    "article_id": "50",
    "source": "azerbaijan.az",
    "link": "https://azerbaijan.az/news/17625",
    "pub_date": "2025-11-16 00:00:00.000",
    "title": "Daşkənddə Mərkəzi Asiya Dövlət Başçılarının 7-ci Məşvərət Görüşü keçirilib Prezident İlham Əliyev tədbirdə çıxış edib",
    "content": "Noyabrın 16-da Özbəkistanın paytaxtı Daşkənddə Mərkəzi Asiya Dövlət Başçılarının 7-ci Məşvərət Görüşü keçirilib.\n\nAZƏRTAC xəbər verir ki, Azərbaycan Respublikasının Prezidenti İlham Əliyev Konqres Mərkəzinə gəldi.\n\nÖzbəkistan Prezidenti Şavkat Mirziyoyev dövlətimizin başçısını qarşıladı.\n\nTədbirin iştirakçıları birgə foto çəkdirdilər.\n\nGörüşdə çıxış edən Özbəkistan Respublikasının Prezidenti Şavkat Mirziyoyev qardaş xalqlar üçün tarixi bir gün yaşandığını vurğulayaraq dedi: “Biz Azərbaycan Respublikasının tamhüquqlu iştirakçı qismində Mərkəzi Asiya Dövlət Başçılarının Məşvərət Görüşü formatına qoşulmasına dair prinsipial qərarlar qəbul edirik. Biz Mərkəzi Asiya ilə Cənubi Qafqaz arasında güclü bir körpü quracağıq və vahid əməkdaşlıq məkanının formalaşmasına yol açacağıq. Bu, sözsüz ki, hər iki regionun strateji qarşılıqlı əlaqəsini və dayanıqlılığını gücləndirəcək. Bu vacib qərarı qəbul etdiklərinə görə bütün həmkarlarıma səmimi-qəlbdən təşəkkürümü bildirmək və Məşvərət görüşlərinə tamhüquqlu iştirakçı qismində qoşulması münasibətilə İlham Heydər oğlunu təbrik etmək istəyirəm”.\n\nŞavkat Mirziyoyev bildirdi ki, həmrəyliyin gücləndirilməsi və birgə inkişafa can atmaq Mərkəzi Asiyanın beynəlxalq mövqeyinin möhkəmlənməsinə və qlobal rolunun artırılmasına töhfə verir. “Mərkəzi Asiya +” formatlarının qarşılıqlı fəaliyyəti güclənib. Region nüfuzlu beynəlxalq platformalarda vahid mövqedən çıxış edir. Şübhəsiz ki, Azərbaycanın bizim formata qoşulması ilə regionumuzun qlobal miqyasda səsi daha əhəmiyyətli olacaq”, - deyə Özbəkistan Prezidenti vurğuladı.\n\n“Bu gün Azərbaycanın tamhüquqlu iştirakçı qismində bizim formata qoşulmasına dair tarixi qərar qəbul etdik”. Bu fikri isə Qazaxıstan Respublikasının Prezidenti Kasım-Jomart Tokayev söylədi. O, Azərbaycanın bu yeni formatda regional əməkdaşlığın möhkəmləndirilməsinə mühüm töhfə verəcəyinə əminliyini ifadə etdi.\n\nQırğız Respublikasının Prezidenti Sadır Japarov da ölkəsinin Azərbaycanın tamhüquqlu üzv qismində Məşvərət görüşləri formatına qoşulması təşəbbüsünü dəstəklədiyini vurğulayaraq qeyd etdi: “Qardaş Azərbaycanın iştirakı ilə formatımızın genişləndirilməsi Mərkəzi Asiyanın qarşısında xüsusilə beynəlxalq tranzit, logistika və energetika sahələrində yeni imkanlar, geniş əməkdaşlıq üfüqləri açacaq. Bu gün əminliklə deyə bilərik ki, Mərkəzi Asiya Dövlət Başçılarının Məşvərət görüşlərinin formatı baş tutub. Bu format öz səmərəliliyini sübut edib, təkcə regionumuzda mövcud problemlərin müzakirə olunduğu deyil, həm də yeni təşəbbüslərin və təkliflərin fəal şəkildə irəli sürüldüyü real, özünəməxsus yeganə platformaya çevrilib”.\n\n“Bu gün regionun yeni nəqliyyat arteriyasının meydana çıxmasının şahidi oluruq”, - deyən Sadır Japarov əlavə etdi ki, strateji cəhətdən mühüm Çin-Qırğızıstan-Özbəkistan dəmir yolunun tikintisi logistikanı birləşdirməklə yanaşı, həm də formatını genişləndirəcək, ölkələrimizə Asiya və Avropanın çox böyük bazarlarına ən qısa yolu açacaq. Bu kontekstdə Zəngəzur dəhlizinin tikintisi layihəsi Çin-Qırğızıstan-Özbəkistan dəmir yolunun məntiqi və strateji davamı kimi görünür.\n\nTacikistan Respublikasının Prezidenti Emoməli Rəhmon da ölkəmizi Məşvərət görüşlərinə qoşulması münasibətilə təbrik edərək dedi: “Hörmətli İlham Heydər oğlu Əliyevi Azərbaycan Respublikasının Mərkəzi Asiya Dövlət Başçılarının Məşvərət görüşlərinə qoşulması münasibətilə təbrik edirəm. Sevindirici haldır ki, məkanımız beynəlxalq və regional proseslərin mühüm iştirakçısının timsalında öz əhəmiyyətini inamla artırır. Bu, balanslaşdırılıb və region ölkələrinin artan maraqlarının inkişafına səyləri nümayiş etdirir”.\n\nTədbirdə çıxış edən Türkmənistan Prezidenti Sərdar Berdiməhəmmədov dövlətimizin başçısına Azərbaycanın tamhüquqlu iştirakçı qismində Məşvərət görüşlərinə qoşulması münasibətilə təbriklərini çatdırdı.\n\nÖzbəkistan Prezidenti Şavkat Mirziyoyev dedi: “İndi isə icazənizlə, söz Azərbaycan Respublikasının Prezidenti hörmətli İlham Heydər oğlu Əliyevə verilir. Buyurun, İlham Heydər oğlu”.\n\nPrezident İlham",
    "gold_entities": {
      "persons": [
        "İlham Əliyev",
        "Şavkat Mirziyoyev",
        "Kasım-Jomart Tokayev",
        "Sadır Japarov",
        "Emoməli Rəhmon",
        "Sərdar Berdiməhəmmədov"
      ],
      "organizations": [
        "AZƏRTAC",
        "Mərkəzi Asiya Dövlət Başçılarının Məşvərət Görüşü",
        "Konqres Mərkəzi"
      ],
      "locations": [
        "Daşkənd",
        "Özbəkistan",
        "Mərkəzi Asiya",
        "Cənubi Qafqaz",
        "Çin",
        "Qırğızıstan",
        "Azərbaycan",
        "Zəngəzur"
      ],
      "positions": [
        "Azərbaycan Respublikasının Prezidenti",
        "Özbəkistan Respublikasının Prezidenti",
        "Qazaxıstan Respublikasının Prezidenti",
        "Qırğız Respublikasının Prezidenti",
        "Tacikistan Respublikasının Prezidenti",
        "Türkmənistan Prezidenti"
      ],
      "dates": [
        "Noyabrın 16-da",
        "7-ci Məşvərət Görüşü"
      ]
    },
    "manually_verified": true,
    "annotator_notes": ""
  },
  {
    "article_id": "330",
    "source": "azerbaijan.az",
    "link": "https://azerbaijan.az/news/16829",
    "pub_date": "2025-09-05 00:00:00.000",
    "title": "Madat Babayan ibtidai istintaqa ifadəsində Xocalı soyqırımı zamanı xüsusi qəddarlığı ilə seçilən Ermənistan silahlı qüvvələrinin bəzi hərbçilərinin adlarını açıqlayıb – MƏHKƏMƏ",
    "content": "Ermənistanın Azərbaycana qarşı hərbi təcavüzü nəticəsində sülh və insanlıq əleyhinə cinayətlər, müharibə cinayətləri, o cümlədən təcavüzkar müharibənin hazırlanması və aparılması, soyqırımı, müharibə qanunlarını və qaydalarını pozma, habelə terrorçuluq, terrorçuluğu maliyyələşdirmə, hakimiyyəti zorla ələ keçirmə, onu zorla saxlama və digər çoxsaylı cinayətlər törətməkdə təqsirləndirilən Ermənistan Respublikasının vətəndaşları Arayik Harutyunyan, Arkadi Qukasyan, Bako Sahakyan, Davit İşxanyan, David Babayan, Levon Mnatsakanyan və digərlərinin barəsində olan cinayət işləri üzrə açıq məhkəmə prosesinin baxış iclası sentyabrın 4-də davam etdirilib.\n\nAZƏRTAC xəbər verir ki, Bakı Hərbi Məhkəməsində hakimlər Zeynal Ağayevin sədrliyi ilə, Camal Ramazanovdan və Anar Rzayevdən ibarət tərkibdə (ehtiyat hakim Günel Səmədova) keçirilən məhkəmə iclasında təqsirləndirilən şəxslərin hər biri bildikləri dildə tərcüməçi, həmçinin müdafiələri üçün vəkillərlə təmin olunub.\n\nİclasda təqsirləndirilən şəxslər, onların müdafiəçiləri, zərərçəkmiş şəxslərin bir qismi, onların hüquqi varisləri və nümayəndələri, həmçinin dövlət ittihamını müdafiə edən prokurorlar iştirak ediblər.\n\nMəhkəmə prosesi təqsirləndirilən şəxs Qarik Martirosyanın cinayət işi üzrə ibtidai istintaqa verdiyi ifadələrin və ona aid elan olunan digər sənədlərin səsləndirilməsi ilə davam etdirilib.\n\nOnun ibtidai istintaqa verdiyi ifadələrə əsasən, 1993-cü ilin əvvəllərindən 1994-cü ilin sonlarınadək, habelə 2020-ci ildə 44 günlük müharibə zamanı və 2023-cü ilin yanvar ayından sentyabrın 20-dək olan müddət ərzində döyüş mövqelərində növbətçilik çəkib, silahla Azərbaycan əsgərləri istiqamətində atəşlər açıb.\n\nXocalı rayonu ərazisində yaranmış “Əsgəran özünümüdafiə birləşmələri” adlı hərbi birləşməyə Vitali Balasanyan rəhbərlik edib. O da 1993-cü ilin əvvəllərindən etibarən həmin hərbi birləşmələrin tərkibinə daxil olub.\n\n44 günlük müharibə başa çatdıqdan sonra “Əsgəran rayon icra hakimiyyəti”ndən “rayona tabe olan kəndləri qoruyan” şəxslərə pul verildiyini eşidib oraya gedib, ona təxminən 200 min Ermənistan dramı (500 ABŞ dolları) məbləğində pul vəsaiti verilib.\n\n2023-cü ilin yanvar ayından aylıq əməkhaqqı müqabilində Azərbaycanın həmin vaxt Ermənistan silahlı qüvvələrinin işğalı altında olan ərazilərində postda durub. Xidmət zamanı onlara AKS markalı avtomat təhkim olunub. 2023-cü il sentyabrın 19-20-də Azərbaycan Ordusunun keçirdiyi antiterror əməliyyatı zamanı tutulub.\n\nDaha sonra təqsirləndirilən şəxs Qurgen Stepanyanın cinayət işi üzrə ibtidai istintaqa verdiyi ifadələr və ona aid elan olunan digər sənədlər səsləndirilib.\n\nO, ibtidai istintaqa ifadəsində Ermənistan Respublikasının vətəndaşı olduğunu, 2005-ci il noyabrın 3-də Vayk rayon (red: Dərələyəz mahalı, Paşalı rayonu) hərbi komissarlığı tərəfindən hərbi xidmətə çağırıldığını qeyd edib. Hərbi xidmətini Azərbaycanın həmin vaxt Ermənistan silahlı qüvvələrinin işğalı altında olan Hadrut qəsəbəsində yerləşən hərbi hissədə əsgər kimi keçirib.\n\nHərbi hissənin komandiri polkovnik Vaçaqan Nersesyan, tabor komandiri mayor Aşot Harutyunyan, bölük komandiri isə kapitan Armen Harutyunyan olub. Hərbi hissənin təyinatı Füzuli rayonunda yaradılmış postlarda hərbi qulluqçuların növbətçilik qaydasında həmin postlarda xidmət etmək olub. 2007-ci il noyabrın 3-də hərbi xidməti başa vuraraq Ermənistan Respublikasına, Cermux şəhərinə qayıdıb.\n\nQarik Martirosyan, Melikset Paşayan, Erik Qazaryan və David Allahverdiyan ilə birlikdə 2023-cü ilin yanvar ayından sentyabrın 20-dək həmin vaxt işğal altında olan Əsgəran rayonunda kəndin “icra nümayəndəsi” Edo Musayelyanın rəhbərliyi ilə yaradılmış postda xidmət edib.\n\nDaha sonra təqsirləndirilən şəxs Madat Babayanın cinayət işi üzrə ibtidai istintaqa verdiyi ifadələr və ona aid elan olunan digər sənədlər səsləndirilib.\n\nMadat Babayan ibtidai istintaqa ifadəsində bildirib ki, 1988-ci ildə Xankəndi şəhərində ermənilər silahlı dəstələr yaradaraq müxtəlif ərazilərdə azərbaycanlı əhaliyə qarşı kütləvi qırğınlar tə",
    "gold_entities": {
      "persons": [
        "Madat Babayan",
        "Arayik Harutyunyan",
        "Arkadi Qukasyan",
        "Bako Sahakyan",
        "Davit İşxanyan",
        "David Babayan",
        "Levon Mnatsakanyan",
        "Zeynal Ağayev",
        "Camal Ramazanov",
        "Anar Rzayev",
        "Günel Səmədova",
        "Qarik Martirosyan",
        "Qurgen Stepanyan",
        "Vitali Balasanyan",
        "Vaçaqan Nersesyan",
        "Aşot Harutyunyan",
        "Armen Harutyunyan",
        "Edo Musayelyan"
      ],
      "organizations": [
        "AZƏRTAC",
        "Bakı Hərbi Məhkəməsi",
        "Ermənistan silahlı qüvvələri",
        "“Əsgəran özünümüdafiə birləşmələri”"
      ],
      "locations": [
        "Bakı",
        "Azərbaycan",
        "Ermənistan",
        "Xocalı",
        "Əsgəran",
        "Hadrut",
        "Füzuli",
        "Cermux"
      ],
      "positions": [
        "hakim",
        "polkovnik",
        "mayor",
        "kapitan"
      ],
      "dates": [
        "sentyabrın 4-də",
        "1993-cü ilin əvvəllərindən 1994-cü ilin sonlarınadək",
        "2020-ci ildə",
        "2023-cü ilin yanvar ayından sentyabrın 20-dək",
        "2005-ci il noyabrın 3-də",
        "2007-ci il noyabrın 3-də",
        "1988-ci ildə"
      ]
    },
    "manually_verified": true,
    "annotator_notes": ""
  },
  {
    "article_id": "933",
    "source": "azerbaijan.az",
    "link": "https://azerbaijan.az/news/15070",
    "pub_date": "2025-01-07 00:00:00.000",
    "title": "Azərbaycan Prezidenti İlham Əliyev yerli televiziya kanallarına müsahibə verib",
    "content": "Azərbaycan Respublikasının Prezidenti İlham Əliyev yanvarın 7-də yerli televiziya kanallarına müsahibə verib.\n\nAZƏRTAC müsahibəni təqdim edir.\n\nAzərbaycan Televiziyasından Vüsal Mətləb: Xoş gördük, cənab Prezident. Əvvəlcə, icazənizlə, artıq ənənəyə çevrilmiş bu müsahibə formatına görə Sizə təşəkkür etmək istəyirik. Çünki bu, bizə ictimaiyyəti maraqlandıran məsələlərlə bağlı Sizin fikirlərinizi ətraflı şəkildə öyrənmək imkanı yaradır. Növbəti belə fürsət üçün minnətdarıq.\n\nİstərdim, 2024-cü ilin yekunları ilə başlayaq. 2024-cü ilin sosial-iqtisadi yekunlarının göstəriciləri barədə nə demək olar və bu göstəricilər 2025-ci il üçün hansı proqnozlara əsas yaradır?\n\nPrezident İlham Əliyev: Keçən il iqtisadi inkişaf baxımından yenə də uğurlu il olmuşdur. Azərbaycanın iqtisadiyyatı inkişaf etmişdir. Hesab edirəm ki, inkişaf templəri, bugünkü dünyanın mənzərəsinə nəzər salsaq, müsbət sayıla bilər. Yəni, ümumi daxili məhsul 4 faizdən çox artmışdır. Əslində, bizim üçün əsas göstərici qeyri-neft sektorunun inkişafıdır. Çünki bildiyiniz kimi, biz son vaxtlar neft hasilatında tənəzzüllə üzləşmişdik və hesab edirəm ki, aparılan danışıqlar, göstərilən səylər nəticəsində artıq bu tənəzzülə son qoyulacaq və neft hasilatı sabit qalacaq. Beləliklə, neft hasilatının azalması bundan sonra ümumi daxili məhsula mənfi təsir göstərməyəcək. Ona görə biz ümumi iqtisadi göstəricilərə nəzər saldıqda, ilk növbədə, qeyri-neft sektorunun parametrlərini nəzərə alırdıq. Burada da inkişaf daha uğurludur, 6 faizdən çox artıbdır. Nəzərə alsaq ki, artıq uzun illər bizim iqtisadi inkişafla bağlı əsas hədəflərimizdən biri sənaye istehsalının artırılmasıdır, qeyri-neft sənaye sektorunda artım daha da yüksəkdir. Bu, 7 faizdən çoxdur. Yəni, əgər dünya iqtisadiyyatının artım templərinə və inkişaf etmiş ölkələrin inkişafına, yaxud da ki, tənəzzülə nəzər salsaq, görərik ki, Azərbaycan iqtisadiyyatı uğurla inkişaf edib. Əlbəttə ki, bunun təməlində düşünülmüş siyasət dayanır.\n\nBu göstəricilər, sadəcə olaraq, keçən ilin məhsulu deyil. Uzun illər aparılan iqtisadi islahatlar, şəffaflıq, inhisarçılığa qarşı mübarizə, investisiyaların cəlb edilməsi, investisiya iqliminin yaxşılaşdırılması nəticəsində biz beynəlxalq aparıcı reytinq agentliklərinin Azərbaycana olan münasibətində müsbət dəyişiklik görürük. Yəni, onlar da reallıqları inkar edə bilməzlər. Halbuki mən hesab edirəm ki, bizim beynəlxalq reytinqimiz indikindən daha yüksək səviyyəyə layiqdir və müəyyən səbəblər üzündən hələ ki, aparıcı reytinq agentlikləri daha da təvazökar yanaşmanı sərgiləyirlər. Yəni, bütün bunlar onu deməyə əsas verir ki, biz iqtisadi sahədə dayanıqlı inkişafa nail ola bilmişik və əminəm ki, bu il və gələn illərdə bu dinamika saxlanılacaq.\n\nO ki qaldı maliyyə vəziyyətimizə, biz keçən il maliyyə vəziyyətimizi böyük dərəcədə yaxşılaşdıra, öz rezervlərimizi artıra bilmişik. Baxmayaraq ki, keçən ilin büdcəsi rekord səviyyədə idi və bir çox sosial proqramlar icra edildi, o cümlədən Qarabağın bərpası ilə bağlı böyük vəsait səfərbər olundu. Buna baxmayaraq, biz optimallaşmanı elə təşkil etmişik ki, valyuta ehtiyatlarımız daha da artdı. İl ərzində valyuta ehtiyatlarımız təqribən 5 milyard dollardan çox artıb və bu gün bu rəqəm 72 milyard dollara bərabərdir. Əhalisi 10 milyon olan ölkə üçün bu, çox böyük göstəricidir. Çünki hər şey müqayisədə ölçülür. Dünya ölkələrinin valyuta ehtiyatlarının hesablanması, əlbəttə ki, adambaşına düşən ehtiyatlara söykənməlidir və bu göstəriciyə görə Azərbaycan dünyada aparıcı ölkələrin sırasındadır.\n\nİkinci vacib göstərici ümumi daxili məhsulun xarici borca olan nisbətidir. Hesab edirəm ki, biz burada da dünyada liderlər sırasındayıq. Çünki bizim xarici borcumuz ümumi daxili məhsulumuzun cəmi 7.2 faizini təşkil edir. Müqayisə üçün deyə bilərəm ki, əksər inkişaf etmiş ölkələrdə bu, 100 faizdən də çoxdur və 7.2 faiz səviyyə doğrudan da çox böyük nəticədir. Məhz buna görə, mən hesab edirəm ki, beynəlxalq reytinq agentlikləri Azərbaycana daha ədalətli mövqe nümayiş etdirməlidirlər",
    "gold_entities": {
      "persons": [
        "İlham Əliyev",
        "Vüsal Mətləb"
      ],
      "organizations": [
        "AZƏRTAC",
        "Azərbaycan Televiziyası"
      ],
      "locations": [
        "Azərbaycan"
      ],
      "positions": [
        "Azərbaycan Respublikasının Prezidenti"
      ],
      "dates": [
        "yanvarın 7-də",
        "2024-cü il",
        "2025-ci il"
      ]
    },
    "manually_verified": true,
    "annotator_notes": ""
  },
  {
    "article_id": "8581",
    "source": "trend.az",
    "link": "https://az.trend.az/azerbaijan/culture/4102189.html",
    "pub_date": "2025-10-10 14:36:00.000",
    "title": "\"Azərbaycanfilm” kinostudiyasının rəhbərliyində dəyişikliklər olub",
    "content": "Bakı.Trend:\n\n\"Azərbaycanfilm” kinostudiyasının rəhbər heyətində dəyişikliklər\nolub.\n\nQeyd olunub ki, kinostudiyanın direktor müavini Davud Məlikbəyli\nvə aparat rəhbəri Aslan Rəhimov işdən azad ediliblər.",
    "gold_entities": {
      "persons": [
        "Davud Məlikbəyli",
        "Aslan Rəhimov"
      ],
      "organizations": [
        "Trend",
        "Azərbaycanfilm kinostudiyası"
      ],
      "locations": [
        "Bakı"
      ],
      "positions": [
        "direktor müavini",
        "aparat rəhbəri"
      ],
      "dates": [
        "2025-10-10"
      ]
    },
    "manually_verified": true,
    "annotator_notes": ""
  },
  {
    "article_id": "8663",
    "source": "trend.az",
    "link": "https://az.trend.az/other/world/4101928.html",
    "pub_date": "2025-10-10 07:36:32.000",
    "title": "Filippin sahillərində güclü zəlzələ olub",
    "content": "Bakı. Trend:\n\nFilippin sahillərində 7,3 maqnitudalı zəlzələ olub.\n\nTrend xəbər verir ki, bu\nbarədə Avropa-Aralıq dənizi Seysmoloji Mərkəzi məlumat yayıb.\n\nMəlumatına görə, zəlzələnin episentri Mati şəhərindən 60 km\nşimal-şərqdə yerləşib, ocağı isə 62 km dərinlikdə olub.\n\nZərərçəkənlər və dağıntılar barədə məlumat verilməyib.",
    "gold_entities": {
      "persons": [],
      "organizations": [
        "Trend",
        "Avropa-Aralıq dənizi Seysmoloji Mərkəzi"
      ],
      "locations": [
        "Filippin",
        "Mati"
      ],
      "positions": [],
      "dates": [
        "2025-10-10"
      ]
    },
    "manually_verified": true,
    "annotator_notes": ""
  },
  {
    "article_id": "8412",
    "source": "trend.az",
    "link": "https://az.trend.az/other/world/4102723.html",
    "pub_date": "2025-10-11 21:34:00.000",
    "title": "Efiopiyada 5,5 bal gücündə zəlzələ olub",
    "content": "Bakı. Trend:\n\nEfiopiyada 5,5 bal gücündə zəlzələ qeydə alınıb.\n\nTrend xəbər verir\nki, bu barədə Avropa-Aralıq dənizi Seysmoloji Mərkəzi məlumat\nyayıb.\n\nMəlumata görə, yeraltı təkanların episentri 500 mindən çox\ninsanın yaşadığı Mek'ele şəhərindən 51 km şimal-şərqdə yerləşib.\nZəlzələnin ocağı 10 km dərinlikdə olub.\n\nHazırda tələfat və dağıntılar barədə məlumat verilmir.",
    "gold_entities": {
      "persons": [],
      "organizations": [
        "Trend",
        "Avropa-Aralıq dənizi Seysmoloji Mərkəzi"
      ],
      "locations": [
        "Efiopiya",
        "Mek'ele"
      ],
      "positions": [],
      "dates": [
        "2025-10-11"
      ]
    },
    "manually_verified": true,
    "annotator_notes": ""
  },
  {
    "article_id": "3148",
    "source": "trend.az",
    "link": "https://az.trend.az/azerbaijan/sports/4117744.html",
    "pub_date": "2025-11-14 21:00:00.000",
    "title": "Belçika millisinin üzvü bu kluba keçə bilər",
    "content": "Bakı. Trend:\n\n\"Lester Siti\"nin müdafiəçisi Vaut Faes karyerasını Türkiyə Super\nLiqasında davam etdirə bilər.\n\nTrend xəbər verir ki, bu\nbarədə xarici KİV-lər məlumat yayıb.\n\nMəlumata görə, \"Beşiktaş\" belçikalı futbolçunu transfer etmək\nistəyir. İstanbul nəhəngi Faesi satınalma bəndi ilə icarəyə\ngötürməyi planlaşdırır.\n\nQeyd edək ki, \"Lester Siti\" Vaut Faesi 2022-ci ilin yayında\n\"Renn\"dən transfer edib.",
    "gold_entities": {
      "persons": [
        "Vaut Faes"
      ],
      "organizations": [
        "Trend",
        "Lester Siti",
        "Beşiktaş",
        "Renn",
        "Türkiyə Super Liqası"
      ],
      "locations": [
        "Türkiyə",
        "İstanbul",
        "Belçika"
      ],
      "positions": [
        "müdafiəçi"
      ],
      "dates": [
        "2022-ci ilin yayında",
        "2025-11-14"
      ]
    },
    "manually_verified": true,
    "annotator_notes": ""
  },
  {
    "article_id": "7305",
    "source": "trend.az",
    "link": "https://az.trend.az/other/world/4106014.html",
    "pub_date": "2025-10-19 10:06:00.000",
    "title": "Yer kürəsində maqnit qasırğası müşahidə olunur",
    "content": "Bakı. Trend:\n\nYer kürəsində növbəti maqnit qasırğası başlayıb.\n\nTrend xəbər verir\nki, bu, oktyabr ayı ərzində qeydə alınan üçüncü belə hadisədir.\nƏvvəlki maqnit qasırğaları 1–3 oktyabr və 12 oktyabr tarixlərində\nbaş vermişdi.\n\nMəlumata görə, hazırda Yer maqnit sahəsindəki narahatlıq\ndərəcəsi beşballıq şkala üzrə G1 səviyyəsinə çatıb.\n\nQeyd edək ki, bu şkalada G5 “ekstremal güclü”, G1 isə “zəif”\nmaqnit qasırğası kimi qiymətləndirilir.",
    "gold_entities": {
      "persons": [],
      "organizations": [
        "Trend"
      ],
      "locations": [
        "Yer kürəsi"
      ],
      "positions": [],
      "dates": [
        "oktyabr",
        "1–3 oktyabr",
        "12 oktyabr",
        "2025-10-19"
      ]
    },
    "manually_verified": true,
    "annotator_notes": ""
  },
  {
    "article_id": "4357",
    "source": "trend.az",
    "link": "https://az.trend.az/azerbaijan/gundem/4114340.html",
    "pub_date": "2025-11-06 17:56:00.000",
    "title": "COP30 üçün Braziliyaya ezam olunan şəxslərə əlavə ödəniş ediləcək",
    "content": "Bakı. Trend:\n\nCOP29 və COP30 tədbirləri çərçivəsində 2025-ci ildə Belem\nşəhərinə ezam olunan heyət üzvlərinin təqdim edilmiş sənədlərə\nəsasən, faktiki mehmanxana xərclərinin 1 günlük məbləği ezamiyyə\nxərclərinin 1 günlük normasının (qeyd olunan əlavə nəzərə\nalınmaqla) 60 faizindən çox olduğu halda həmin fərq mehmanxana\ngünləri üçün ezamiyyə xərclərinə əlavə xərc olaraq ödəniləcək.\n\nTrend xəbər\nverir ki, bununla bağlı Baş nazir Əli Əsədov müvafiq qərar\nimzalayıb.",
    "gold_entities": {
      "persons": [
        "Əli Əsədov"
      ],
      "organizations": [
        "Trend",
        "COP29",
        "COP30"
      ],
      "locations": [
        "Belem",
        "Braziliya"
      ],
      "positions": [
        "Baş nazir"
      ],
      "dates": [
        "2025-ci ildə",
        "2025-11-06"
      ]
    },
    "manually_verified": true,
    "annotator_notes": ""
  },
  {
    "article_id": "7405",
    "source": "trend.az",
    "link": "https://az.trend.az/azerbaijan/sports/4105710.html",
    "pub_date": "2025-10-18 05:19:00.000",
    "title": "Hans Hatebur “Lion”un heyətində çıxış edəcək",
    "content": "Bakı. Trend:\n\nHans Hatebur mövsümün sonunadək “Lion”un heyətində çıxış\nedəcək.\n\nTrend xəbər verir ki, \"Lion\"\nyarımmüdafiəçini “Renn”dən icarəyə götürdüyünü açıqlayıb. Bu, hər\nLiqa 1 klubuna transfer pəncərəsi bağlandıqdan sonra bir azad\nagenti və ya başqa bir Fransa klubunun futbolçusunu transfer etməyə\nicazə verən “coker qaydası”ndan istifadə etməklə mümkün olub.\n\n“Atalanta”dakı çıxışları ilə tanınan 31 yaşlı niderlandlı\nfutbolçu Fransa çempionatında cari mövsümdə cəmi bir oyun\nkeçirib.",
    "gold_entities": {
      "persons": [
        "Hans Hatebur"
      ],
      "organizations": [
        "Trend",
        "Lion",
        "Renn",
        "Atalanta",
        "Liqa 1"
      ],
      "locations": [
        "Fransa"
      ],
      "positions": [
        "yarımmüdafiəçi"
      ],
      "dates": [
        "mövsümün sonunadək",
        "2025-10-18"
      ]
    },
    "manually_verified": true,
    "annotator_notes": ""
  },
  {
    "article_id": "5886",
    "source": "trend.az",
    "link": "https://az.trend.az/azerbaijan/sports/4110052.html",
    "pub_date": "2025-10-28 19:48:00.000",
    "title": "Messi dünya çempionatında oynamaq istəyir",
    "content": "Bakı. Trend:\n\nLionel Messi dünya çempionatında oynamaq istəyir\n\nTrend xarici KİV-lərə\nistinadən xəbər verir ki, Argentina millisinin və ABŞ-ın \"İnter\nMayami\" komandasının futbolçusu Lionel Messi 2026-cı il dünya\nçempionatında oynamaq istəyir.\n\n38 yaşlı hücumçu bu barədə “Mundo Deportivo” nəşrinə\naçıqlamasında deyib. O bildirib ki, mundialda iştirak etmək son\ndərəcədə gözəl olardı.\n\nQeyd edək ki, DÇ-2026-ya ABŞ, Kanada və Meksika birgə ev\nsahibliyi edəcək. Mundial ilk dəfə 48 komandanın iştirakı ilə\nkeçiriləcək.",
    "gold_entities": {
      "persons": [
        "Lionel Messi"
      ],
      "organizations": [
        "Trend",
        "Argentina millisi",
        "İnter Mayami",
        "Mundo Deportivo",
        "DÇ-2026"
      ],
      "locations": [
        "ABŞ",
        "Kanada",
        "Meksika"
      ],
      "positions": [
        "hücumçu"
      ],
      "dates": [
        "2026-cı il",
        "2025-10-28"
      ]
    },
    "manually_verified": true,
    "annotator_notes": ""
  },
  {
    "article_id": "3660",
    "source": "trend.az",
    "link": "https://az.trend.az/azerbaijan/sports/4116200.html",
    "pub_date": "2025-11-12 11:05:00.000",
    "title": "Əliyar Ağayev Xorvatiya yığmasının oyununa təyinat aldı",
    "content": "Bakı. Trend:\n\nFIFA referisi Əliyar Ağayev növbəti təyinat alıb. Ə.Ağayev\nDÇ-2026-nın seçmə mərhələsi çərçivəsində keçiriləcək Xorvatiya –\nFarer adaları matçının baş hakimi olacaq.\n\nTrend xəbər verir ki, bu barədə AFFA məlumat\nyayıb.\n\nBildirilib ki, ona Zeynal Zeynalov və Akif Əmirəli kömək\nedəcəklər.\n\nDördüncü hakim funksiyasını Elçin Məsiyev yerinə yetirəcək.\nPortuqaliyalı Tiaqo Martins VAR, onun həmyerlisi Bruno Esteves isə\nAVAR kimi fəaliyyət göstərəcək.\n\nQarşılaşma noyabrın 14-də Riyeka şəhərinin eyniadlı stadionunda\nkeçiriləcək.",
    "gold_entities": {
      "persons": [
        "Əliyar Ağayev",
        "Zeynal Zeynalov",
        "Akif Əmirəli",
        "Elçin Məsiyev",
        "Tiaqo Martins",
        "Bruno Esteves"
      ],
      "organizations": [
        "Trend",
        "FIFA",
        "AFFA",
        "VAR",
        "AVAR",
        "DÇ-2026"
      ],
      "locations": [
        "Xorvatiya",
        "Farer adaları",
        "Riyeka",
        "Portuqaliya"
      ],
      "positions": [
        "baş hakim",
        "dördüncü hakim"
      ],
      "dates": [
        "noyabrın 14-də",
        "2025-11-12"
      ]
    },
    "manually_verified": true,
    "annotator_notes": ""
  },
  {
    "article_id": "4823",
    "source": "trend.az",
    "link": "https://az.trend.az/other/world/4113000.html",
    "pub_date": "2025-11-04 12:42:00.000",
    "title": "Belçikada \"F-35\" qırıcılarının tədarükü qalmaqala səbəb olub",
    "content": "Bakı. Trend:\n\nBelçikada ABŞ istehsalı olan \"F-35\" qırıcılarının tədarükünün\nbaşlanması ilə bağlı qalmaqal meydana gəlib.\n\nTrend bu barədə\nxarici KİV-ə istinadən xəbər verir.\n\nMəlumata görə, bu hərbi təyyarələr istismar baxımından həddindən\nartıq bahalı və kiçik krallıq üçün çox səs-küylü hesab olunur.\nBahalı yeni qırıcılarla bağlı ilk tənqid dalğası Belçikanın müdafiə\nnaziri Teo Frankenin federal parlamentdəki çıxışından sonra\nyaranıb.\n\nQeyd olunur ki, F-35 təyyarəsinin bir saatlıq uçuşunun dəyəri\nBelçika üçün olduqca baha başa gəlir - 50 min avrodan çox.",
    "gold_entities": {
      "persons": [
        "Teo Franken"
      ],
      "organizations": [
        "Trend",
        "F-35",
        "ABŞ",
        "Belçikanın federal parlamenti"
      ],
      "locations": [
        "Belçika",
        "ABŞ"
      ],
      "positions": [
        "Belçikanın müdafiə naziri"
      ],
      "dates": [
        "2025-11-04"
      ]
    },
    "manually_verified": true,
    "annotator_notes": ""
  },
  {
    "article_id": "805",
    "source": "trend.az",
    "link": "https://az.trend.az/azerbaijan/sports/4124330.html",
    "pub_date": "2025-12-01 21:00:00.000",
    "title": "\"Yuventus\"un hücumçusu sıradan çıxıb",
    "content": "Bakı. Trend:\n\nİtaliyanın \"Yuventus\" klubunun heyətində ciddi itki baş\nverib.\n\nTrend xarici\nKİV-ə istinadən xəbər verir ki, \"ağ-qaralar\"ın hücumçusu Duşan\nVlahoviç sıradan çıxıb.\n\nSerbiyalı futbolçu A Seriyasının 13-cü turunun \"Kalyari\" ilə\nmatçında (2:1) ayaq əzələsindən zədə alıb. Vlahoviçin zədəsi\nciddidir. 25 yaşlı forvard təxminən 3 ay yaşıl meydanlardan uzaq\nqalacaq.\n\nQeyd edək ki, Duşan Vlahoviç bu mövsüm \"Yuventus\"un heyətində\nmeydana çıxdığı 20 rəsmi matçda 8 qol və 2 məhsuldar ötürmə ilə\nyadda qalıb. Onun Turin təmsilçisi ilə müqaviləsi mövsümün sonunda\nbaşa çatır.",
    "gold_entities": {
      "persons": [
        "Dušan Vlahoviç"
      ],
      "organizations": [
        "Trend",
        "Yuventus",
        "Kalyari",
        "A Seriyası"
      ],
      "locations": [
        "İtaliya",
        "Turin"
      ],
      "positions": [
        "hücumçu"
      ],
      "dates": [
        "2025-12-01",
        "təxminən 3 ay",
        "mövsümün sonunda"
      ]
    },
    "manually_verified": true,
    "annotator_notes": ""
  },
  {
    "article_id": "6825",
    "source": "trend.az",
    "link": "https://az.trend.az/business/4107405.html",
    "pub_date": "2025-10-22 13:16:00.000",
    "title": "Mərkəzi Bankın sədri: Hazırda “BTB Bank”ın fəaliyyəti ilə bağlı hər hansı problem görmürük",
    "content": "Bakı. Trend:\n\nHazırda “BTB Bank”ın Mərkəzi Bankın tələblərinə cavab verməməsi\nilə bağlı bir fakt yoxdur. Biz bunu nəzarət altında saxlayırıq.\nBank dayanıqlıdır.\n\nTrend xəbər verir ki, bunu Mərkəzi Bankın sədri Taleh Kazımov\nfaiz dəhlizinin parametrləri ilə bağlı keçirdiyi brifinqdə\ndeyib.\n\nO qeyd edib ki, “BTB Bank” bütün prudensial tələblərə riayət\nedir.\n\n“Cəlb edilmiş əmanətlərin 96,3 faizi sığortalıdır. Bankın\nfəaliyyəti ilə bağlı hər hansı problem görmürük. Bizim nəzarət\ntədbirlərimizin nəticəsi olaraq bankın dayanıqlılığı artıb və\nfəaliyyətini davam etdirir”, - deyə Taleh Kazımov əlavə edib.",
    "gold_entities": {
      "persons": [
        "Taleh Kazımov"
      ],
      "organizations": [
        "Trend",
        "Mərkəzi Bank",
        "BTB Bank"
      ],
      "locations": [
        "Bakı",
        "Azərbaycan"
      ],
      "positions": [
        "Mərkəzi Bankın sədri"
      ],
      "dates": [
        "2025-10-22"
      ]
    },
    "manually_verified": true,
    "annotator_notes": ""
  },
  {
    "article_id": "3544",
    "source": "trend.az",
    "link": "https://az.trend.az/azerbaijan/society/4116625.html",
    "pub_date": "2025-11-12 18:44:00.000",
    "title": "Nəsiminin yeni icra başçısı kollektivə təqdim olundu",
    "content": "Bakı. Trend:\n\nNəsimi Rayon İcra Hakimiyyətinin yeni başçısı Elxan İbrahimov\nkollektivə təqdim olunub.\n\nTrend xəbər verir ki,\nAzərbaycan Respublikası Prezidentinin Sərəncamı ilə Nəsimi Rayon\nİcra Hakimiyyətinin başçısı təyin olunan Elxan Oqtay oğlu İbrahimov\nbu gün Azərbaycan Respublikası Prezidentinin köməkçisi –\nƏrazi-təşkilat məsələləri şöbəsinin müdiri Zeynal Nağdəliyev\ntərəfindən rayon ictimaiyyətinin nümayəndələrinin iştirakı ilə\nkollektivə təqdim olunub.\n\nTəqdimatda Zeynal Nağdəliyev çıxış edib və ölkə başçısının\ntapşırıq və tövsiyələrini çatdırıb.\n\nElxan İbrahimov ona göstərilən etimada görə minnətdarlıq\nedib.",
    "gold_entities": {
      "persons": [
        "Elxan İbrahimov",
        "Zeynal Nağdəliyev"
      ],
      "organizations": [
        "Trend",
        "Nəsimi Rayon İcra Hakimiyyəti",
        "Azərbaycan Respublikası Prezidentinin Administrasiyası"
      ],
      "locations": [
        "Bakı",
        "Nəsimi"
      ],
      "positions": [
        "Nəsimi Rayon İcra Hakimiyyətinin başçısı",
        "Azərbaycan Respublikası Prezidentinin köməkçisi",
        "Ərazi-təşkilat məsələləri şöbəsinin müdiri"
      ],
      "dates": [
        "bu gün",
        "2025-11-12"
      ]
    },
    "manually_verified": true,
    "annotator_notes": ""
  },
  {
    "article_id": "5716",
    "source": "trend.az",
    "link": "https://az.trend.az/azerbaijan/incident/4110483.html",
    "pub_date": "2025-10-29 17:07:00.000",
    "title": "Mənimsəmədə ittiham olunan şirkət rəhbərinin cəzası azaldılıb",
    "content": "Bakı. Trend:\n\nXüsusilə külli miqdarda mənimsəmədə ittiham olunan şirkət\nrəhbəri Üzeyir Həsənov barəsində olan hökmdən verdiyi kassasiya\nşikayəti üzrə məhkəmə prosesi keçirilib.\n\nTrend xəbər\nverir ki, Ali Məhkəmədə keçirilən prosesdə qərar qəbul edilib.\n\nQərara əsasən, təqsirləndirilən şəxsin cəzası 10 ildən 8 ilə\nendirilib.\n\nBildirək ki, Bakı Ağır Cinayətlər Məhkəməsinin hökmünə əsasən,\nÜzeyir Həsənov 11 il müddətə azadlıqdan məhrum edilsə də, Bakı\nApellyasiya Məhkəməsi qərarı dəgişərək cəzanı 10 ilə\nendirmişdi.\n\nTəqsirləndirilən şəxs Cinayət Məəcəlləsinin 179.3.2-ci (\nMənimsəmə, külli miqdarda törədildikdə) maddəsi ilə ittiham\nedilib.",
    "gold_entities": {
      "persons": [
        "Üzeyir Həsənov"
      ],
      "organizations": [
        "Trend",
        "Ali Məhkəmə",
        "Bakı Ağır Cinayətlər Məhkəməsi",
        "Bakı Apellyasiya Məhkəməsi",
        "Cinayət Məcəlləsi"
      ],
      "locations": [
        "Bakı",
        "Azərbaycan"
      ],
      "positions": [
        "şirkət rəhbəri"
      ],
      "dates": [
        "2025-10-29",
        "10 il",
        "8 il"
      ]
    },
    "manually_verified": true,
    "annotator_notes": ""
  },
  {
    "article_id": "2025",
    "source": "trend.az",
    "link": "https://az.trend.az/azerbaijan/sports/4121022.html",
    "pub_date": "2025-11-22 15:31:00.000",
    "title": "UEFA \"Ayntraxt\"ı cərimələdi",
    "content": "Bakı. Trend:\n\nUEFA \"Qarabağ\"ın Çempionlar Liqasının Liqa mərhələsindəki\nrəqiblərindən \"Ayntraxt\"ı (Frankfurt, Almaniya) cərimələnib.\n\nTrend xarici\nKİV-ə istinadən xəbər verir ki, bu barədə qurumun saytı məlumat\nyayıb.\n\nAlmaniya təmsilçisinin cəzalandırılmasına səbəb klubun və\nazarkeşlərinin \"Liverpul\"la matçda qayda pozuntularına yol verməsi\nolub.\n\n\"Ayntraxt\" ictimai keçidlərin bağlanmasına görə 11000 avro\nödəyəcək. Həmçinin klub irotexniki vasitələrdən istifadəyə görə\n10750 avro, idman tədbirinə uyğun olmayan mesajların ötürülməsinə\ngörə 17500 avro cərimələnib.\n\nQeyd edək ki, \"Qarabağ\"la \"Ayntraxt\" arasında matç 21 yanvar\n2026-cı ildə Bakıda keçiriləcək.",
    "gold_entities": {
      "persons": [],
      "organizations": [
        "Trend",
        "UEFA",
        "Qarabağ",
        "Ayntraxt",
        "Liverpul",
        "Çempionlar Liqası"
      ],
      "locations": [
        "Frankfurt",
        "Almaniya",
        "Bakı"
      ],
      "positions": [],
      "dates": [
        "21 yanvar 2026-cı il",
        "2025-11-22"
      ]
    },
    "manually_verified": true,
    "annotator_notes": ""
  },
  {
    "article_id": "2943",
    "source": "trend.az",
    "link": "https://az.trend.az/other/world/4118351.html",
    "pub_date": "2025-11-17 08:12:00.000",
    "title": "Vyetnamda torpaq sürüşməsi nəticəsində altı nəfər ölüb",
    "content": "Bakı. Trend:\n\nVyetnamın mərkəzində yerləşən Xanhoa əyalətində dağ yolunda baş\nverən torpaq sürüşməsi ağır qəza ilə nəticələnib.\n\nTrend xəbər verir\nki, hadisə zamanı sərnişin avtobusunun uçması nəticəsində ən azı\naltı nəfər ölüb, 19 nəfər yaralanıb.\n\nVnExpress-in məlumatına görə, faciə 16 noyabr axşamı 27C Milli\nMagistral Yolundakı Xanle Aşırımında qeydə alınıb. Güclü yağışların\nyaratdığı sürüşmə 32 sərnişin daşıyan avtobusun üzərinə çöküb.\nTorpaq və qayaların yolu bağlaması səbəbindən xilasedicilərin\nhadisə yerinə çatması iki saatdan çox vaxt aparıb.\n\nXilasetmə əməliyyatları bazar ertəsi səhəri də davam etdirilib.\nLakin güclü yağış və yeni sürüşmə riski işləri çətinləşdirir.",
    "gold_entities": {
      "persons": [],
      "organizations": [
        "Trend",
        "VnExpress",
        "27C Milli Magistral Yol"
      ],
      "locations": [
        "Vyetnam",
        "Xanhoa",
        "Xanle Aşırımı"
      ],
      "positions": [],
      "dates": [
        "16 noyabr axşamı",
        "bazar ertəsi səhəri",
        "2025-11-17"
      ]
    },
    "manually_verified": true,
    "annotator_notes": ""
  },
  {
    "article_id": "510",
    "source": "trend.az",
    "link": "https://az.trend.az/azerbaijan/society/4125168.html",
    "pub_date": "2025-12-03 15:24:00.000",
    "title": "Bakıda NATO-nun mobil təlim qrupu tərəfindən seminar-məşğələ keçirilir",
    "content": "Bakı.Trend:\n\n2025-ci ilin NATO ilə Fərdi Tərəfdaşlıq üzrə Əməkdaşlıq\nProqramına əsasən, NATO-nun Brunssum Birgə Qüvvələr Komandanlığının\nmobil təlim qrupu tərəfindən “Əldə düzəldilmiş partlayıcı qurğulara\nqarşı mübarizə” mövzusunda seminar-məşğələ keçirilir.\n\nTrend xəbər\nverir ki, bu barədə Müdafiə Nazirliyi məlumat yayıb.\n\nBildirilib ki, tədbirdə Müdafiə Nazirliyinin Mühəndis Qoşunları\nBaş İdarəsinin və onun tabeliyindəki hərbi hissələrdə xidmət edən\nhərbi qulluqçuların, həmçinin xüsusi təyinatlı təhsil\nmüəssisələrinin mühəndis ixtisaslı zabitləri iştirak edirlər.\n\nKeçirilən məşğələ zamanı iştirakçılara müxtəlif mövzularda\nbrifinqlər təqdim edilir.\n\nSeminar-məşğələ dekabrın 5-dək davam edəcək.",
    "gold_entities": {
      "persons": [],
      "organizations": [
        "Trend",
        "NATO",
        "NATO-nun Brunssum Birgə Qüvvələr Komandanlığı",
        "Müdafiə Nazirliyi",
        "NATO ilə Fərdi Tərəfdaşlıq üzrə Əməkdaşlıq Proqramı"
      ],
      "locations": [
        "Bakı",
        "Brunssum"
      ],
      "positions": [],
      "dates": [
        "2025-ci il",
        "dekabrın 5-dək",
        "2025-12-03"
      ]
    },
    "manually_verified": true,
    "annotator_notes": ""
  },
  {
    "article_id": "7990",
    "source": "trend.az",
    "link": "https://az.trend.az/business/finance/4103930.html",
    "pub_date": "2025-10-14 17:52:32.000",
    "title": "BVF Azərbaycanda ÜDM artımı dinamikası üzrə tarixi icmalı təqdim edib",
    "content": "Bakı. Trend:\n\nBeynəlxalq Valyuta Fondu (BVF) Azərbaycanın real ÜDM artımına\ndair tarixi məlumatları dərc edib. Bu statistik məlumatlar son iki\nonillikdə ölkə iqtisadiyyatında müşahidə olunan əhəmiyyətli\ndalğalanmaları nümayiş etdirir.\n\nBu barədə Trend\nBVF-ə istinadən xəbər verir.\n\nBVF-in məlumatına əsasən, Azərbaycanın ÜDM artımı müxtəlif\nillərdə aşağıdakı kimi olub:\n\n2007–2016: illik orta artım – 5,6 faiz\n\n2017: 0,2 faiz\n\n2018: 1,5 faiz\n\n2019: 2,5 faiz\n\n2020: –4,2 faiz\n\n2021: 5,6 faiz\n\n2022: 4,7 faiz\n\n2023: 1,4 faiz\n\n2024: 4,1 faiz\n\nYenilənmiş proqnozlara görə, Azərbaycanda iqtisadi artım 2025-ci\nildə 3 faiz, 2026-cı ildə isə 2,5 faiz təşkil edəcək. Bu, 2024-cü\nildəki 4,1 faiz göstəricisi ilə müqayisədə azalmadır",
    "gold_entities": {
      "persons": [],
      "organizations": [
        "Trend",
        "Beynəlxalq Valyuta Fondu (BVF)"
      ],
      "locations": [
        "Azərbaycan"
      ],
      "positions": [],
      "dates": [
        "2007–2016",
        "2017",
        "2018",
        "2019",
        "2020",
        "2021",
        "2022",
        "2023",
        "2024",
        "2025-ci il",
        "2026-cı il",
        "2025-10-14"
      ]
    },
    "manually_verified": true,
    "annotator_notes": ""
  },
  {
    "article_id": "2643",
    "source": "trend.az",
    "link": "https://az.trend.az/azerbaijan/society/4119255.html",
    "pub_date": "2025-11-18 20:01:00.000",
    "title": "Əlaqələndirmə Qərargahının üzvləri Zəngəzur dəhlizi üzrə görülən işlər və Ağbənd-Kəlalə körpüsünün inşası prosesi ilə tanış olublar (FOTO)",
    "content": "Bakı. Trend:\n\nNoyabrın 18-də Azərbaycan Respublikasının Prezidenti\nAdministrasiyasının və Azərbaycan Respublikasının işğaldan azad\nedilmiş ərazilərində məsələlərin mərkəzləşdirilmiş qaydada həlli\nilə bağlı Əlaqələndirmə Qərargahının üzvləri Zəngəzur dəhlizində\navtomobil yolunun və dəmir yolu xəttinin, eyni zamanda, Araz çayı\nüzərində tikilən Ağbənd-Kəlalə körpüsünün inşası prosesi ilə tanış\nolublar.\n\nTrend xəbər\nverir ki, tanışlıq zamanı bu nəqliyyat qovşaqlarının regionda\nnəqliyyat əlaqələrinin yaradılmasında xüsusi əhəmiyyət kəsb etdiyi\nvurğulanıb.\n\nHəmçinin ərazidə gömrük xidmətinin təşkili və bu istiqamətdə\naparılan işlər nəzərdən keçirilib, aidiyyəti dövlət qurumlarının\nnümayəndələri tərəfindən yerində müvafiq brifinqlər verilib.",
    "gold_entities": {
      "persons": [],
      "organizations": [
        "Trend",
        "Azərbaycan Respublikasının Prezidenti Administrasiyası",
        "Əlaqələndirmə Qərargahı"
      ],
      "locations": [
        "Zəngəzur dəhlizi",
        "Araz çayı",
        "Ağbənd-Kəlalə körpüsü"
      ],
      "positions": [],
      "dates": [
        "Noyabrın 18-də",
        "2025-11-18"
      ]
    },
    "manually_verified": true,
    "annotator_notes": ""
  },
  {
    "article_id": "5773",
    "source": "trend.az",
    "link": "https://az.trend.az/azerbaijan/society/4110333.html",
    "pub_date": "2025-10-29 13:44:00.000",
    "title": "İtkin şəhid İlham Mehdiyev dəfn edilib",
    "content": "Bakı.Trend:\n\nBirinci Qarabağ müharibəsinin itkin şəhidi İlham İmdad oğlu\nMehdiyev oktyabrın 29-da paytaxtın Suraxanı rayonu ərazisində\nyerləşən “Dədə Qorqud” qəbiristanlığındakı Şəhidlər xiyabanında\ndəfn olunub.\n\nTrend xəbər\nverir ki, dəfn mərasimində şəhidin ailə üzvləri, Müdafiə, Daxili\nİşlər, Fövqəladə Hallar nazirliklərinin əməkdaşları, Suraxanı,\nSabunçu, Xətai Rayon İcra Hakimiyyətlərinin nümayəndələri, müharibə\nveteranları, şəhid ailələri və sakinlər iştirak ediblər.\n\nİtkin şəhid yaylım atəşi və hərbi orkestrin müşayiəti ilə\nAzərbaycanın Dövlət Himninin sədaları altında torpağa\ntapşırılıb.\n\nQeyd edək ki, İlham Mehdiyev Birinci Qarabağ müharibəsində itkin\ndüşmüş hesab edilən və şəxsiyyətləri müəyyənləşdirilərək bu gün\ndəfn olunan dörd şəhiddən biridir.",
    "gold_entities": {
      "persons": [
        "İlham Mehdiyev"
      ],
      "organizations": [
        "Trend",
        "Müdafiə Nazirliyi",
        "Daxili İşlər Nazirliyi",
        "Fövqəladə Hallar Nazirliyi",
        "Suraxanı Rayon İcra Hakimiyyəti",
        "Sabunçu Rayon İcra Hakimiyyəti",
        "Xətai Rayon İcra Hakimiyyəti",
        "Dədə Qorqud qəbiristanlığı",
        "Şəhidlər xiyabanı"
      ],
      "locations": [
        "Bakı",
        "Suraxanı"
      ],
      "positions": [
        "şəhid"
      ],
      "dates": [
        "oktyabrın 29-da",
        "Birinci Qarabağ müharibəsi",
        "2025-10-29"
      ]
    },
    "manually_verified": true,
    "annotator_notes": ""
  },
  {
    "article_id": "5073",
    "source": "trend.az",
    "link": "https://az.trend.az/business/4112393.html",
    "pub_date": "2025-11-03 12:19:47.000",
    "title": "Azərbaycan və Ukrayna səhiyyə sənayesi sahəsində işbirliyinin dərinləşdirilməsi imkanlarını dəyərləndirib",
    "content": "Bakı. Trend:\n\nAzərbaycan və Ukrayna arasında səhiyyə sənayesi sahəsində\nişbirliyinin dərinləşdirilməsi barədə müzakirə aparılıb.\n\nBu barədə Trend İqtisadiyyat Nazirliyinə istinadən xəbər\nverir.\n\nBelə ki, iqtisadiyyat nazirinin müavini Səməd Bəşirli Ukraynanın\nsəhiyyə naziri Viktor Lyaşko ilə görüşüb.\n\nİqtisadiyyat Nazirliyində keçirilən görüşdə Azərbaycanın Ukrayna\nilə iqtisadi əməkdaşlığa önəm verdiyi qeyd olunub. Ukrayna ilə\nmüxtəlif iqtisadi istiqamətlər üzrə əlaqələrin genişləndirilməsi\nüçün imkanlar diqqətə çatdırılıb. Bildirilib ki, ticarət və\ninvestisiya əməkdaşlığı münasibətlərdə mühüm\nistiqamətlərdəndir.\n\nTərəflər Azərbaycan və Ukrayna arasında səhiyyə sənayesi\nsahəsində işbirliyinin dərinləşdirilməsi, dərman vasitələrinin\nbirgə istehsalı barədə fikir mübadiləsi aparıblar.",
    "gold_entities": {
      "persons": [
        "Səməd Bəşirli",
        "Viktor Lyaşko"
      ],
      "organizations": [
        "Trend",
        "İqtisadiyyat Nazirliyi"
      ],
      "locations": [
        "Azərbaycan",
        "Ukrayna"
      ],
      "positions": [
        "iqtisadiyyat nazirinin müavini",
        "Ukraynanın səhiyyə naziri"
      ],
      "dates": [
        "2025-11-03"
      ]
    },
    "manually_verified": true,
    "annotator_notes": ""
  },
  {
    "article_id": "2115",
    "source": "trend.az",
    "link": "https://az.trend.az/other/world/4120755.html",
    "pub_date": "2025-11-21 20:00:00.000",
    "title": "COP30-un razılaşma mətni qəbuledilməzdir - Avropa komissarı",
    "content": "Bakı. Trend:\n\nCOP30-un Belemdə başa çatmasına bir neçə saat qalmış iqlim üzrə\nAvropa komissarı Vopke Hoekstra vəziyyətin son dərəcə narahatedici\nolduğunu bildirib.\n\nTrend xəbər\nverir ki, Avropa İttifaqı mövcud layihə mətninin istixana qazı\nemissiyalarının azaldılması baxımından yetərli olmadığını\nbildirib.\n\n“Hazırda masada olan mətn qəbuledilməzdir. Lazım olan yerdən bu\nqədər uzaq olduğumuza görə, təəssüf ki, sammitin razılaşma olmadan\nbitməsi real ehtimaldır”, - deyə Hoekstra əlavə edib.\n\nO diqqətə çatdırıb ki, bu mətn məyusedicidir:\n\n”Layihədə fosil yanacaqlar haqqında heç bir qeyd yoxdur: nə\nonların mərhələli şəkildə dayandırılmasından, nə də bunun üçün\ntələb olunan “yol xəritəsi”ndən. Halbuki Avropa, Latın Amerikası və\nada ölkələri daxil olmaqla 80-dən çox ölkə bunun mətnə daxil\nedilməsini tələb edir”.",
    "gold_entities": {
      "persons": [
        "Vopke Hoekstra"
      ],
      "organizations": [
        "Trend",
        "Avropa İttifaqı",
        "COP30"
      ],
      "locations": [
        "Belem",
        "Avropa",
        "Latın Amerikası"
      ],
      "positions": [
        "iqlim üzrə Avropa komissarı"
      ],
      "dates": [
        "2025-11-21"
      ]
    },
    "manually_verified": true,
    "annotator_notes": ""
  },
  {
    "article_id": "6994",
    "source": "trend.az",
    "link": "https://az.trend.az/azerbaijan/gundem/4106857.html",
    "pub_date": "2025-10-21 15:38:00.000",
    "title": "Azərbaycan və İran nümayəndələri mobil rabitə şəbəkələrinin tənzimlənməsini müzakirə ediblər",
    "content": "Bakı. Trend:\n\nTehran şəhərində Azərbaycan və İran arasında mobil rabitə\nşəbəkələrinin koordinasiyası üzrə görüş keçirilib.\n\nRəqəmsal İnkişaf və Nəqliyyat Nazirliyindən (RİNN) Trend-ə verilən məlumata\ngörə, görüşdə RİNN, İnformasiya Kommunikasiya Texnologiyaları\nAgentliyi, Dövlət Radiotezliklər İdarəsi və mobil rabitə\noperatorlarının mütəxəssisləri iştirak ediblər.\n\nBildirilib ki, görüşdə Azərbaycan və İranın sərhədyanı\nərazilərində mövcud və perspektivdə olan mobil rabitə şəbəkələrinin\ntənzimlənməsi məsələləri geniş müzakirə edilib, zəruri texniki\nrazılaşmalar əldə olunub.\n\nHəmçinin TV və FM radio yayımları, 700/800 MHs zolaqların\nboşaldılması üzrə 10-12 iyun 2025-ci il tarixində Bakı şəhərində\nəldə olunan razılaşmalar çərçivəsində görülən işlər müzakirə\nedilib.\n\nQeyd olunan məsələlər üzrə əməkdaşlığın davam etdirilməsi qərara\nalınıb.",
    "gold_entities": {
      "persons": [],
      "organizations": [
        "Trend",
        "Rəqəmsal İnkişaf və Nəqliyyat Nazirliyi (RİNN)",
        "İnformasiya Kommunikasiya Texnologiyaları Agentliyi",
        "Dövlət Radiotezliklər İdarəsi"
      ],
      "locations": [
        "Tehran",
        "İran",
        "Azərbaycan",
        "Bakı"
      ],
      "positions": [],
      "dates": [
        "10-12 iyun 2025-ci il",
        "2025-10-21"
      ]
    },
    "manually_verified": true,
    "annotator_notes": ""
  },
  {
    "article_id": "7761",
    "source": "trend.az",
    "link": "https://az.trend.az/business/4104661.html",
    "pub_date": "2025-10-16 09:29:27.000",
    "title": "9 ayda Azərbaycanda istehsal olunan qaz kondensatının həcmi açıqlanıb",
    "content": "Bakı. Trend:\n\nBu ilin yanvar-sentyabr aylarında Azərbaycanda 518,8 min ton qaz\nkondensatı istehsal olunub.\n\nTrend bu barədə\nAzərbaycan Respublikasının Dövlət Statistika Komitəsinə istinadən\nxəbər verir.\n\nMəlumata əsasən, bu göstərici ötən ilin eyni dövrü ilə\nmüqayisədə 25,9 min ton və ya 5,3 faiz çoxdur.\n\nBelə ki, ötən ilin yanvar-sentyabr aylarında ölkədə cəmi 492,9\nmin ton qaz kondensatı hasil olunub.\n\nBu ilin 1 oktyabr tarixinə hazır məhsul ehtiyatı 27,9 min ton\ntəşkil edib.\n\nNeft məhsulları istehsalı sahəsində ümumi istehsal həcmi 4,047\nmilyard manat olub ki, bu da ötən ilin müvafiq dövrü ilə müqayisədə\n0,4 faiz çoxdur. Mazut istehsalı 2,1 dəfə, neft koksunun istehsalı\n8,5 faiz, qazoyl (dizel yanacağı) istehsalı 6,2 faiz, kerosin\nistehsalı isə 5,3 faiz artıb. Eyni zamanda, neft bitumu istehsalı\n9,9 faiz, sürtkü yağlarının istehsalı isə 44,7 faiz azalıb.",
    "gold_entities": {
      "persons": [],
      "organizations": [
        "Trend",
        "Azərbaycan Respublikasının Dövlət Statistika Komitəsi"
      ],
      "locations": [
        "Azərbaycan"
      ],
      "positions": [],
      "dates": [
        "yanvar-sentyabr ayları",
        "1 oktyabr",
        "2025-10-16"
      ]
    },
    "manually_verified": true,
    "annotator_notes": ""
  },
  {
    "article_id": "6693",
    "source": "trend.az",
    "link": "https://az.trend.az/business/4107777.html",
    "pub_date": "2025-10-23 10:53:00.000",
    "title": "Neft Fondu qızıl alışını artırıb",
    "content": "Bakı. Trend:\n\nBu ilin III rübündə Azərbaycan Dövlət Neft Fondu (ARDNF) qızıl\nehtiyatlarını 184,8 tona çatdırıb.\n\nTrend bu\nbarədə Fonda istinadən xəbər verir.\n\nMəlumata görə, bu, ötən ilin eyni dövrü ilə müqayisədə 57,8 ton\nvə ya 45,5% çoxdur.\n\nBu ilin oktyabrın 1-nə ARDNF-in investisiya portfelində qızılın\nxüsusi çəkisi 32,8% olub ki, bu da iyulun 1-i ilə müqayisədə 4 faiz\nbəndi çoxdur.\n\n“Qızıl bazarı hesabat dövründə ardıcıl olaraq tarixi maksimum\nsəviyyələri yeniləyərək yüksək gəlirlilik nümayiş etdirib. Qlobal\nmiqyasda davam edən qeyri-müəyyənliklər, mərkəzi banklar tərəfindən\nhəyata keçirilən iri həcmli alışlar və digər mənbələrdən mövcud\ntələbat qızılın qiymətinin yüksəlməsinə səbəb olub. Nəticə\netibarilə, bu amillər Dövlət Neft Fondunun qızıl altportfelinin\nperformansını əhəmiyyətli dərəcədə yaxşılaşdırmış və büdcədənkənar\ngəlirlərin artımına töhfə verib”, - məlumatda vurğulanıb.",
    "gold_entities": {
      "persons": [],
      "organizations": [
        "Trend",
        "Azərbaycan Dövlət Neft Fondu (ARDNF)"
      ],
      "locations": [
        "Azərbaycan"
      ],
      "positions": [],
      "dates": [
        "III rüb",
        "oktyabrın 1-nə",
        "iyulun 1-i",
        "2025-10-23"
      ]
    },
    "manually_verified": true,
    "annotator_notes": ""
  },
  {
    "article_id": "1090",
    "source": "trend.az",
    "link": "https://az.trend.az/azerbaijan/society/4123563.html",
    "pub_date": "2025-11-29 10:22:00.000",
    "title": "Azərbaycanda İKT sahəsində insan kapitalının inkişafı prioritetdir - İRİA rəsmisi",
    "content": "Bakı.Trend:\n\nAzərbaycanda İKT sahəsində insan kapitalının formalaşdırılması\ndövlətin prioritet istiqamətlərindən biridir.\n\nTrend xəbər\nverir ki, bu fikirləri bu gün İnnovasiya və Rəqəmsal İnkişaf\nAgentliyinin təşkil etdiyi\nİnnovasiya və Rəqəmsal İnkişaf Agentliyinin idarə heyətinin sədr\nmüavini Rəşad Xalıqov “İKT Karyera Sərgisi 2025”də çıxışı zamanı\nsəsləndirib.\n\nO qeyd edib ki, ölkədə bu sahədə fəaliyyət göstərən insan\nkapitalının formalaşdırılması əsas məqsədlərdəndir.\n\n“Bu sərgiyə 900-dən çox gənc müraciət edib. İRİA olaraq İKT\nsahəsində fəal göstərən gənclərin formalaşdırılmasında müxtəlif\nsəpkidə proqramlar həyata keçiririk.10000-dən çox şəxsin beynəlxalq\ntəcrübə keçməsinə, olimpiyadalarda təmsil olunmasına görə layihələr\nhəyata keçirmişik”.\n\nR.Xalıqov qeyd edib ki, həmin layihələr insan kapitalı\nbaxımından mühüm layihələrdir.\n\nO, universitetlərlə İRİA-nın əməkdaşlığının mühüm əhəmiyyət\ndaşıdığını vurğulayıb.",
    "gold_entities": {
      "persons": [
        "Rəşad Xalıqov"
      ],
      "organizations": [
        "Trend",
        "İnnovasiya və Rəqəmsal İnkişaf Agentliyi (İRİA)",
        "İKT Karyera Sərgisi 2025"
      ],
      "locations": [
        "Azərbaycan"
      ],
      "positions": [
        "idarə heyətinin sədr müavini"
      ],
      "dates": [
        "2025",
        "2025-11-29"
      ]
    },
    "manually_verified": true,
    "annotator_notes": ""
  },
  {
    "article_id": "3025",
    "source": "trend.az",
    "link": "https://az.trend.az/other/world/4118122.html",
    "pub_date": "2025-11-16 06:39:00.000",
    "title": "Dünyadakı qızılın təxminən 20 faizi mərkəzi banklarda saxlanılır",
    "content": "Bakı. Trend:\n\nBəşəriyyətin ilk tanış olduğu metallardan qızılın təyinatı\nəsrlər boyu çox da dəyişməyib. Dünyada istehsal edilən sarı metalın\n49 faizi zinət əşyalarının hazırlanmasına sərf olunur. Bu məsələ\nÇin və Hindistan kimi ölkələrdə daha kütləvidir. Bu 2 ölkənin\nəhalisi ənənəvi olaraq qızıl məmulatları alır və nəsildən-nəslə\nötürür.\n\nTrend xəbər verir ki, bu\nbarədə Dünya Qızıl Şurasının hesabatında bildirilir.\n\nQeyd olunur ki, dünyadakı qızılın təxminən 20 faizi mərkəzi\nbanklarda saxlanılır. Bu rezervlər ölkələrin maliyyə sabitliyi üçün\nzəruridir. İqtisadi böhran dövründə qızıl təhlükəsiz liman rolu\noynayır.\n\nQızılın 19 faizi isə birja sövdələşmələrində maliyyə aləti kimi\nistifadə olunur.\n\nBu qiymətli metalın 9 faizə qədəri sənaye ehtiyaclarına sərf\nolunur. Kosmik, elektronika və hərb sənayesində həssas detalların\nistehsalı üçün qızıl əvəzedilməzdir. Bununla belə, sənayedə\nistifadə həcminə görə gümüş son 100 ildə hər zaman qızılı\nüstələyib.",
    "gold_entities": {
      "persons": [],
      "organizations": [
        "Trend",
        "Dünya Qızıl Şurası",
        "mərkəzi banklar"
      ],
      "locations": [
        "Çin",
        "Hindistan"
      ],
      "positions": [],
      "dates": [
        "əsrlər boyu",
        "2025-11-16"
      ]
    },
    "manually_verified": true,
    "annotator_notes": ""
  },
  {
    "article_id": "1072",
    "source": "trend.az",
    "link": "https://az.trend.az/azerbaijan/society/4123628.html",
    "pub_date": "2025-11-29 12:38:00.000",
    "title": "Sabahın hava PROQNOZU",
    "content": "Bakı. Trend:\n\nAzərbaycanda noyabrın 30-da havanın bəzi yerlərdə çiskinli\nolacağı gözlənilir.\n\nBu barədə Trend-ə Milli\nHidrometeorologiya Xidmətindən məlumat verilib.\n\nBakıda və Abşeron yarımadasında hava şəraitinin dəyişkən buludlu\nolacağı, arabir tutulacağı gözlənilir. Günün birinci yarısında bəzi\nyerlərdə çiskinli yağış yağacağı ehtimalı var. Gecə və səhər arabir\nduman olacaq. Cənub-şərq küləyi əsəcək.\n\nHavanın temperaturu gecə 9 dərəcədən 12 dərəcəyədək, gündüz 14\ndərəcədən 17 dərəcəyədək olacağı gözlənilir. Atmosfer təzyiqi 764\nmm civə sütunu, nisbi rütubət gecə 80-85 %, gündüz 70-75 % təşkil\nedəcək.\n\nAzərbaycanın rayonlarında havanın əsasən yağmursuz keçəcəyi\ngözlənilir. Lakin gecə və səhər bəzi şərq rayonlarda çiskinli yağış\nyağacağı ehtimalı var. Bəzi yerlərdə arabir duman olacaq. Şərq\nküləyi əsəcək.\n\nHavanın temperaturu gecə 4 dərəcədən 9 dərəcəyədək, gündüz 13\ndərəcədən 16 dərəcəyədək, dağlarda gecə 3 dərəcə şaxtadan 2\ndərəcəyədək, gündüz 5 dərəcədən 10 dərəcəyədək olacaq.",
    "gold_entities": {
      "persons": [],
      "organizations": [
        "Trend",
        "Milli Hidrometeorologiya Xidməti"
      ],
      "locations": [
        "Azərbaycan",
        "Bakı",
        "Abşeron yarımadası"
      ],
      "positions": [],
      "dates": [
        "noyabrın 30-da",
        "2025-11-29"
      ]
    },
    "manually_verified": true,
    "annotator_notes": ""
  },
  {
    "article_id": "474",
    "source": "trend.az",
    "link": "https://az.trend.az/business/4125261.html",
    "pub_date": "2025-12-03 17:45:05.000",
    "title": "İƏİT mütəxəssisləri Azərbaycanda transfer qiymətləri üzrə vergi təlimləri aparıb",
    "content": "Bakı. Trend:\n\nİqtisadi Əməkdaşlıq və İnkişaf Təşkilatının (İƏİT) nümayəndə\nheyəti “Vergitutma bazasının aşınması və mənfəətin süni şəkildə\nköçürülməsi (BEPS) layihəsi üzrə giriş proqramı və transfer\nqiymətlərinin tətbiqi” mövzusunda təlimlərin keçirilməsi məqsədilə\nİqtisadiyyat Nazirliyi yanında Dövlət Vergi Xidmətində olub.\n\nBu barədə Trend dövlət xidmətinə istinadən xəbər verir.\n\nBildirilib ki, tədbirin keçirilməsində məqsəd transfer\nqiymətləri üzrə siyasət və inzibatçılıq sahəsində Dövlət Vergi\nXidməti əməkdaşlarının peşəkar potensialının gücləndirilməsi, eyni\nzamanda İqtisadi Əməkdaşlıq və İnkişaf Təşkilatı ilə əməkdaşlığın\ninkişaf etdirilməsidir. Səfər çərçivəsində Dövlət Vergi Xidmətinin\nMərkəzi Aparatının, Tədris Mərkəzinin, Milli Gəlirlər Baş\nİdarəsinin və Bakı şəhəri Lokal Gəlirlər Baş İdarəsinin əməkdaşları\nüçün geniş proqramlı təlimlər keçirilib.\n\nSəfər çərçivəsində Beynəlxalq vergitutma və vergi monitorinqi\nbaş idarəsinin rəhbərliyi ilə qarşılıqlı maraq doğuran mövzular\nətrafında fikir mübadiləsi aparılıb.",
    "gold_entities": {
      "persons": [],
      "organizations": [
        "Trend",
        "İqtisadi Əməkdaşlıq və İnkişaf Təşkilatı (İƏİT)",
        "BEPS",
        "Dövlət Vergi Xidməti",
        "İqtisadiyyat Nazirliyi"
      ],
      "locations": [
        "Azərbaycan",
        "Bakı"
      ],
      "positions": [],
      "dates": [
        "2025-12-03"
      ]
    },
    "manually_verified": true,
    "annotator_notes": ""
  },
  {
    "article_id": "7479",
    "source": "trend.az",
    "link": "https://az.trend.az/business/4105500.html",
    "pub_date": "2025-10-17 15:19:05.000",
    "title": "Bakıda Türk Dövlətləri Təşkilatının Sənaye, Elm, Texnologiya və İnnovasiya Nazirlərinin 2-ci İclası keçiriləcək",
    "content": "Bakı. Trend:\n\nBu ilin 23-24 oktyabr tarixlərində Bakıda İqtisadiyyat\nNazirliyinin təşkilatçılığı ilə Türk Dövlətləri Təşkilatına üzv\nölkələrin (TDT) Sənaye, Elm, Texnologiya və İnnovasiya Nazirlərinin\n2-ci İclası keçiriləcək.\n\nTrend\nİqtisadiyyat Nazirliyinə istinadən xəbər verir ki, iclasın\nkeçirilməsində məqsəd TDT ölkələri arasında sənaye, elmi tədqiqat,\ninnovasiya, texnologiya, investisiya, sahibkarlığın inkişafı və s.\nsahələrdə əməkdaşlığın inkişaf etdirilməsidir.\n\nMəlumata görə, toplantı çərçivəsində oktyabrın 23-də TDT\nölkələrinin aidiyyəti qurumlarının nümayəndə heyətlərinin iştirakı\nilə işçi qrupun iclası keçiriləcək. İclasda Fəaliyyət Planında\nnəzərdə tutulan təşəbbüslər və onların icrası üzrə gələcək\naddımlarla bağlı fikir mübadiləsi aparılacaq.\n\nQeyd edilib ki, oktyabrın 24-də TDT-nin Sənaye, Elm, Texnologiya\nvə İnnovasiya Nazirlərinin 2-ci İclası çərçivəsində sənaye və\ntexnologiyalar sahəsində strateji tərəfdaşlıq istiqamətləri, elm,\ninnovasiya, investisiya, kiçik və orta sahibkarlıq və digər\nistiqamətlərdə əməkdaşlıq mexanizmləri müzakirə olunacaq.",
    "gold_entities": {
      "persons": [],
      "organizations": [
        "Trend",
        "İqtisadiyyat Nazirliyi",
        "Türk Dövlətləri Təşkilatı (TDT)"
      ],
      "locations": [
        "Bakı"
      ],
      "positions": [],
      "dates": [
        "23-24 oktyabr",
        "oktyabrın 23-də",
        "oktyabrın 24-də",
        "2025-10-17"
      ]
    },
    "manually_verified": true,
    "annotator_notes": ""
  },
  {
    "article_id": "3079",
    "source": "trend.az",
    "link": "https://az.trend.az/azerbaijan/society/4117970.html",
    "pub_date": "2025-11-15 12:53:00.000",
    "title": "Sabah hava necə olacaq? - PROQNOZ",
    "content": "Bakı. Trend:\n\nNoyabrın 16-da gözlənilən hava şəraiti açıqlanıb.\n\nTrend xəbər\nverir ki, bu barədə Milli Hidrometeorologiya Xidməti məlumat\nyayıb.\n\nMəlumata əsasən, Bakıda və Abşeron yarımadasında hava şəraitinin\ndəyişkən buludlu olacağı, arabir tutulacağı, əsasən yağmursuz\nkeçəcəyi gözlənilir. Gecə və səhər bəzi yerlərdə zəif duman olacaq.\nCənub-qərb küləyi gündüz şimal-qərb küləyi ilə əvəz olunacaq.\n\nHavanın temperaturu gecə 10 dərəcədən 14 dərəcəyə, gündüz 16\ndərəcədən 19 dərəcəyə qədər isti olacaq. Atmosfer təzyiqi 761 mm\ncivə sütunundan 767 mm civə sütununa yüksələcək. Nisbi rütubət\n70-80 % təşkil edəcək.\n\nAzərbaycanın rayonlarında havanın əsasən yağmursuz keçəcəyi, lakin\ngündüz qərb rayonlarından başlayaraq bəzi yerlərdə arabir yağış\nyağacağı gözlənilir. Ayrı-ayrı yerlərdə leysan xarakterli olacağı,\nşimşək çaxacağı, dolu düşəcəyi, yüksək dağlıq ərazilərdə qar\nyağacağı ehtimalı var. Bəzi yerlərdə arabir duman olacaq. Mülayim\nqərb küləyi əsəcək.\n\nHavanın temperaturu gecə 9 dərəcədən 12, gündüz 16 dərəcədən 19\ndərəcəyə, dağlarda gecə 1 dərəcədən 5, gündüz 5 dərəcədən 9\ndərəcəyə qədər isti olacaq.",
    "gold_entities": {
      "persons": [],
      "organizations": [
        "Trend",
        "Milli Hidrometeorologiya Xidməti"
      ],
      "locations": [
        "Azərbaycan",
        "Bakı",
        "Abşeron yarımadası"
      ],
      "positions": [],
      "dates": [
        "Noyabrın 16-da",
        "2025-11-15"
      ]
    },
    "manually_verified": true,
    "annotator_notes": ""
  },
  {
    "article_id": "1535",
    "source": "trend.az",
    "link": "https://az.trend.az/business/4122263.html",
    "pub_date": "2025-11-26 11:44:41.000",
    "title": "MDB Dəmir Yolu Nəqliyyatı Şurasına üzv ölkələrin yük dövriyyəsi ABŞ və Aİ göstəricilərini üstələyir",
    "content": "Bakı. Trend:\n\nMDB Dəmir Yolu Nəqliyyatı Şurasının üzv ölkələrinin yük\ndövriyyəsi ABŞ və Aİ göstəricilərini üstələyir.\n\nTrend xəbər\nverir ki, bunu “Rusiya Dəmir Yolları” ASC-nin baş direktoru Oleq\nBelozyorov MDB-nin Dəmir Yolu Nəqliyyatı Şurasının Bakıda keçirilən\n83-cü iclasında çıxışında deyib.\n\n“Keçən ilin yekunlarına görə, Şuraya üzv ölkələrin dəmir\nyollarında yük dövriyyəsi ümumilikdə təxminən 3 trilyon\nton-kilometr təşkil edib. Bu, ABŞ-nin birinci dərəcəli dəmir\nyollarının göstəricilərindən 1,3 dəfə, yəni 30% çoxdur və Avropa\nİttifaqının göstəricilərindən isə demək olar ki, 8 dəfə yüksəkdir”,\n- deyə o bildirib.\n\nOnun sözlərinə görə, Şuranın daim diqqət mərkəzində dəmir\nyollarının istismar fəaliyyəti, sərnişin və yük daşımalarının\nşəraiti, rəqəmsallaşma, qatar hərəkətinin təhlükəsizliyinin təmin\nedilməsi, uçot və qarşılıqlı hesablaşmalar sistemi, səhiyyə və\nsosial sahə, həmçinin elmi-texniki əməkdaşlıq durur.\n\n“Biz irəli gedirik və Şurada müttəfiq dəmir yollarının\niqtisadiyyat və nəqliyyat sahələrində baş verən dəyişikliklərə\nuyğunlaşmasına kömək edən yeni qarşılıqlı fəaliyyət mexanizmlərini\nhəyata keçiririk”, – deyə O. Belozyorov vurğulayıb.",
    "gold_entities": {
      "persons": [
        "Oleq Belozyorov"
      ],
      "organizations": [
        "Trend",
        "MDB Dəmir Yolu Nəqliyyatı Şurası",
        "Rusiya Dəmir Yolları ASC"
      ],
      "locations": [
        "Bakı",
        "ABŞ",
        "Avropa İttifaqı"
      ],
      "positions": [
        "baş direktor"
      ],
      "dates": [
        "83-cü iclas",
        "keçən il",
        "2025-11-26"
      ]
    },
    "manually_verified": true,
    "annotator_notes": ""
  },
  {
    "article_id": "2889",
    "source": "trend.az",
    "link": "https://az.trend.az/business/4118488.html",
    "pub_date": "2025-11-17 12:23:00.000",
    "title": "WUF13 - mənzil sahəsində dayanıqlı və inklüziv həllərin birgə axtarış üçün unikal platformadır - BMT",
    "content": "Bakı. Trend:\n\nÜmumdünya Şəhərsalma Forumu (WUF13) mənzil sahəsində dayanıqlı\nvə inklüziv həllərin birgə axtarışı üçün unikaldır\nplatformadır.\n\nTrend xəbər verir\nki, bunu bu gün Birləşmiş Millətlər Təşkilatının Məskunlaşma\nProqramının (UN-HABITAT) İcraçı Direktoru Anaklaudiya Marineyro\nSenteno Rosbah diplomatik korpus üçün WUF13-ə həsr olunmuş\nbrifinqdə bildirib.\n\n\"WUF13 - mənzil sektorunun qlobal miqyasda inklüzivliyi,\nbərabərliyi və iqlim dayanıqlığını necə təşviq edə biləcəyinin\naraşdırılması baxımından bütün iştirakçıları və maraqlı tərəfləri\nbirləşdirən unikal bir platformadır\", - deyə o bildirib.\n\nRosbah vurğulayıb ki, dünya hər gün dərinləşən qlobal mənzil\nböhranı ilə üzləşir. Təxminən 3 milyard insan qeyri-kafi şəraitdə\nyaşayır, 1 milyarddan çoxu xarabalıqlarda və qeyri-rəsmi yaşayış\nməntəqələrindədir, 300 milyondan çox insan isə evsizdir.\n\nQeyd edək ki, WUF13 17-22 may 2026-cı il tarixlərində Bakıda\nkeçiriləcək. Forum BMT-nin UN-HABITAT Proqramı ilə Azərbaycan\nhökuməti əməkdaşlığı çərçivəsində təşkil olunur. Tədbir müxtəlif\nölkələrdən hökumət, bələdiyyə, özəl sektor, vətəndaş cəmiyyəti,\ngənclər və akademik dairələr, eləcə də beynəlxalq təşkilatların\nnümayəndələrini bir araya gətirəcək.",
    "gold_entities": {
      "persons": [
        "Anaklaudiya Marineyro Senteno Rosbah"
      ],
      "organizations": [
        "Trend",
        "BMT",
        "UN-HABITAT",
        "Ümumdünya Şəhərsalma Forumu (WUF13)"
      ],
      "locations": [
        "Bakı",
        "Azərbaycan"
      ],
      "positions": [
        "UN-HABITAT İcraçı Direktoru"
      ],
      "dates": [
        "17-22 may 2026-cı il",
        "2025-11-17"
      ]
    },
    "manually_verified": true,
    "annotator_notes": ""
  },
  {
    "article_id": "829",
    "source": "trend.az",
    "link": "https://az.trend.az/business/4124259.html",
    "pub_date": "2025-12-01 17:40:00.000",
    "title": "Azərbaycanda BOKT-ların fəaliyyət istiqamətlərinin genişləndirilməsi üzrə müzakirələr aparılıb",
    "content": "Bakı. Trend:\n\nAzərbaycanda bank olmayan kredit təşkilatlarının (BOKT)\ninstitusional gücləndirilməsi, eləcə də fəaliyyət istiqamətlərinin\ngenişləndirilməsi müzakirə edilib.\n\nTrend bu\nbarədə Azərbaycan Mərkəzi Bankına (AMB) istinadən xəbər verir.\n\nBelə ki, Azərbaycan Mərkəzi Bankının (AMB) baş direktoru Fuad\nİsayev Azərbaycan Mikromaliyyə Assosiasiyanın rəhbərliyi, ona üzv\nolan və digər bank olmayan kredit təşkilatlarının rəhbər heyəti ilə\ngörüşüb.\n\nGörüş iştirakçılarına cari ilin doqquz ayı üzrə bank olmayan\nkredit təşkilatlarının fəaliyyətinin maliyyə nəticələri, requlyativ\nçərçivənin təkmilləşdirilməsi, eləcə də sektorun sağlamlaşdırılması\nistiqamətində görülmüş işlər barədə məlumat verilib. Əlavə olaraq\nmaliyyələşmə imkanlarının genişləndirilməsi, dövlət fondları ilə\nəməkdaşlıq, təşkilatların regionlarda, eləcə də işğaldan azad\nolunmuş ərazilərdə və Naxçıvan Muxtar Respublikasında fəaliyyət\nperspektivləri, qanunvericiliyin tələbləri və digər məsələlər\nətraflı müzakirə edilib.\n\nGörüşdə həmçinin Mərkəzi Bank tərəfindən bank olmayan kredit\ntəşkilatlarının institusional gücləndirilməsi, eləcə də fəaliyyət\nistiqamətlərinin genişləndirilməsi və dayanaqlılığının təmin\nolunması çərçivəsində növbəti dövrdə görüləcək işlərə dair məlumat\ntəqdim olunub.",
    "gold_entities": {
      "persons": [
        "Fuad İsayev"
      ],
      "organizations": [
        "Trend",
        "Azərbaycan Mərkəzi Bankı (AMB)",
        "Azərbaycan Mikromaliyyə Assosiasiyası",
        "bank olmayan kredit təşkilatları (BOKT)"
      ],
      "locations": [
        "Azərbaycan",
        "Naxçıvan Muxtar Respublikası"
      ],
      "positions": [
        "AMB-nin baş direktoru"
      ],
      "dates": [
        "cari ilin doqquz ayı",
        "2025-12-01"
      ]
    },
    "manually_verified": true,
    "annotator_notes": ""
  },
  {
    "article_id": "7323",
    "source": "trend.az",
    "link": "https://az.trend.az/azerbaijan/politics/4105788.html",
    "pub_date": "2025-10-19 00:01:00.000",
    "title": "44 günlük Vətən müharibəsinin xronikası: 19 oktyabr",
    "content": "Bakı. Trend:\n\n2020-ci il sentyabrın 27-də Ermənistan silahlı qüvvələrinin\ncəbhəboyu genişmiqyaslı təxribat törətməsinə cavab olaraq\nAzərbaycan Ordusu sonradan \"Dəmir yumruq\" adlandırılan əks-hücum\nəməliyyatına başladı. 44 gün davam edən Vətən müharibəsi təxminən\notuzillik işğala son qoyulması və ərazi bütövlüyümüzün bərpası ilə\nnəticələndi.\n\nTrend Vətən\nmüharibəsinin oktyabrın 19-na olan xronikasını təqdim edir:\n\n- Prezident İlham Əliyev Türkiyə Böyük Millət Məclisinin\nSədrinin başçılıq etdiyi nümayəndə heyətini qəbul edib.\n\n- Prezident İlham Əliyev Rusiyanın TASS informasiya agentliyinə\nvideomüsahibə verib.\n\n- Prezident İlham Əliyev Elçin Quliyevi Xudafərin körpüsündə\nAzərbaycan bayrağının qaldırılması münasibətilə təbrik edib.\n\n- Düşmənin döyüş texnikası və silah-sursatı məhv edilib. Ermənistanın məhv edilən hərbi\ntexnikalarının siyahısı açıqlanıb.\n\n- Düşmən taborunun qərargah rəisi məhv edilib.\n\n- Ermənistan silahlı qüvvələri Tərtər rayonunu atəşə tutması\nnəticəsində, ev sahibi ağır xəsarət alıb.\n\n- İran Ermənistana məxsus PUA-nı vurub.\n\n- Ermənistan dövlət sərhədində mövqelərimizi atəşə tutub.\n\n- Azərbaycan Ordusu ermənilərin atıb qaçdığı daha bir neçə hərbi texnikanı ələ keçirib.\n\n- Müdafiə Nazirliyi Cəbrayıl və Füzuli istiqamətində düşməndən\nələ keçirilən hərbi qənimətlərin videogörüntüsünü yayımlayıb.",
    "gold_entities": {
      "persons": [
        "İlham Əliyev",
        "Elçin Quliyev"
      ],
      "organizations": [
        "Trend",
        "Azərbaycan Ordusu",
        "Türkiyə Böyük Millət Məclisi",
        "TASS",
        "Müdafiə Nazirliyi",
        "Ermənistan silahlı qüvvələri",
        "İran"
      ],
      "locations": [
        "Azərbaycan",
        "Ermənistan",
        "Tərtər",
        "Cəbrayıl",
        "Füzuli",
        "Xudafərin"
      ],
      "positions": [
        "Azərbaycan Prezidenti"
      ],
      "dates": [
        "2020-ci il sentyabrın 27-də",
        "19 oktyabr",
        "44 gün",
        "2025-10-19"
      ]
    },
    "manually_verified": true,
    "annotator_notes": ""
  },
  {
    "article_id": "5823",
    "source": "trend.az",
    "link": "https://az.trend.az/azerbaijan/society/4110206.html",
    "pub_date": "2025-10-29 10:59:00.000",
    "title": "Azərbaycan Elektron İştirakçılıq İndeksində 10 pillə irəliləyib - Nazir müşaviri",
    "content": "Bakı. Trend:\n\nÖtən illər ərzində Azərbaycan rəqəmsal transformasiya və\nelektron idarəetmə sahəsində də müəyyən nailiyyətlər əldə edib.\n\nTrend xəbər\nverir ki, bunu rəqəmsal inkişaf və nəqliyyat nazirinin müşaviri\nRəşad Bayramov Beynəlxalq Telekommunikasiya İttifaqının Ümumdünya\nTelekommunikasiya İnkişafı Konfransı (WTDC-25) üzrə keçirilən media\nnümayəndələri üçün informasiya sessiyasında deyib.\n\nOnun sözlərinə görə, startap ekosisteminin böyüməsi,\ntexnoparkların fəaliyyətində gözəçarpan fərqlər, rəqəmsal hökumətə\nkeçid, infrastrukturun gücləndirilməsi, dövlət xidmətlərinin\nrəqəmsallşadırlması olan irəliləyişlər Azərbaycanın müvafiq\nreytinqlərdə irəliləməsinə səbəb olub:\n\n\"Məsələn, Azərbaycan ilk dəfə olaraq BMT-nin Elektron Hökumətin\nİnkişafı indeksində yüksək nəticələrə nail olub. Ölkənin onlayn\ndövlət xidmətləri və Telekommunikasiya infrastrukturu\ngöstəricilərində isə 21% artım müşahidə olunub. Bundan əlavə,\nAzərbaycanın Elektron İştirakçılıq İndeksində yeri 10 pillə irəli\ngedərək il ərzində 28% irəliləyiş əldə edib\".\n\n\"Azərbaycan üçün bu gün qeyri-neft sektorunun inkişafı strateji\nəhəmiyyət kəsb edir. Bu sektorun inkişafında İKT-nin rolu\ngünü-gündən artır. 2025-ci ilin yanvar-sentyabr aylarında\nAzərbaycanın informasiya və rabitə sektoru üzrə gəlirləri 2024-cü\nilin müvafiq dövrünə nisbətən 6,9% artaraq 2,7 milyard manat təşkil\nedib\", - deyə nazir müşaviri əlavə edib.",
    "gold_entities": {
      "persons": [
        "Rəşad Bayramov"
      ],
      "organizations": [
        "Trend",
        "Beynəlxalq Telekommunikasiya İttifaqı",
        "WTDC-25",
        "BMT"
      ],
      "locations": [
        "Azərbaycan"
      ],
      "positions": [
        "rəqəmsal inkişaf və nəqliyyat nazirinin müşaviri"
      ],
      "dates": [
        "2025-ci ilin yanvar-sentyabr ayları",
        "2024-cü il",
        "2025-10-29"
      ]
    },
    "manually_verified": true,
    "annotator_notes": ""
  },
  {
    "article_id": "1606",
    "source": "trend.az",
    "link": "https://az.trend.az/azerbaijan/gundem/4121956.html",
    "pub_date": "2025-11-25 20:20:00.000",
    "title": "Soydaşlarımız Odessada ağacəkmə aksiyası keçirib (FOTO)",
    "content": "Bakı. Trend:\n\nUkraynanın Odessa şəhərində “Birlik” Diaspor Təşkilatı və\nsoydaşlarımız 8 Noyabr – Zəfər Günü münasibətilə ağacəkmə aksiyası\nkeçiriblər.\n\nBu barədə Trend-ə Diasporla İş üzrə Dövlət Komitəsindən məlumat\nverilib.\n\nBildirilib ki, Odessada salınması planlaşdırılan “Azərbaycan”\nparkında təşkil olunan aksiyada soydaşlarımızla yanaşı, Odessa\nşəhər merinin birinci müavini Aleksandr Filatov, meriyanın\nnümayəndələri, Odessanın ictimai-siyasi xadimləri iştirak\nediblər.\n\nAleksandr Filatov şəhərin etnik azərbaycanlı sakinlərinin\nOdessanın inkişafında, ətraf mühitinin qorunmasında fəal iştirak\netdiklərini bildirib. O, 300-dən artıq ağacın əkilməsinin Odessa\nşəhərinin ekologiyasına dəyərli töhfə verəcəyini diqqətə\nçatdırıb.\n\n“Birlik” Diaspor Təşkilatının sədri Cəlil Astanov müharibə\nşəraitinə baxmayaraq, 30 mindən çox azərbaycanlının Odessa\nşəhərində və vilayətində aktiv fəaliyyətlərini davam etdirdiyini\nsöyləyib. “Bugünkü aksiyamız Zəfərimizin 5 illiyinə həsr edilib.\nHəmçinin aksiya zamanı milli mətbəximiz də nümayiş olunub”, - deyə\nsoydaşımız məlumat verib.\n\nQeyd edək ki, sahəsi 3 hektardan artıq olacaq parkda\nAzərbaycanın tarixi və mədəniyyətini əks etdirən məlumat guşələri,\nmuzey, uşaqlar və böyüklər üçün istirahət məkanları, idman\nzonaları, eləcə də “Azərbaycan” foto guşəsinin yaradılması\nplanlaşdırılır. Şəhər ictimaiyyəti layihəni yüksək qiymətləndirir\nvə parkın həm sakinlər, həm də turistlər üçün cəlbedici bir məkan\nolacağına inanır.",
    "gold_entities": {
      "persons": [
        "Aleksandr Filatov",
        "Cəlil Astanov"
      ],
      "organizations": [
        "Trend",
        "Diasporla İş üzrə Dövlət Komitəsi",
        "“Birlik” Diaspor Təşkilatı",
        "“Azərbaycan” parkı"
      ],
      "locations": [
        "Odessa",
        "Ukrayna"
      ],
      "positions": [
        "Odessa şəhər merinin birinci müavini",
        "“Birlik” Diaspor Təşkilatının sədri"
      ],
      "dates": [
        "8 Noyabr – Zəfər Günü",
        "Zəfərin 5 illiyi",
        "2025-11-25"
      ]
    },
    "manually_verified": true,
    "annotator_notes": ""
  },
  {
    "article_id": "1655",
    "source": "trend.az",
    "link": "https://az.trend.az/business/energy/4121923.html",
    "pub_date": "2025-11-25 15:24:00.000",
    "title": "bp AÇG-də neftvermənin artırılması üzrə texnologiyaların tətbiqinin riskləri barədə danışıb",
    "content": "Bakı. Trend:\n\nNeftvermənin artırılması texnologiyalarının (EOR) tətbiqi ciddi\nrisklərlə müşayiət olunur - buna “Azəri-Çıraq-Günəşli” (AÇG)\nyatağında bahalı quyuların potensial itkisi də daxildir.\n\nTrend xəbər verir\nki, bunu bu gün AÇG sahəsinin işlənilməsi üzrə meneceri Əfqan\nHüseynov Bakıda keçirilən SPE Xəzər Texniki Konfransında deyib.\n\nOnun sözlərinə görə, iki pilot layihə çərçivəsində üç quyu\nseçilib və AÇG-də dənizdə qazma işlərinin aparılması iri həcmli\ninvestisiyalar tələb edir.\n\n“Biz riskləri təhlil etmişik və bilməliyik ki, bu quyuları itirə\nbilərik. Bu cür layihələrin real qiyməti budur. Əgər hər hansı\nelement işləməzsə, məsələn, su vurulan injektor quyusu kimi bir\nquyu bağlana bilər və onun silinməsinə hazır olmaq lazımdır”, – A.\nHüseynov vurğulayıb.\n\nO qeyd edib ki, texnologiyanın nə üçün tətbiq edildiyini,\ndəyərin harada yaradıldığını, hansı müddətdə və hansı pilot\nsahələrdə sınaqdan keçirilməli olduğunu dəqiq anlamaq vacibdir.\n\nA.Hüseynov həmçinin təklif olunan dəstəyə görə SOCAR-a\nminnətdarlığını ifadə edib. “Çoxsaylı, bəlkə də fəaliyyətsiz qalan\nquyuların mövcudluğu fonunda SOCAR bizə – əgər EOR daxil olmaqla\nkonkret layihələr varsa – təcrübələr aparılması üçün quyular təqdim\netməyi təklif edib. Lakin risk profilini dəqiq anlamaq vacibdir”, –\ndeyə o bildirib.\n\nA. Hüseynovun sözlərinə görə, quyuların xaotik şəkildə\nitirilməsi ciddi nəticələrə səbəb ola bilər.\n\n“EOR – müəyyən mərhələdə mütləq tətbiq olunmalı texnologiyadır,\nlakin onunla bağlı risklərə hazır olmaq vacibdir”, – bp nümayəndəsi\nqeyd edib.",
    "gold_entities": {
      "persons": [
        "Əfqan Hüseynov"
      ],
      "organizations": [
        "Trend",
        "bp",
        "SOCAR",
        "Azəri-Çıraq-Günəşli (AÇG)",
        "SPE Xəzər Texniki Konfransı"
      ],
      "locations": [
        "Bakı"
      ],
      "positions": [
        "AÇG sahəsinin işlənilməsi üzrə menecer"
      ],
      "dates": [
        "2025-11-25"
      ]
    },
    "manually_verified": true,
    "annotator_notes": ""
  },
  {
    "article_id": "5902",
    "source": "trend.az",
    "link": "https://az.trend.az/business/4110014.html",
    "pub_date": "2025-10-28 18:08:00.000",
    "title": "Energetika Nazirliyində enerji effektivliyi potensialının qiymətləndirilməsi üzrə tədbir keçirilib (FOTO)",
    "content": "Bakı. Trend:\n\nEnergetika Nazirliyində Azərbaycan Respublikasının Dövlət Neft\nŞirkəti (SOCAR), Heydər Əliyev adına Neft Emalı Zavodu, Qaz Emalı\nZavodu, SOCAR UNİPER MMC, \"Azərenerji\" ASC, \"Azəristiliktəchizat\"\nASC, “Təmiz Şəhər” ASC, \"Azərbaycan Şəkər İstehsalat Birliyi\" MMC,\nÜmid Babək Əməliyyat Şirkəti, “bp” şirkəti və “Şahdağ Turizm\nMərkəzi” QSC-nin nümayəndələrinin iştirakı ilə elektrik və istilik\nenerjisi istehsalı və təbii qazın emalı üzrə effektivlik\npotensialının qiymətləndirilməsi ilə bağlı tədbir keçirilib.\n\nTrend xəbər verir ki, görüşdə\nenerji resurslarından səmərəli istifadəyə yönəlmiş enerji\neffektivliyi tədbirlərinin hazırlanması və icrasını təmin etmək,\nhəmçinin qənaət oluna biləcək enerjinin miqdarının\nmüəyyənləşdirilməsi üçün texniki cəhətdən mümkünlüyü və iqtisadi\nbaxımdan əlverişliliyi nəzərə almaqla effektivlik potensialının\nqiymətləndirilməsi və bu məqsədlə hesabatların müvafiq qaydada\ndoldurulması məsələləri müzakirə edilib.\n\nEnergetika nazirinin müavini Elnur Soltanov “Enerji\nresurslarından səmərəli istifadə və enerji effektivliyi haqqında”\nqanun və bu qanunun tətbiqi ilə bağlı enerji effektivliyinin\npotensialının qiymətləndirilməsi qaydalarının əhəmiyyəti barədə\ndanışıb.\n\nO, enerji qənaətinin ən böyük enerji mənbələrindən olduğunu\nvurğulayaraq, enerjidən səmərəli istifadənin ölkəmizin dayanıqlı\ninkişafı üçün mühüm əhəmiyyət kəsb etdiyini bildirib. Bu baxımdan,\nenerji effektivliyinə dair hesabatların vacibliyi xüsusi qeyd\nedilib.\n\nTədbirdə qiymətləndirmə qaydalarına bağlı meyarlar və\nhesabatlarda yer alan məqamlar barədə ətraflı fikir mübadiləsi\naparılıb, müvafiq tövsiyələr verilib.",
    "gold_entities": {
      "persons": [
        "Elnur Soltanov"
      ],
      "organizations": [
        "Trend",
        "Energetika Nazirliyi",
        "SOCAR",
        "Heydər Əliyev adına Neft Emalı Zavodu",
        "Qaz Emalı Zavodu",
        "SOCAR UNİPER MMC",
        "Azərenerji ASC",
        "Azəristiliktəchizat ASC",
        "Təmiz Şəhər ASC",
        "Azərbaycan Şəkər İstehsalat Birliyi MMC",
        "Ümid Babək Əməliyyat Şirkəti",
        "Şahdağ Turizm Mərkəzi QSC",
        "bp"
      ],
      "locations": [
        "Azərbaycan",
        "Bakı"
      ],
      "positions": [
        "energetika nazirinin müavini"
      ],
      "dates": [
        "2025-10-28"
      ]
    },
    "manually_verified": true,
    "annotator_notes": ""
  },
  {
    "article_id": "2276",
    "source": "trend.az",
    "link": "https://az.trend.az/azerbaijan/society/4120276.html",
    "pub_date": "2025-11-20 21:28:00.000",
    "title": "Şəkidə 300-ə yaxın ilk təşkilat sədrləri bir araya gəldi (FOTO)",
    "content": "Bakı. Trend:\n\nAHİK-in üzv təşkilatı Elm və Təhsil İşçiləri Həmkarlar İttifaqı\n(ETİHİ) Respublika Komitəsi üzv təşkilatlarla bilavasitə ünsiyyətin\nvə əməkdaşlıq mühitinin gücləndirilməsi istiqamətində ardıcıl\ntədbirlərini davam etdirir.\n\nTrend xəbər verir ki, bu\nçərçivədə növbəti regional görüş noyabrın 20-də Şəki şəhər Heydər\nƏliyev Mərkəzində baş tutub.\n\nGörüşə Şəki şəhəri, Oğuz və Balakən rayonlarının təhsil\nmüəssisələrində fəaliyyət göstərən ilk həmkarlar ittifaqı\ntəşkilatlarının sədrləri qatılıblar.\n\nTədbirdə ETİHİ Respublika Komitəsinin sədri Araz Paşayev, sədr\nmüavini Mirzə Cəfərzadə,və Komitənin məsul əməkdaşları iştirak\nediblər.\n\nAraz Paşayev çıxışında AHİK-in sosial tərəfdaşlıq xəttinə uyğun\nolaraq əmək münasibətlərinin tənzimlənməsi prosesində həmkarlar\nittifaqlarının strateji mövqeyini diqqətə çatdırıb, üzv təşkilatlar\narasında həmrəyliyin və vahid fəaliyyət xəttinin əsas hədəf\nolduğunu vurğulayıb. O, birbaşa dialoqun genişləndirilməsi və ilk\ntəşkilatlara sistemli dəstəyin artırılmasının Komitənin əsas\nistiqamətlərindən olduğunu bildirib.\n\nGörüşdə sosial müdafiə, maarifləndirmə, əmək münasibətləri və\nişçi hüquqlarının təminatı üzrə həyata keçirilən təşəbbüslərlə\nbağlı təqdimatlar edilib.\n\nİlk təşkilat sədrləri ilə sual-cavab əsasında fikir mübadiləsi\naparılıb, səsləndirilən rəy və təkliflər qeydə alınıb.\n\nETİHİ rəhbərliyi tərəfindən regional görüşlərin digər bölgələrdə\ndə davam etdiriləcəyini və üzv təşkilatlarla qarşılıqlı fəaliyyətin\ngücləndirilməsinin prioritet olduğunu diqqətə çatdırılıb.\n\nQeyd edəki ki, Elm və Təhsil İşçiləri Həmkarlar İttifaqı\nRespublika Komitəsi hazırda ölkə üzrə 405 mindən artıq ittifaq\nüzvünü, 6 minə yaxın ilk təşkilatı və təxminən 147 üzv təşkilatı\nözündə birləşdirir.",
    "gold_entities": {
      "persons": [
        "Araz Paşayev",
        "Mirzə Cəfərzadə"
      ],
      "organizations": [
        "Trend",
        "AHİK",
        "Elm və Təhsil İşçiləri Həmkarlar İttifaqı (ETİHİ) Respublika Komitəsi",
        "Heydər Əliyev Mərkəzi"
      ],
      "locations": [
        "Şəki",
        "Oğuz",
        "Balakən"
      ],
      "positions": [
        "ETİHİ Respublika Komitəsinin sədri",
        "sədr müavini"
      ],
      "dates": [
        "noyabrın 20-də",
        "2025-11-20"
      ]
    },
    "manually_verified": true,
    "annotator_notes": ""
  },
  {
    "article_id": "8176",
    "source": "trend.az",
    "link": "https://az.trend.az/azerbaijan/politics/4103344.html",
    "pub_date": "2025-10-13 18:35:00.000",
    "title": "Bakıda Azərbaycan-İran əməkdaşlığının aktual məsələləri müzakirə olunub",
    "content": "Bakı. Trend:\n\nOktyabrın 13-də Azərbaycan Respublikası Baş nazirinin müavini\nŞahin Mustafayev İran İslam Respublikasının yol və şəhərsalma\nnaziri Fərzanə Sadiqlə görüşüb.\n\nNazirlər Kabinetindən Trend-ə\nverilən məlumata görə, görüşdə Azərbaycan ilə İran arasında\nmünasibətlərin hərtərəfli inkişafından məmnunluq ifadə olunub.\n\nQarşılıqlı faydalı əməkdaşlığın gündəliyində duran aktual\nməsələlər, xüsusilə də nəqliyyat-tranzit, energetika, gömrük və\ndigər sahələr ətrafında fikir mübadiləsi aparılıb.\n\nAzərbaycan Respublikasının Şərqi Zəngəzur iqtisadi rayonu ilə\nNaxçıvan Muxtar Respublikası arasında nəqliyyat bağlantılarının\ninkişafı layihəsi çərçivəsində Araz çayı üzərində Ağbənd-Kəlalə\navtomobil yolları körpüsünün və gömrük-sərhəd infrastrukturunun\ntikintisi üzrə işlərin yekunlaşdırılması ilə bağlı məsələlər\nmüzakirə olunub.\n\nTərəflər Şimal-Cənub beynəlxalq nəqliyyat dəhlizinin inkişaf\netdirilməsi ilə bağlı gündəlikdə duran aktual məsələləri nəzərdən\nkeçiriblər.\n\nQeyd olundu ki, Şimal-Cənub dəhlizi ilə daşımaların həcmi\n2025-ci ilin 9 ayı ərzində 8.3% artıb və bunun da 10.4%-i\navtomobil, 2%-i isə dəmiryolu daşımalarının payına düşür.\n\nDəhliz boyunca infrastrukturun genişləndirilməsi istiqamətində\ngörülən işlərin uzlaşdırılmış şəkildə aparılmasının və\nyükdaşımaların həcminin davamlı artımının təmin edilməsinin mühüm\nönəm kəsb etdiyi bildirilib. Bu kontekstdə dəhlizin vacib\nkomponenti olan Cənub Yük Terminalının tikintisi üzrə işlərin\ntamamlanmasının əhəmiyyəti vurğulanıb.\n\nHəmçinin Astaraçay çayı üzərində inşa olunmuş avtomobil\nkörpüsünün tam gücü ilə işə salınması üçün görüləcək zəruri\ntədbirlər barədə fikir mübadiləsi aparılıb.\n\nTərəflər eyni zamanda Bakıda keçirilən Azərbaycan-İran-Rusiya\ngörüşünün üç ölkə arasında ticarət-iqtisadi, nəqliyyat və enerji\nəlaqələrinin daha da genişləndirilməsi baxımından önəmini qeyd\nediblər.",
    "gold_entities": {
      "persons": [
        "Şahin Mustafayev",
        "Fərzanə Sadiq"
      ],
      "organizations": [
        "Trend",
        "Nazirlər Kabineti",
        "Şimal-Cənub beynəlxalq nəqliyyat dəhlizi"
      ],
      "locations": [
        "Bakı",
        "Azərbaycan",
        "İran",
        "Şərqi Zəngəzur",
        "Naxçıvan Muxtar Respublikası",
        "Araz çayı",
        "Ağbənd-Kəlalə körpüsü",
        "Astaraçay çayı",
        "Rusiya"
      ],
      "positions": [
        "Azərbaycan Respublikası Baş nazirinin müavini",
        "İran İslam Respublikasının yol və şəhərsalma naziri"
      ],
      "dates": [
        "Oktyabrın 13-də",
        "2025-ci ilin 9 ayı",
        "2025-10-13"
      ]
    },
    "manually_verified": true,
    "annotator_notes": ""
  },
  {
    "article_id": "5298",
    "source": "trend.az",
    "link": "https://az.trend.az/azerbaijan/society/4111684.html",
    "pub_date": "2025-10-31 23:45:28.000",
    "title": "“ART Weekend” çərçivəsində “Püstə: canlı irs” performansı təqdim edilib (FOTO)",
    "content": "Bakı. Trend:\n\nOktyabrın 31-də “Bakıya Uçuş. İncəsənət həftəsonu. Gələcəyimizi\nİNDİ Duy” (“Fly to Baku. Art Weekend. Sense the Future NOW”)\nlayihəsinin daha bir tədbiri - “Püstə: canlı irs” təqdimatı Maqsud\nİbrahimbəyov Yaradıcılıq Mərkəzində keçirilib.\n\nTrend xəbər verir\nki, əvvəlcə Maqsud İbrahimbəyovun “Püstə ağacı” hekayəsi əsasında\nhazırlanan monotamaşa təqdim edilib.\n\nOxucunu duyğular, xatirələr və nostalji dünyasına aparan əsərin\nmərkəzində keçmişlə bu gün arasındakı ayrılmaz bağlılığın rəmzinə\nçevrilən püstə ağacı dayanır.\n\nMaqsud İbrahimbəyovun ən təsirli əsərlərindən biri olan bu\nhekayədə hadisələr bir uşağın gözü ilə nəql olunur. Bu monotamaşada\nmüharibə illərindəki uşaqlığını xatırlayan artıq böyümüş oğlan\nobrazını isə Azərbaycanın Əməkdar artisti Şövqi Hüseynov\ncanlandırıb.\n\nTamaşaçılar onunla birlikdə mərkəzində iri bir püstə ağacı bitən\nkiçik Bakı həyətinə səyahət ediblər.\n\nSonra \"Azərxalça” ASC-nin toxuduğu triptix – üç xalçadan ibarət\nəsər təqdim olunub.\n\nHeydər Əliyev Fondunun vitse-prezidenti, IDEA İctimai Birliyinin\ntəsisçisi və rəhbəri Leyla Əliyeva kompozisiya ilə tanış olub.\n\nBildirilib ki, kompozisiya çətinliklərə baxmayaraq həyatın\nyenidən başlaya və bar verə biləcəyini göstərir. Su isə triptixdə\nüç hissəni birləşdirən mühüm rəmz kimi verilir. O, böyümə və\ninkişaf üçün zəruri həyat gücünün rəmzi olaraq həyatın dövri\nxarakterini vurğulayır.\n\nDaha sonra Leyla Əliyevanın iştirakı ilə Mərkəzin terrasında\npüstə ağacı əkilib.\n\nQeyd edək ki, bu mərasim suya, həyata və təbiətə qayğının rəmzi\nkimi təcəssüm olunur. Püstə - keçmişlə gələcəyin, sənətlə\nekologiyanın, insanla torpağın vəhdəti kimi qələmə verilir.\n\nDaha sonra IDEA İctimai Birliyinin təsisçisi və rəhbəri\nİçərişəhərdə təşkil olunmuş Zeytun Festivalını ziyarət edib.\nÖlkəmizin ayrı-ayrı bölgələrindən gətirilən zeytun və zeytun\nməhsulları ilə tanış olub. Festivala gələn şəhərimizin qonaqları və\nturistlərlə səmimi söhbət atmosferində keçən ziyarətdə xatirə\nşəkilləri də çəkilib.",
    "gold_entities": {
      "persons": [
        "Maqsud İbrahimbəyov",
        "Şövqi Hüseynov",
        "Leyla Əliyeva"
      ],
      "organizations": [
        "Trend",
        "ART Weekend",
        "Bakıya Uçuş. İncəsənət həftəsonu. Gələcəyimizi İNDİ Duy",
        "Maqsud İbrahimbəyov Yaradıcılıq Mərkəzi",
        "Azərxalça ASC",
        "Heydər Əliyev Fondu",
        "IDEA İctimai Birliyi",
        "Zeytun Festivalı"
      ],
      "locations": [
        "Bakı",
        "İçərişəhər"
      ],
      "positions": [
        "Azərbaycanın Əməkdar artisti",
        "Heydər Əliyev Fondunun vitse-prezidenti",
        "IDEA İctimai Birliyinin təsisçisi",
        "IDEA İctimai Birliyinin rəhbəri"
      ],
      "dates": [
        "Oktyabrın 31-də",
        "2025-10-31"
      ]
    },
    "manually_verified": true,
    "annotator_notes": ""
  },
  {
    "article_id": "7457",
    "source": "trend.az",
    "link": "https://az.trend.az/business/4105584.html",
    "pub_date": "2025-10-17 17:45:43.000",
    "title": "Mərkəzi Asiya və Qafqazdakı infrastruktur layihələri ticarət əlaqələrinin gücləndirilməsində əsas rol oynayır - BVF",
    "content": "Bakı. Trend:\n\nMərkəzi Asiya və Qafqazdakı infrastruktur layihələri ticarət\nəlaqələrinin gücləndirilməsində əsas rol oynayır.\n\nBunu brifinqdə Trend-in sualını cavablandıran Beynəlxalq Valyuta\nFondunun Yaxın Şərq və Mərkəzi Asiya departamentinin direktoru\nCihad Azur deyib.\n\n“Qafqaz və Mərkəzi Asiya ölkələrinin orta iqtisadi artım tempi\nhələ də yüksək olaraq qalır və bu il 5,6% təşkil edəcək ki, bu da\nbahar toplantılarındakı qiymətləndirmələrlə müqayisədə proqnozun\n0,7 faiz bəndi yüksəlməsini əks etdirir. Belə yüksək artım\nsəviyyəsi nə ilə izah oluna bilər? Dayanıqlı daxili tələbat, kredit\nekspansiyası , eləcə də stabil və ya böyük həcmdə neft-qaz ixracı\nmövcuddur.\n\nArtımın tədricən orta səviyyəyə- təxminən 4%-ə qədər\nyavaşlayacağını gözləyirik. Hərçənd, neft və qaz ixracatçısı olan\nölkələrlə idxalçı ölkələr arasında vəziyyət fərqlidir”, - deyə Azur\nbildirib.\n\nO, həmçinin Mərkəzi Asiya və Qafqazın əksər ölkələrində\ninflyasiyanın sürətləndiyini vurğulayıb.\n\n“Bu, müəyyən dərəcədə tələbin yaratdığı təzyiq və həmçinin,\nxüsusilə Rusiyadan gələn inflyasiya idxalı ilə bağlıdır. Bəzi\nölkələrdə isə elektrik enerjisi sahəsində tarif islahatları qiymət\nartımına təsir edib. Son illərdə Qafqaz və Mərkəzi Asiya ölkələri\nnisbətən yüksək artım səviyyəsi nümayiş etdirir və daxili region\nəməkdaşlığının inkişafında, o cümlədən bir sıra infrastruktur\nlayihələrində uğurlar əldə edirlər. Xüsusilə şərqdən qərbə, Çin-dən\nmüxtəlif ticarət marşrutlarına ticarət əlaqələrinin\ngücləndirilməsində dəmir yolu və elektrik enerjisi sahəsindəki\nlayihələr mühüm əhəmiyyət daşıyır. Bu layihələr həmçinin region\nölkələri arasında əlaqəliliyin artırılması və iqtisadi\ninteqrasiyanın genişləndirilməsi üçün imkanlar yaradır”, - deyə\nAzur bildirib.\n\nO əlavə edib ki, bu cür layihələrin həyata keçirilməsi bəzi\nhallarda borc yükünə təsir göstərə bilər.\n\n“Biz ölkələri ehtiyatlı olmağa çağırırıq - həm iqtisadi\nəsasların möhkəmləndirilməsi, həm də uzunmüddətli layihələrin idarə\nolunması baxımından. Bu layihələrin öhdəliklər baxımından yaxşı\nidarə olunması və ümumi borc səviyyəsinin dayanıqlı qalması\nvacibdir”, - deyə BVF direktoru yekunlaşdırıb.",
    "gold_entities": {
      "persons": [
        "Cihad Azur"
      ],
      "organizations": [
        "Trend",
        "Beynəlxalq Valyuta Fondu (BVF)"
      ],
      "locations": [
        "Mərkəzi Asiya",
        "Qafqaz",
        "Çin",
        "Rusiya"
      ],
      "positions": [
        "BVF-in Yaxın Şərq və Mərkəzi Asiya departamentinin direktoru"
      ],
      "dates": [
        "bu il",
        "2025-10-17"
      ]
    },
    "manually_verified": true,
    "annotator_notes": ""
  },
  {
    "article_id": "1142",
    "source": "trend.az",
    "link": "https://az.trend.az/business/4123400.html",
    "pub_date": "2025-11-28 17:17:00.000",
    "title": "Qarabağ və Şərqi Zəngəzurda yeni yaradılan iş yerlərinin sayı artıb (CƏDVƏL)",
    "content": "Bakı. Trend:\n\nBu ilin ilk 9 ayında Qarabağ və Şərqi Zəngəzur iqtisadi\nrayonlarında 2 560 yeni iş yeri açılıb.\n\nBu barədə Trend Dövlət Statistika Komitəsindən məlumat əldə\nedib.\n\nMəlumata əsasən, bu, ötən ilin eyni dövründəki göstərici ilə\nmüqayisədə 723 vahid və ya 39,3% çoxdur.\n\nMəlumata görə, hesabat dövründə Qarabağda 1 855 (58,4% çox),\nŞərqi Zəngəzurda isə 705 (5,9% çox) yeni iş yerləri yaradılıb.\n\nDövr ərzində Qarabağ iqtisadi rayonu üzrə yeni yaradılan ən çox\niş yeri Xankəndinin (516), Şərqi Zəngəzur iqtisadi rayonu üzrə isə\nLaçın rayonunun (312) payına düşüb.\n\nQarabağ və Şərqi Zəngəzur iqtisadi rayonları üzrə 2025-ci ilin\nyanvar-sentyabr ayları ərzində yeni yaradılan iş yerlərinə dair\ngöstəriciləri təqdim edirik:\n\nQarabağ iqtisadi rayonu\n\n1855\n\nXankəndi şəhəri\n\n516\n\nAğcabədi rayonu\n\n79\n\nAğdam rayonu\n\n143\n\nAğdərə rayonu\n\n32\n\nBərdə rayonu\n\n281\n\nFüzuli rayonu\n\n135\n\nXocalı rayonu\n\n80\n\nXocavənd rayonu\n\n43\n\nŞuşa rayonu\n\n46\n\nTərtər rayonu\n\n500\n\nŞərqi Zəngəzur iqtisadi rayonu\n\n705\n\nCəbrayıl rayonu\n\n133\n\nKəlbəcər rayonu\n\n172\n\nQubadlı rayonu\n\n45\n\nLaçın rayonu\n\n312\n\nZəngilan rayonu\n\n43\n\nÜmumilikdə, 2025-ci ilin doqquz ayı ərzində ölkədə 77,7 min yeni\niş yerləri açılıb. Bu dövrdə yaradılmış iş yerlərinin 91,4 faizi\nqeyri-dövlət sektorunda açılıb. Yeni açılmış iş yerlərinin 75,9\nfaizi Bakı şəhərinin, 0,8 faizi Naxçıvan Muxtar Respublikasının,\n23,3 faizi digər regionların, o cümlədən 7,2 faizi Abşeron-Xızı,\n2,7 faizi Quba-Xaçmaz, 2,7 faizi Şəki-Zaqatala, 2,4 faizi Qarabağ,\n1,9 faizi Gəncə-Daşkəsən, 1,5 faizi Şirvan-Salyan, 1,2 faizi\nLənkəran-Astara, 0,9 faizi Şərqi Zəngəzur, 0,9 faizi Mərkəzi Aran,\n0,8 faizi Qazax-Tovuz, 0,6 faizi Mil-Muğan və 0,5 faizi Dağlıq\nŞirvan iqtisadi rayonlarının payına düşüb. Yeni açılmış iş\nyerlərinin 9,1 faizi yeni yaradılmış müəssisə və təşkilatlarda,\n89,8 faizi mövcud müəssisə və təşkilatlarda, 0,4 faizi fəaliyyətini\nbərpa etmiş müəssisə və təşkilatlarda, 0,7 faizi isə digər\ntədbirlər üzrə yaradılıb.\n\nBununla yanaşı, 2025-ci ilin doqquz ayı ərzində ölkədə 8,2 min\niş yeri bağlanıb. Bu dövrdə bağlanmış iş yerlərinin 47,4 faizi\nqeyri-dövlət sektorunun payına düşüb. İş yerlərinin 27,3 faizi\nmüəssisə və təşkilatların fəaliyyətlərinin dayandırılması, 72,7\nfaizi isə fəaliyyət göstərən müəssisə və təşkilatlarda aparılan\nixtisarlar ilə əlaqədar bağlanıb.",
    "gold_entities": {
      "persons": [],
      "organizations": [
        "Trend",
        "Dövlət Statistika Komitəsi"
      ],
      "locations": [
        "Qarabağ",
        "Şərqi Zəngəzur",
        "Xankəndi",
        "Laçın",
        "Azərbaycan",
        "Bakı",
        "Naxçıvan Muxtar Respublikası"
      ],
      "positions": [],
      "dates": [
        "ilk 9 ay",
        "2025-ci ilin yanvar-sentyabr ayları",
        "2025-11-28"
      ]
    },
    "manually_verified": true,
    "annotator_notes": ""
  },
  {
    "article_id": "8902",
    "source": "trend.az",
    "link": "https://az.trend.az/azerbaijan/politics/4101238.html",
    "pub_date": "2025-10-08 16:58:00.000",
    "title": "Bir sıra inzibati xətalar haqqında işlər üzrə protokol tərtib etmək səlahiyyəti olan vəzifəli şəxslərin siyahısına dəyişiklik edilib",
    "content": "Bakı. Trend:\n\n“Rayon (şəhər) məhkəmələrinin və hərbi məhkəmələrin baxdığı\ninzibati xətalar haqqında işlər üzrə protokol tərtib etmək\nsəlahiyyəti olan vəzifəli şəxslərin Siyahısı”na dəyişiklik\nedilib.\n\nTrend xəbər\nverir ki, bu barədə Prezident İlham Əliyevin “Azərbaycan\nRespublikasının Cinayət Məcəlləsində və Azərbaycan Respublikasının\nİnzibati Xətalar Məcəlləsində dəyişiklik edilməsi haqqında”\nAzərbaycan Respublikasının 2025-ci il 11 aprel tarixli 178-VIIQD\nnömrəli Qanununun icrası ilə əlaqədar fərmanında qeyd olunub.\n\nFərmanda qeyd edilib:\n\nMəcəllənin 279.2-ci və 279.3-cü maddələrində nəzərdə tutulmuş\ninzibati xətalar haqqında işlər üzrə protokol:\n\n22-2.1. elektrik közərmə lampalarının idxalına münasibətdə\nAzərbaycan Respublikasının Dövlət Gömrük Komitəsi adından – bu\nSiyahının 46.1-ci bəndində nəzərdə tutulan vəzifəli şəxslər;\n\n2-2.1. elektrik közərmə lampalarının idxalına münasibətdə\nAzərbaycan Respublikasının Dövlət Gömrük Komitəsi adından – bu\nSiyahının 46.1-ci bəndində nəzərdə tutulan vəzifəli şəxslər;\n\n22-2.2. elektrik közərmə lampalarının istehsalına münasibətdə\nAzərbaycan Respublikasının Energetika Nazirliyi adından –\nenergetika naziri, onun müavinləri, Aparatın rəhbəri, onun müavini,\nşöbə müdiri, onun müavini, sektor müdiri, baş məsləhətçi, böyük\nməsləhətçi, aparıcı məsləhətçi, məsləhətçi, Nazirliyin tabeliyində\nEnerji Məsələlərini Tənzimləmə Agentliyi İdarə Heyətinin sədri,\nonun müavinləri, departament direktoru, onun müavini, şöbə müdiri,\nsektor müdiri, baş mütəxəssis, böyük mütəxəssis, aparıcı\nmütəxəssis, mütəxəssis, filial rəhbəri, onun müavini, baş müfəttiş,\nböyük müfəttiş, aparıcı müfəttiş, müfəttiş;\n\n22-2.3. elektrik közərmə lampalarının satışına münasibətdə:\n\n22-2.3.1. inzibati xətanı aşkar etmiş Azərbaycan Respublikasının\nEnergetika Nazirliyi adından – bu Siyahının 22-2.2-ci bəndində\nnəzərdə tutulan vəzifəli şəxslər;\n\n22-2.3.2. inzibati xətanı aşkar etmiş Azərbaycan Respublikasının\nPrezidenti yanında Antiinhisar və İstehlak Bazarına Nəzarət Dövlət\nAgentliyi adından – Agentliyin sədri, onun müavinləri, Aparatın\nrəhbəri, onun müavini, şöbə müdiri, onun müavini, sektor müdiri,\nbaş məsləhətçi, böyük məsləhətçi, aparıcı məsləhətçi, məsləhətçi,\nregional bölmənin rəhbəri, onun müavini, sektor müdiri, baş\nməsləhətçi, böyük məsləhətçi, aparıcı məsləhətçi, məsləhətçi.”.\n\n2. Bu Fərman 60 Vt və daha yuxarı gücə malik olan közərmə\nlampalarına münasibətdə 2026-cı il yanvarın 1-dən, 25 Vt-dan (25 Vt\ndaxil olmaqla) 60 Vt-a qədər gücə malik olan közərmə lampalarına\nmünasibətdə 2026-cı il iyulun 1-dən qüvvəyə minir.",
    "gold_entities": {
      "persons": [
        "İlham Əliyev"
      ],
      "organizations": [
        "Trend",
        "Azərbaycan Respublikasının Cinayət Məcəlləsi",
        "Azərbaycan Respublikasının İnzibati Xətalar Məcəlləsi",
        "Azərbaycan Respublikasının Dövlət Gömrük Komitəsi",
        "Energetika Nazirliyi",
        "Enerji Məsələlərini Tənzimləmə Agentliyi",
        "Prezidenti yanında Antiinhisar və İstehlak Bazarına Nəzarət Dövlət Agentliyi"
      ],
      "locations": [
        "Azərbaycan"
      ],
      "positions": [
        "Azərbaycan Prezidenti",
        "energetika naziri"
      ],
      "dates": [
        "2025-ci il 11 aprel",
        "2026-cı il yanvarın 1-dən",
        "2026-cı il iyulun 1-dən",
        "2025-10-08"
      ]
    },
    "manually_verified": true,
    "annotator_notes": ""
  },
  {
    "article_id": "5966",
    "source": "trend.az",
    "link": "https://az.trend.az/azerbaijan/society/4109783.html",
    "pub_date": "2025-10-28 13:19:00.000",
    "title": "Pilotsuz uçuş aparatları ilə bağlı aparılan tədqiqatların elmi-nəzəri nəticələri müzakirə olunub",
    "content": "Bakı.Trend:\n\nElm və Təhsil Nazirliyinin İnformasiya Texnologiyaları\nİnstitutunun növbəti elmi seminarı keçirilib.\n\nBu barədə Trend-ə institutdan məlumat verilib.\n\nAMEA-nın vitse-prezidenti, institutun baş direktoru akademik\nRasim Əliquliyev seminarın “Pilotsuz uçuş aparatlarının\nkibertəhlükəsizliyinin təmin olunması üçün metod və alqoritmlərin\nişlənməsi” mövzusunda dissertasiya işi çərçivəsində əldə olunan\nelmi-nəzəri nəticələrin müzakirəsinə həsr olunduğunu bildirib.\n\nİnstitutun doktorantı Orxan Vəlixanlı məruzəni təqdim edərək\ndissertasiya işinin aktuallığı, məqsədi, elmi yeniliyi, qarşıya\nqoyulmuş məsələlər, eləcə də iş çərçivəsində aparılmış elmi-praktik\ntədqiqatların nəticələri haqqında məlumat verib. Qeyd edib ki,\n“Azərbaycan Respublikasının informasiya təhlükəsizliyi və\nkibertəhlükəsizliyə dair 2023 – 2027-ci illər üçün Strategiyası” və\n“Azərbaycan Respublikasının 2025-2028-ci illər üçün Süni İntellekt\nStrategiyası”ndan irəli gələn məsələlər, o cümlədən son dövrlərdə\npilotsuz uçuş aparatlarının (PUA) həm mülki, həm də hərbi sahədə\ngeniş tətbiq olunması və s. bu kimi amillər dissertasiya işinin\naktuallığını şərtləndirir.\n\nO.Vəlixanlı bildirib ki, dissertasiya işinin məqsədi PUA-lara\nedilən bəzi növ kiberhücumları yüksək dəqiqliklə aşkarlaya bilən,\nsürətli, özü-özünə öyrənən, bu hücumların təsirinə qarşı dayanıqlı\nolan intellektual metod və alqoritmlərin işlənməsidir.\n\nTədqiqatçı dissertasiya işi üzrə “Pilotsuz uçuş aparatlarının\nkibertəhlükəsizlik üzrə elmi-nəzəri problemlərinin analizi” ilə\nbağlı PUA-ların əsas komponentləri, funksional missiyasının\naraşdırıldığını, təsnifatının aparıldığını, bu aparatların\nkibertəhlükəsizlik problemlərinin ətraflı tədqiq olunduğunu diqqətə\nçatdırıb.\n\nDissertasiya işinə dair geniş fikir mübadiləsi aparılıb, suallar\ncavablandırılıb.\n\nAkademik Rasim Əliquliyev PUA-ların kibertəhlükəsizliyinin təmin\nolunması istiqamətdə əldə edilən nəticələrə münasibətini bildirib.\nAlim ağıllı idarəetmə sistemləri və süni intellekt texnologiyaları\nilə təchiz olunan, müşahidə, kəşfiyyat və digər strateji təyinatlı\ntapşırıqların icrasında geniş tətbiq olunan yüksək texnoloji\ninnovasiya məhsulu – PUA-ların təhlükəsizliyinin təmin olunması\nməsələlərinin müasir dövrün prioritet istiqamətlərindən biri\nolduğunu bildirib. Akademik R.Əliquliyev bu aparatların\nkibertəhlükəsizliyi problemlərinin dərindən araşdırılmasının\nvacibliyinə toxunub, bu istiqamətdə aparılan tədqiqatın\naktuallığını vurğulayıb.\n\nAkademik R.Əliquliyev dissertasiya işi çərçivəsində əldə olunmuş\nelmi-praktiki nəticələrin PUA-ların kiberdayanıqlıq səviyyəsinin\nyüksəldilməsi baxımından mühüm əhəmiyyət kəsb etdiyini söyləyib.\nAkademik R.Əliquliyev elmi seminarda səsləndirilən irad və\ntəkliflərin tədqiqat işinin daha da təkmilləşdirilməsi baxımından\ndəyərli olduğunu bildirib, hər bir tövsiyənin nəzərə alınmasının\nönəmini xüsusi qeyd edib.",
    "gold_entities": {
      "persons": [
        "Rasim Əliquliyev",
        "Orxan Vəlixanlı"
      ],
      "organizations": [
        "Trend",
        "Elm və Təhsil Nazirliyi",
        "İnformasiya Texnologiyaları İnstitutu",
        "AMEA",
        "Azərbaycan Respublikasının informasiya təhlükəsizliyi və kibertəhlükəsizliyə dair 2023–2027-ci illər üçün Strategiyası",
        "Azərbaycan Respublikasının 2025–2028-ci illər üçün Süni İntellekt Strategiyası"
      ],
      "locations": [
        "Azərbaycan"
      ],
      "positions": [
        "AMEA-nın vitse-prezidenti",
        "institutun baş direktoru",
        "institutun doktorantı"
      ],
      "dates": [
        "2023–2027",
        "2025–2028",
        "2025-10-28"
      ]
    },
    "manually_verified": true,
    "annotator_notes": ""
  },
  {
    "article_id": "5981",
    "source": "trend.az",
    "link": "https://az.trend.az/azerbaijan/gundem/4109739.html",
    "pub_date": "2025-10-28 12:18:00.000",
    "title": "Azərbaycana gəlmək istəyən İraq vətəndaşlarının çətinliklərlə üzləşmələri barədə iddialara aydınlıq gətirilib",
    "content": "Bakı. Trend:\n\nSon günlərdə bəzi kütləvi informasiya vasitələrində Azərbaycana\nturizm məqsədilə səfər etmək istəyən İraq vətəndaşlarının\nçətinliklərlə üzləşdiyi barədə bəzi iddialar yayılıb.\n\nAzərbaycanın İraqdakı Səfirliyindən Trend-ə bildirilib ki,\nbu iddiaların heç bir əsası yoxdur və həqiqəti əks etdirməyən bu\nkimi məlumatların yayılması yanlışdır.\n\nQeyd olunub ki, İraqda viza müraciətlərinin qəbulu və emalı\nprosesinin sürətləndirilməsi, ölkəmizə turizm məqsədilə səfər etmək\nistəyən İraq vətəndaşlarına daha keyfiyyətli xidmətin göstərilməsi,\nviza rəsmiləşdirilməsi məqsədilə saxta sənədlərlə müraciət edən\nşəxslərlə mübarizənin gücləndirilməsi məqsədilə Xarici İşlər\nNazirliyi ilə müvafiq sahə üzrə ən irimiqyaslı beynəlxalq şirkət\nolan “VFS Global” arasında Anlaşma Memorandumu imzalanıb:\n\n“Bu memoranduma uyğun olaraq İraq vətəndaşlarının, o cümlədən bu\nölkədəki digər əcnəbi və vətəndaşlığı olmayan şəxslərin turizm\nməqsədli viza müraciətlərinin qəbul edilməsi 10 iyul 2024-cü il\ntarixindən etibarən “VFS Global” şirkətinin Bağdad şəhərindəki\nofisinin “Azərbaycan Viza Müraciətləri Mərkəzi” tərəfindən təşkil\nolunur. Ölkəmizə səfər etmək istəyən hər bir İraq Respublikası\nvətəndaşı viza rəsmiləşdirilməsi barədə zəruri məlumat əldə etmək\nməqsədilə Azərbaycanın İraqdakı Səfirliyi üçün fəaliyyət göstərən\nsözügedən “Viza Mərkəzi”nə müraciət edə bilər”.\n\nVurğulanıb ki, Azərbaycanən İraqdakı Səfirliyi və “VFS Global”\nşirkətinin Bağdad şəhərindəki ofisinin “Azərbaycan Viza\nMüraciətləri Mərkəzi” tərəfindən İraq vətəndaşlarının viza\nmüraciətləri ilə bağlı sənədlərin qəbulu, icraatı və təhvil\nverilməsi Azərbaycan qanunvericiliyi ilə müəyyən edilmiş qaydada\nhəyata keçirilir. Mərkəz çərçivəsində bütün xidmətlər Anlaşma\nMemorandumunda müəyyən edilmiş vahid xidmət haqqları əsasında\ntəşkil olunur.\n\n“Mərkəzin fəaliyyətinə Azərbaycanın İraqdakı Səfirliyi və “VFS\nGlobal” şirkətinin baş ofisi tərəfindən ciddi nəzarət edilir, həmin\nmərkəzin fəaliyyəti üzrə mütəmadi əsasda monitorinq aparılır.\n\nBununla yanaşı, müvafiq sahə üzrə şəffaflığın təmin edilməsi\nməqsədilə İraqda mənfi reputasiyaya malik turizm şirkətlərindən\nsənədlərin qəbul edilməsi qadağan olunub.\n\nAparılmış sözügedən tədbirlər nəticəsində ölkəmizə turizm\nməqsədilə səfər etmiş İraq Respublikası vətəndaşlarının sayında\nciddi artım müşahidə olunmaqdadır.\n\nBelə ki, 2025-ci ilin ilk 3 ayı ərzində Azərbaycanla İraq\narasında birbaşa uçuşların olmadığına və bu ilin iyun ayında İraqın\nhava məkanının bağlı olmasına baxmayaraq, 2025-ci ilin 27 oktyabr\ntarixinədək Səfirlik tərəfindən 5 904 müraciət\nqəbul edilib. Bunlardan 5 650 viza rəsmiləşdirilib\n(2024-cü il ərzində 4 800 viza müraciəti qəbul\nedilib).\n\nMətbuat vasitəsilə şikayət edən şirkətlər tərəfindən nə\nölkəmizin İraqdakı Səfirliyinə, nə də “Viza Mərkəzinə” hər hansı\nmüraciət təqdim edilməyib. Şikayətdə adı hallanan “Alkaither”\nşirkəti Azərbaycan kütləvi informasiya vasitələrində onun adından\nyayılan müraciətin saxta olduğunu bildirərək Azərbaycana səfər\netmək istəyən İraq vətəndaşlarının viza müraciətləri ilə bağlı hər\nhansı çətinliyin müşahidə olunmadığı barədə məlumat verib.\n\nMüvafiq sahə üzrə daxil olan bütün müraciətlər, o cümlədən\nşikayətlər Xarici İşlər Nazirliyi və Səfirlik tərəfindən ciddi\nyoxlanılır və yoxlama nəticəsində müvafiq nöqsanlar qeydə alındıqda\nonların aradan qaldırılması üçün zəruri tədbirlər görülür”, - deyə\nməlumatda qeyd edilib.",
    "gold_entities": {
      "persons": [],
      "organizations": [
        "Trend",
        "Azərbaycanın İraqdakı Səfirliyi",
        "Xarici İşlər Nazirliyi",
        "VFS Global",
        "Azərbaycan Viza Müraciətləri Mərkəzi",
        "Alkaither"
      ],
      "locations": [
        "İraq",
        "Bağdad",
        "Azərbaycan"
      ],
      "positions": [],
      "dates": [
        "10 iyul 2024-cü il",
        "2025-ci ilin ilk 3 ayı",
        "2025-ci ilin 27 oktyabrınadək",
        "2024-cü il",
        "2025-10-28"
      ]
    },
    "manually_verified": true,
    "annotator_notes": ""
  },
  {
    "article_id": "649",
    "source": "trend.az",
    "link": "https://az.trend.az/azerbaijan/politics/4124759.html",
    "pub_date": "2025-12-02 18:17:00.000",
    "title": "Azərbaycan standart müəyyən edir: TDT-də yeni “Diaspor üzrə Birgə Fəaliyyət Planı” qəbul olundu (FOTO)",
    "content": "Bakı. Trend:\n\nMacarıstanın paytaxtı Budapeştdə Türk Dövlətləri Təşkilatına üzv\nölkələrin diaspor məsələlərinə cavabdeh dövlət qurumlarının\nrəhbərlərinin 7-ci toplantısı keçirilib.\n\nTədbir tükdilli ölkələr arasında əməkdaşlığın müasir xarici\nsiyasətin əsas istiqamətlərindən biri olan ictimai diplomatiya\nsahəsində daha da dərinləşdirilməsi üçün mühüm platformaya\nçevrildi. İclasda TDT-nin Baş katibi, Türkiyə, Azərbaycan,\nQazaxıstan, Qırğızıstan, Özbəkistan və ev sahibi ölkə olan\nMacarıstanın təmsilçiləri iştirak ediblər. Azərbaycanı tədbirdə\nDiasporla İş üzrə Dövlət Komitəsinin sədri Fuad Muradov təmsil edib\nvə onun mövqeyi müzakirələrin əsas diqqət mərkəzlərindən biri\nolub.\n\nDiaspor siyasəti artıq uzun müddətdir ki, xaricdə yaşayan\nsoydaşlara dəstək çərçivəsini aşaraq daha geniş məzmun kəsb edib.\nBu gün diaspor fəaliyyəti beynəlxalq təsir rıçağı kimi çıxış edir,\nTDT ölkələrinə ümumi humanitar və mədəni kontekst yaratmağa,\ninformasiya mühitində mövcudluğunu gücləndirməyə və qlobal\nsəviyyədə strateji maraqları irəli sürməyə imkan verir. Dünyanın\nmüxtəlif ölkələrində yaşayan milyonlarla türkdilli insan böyük\npotensiala malikdir və bu potensialın həyata keçirilməsi üçün\nsistemli, qarşılıqlı əlaqəli və bir-birini tamamlayan yanaşmalara\nehtiyac duyulur. Məhz diaspor ümumi dəyərlərin, mədəniyyətin və\ndilin qlobal daşıyıcısına çevrilir, eyni zamanda türk dövlətləri\nilə beynəlxalq ictimaiyyət arasında körpü rolunu oynayır.\n\nAzərbaycan son illərdə diaspor siyasətinin ən kompleks və\neffektiv modelini quraraq TDT-nin digər üzvləri üçün nümunəyə\nçevrilib. Xaricdəki azərbaycanlı icmaları ilə çoxpilləli, müasir və\ndavamlı qarşılıqlı fəaliyyət sistemi yaradılıb. Bu sistem daimi\nkommunikasiya, dəstək proqramları, təhsil təşəbbüsləri və geniş\nmədəni fəaliyyətlər üzərində qurulub. Nəticədə Azərbaycan diasporu\nilə əlaqələr güclənib və ölkənin beynəlxalq humanitar təsir alətinə\nçevrilib.\n\nFuad Muradov çıxışında türk dövlətləri arasında humanitar sahədə\nəməkdaşlığın strateji əhəmiyyət daşıdığını vurğulayıb. O, TDT-nin\nNaxçıvan Sazişi əsasında yaradılmasını xatırladaraq ölkələr\narasında əməkdaşlığın son illərdə daha da intensivləşdiyini\nbildirib. Onun sözlərinə görə, məhz Türk Diasporunun Birgə\nFəaliyyət Strategiyasının həyata keçirilməsi bu əməkdaşlığı\nsistemli şəkildə möhkəmləndirir: “TDT çərçivəsində keçirilən\nikitərəfli və çoxtərəfli görüşlər, proqramlar, forumlar və\ntəşəbbüslər ölkələrimiz arasında əməkdaşlığın genişlənməsinə və\nmöhkəmlənməsinə mühüm töhfə verir”, – deyə Fuad Muradov qeyd\nedib.\n\nBudapeştdə diaspor fəaliyyətinin koordinasiyası məsələləri\nxüsusi diqqət mərkəzində olub və bu sahədə Azərbaycan təcrübəsi\ntürkdilli dünyada ən uğurlulardan biri kimi qiymətləndirilib.\nDövlət Komitəsi ardıcıl şəkildə beynəlxalq tərəfdaşlıq əlaqələri\nqurur, diaspor təşkilatları ilə sistemli iş aparır, dezinformasiya\nilə bağlı çağırışlara operativ reaksiya verir və türk dövlətləri\nüçün vahid humanitar gündəliyin formalaşdırılmasını fəal şəkildə\nmüdafiə edir. Toplantıda çıxış edən nümayəndələr ümumi işin\n“uzlaşdırılmış strategiyalar və ortaq məsuliyyət” prinsipləri\nəsasında davam etdirilməsinin vacibliyini vurğuladılar ki, bu da\nAzərbaycan modelinə tam uyğundur.\n\nGörüşün ən vacib nəticələrindən biri 2026-cı il üçün “Diaspor\nüzrə Birgə Fəaliyyət Planı”nın qəbul edilməsi oldu. Bu sənəd türk\ndövlətlərinin humanitar və mədəni siyasət sahəsində vahid xətt\nformalaşdırmaq istiqamətində səylərini birləşdirir. Planın qəbul\nolunması geniş təcrübə mübadiləsinin, çoxistiqamətli müzakirələrin\nvə Azərbaycanın aktiv mövqeyinin nəticəsidir. Bu addım bir daha\nAzərbaycanın türk dünyasının ictimai diplomatiyasının\nformalaşdırılmasında əsas mərkəzlərdən biri olduğunu\ntəsdiqlədi.\n\nBudapeşt toplantısı göstərdi ki, TDT ölkələri qarşılıqlı\ntamamlanma və strateji koordinasiya prinsipləri əsasında yeni\nictimai diplomatiya arxitekturasına keçməkdə maraqlıdır. Bu\nkontekstdə Azərbaycanın Diasporla İş üzrə Dövlət Komitəsinin\nfəaliyyəti sistemli yanaşması, uzunmüddətli vizionu və yenilikç",
    "gold_entities": {
      "persons": [
        "Fuad Muradov"
      ],
      "organizations": [
        "Trend",
        "Türk Dövlətləri Təşkilatı (TDT)",
        "Diasporla İş üzrə Dövlət Komitəsi",
        "Naxçıvan Sazişi",
        "Diaspor üzrə Birgə Fəaliyyət Planı"
      ],
      "locations": [
        "Budapeşt",
        "Macarıstan",
        "Türkiyə",
        "Azərbaycan",
        "Qazaxıstan",
        "Qırğızıstan",
        "Özbəkistan"
      ],
      "positions": [
        "Diasporla İş üzrə Dövlət Komitəsinin sədri"
      ],
      "dates": [
        "2026-cı il",
        "7-ci toplantı",
        "2025-12-02"
      ]
    },
    "manually_verified": true,
    "annotator_notes": ""
  },
  {
    "article_id": "7208",
    "source": "trend.az",
    "link": "https://az.trend.az/azerbaijan/society/4106230.html",
    "pub_date": "2025-10-20 11:11:02.000",
    "title": "Sümük sağlamlığını qoruma tədbirləri uşaqlıq və gənclik dövründən başlanmalıdır - SN (FOTO)",
    "content": "Bakı. Trend:\n\n1997-ci ildən etibarən hər il oktyabrın 20-si Ümumdünya\nOsteoporozla Mübarizə Günü kimi qeyd edilir. Həmin tarix Ümumdünya\nSəhiyyə Təşkilatının (ÜST) təşəbbüsü ilə profilaktika, diaqnostika\nvə metabolik sümük xəstəliklərinin müalicəsi haqqında cəmiyyəti\nməlumatlandırmaq məqsədilə təsis edilib.\nOsteoporozun yaranma səbəbləri, növləri və əlamətləri, onun\nmüalicəsi və digər suallara Səhiyyə Nazirliyi Elmi-Tədqiqat\nTravmatologiya və Ortopediya İnstitutunun Baş direktorunun müavini\n– baş həhim Nizami Məmmədov Nazirliyin rəsmi saytına verdiyi\nmüsahibədə aydınlıq gətirir.\n\nTrend\nhəmin müsahibəni təqdim edir:\n\n– Nizami müəllim, ilk öncə bilmək istərdik ki, osteoporoz\nnədir?\n\n– Osteoporoz sümük toxuması kütləsinin və keyfiyyətinin azalması\nilə xarakterizə olunan, sümükləri zəif və kövrək edən metabolik\nxəstəlikdir. Bu xəstəlik zamanı sümükdə mineral komponentlərin\nmiqdarı azalır, həm də onun mikroarxitekturası pozulur. Nəticədə,\nsümük mexaniki gücünü itirir və minimal travma ilə belə sınıq baş\nverə bilir. ÜST-nin tərifinə görə, osteoporoz sistemli sümük\nxəstəliyi olub, əsas klinik əlaməti az travmalı və ya heç travma\nolmadan baş verən sınıqlardır.\nBu xəstəliyin cəmiyyət üçün təhlükəsi onun uzun illər simptom\nverməməsi, yalnız sınıq baş verdikdə özünü göstərməsi və artıq gec\nmərhələdə aşkar olunması ilə bağlıdır. Ona görə də, osteoporoz\ntez-tez “səssiz epidemiya” adlandırılır.\n\n– Doktor, bu xəstəlik kimlərdə daha çox rast gəlir?\n\n– Osteoporoz qadınlarda, xüsusən də menopauza sonrası dövrdə\ndaha çox müşahidə olunur. Qadınlarda hormonal səbəblər ön planda\nolsa da, kişilərdə yaşlanma, xroniki xəstəliklər və həyat tərzi\nfaktorları əsas rol oynayır.\nBundan əlavə, uzun müddət yataq rejimində qalan xəstələr, qidalanma\npozğunluğu olan şəxslər və bəzi xroniki xəstəliklərdən əziyyət\nçəkənlər də yüksək risk qrupuna daxildir.\n\n– Osteoporozun yaranma səbəbləri nələrdir?\n\n– Xəstəliyin yaranması çoxfaktorlu prosesdir. Onun birinci\nsəbəbi insanın yaşlanmasıdır. İnsan təbii olaraq 30–35 yaşında\nsümük kütləsinin ən yüksək səviyyəsinə çatır və bundan sonra\nyavaş-yavaş azalmağa başlayır. Xüsusən qadınlarda menopauza sonrası\ndövrdə estrogen hormonunun kəskin azalması sümük itkisini\nsürətləndirir.\nGenetik amillər də əhəmiyyətlidir. Birinci dərəcəli qohumlarda\nosteoporoz və ya bud boynu sınıqları müşahidə olunubsa, bu, riskin\nyüksək olduğunu göstərir. Qidalanma da mühüm rol oynayır.\nOrqanizm kifayət qədər kalsium və D vitamini qəbul etmədikdə, sümük\ntoxumasının möhkəmliyi azalır. Hərəkətsizlik, yəni fiziki\naktivliyin az olması sümük toxumasının stimullaşdırılmamasına\ngətirib çıxarır və nəticədə sümük kütləsi daha tez itirilir.\nSiqaret, alkoqol və uzun müddət kortikosteroid qəbulu da sümük\nmetabolizmini pozur.\nBütün bu amillər birləşərək osteoporozun yaranmasına zəmin\nyaradır.\n\n– Xəstəliyin klinik əlamətləri nələrdir?\n\n– Osteoporozun ən təhlükəli xüsusiyyəti uzun müddət gizli\nqalmasıdır. İnsan illərlə sümük itkisi yaşasa da, bunu hiss etmir.\nYalnız sümük kütləsinin xeyli azalmasından sonra klinik əlamətlər\nmeydana çıxır. Bel və kürək nahiyəsində xroniki, sönük ağrılar,\nboyun getdikcə qısalması və qamburluq bu əlamətlərdəndir.\nƏn diqqətçəkən klinik nəticə isə yüngül yıxılmadan sonra baş verən\nsınıqlardır. Xüsusən bud boynu sınıqları, fəqərə sınıqları və bilək\nsınıqları osteoporozun tipik göstəricisidir. Bu sınıqlar insanın\nhəyat keyfiyyətini ciddi şəkildə azaldır və bəzən ömür uzunluğunu\nda qısaldır.\n\n– Osteoporoz necə diaqnostika olunur?\n\n– Diaqnostikanın əsas üsulu sümük mineral sıxlığının\nölçülməsidir. Bunun üçün istifadə olunan densitometriya (DEXA)\nmetodu “qızıl standart” sayılır. “T-score” –2.5 və daha aşağı\nolduqda, osteoporoz diaqnozu qoyulur.\nRentgenoqrafiya yalnız gec mərhələdə sümük nazilməsini göstərir,\nlakin erkən mərhələlərdə kifayət qədər informativ deyil. Biokimyəvi\nanalizlərdə kalsium, fosfor, D vitamini, paratiroid hormonu kimi\ngöstəricilər qiymətləndirilir.\nBundan əlavə, xəstənin anamnezi, ailə tarixi və həyat tərzi\namilləri də ",
    "gold_entities": {
      "persons": [
        "Nizami Məmmədov"
      ],
      "organizations": [
        "Trend",
        "Ümumdünya Səhiyyə Təşkilatı (ÜST)",
        "Səhiyyə Nazirliyi",
        "Elmi-Tədqiqat Travmatologiya və Ortopediya İnstitutu"
      ],
      "locations": [
        "Azərbaycan"
      ],
      "positions": [
        "Baş direktorun müavini",
        "baş həhim"
      ],
      "dates": [
        "oktyabrın 20-si",
        "1997-ci ildən",
        "2025-10-20"
      ]
    },
    "manually_verified": true,
    "annotator_notes": ""
  },
  {
    "article_id": "6040",
    "source": "trend.az",
    "link": "https://az.trend.az/azerbaijan/politics/4109316.html",
    "pub_date": "2025-10-28 07:00:00.000",
    "title": "Zəfər xronikası. 28 oktyabr 2020-ci il: Prezident İlham Əliyev Rusiyanın İnterfaks agentliyinə müsahibə verib (FOTO/VİDEO)",
    "content": "Bakı. Trend:\n\n2020-ci il sentyabrın 27-də Ermənistan silahlı qüvvələrinin\ncəbhəboyu genişmiqyaslı təxribat törətməsinə cavab olaraq\nAzərbaycan Ordusu sonradan \"Dəmir yumruq\" adlandırılan əks-hücum\nəməliyyatına başladı. 44 gün davam edən Vətən müharibəsi təxminən\notuzillik işğala son qoyulması və ərazi bütövlüyümüzün bərpası ilə\nnəticələndi.\n\n2020-ci il oktyabrın 28-də Azərbaycan Respublikasının Prezidenti\nİlham Əliyev Rusiyanın İnterfaks agentliyinə müsahibə verib.\n\nTrend\nmüsahibəni təqdim edir:\n\n-Cənab Prezident, sağ olun ki, gərgin iş qrafikinizdə\nbizim agentliyimizə müsahibə üçün vaxt tapmısınız. Azərbaycan\nSilahlı Qüvvələrinin Dağlıq Qarabağda əks-hücuma başlamasının dünən\ndüz bir ayı tamam oldu. Siz ötən ayı münaqişənin hərbi-siyasi\nnizamlanması baxımından necə qiymətləndirirsiniz?\n\n-Azərbaycan Ordusu döyüş meydanında özünün üstünlüyünü sübut\netdi. İşğal edilmiş ərazilərin xeyli hissəsi bu bir ay ərzində azad\nolundu. Erməni tərəfinin təqribən 30 il ərzində işğal olunmuş\ntorpaqlarda möhkəmləndirilmiş rayonlar yaratmasını nəzərə alsaq,\norada bir neçə müdafiə xətti var idi. Ərazinin relyefi də erməni\ntərəfi üçün daha əlverişlidir, çünki ora dağlıq ərazidir və bizim\nhərbi qulluqçular əks-hücum əməliyyatlarını həyata keçirərkən həm\nmühəndis qurğularını, həm də dağlıq relyefi adlamalı olurdu. Buna\ngörə də bütün bu amillər nəzərə alınmaqla, ölkəmizin ərazilərinin\nxeyli hissəsi bir ay ərzində azad edildi və bu, göstərir ki,\nAzərbaycan Ordusunun dünyada ən yaxşı döyüş qabiliyyətinə malik\nordulardan biri hesab edilməsi əbəs deyildi. Ölkələrin hərbi\npotensialının dəyərləndirilməsi ilə məşğul olan qurumların\nvaxtaşırı dərc etdiyi reytinqlərə əsasən, Azərbaycan Ordusu\ndünyanın aparıcı 50 ordusu sırasındadır. Həm peşəkarlıq, həm təlim,\nhəm döyüş qabiliyyəti, ən başlıcası mənəvi döyüş ruhu, əlbəttə ki,\nAzərbaycan Ordusunun texniki təchizatı da çox cəhətdən bizim\nuğurumuza kömək edib. Biz Füzuli, Cəbrayıl, Zəngilan, Qubadlı\nşəhərlərini, Xocavənd rayonunun bir hissəsini azad etmişik.\nAzərbaycan Ordusunun uğurlu fəaliyyəti, uğurla irəliləməsi davam\nedir. Bu bir ay ərzində mən dəfələrlə demişəm ki, biz bu\nmünaqişənin nizamlanmasının hərbi mərhələdən siyasi mərhələyə\nkeçməsini istəyirik. Lakin təəssüf ki, erməni tərəfi atəşkəs\nrejimini artıq üçüncü dəfə kobud şəkildə pozaraq, bizim azad\netdiyimiz əraziləri yenidən işğal etməyə cəhd göstərərək\nqarşıdurmanı davam etməyə doğru yönəldir. Buna görə sizin sualınıza\nbir daha cavab verirəm - hərbi-siyasi nizamlama yeganə mümkün\nyoldur. Biz istərdik ki, hərbi faza danışıqlar masası arxasında\nbaşa çatsın, Azərbaycan ərazilərinin bundan sonra da işğaldan azad\nolunması məsələləri həll edilsin.\n\n-Cənab Prezident, Siz artıq qeyd etdiniz ki, Bakı hərbi\nfazanı maksimum tez bir müddətdə başa çatdırmaqda maraqlıdır. Sizin\nfikrinizcə, hazırda hərbi faza nə qədər uzun müddət davam edə bilər\nvə Bakı yalnız Dağlıq Qarabağın ətrafındakı yeddi rayonla\nkifayətlənməyə hazırdırmı?\n\n-Bu ay ərzində mən Azərbaycan xalqına müraciətlərimdə, habelə\nçoxsaylı müsahibələrimdə dəfələrlə demişəm ki, biz istənilən anda,\ngünü bu gün dayanmağa hazırıq. Lakin bunun üçün erməni tərəfi işğal\nedilmiş ərazilərin qalan hissəsindən qoşunlarını çıxarmaq barədə\nöhdəlik götürməlidir. Buna görə də hərbi qarşıdurmanın nə qədər\nuzun müddət davam edəcəyini qabaqcadan deyə bilmərəm. Bu, erməni\ntərəfindən asılıdır. Artıq dediyim kimi, onların bizim\ntorpaqlarımızı yenidən işğal altına qaytarmaq üçün göstərdiyi daimi\ncəhdlər fiaskoya uğrayıb. Düşünürəm ki, onların hərbi yolla heç\nnəyə nail olmayacaqlarını anlamaları üçün bu, kifayətdir. Lakin\ntəəssüf ki, onlar dediyim kimi, atəşkəs rejimini artıq üç dəfə\nkobud şəkildə pozmaqla siyasi müstəvidə qeyri-konstruktiv yanaşma\nnümayiş etdirirlər. Bunu nəzərə alaraq biz, əlbəttə, gələcək\nfəaliyyətimizi planlaşdıracağıq. İşğal edilmiş ərazilər məsələsinə\ngəldikdə, şübhəsiz, azərbaycanlılar əvvəl yaşadıqları bütün işğal\nolunmuş ərazilərə qayıtmalıdırlar. Mənim yanaşmam həmişə belə olub.\nAzərbaycanlılar təkcə D",
    "gold_entities": {
      "persons": [
        "İlham Əliyev"
      ],
      "organizations": [
        "Trend",
        "İnterfaks",
        "Azərbaycan Ordusu",
        "Ermənistan silahlı qüvvələri",
        "Dəmir yumruq"
      ],
      "locations": [
        "Azərbaycan",
        "Füzuli",
        "Cəbrayıl",
        "Zəngilan",
        "Qubadlı",
        "Xocavənd"
      ],
      "positions": [
        "Azərbaycan Respublikasının Prezidenti"
      ],
      "dates": [
        "2020-ci il sentyabrın 27-də",
        "2020-ci il oktyabrın 28-də",
        "2025-10-28"
      ]
    },
    "manually_verified": true,
    "annotator_notes": ""
  }
]